Workbook

Sheet Ограничения оценки ВНУТРЕННИЕ!
A1: № | B1: Ограничение | C1: Пояснение
A2: 1
A3: 2
A4: 3
A5: 4
A6: 5
A7: 6
A8: 7
A9: 8
A10: 9
A11: 10

Sheet Лист изменений
A1: 45260
A2: Изменения ФС
A3: 1. | B3: Выделил отдельный раздел по отражению базовых данных по БДР и БДДС из раздела 4.5. Экономика проектов (Уточнил перечень документов и хоз. Операций)
A4: 2. | B4: Перенес трансляцию данных распределенной зарплаты из раздела 4.5. в разделы 7.3. и 7.4. по распредеелнию ЗП, и ОПР/ОХР, соответсвенно
A5: 3. | B5: Добавил строку "Формирование плана доходов по проектам" в раздел 7.1. Бизнес-план
A6: 4. | B6: Раздел 1.6. "переквалифицировал" в Базовый
A7: 5. | B7: Уточнил содержание раздела 5.1.План работ подразделений В новой версии предлагаю его читать как работа РСП (Декомпозиция структуры проекта в рамках работ подарделений, переквалифицировал в Базовый функционал
B8: Уточнил раздел 5.4. "… по ролям", перенес в него работы с прогнозом трудозатрат по ролям
B9: Уточнил терминологию п 2.6. "Технологические графики"
B10: Перенес работу с оперативной загрузкой из раздела 5.1. (Базовый) в раздел 5.3 (весь раздел сформулировал как "Оперативное управление работами и загрузкой исполнителй)
B11: Добавил новый раздел 3.5. "Мониторинг процесса обеспечения ТМЦ под проект в Контуре PM" Как наша гипотеха по тому какая функциональность необходима дл Инжиниринга
B12: Выделил отдельные разделы по распределению ОПР/ОХР в проектном контуре
B13: Перенес получение факта из БП 3 в раздел Интеграции
B14: Отчет по EVA перенесли в базовый функционал в раздел 4.3.
B15: Отчет Динамика экономики перенесли в базовый функционал в раздел 4.4.
B16: Выделена отдельной строкой обмен первичными документами с БП, изменена оценка
B17: Обмен с ЗУП разделен на 2 строки: 1. Получение Начсиленнйо ЗП для целей распределения ЗП в ERP, 2. Часто встречающийся запрос на синхронизацию структуры ТР с кадровыми данными (Прием, перевод, увольнение, ставки ТР)
A18: Изменения в оценке
B19: Изменил параметры ставки с 24 года: - Ставка Стандартизированных преоктов (кейс и проф/мини) 4500 , - Ставка ПРОФ проектов 4900; - Ставка КОРП проектов 5500 Вторая и далее очереди оцениваются "по умолчанию" с учетом длительности предыдущих очередей
B20: Добавил параметры и расчет типа проекта п критериям и подстановку ставки в соответсвии с типом проектв на листы оценок по каждой очереди
B21: Изменил коэффициенты разработки для 500 и 1000+ по умолчанию (в меньшую сторону до х3)
B22: Добавил индикаторы "адекватности" сроков по оценкам по очередям
B23: скорректировал расчет этапов обучения
B24: Скорректировал расчет сроков по этапам
A25: 45321
B26: Уточнил перечень хоз операция, в п. 4.4.
B27: Переформулировали п. 7.8, 7.1. ( с сохранением сути)
B28: Сделал автозаполнение критериев отнесения к ПРОФ и КОРП из Содержания проекта
A29: 45335
B30: Добавили строки прочего функицонала (Использование модулей для ERP и ERP+УХ
A31: 45717 | B31: Добавили Фонд компании и резервы на риски договора
A32: 45805 | B32: Внесена колонка с функционалом и ограничениями реализации на РМ5

Sheet 1.Содержание проекта
A1: Содержание проекта | F1: Заполнено?
A2: 1.Обоснование проекта (потребности, предпосылки) | F2: Группа
A3: Автоматизируемые виды деятельности | D3: Субпродукт (выпускаемый продукт/услуга) | F3: Группа
A4: Выбор из списка (выбрать): | F4: =ISBLANK(B4) -> TRUE
F5: =ISBLANK(B5) -> TRUE
F6: =ISBLANK(B6) -> TRUE
F7: =ISBLANK(B7) -> TRUE
F8: =ISBLANK(B8) -> TRUE
F9: =ISBLANK(B9) -> TRUE
F10: =ISBLANK(B10) -> TRUE
A11: Свои варианты (вписать): | F11: =ISBLANK(B11) -> TRUE
F12: =ISBLANK(B12) -> TRUE
F13: =ISBLANK(B13) -> TRUE
F14: =ISBLANK(B14) -> TRUE
F15: =ISBLANK(B15) -> TRUE
F16: =ISBLANK(B16) -> TRUE
F17: =ISBLANK(B17) -> TRUE
A18: Бизнес потребность (для чего реализуется проект, желательно, с конкретными измеримыми показателями) | E18: Текстовые комментарии | F18: Группа
A19: Выбор из списка (выбрать): | F19: =ISBLANK(B19) -> TRUE
F20: =ISBLANK(B20) -> TRUE
F21: =ISBLANK(B21) -> TRUE
F22: =ISBLANK(B22) -> TRUE
F23: =ISBLANK(B23) -> TRUE
F24: =ISBLANK(B24) -> TRUE
F25: =ISBLANK(B25) -> TRUE
A26: Свои варианты (вписать): | F26: =ISBLANK(B26) -> TRUE
F27: =ISBLANK(B27) -> TRUE
F28: =ISBLANK(B28) -> TRUE
F29: =ISBLANK(B29) -> TRUE
F30: =ISBLANK(B30) -> TRUE
F31: =ISBLANK(B31) -> TRUE
F32: =ISBLANK(B32) -> TRUE
A33: Предпосылки (что сейчас не так - указываются факторы, которые мешают достигнуть бизнес-потребностей, а также история и проблематика, приведшие к идее старта проекта) | E33: Текстовые комментарии | F33: Группа
A34: Выбор из списка (выбрать): | F34: =ISBLANK(B34) -> TRUE
F35: =ISBLANK(B35) -> TRUE
F36: =ISBLANK(B36) -> TRUE
F37: =ISBLANK(B37) -> TRUE
F38: =ISBLANK(B38) -> TRUE
F39: =ISBLANK(B39) -> TRUE
F40: =ISBLANK(B40) -> TRUE
A41: Свои варианты (вписать): | F41: =ISBLANK(B41) -> TRUE
F42: =ISBLANK(B42) -> TRUE
F43: =ISBLANK(B43) -> TRUE
F44: =ISBLANK(B44) -> TRUE
F45: =ISBLANK(B45) -> TRUE
F46: =ISBLANK(B46) -> TRUE
F47: =ISBLANK(B47) -> TRUE
A48: 2.Заполнить функциональную спецификацию (отдельный лист "2.ФС для Заполнения") | F48: Группа
A49: Заполняется функциональный объем внедрения в разрезе Очередей на отдельном листе | E49: Текстовые комментарии | F49: Группа
A50: 3.Резюме проекта | F50: Группа
A51: Организационный объем проекта (Если предполагается пилотный запуск на ограниченном орг.объеме, необходимо отдельно указать орг. объем такого запуска) | E51: Текстовые комментарии | F51: Группа
A52: Центральный офис | F52: Группа
A53: Удаленные офисы без необходимости командировок (перечислить) | F53: Группа
A54: Удаленные офисы с необходимостью командировок (перечислить) | F54: Группа
A55: Матрица пользователей | F55: Группа
A56: Бизнес-роль (должность) | B56: Кол-во пользователей | C56: Типовой/Не типовой профиль | D56: Краткое описание профиля | E56: В каком офисе | F56: =ISBLANK(B56) -> FALSE
C57: Администратор | D57: Профиль предназначен для: • настройки параметров работы и обслуживания информационной системы, • настройки прав доступа других пользователей, • удаления помеченных объектов, • в редких случаях для внесения изменений в конфигурацию. Рекомендуется не использовать для «обычной» работы в информационной системе. | F57: =ISBLANK(B57) -> TRUE
C58: Администратор НСИ проектного офиса | D58: Назначается пользователю, если ему необходимо выполнять административные функции в рамках проектного контура (ввод нормативно-справочной информации) | F58: =ISBLANK(B58) -> TRUE
C59: Руководители проектного офиса | D59: Назначается пользователю, который является руководителем проектного офиса, с правом утверждения проектов, правами руководителя проектов и/или подразделений (с доступом к финансовой информации) и правами ввода нормативно-справочной информации; | F59: =ISBLANK(B59) -> TRUE
C60: Руководитель проектов и/или подразделений (с доступом к финансовой информации) | D60: Назначается пользователю, который является руководителем, администратором проектов или начальником подразделения с правом ввода структуры проекта, планирования трудозатрат, назначением исполнителей, планирования и учету фактических объемов, доходов, расходов и ДДС | F60: =ISBLANK(B60) -> TRUE
C61: Руководитель проектов и/или подразделений (без доступа к финансовой информации) | D61: Назначается пользователю, который является руководителем, администратором проектов или начальником подразделения с правом ввода структуры проекта, планирования трудозатрат, назначения исполнителей, регистрации выполненного объема и фактических затрат материальных ресурсов | F61: =ISBLANK(B61) -> TRUE
C62: Исполнители работ | D62: Дает пользователю право работать с проектными заданиями, вводить информацию в систему по работам на проектах (документ «Распределение рабочего времени за неделю», «Табель учета рабочего времени») и получать отчетность по плановым и фактическим трудозатратам по проектным задачам, по которым пользователь является исполнителем; | F62: =ISBLANK(B62) -> TRUE
C63: Экономист проектного офиса | D63: Назначается пользователю, который является администратором проектов или начальником подразделения с правом ввода фактических объемов, доходов, расходов и ДДС и формирования производственной программы из имеющихся проектов. | F63: =ISBLANK(B63) -> TRUE
C64: Не типовой профиль | D64: Описать ожидаемые полномочия роли | F64: =ISBLANK(B64) -> TRUE
C65: Не типовой профиль | D65: Описать ожидаемые полномочия роли | F65: =ISBLANK(B65) -> TRUE
C66: Не типовой профиль | D66: Описать ожидаемые полномочия роли | F66: =ISBLANK(B66) -> TRUE
C67: Не типовой профиль | D67: Описать ожидаемые полномочия роли | F67: =ISBLANK(B67) -> TRUE
A68: 4.Цели, задачи и результаты проекта (критерии выполнения проекта) | F68: Группа
A69: Критерии успешности проекта | E69: Текстовые комментарии | F69: Группа
A70: Выбор из списка (выбрать): | F70: =ISBLANK(B70) -> TRUE
F71: =ISBLANK(B71) -> TRUE
F72: =ISBLANK(B72) -> TRUE
F73: =ISBLANK(B73) -> TRUE
F74: =ISBLANK(B74) -> TRUE
F75: =ISBLANK(B75) -> TRUE
F76: =ISBLANK(B76) -> TRUE
A77: Свои варианты (вписать): | F77: =ISBLANK(#REF!) -> FALSE
F78: =ISBLANK(B78) -> TRUE
F79: =ISBLANK(B79) -> TRUE
F80: =ISBLANK(B80) -> TRUE
F81: =ISBLANK(B81) -> TRUE
F82: =ISBLANK(B82) -> TRUE
F83: =ISBLANK(B83) -> TRUE
A84: Технология реализации проекта и существенные результаты | F84: Группа
A85: Методические результаты (Если в рамки проекта не должна входить разработка методических документов, это необходимо явно указать) | E85: Текстовые комментарии | F85: =ISBLANK(B85) -> TRUE | G85: Формулу не удалять
A86: Выбор из списка (выбрать): | B86: Не ожидается методической работы и результатов | F86: =ISBLANK(B86) -> FALSE | G86: =IF(OR(B86="Не ожидается методической работы и результатов",B86=""),0,1) -> 0
F87: =ISBLANK(B87) -> TRUE | G87: =IF(OR(B87="Не ожидается методической работы и результатов",B87=""),0,1) -> 0
F88: =ISBLANK(B88) -> TRUE | G88: =IF(OR(B88="Не ожидается методической работы и результатов",B88=""),0,1) -> 0
F89: =ISBLANK(B89) -> TRUE | G89: =IF(OR(B89="Не ожидается методической работы и результатов",B89=""),0,1) -> 0
F90: =ISBLANK(B90) -> TRUE | G90: =IF(OR(B90="Не ожидается методической работы и результатов",B90=""),0,1) -> 0
F91: =ISBLANK(B91) -> TRUE | G91: =IF(OR(B91="Не ожидается методической работы и результатов",B91=""),0,1) -> 0
F92: =ISBLANK(B92) -> TRUE | G92: =IF(OR(B92="Не ожидается методической работы и результатов",B92=""),0,1) -> 0
A93: Свои варианты (вписать): | F93: =ISBLANK(B93) -> TRUE | G93: =IF(OR(B93="Не ожидается методической работы и результатов",B93=""),0,1) -> 0
F94: =ISBLANK(B94) -> TRUE | G94: =IF(OR(B94="Не ожидается методической работы и результатов",B94=""),0,1) -> 0
F95: =ISBLANK(B95) -> TRUE | G95: =IF(OR(B95="Не ожидается методической работы и результатов",B95=""),0,1) -> 0
F96: =ISBLANK(B96) -> TRUE | G96: =IF(OR(B96="Не ожидается методической работы и результатов",B96=""),0,1) -> 0
F97: =ISBLANK(B97) -> TRUE | G97: =IF(OR(B97="Не ожидается методической работы и результатов",B97=""),0,1) -> 0
F98: =ISBLANK(B98) -> TRUE | G98: =IF(OR(B98="Не ожидается методической работы и результатов",B98=""),0,1) -> 0
F99: =ISBLANK(B99) -> TRUE | G99: =IF(OR(B99="Не ожидается методической работы и результатов",B99=""),0,1) -> 0
A100: Документация к информационной системе (указываются ключевые, с точки зрения Заказчика, результаты проекта) | E100: Текстовые комментарии | F100: =ISBLANK(B100) -> TRUE
...

Sheet параметры расчета
C1: Ставка с 25 года | D1: Ставка с 24 года | E1: Ставки 23 года | F1: Изменение ставки
B2: Расчет Ставки | C2: =IF('1.Содержание проекта'!#REF!="КОРП-проект",'параметры расчета'!C5,IF('1.Содержание проекта'!#REF!>12,'параметры расчета'!C4,'параметры расчета'!C3)) -> #REF! | D2: #REF! | H2: Критерии отнесения к типу преокта по ставке
B3: Ставка Кейс; ПРОФ/мини | C3: 5000 | D3: 4500 | E3: 4200 | F3: =C3/E3-1 -> 0.19047619
B4: Ставка ПРОФ | C4: 5500 | D4: 4900 | E4: 4500 | F4: =C4/E4-1 -> 0.22222222 | H4: 1. Необходимо описывать Бизнес-процессы 2. Более 200 пользователей 3. Не стандартные формы документов (Без изменения состава работ и документации) 4. Требуется нагрузочное тестирование
B5: Ставка Заказные | C5: 6500 | D5: 5500 | E5: 4900 | F5: =C5/E5-1 -> 0.32653061 | H5: 1. Технология заказчика (в т.ч. Документация, которая подразумевает расширение состава работ) 2. Оптимизация бизнес-процессов 3. Методология 4. численность Заказчика более 1000 сотрудников (КОРП заказчик) 5. Более 500 пользователей 6. Заявлена документация по ИБ
B6: Резерв РПО | C6: 0.2 | D6: 0.2
B8: Функциональный объем | C8: Базовый/Проф/Экспертный функционал
B9: Темплан и контрактация | C9: ГРУППА | D9: Да
B10: Производственная программа | C10: Базовый | D10: Да | E10: 2
B11: Формирование производственной программы | D11: Да
B12: План-фактный анализ по программе | D12: Да
B13: Тематический план | D13: Да
B14: Сводная загрузка | C14: Базовый | D14: Да | E14: 1
B15: Анализ загрузки подразделений и специальностей по задачам производственной программы | D15: Нет
B16: Ручное выравнивание загрузки подразделений по задачам портфеля проектов | D16: Нет
B17: Расчет цены контракта | C17: ПРОФ | D17: Нет | E17: 2
B18: Расчет цены контракта | D18: Нет
B19: Планирование и мониторинг прохождения тендера | D19: Нет
B20: Выдача поручений по разработке догововора | D20: Нет
B21: Моделирвоание инвест. Портфеля. Ранжирование заявок на проекты. | C21: ПРОФ | D21: Нет | E21: 3
B22: Формирование заявок на проект. Мониторинг состояния завок. | C22: ПРОФ | D22: Нет
B23: Оценка соответствия заявленных проектов стратегическим целям компании | C23: ПРОФ | D23: Нет
B24: Регистрация значений показателей ээфективности проектов (Внутренняя ставка доходности, срок окупаемости,индекс прибыльности, чистый денежный поток, чистая приведенная стоимость) | C24: ПРОФ | D24: Нет
B25: Расчет итогового балла проектов по показателеям эффективности. | C25: ПРОФ | D25: Нет
B26: Формирование бизнес плана по портфелю проектов. | C26: ПРОФ | D26: Нет
B27: Мониторинг договорной компании | C27: ПРОФ | D27: Да | E27: 2
B28: Регистрация юридических условий договора и дополнительных соглашений | C28: ПРОФ | D28: Нет
B29: Согласование и монитринг статусов договора | C29: ПРОФ | D29: Нет
B30: Актуализация БДДС по данным договора | C30: ПРОФ | D30: Нет
B31: Хранение файлов и отсканированных копий договора | C31: ПРОФ | D31: Нет
B32: Мониторинг фаз проектов портфеля (Gate) | C32: ПРОФ | D32: Да | E32: 1
B33: Мониторинг показателей портфеля проектов по методике ворот качества в панели руководителя | C33: ПРОФ | D33: Нет
B34: Управление ЖЦ проектов (портфеля проектов) по методике ворот качества | C34: ПРОФ | D34: Нет
B35: KPI портфеля проектов | C35: ПРОФ | D35: Да | E35: 2
B36: Мониторинг KPI портфеля проектов | D36: Нет
B37: Анализ плановых показателей трудоемкости, бюджетов и объемов работ запланирванных по портфелю и соттоветствующих плановых и фактических показателей проектов входящих в портфель | D37: Нет
B38: Оптимизация темтического плана | C38: Экспертный | D38: Нет | E38: 10
B39: Управление работами и сроками | C39: ГРУППА | D39: Нет
B40: Сформировать календарные планы проектов | C40: Базовый | D40: Да | E40: 2
B41: Регистрация паспорта проекта | C41: Базовый | D41: Да
B42: Декомпозиция проекта до этапов, определенных договором | C42: Базовый | D42: Да
B43: Декомпозиция этапов работ до подэтапов и задач. Определение сроков и длительности выполнения задач и подэтапов. | C43: Базовый | D43: Да
B44: Планирование ключевых и технологических событий («вех») проектов | C44: Базовый | D44: Да
B45: Расчет «критического пути» проекта | C45: Базовый | D45: Да
B46: Использование диаграмм Ганта | C46: Базовый | D46: Да
B47: Формирование сетевого график проектов | C47: Базовый | D47: Да
B48: Версионирование календарного плана проекта | C48: Базовый | D48: Да
B49: План-фактный анализ сроков проекта | C49: Базовый | D49: Да
B50: Анализ отклонений сроков текущего плана проекта от сроков версий плана проекта | C50: Базовый | D50: Да
B51: Учесть выполнение работ проектов | C51: Базовый | D51: Да | E51: 1
B52: Отражение выполнение работ по задачам проекта | C52: Базовый | D52: Да
B53: Прохождение технологических событий проекта | C53: Базовый | D53: Да
B54: Прохождение ключевых событий проекта | C54: Базовый | D54: Да
B55: План-фактный анализ выполнения работ проекта и прохождения клчевых событий и технологических операций | C55: Базовый | D55: Да
B56: Управлять ЖЦ проектов | C56: Базовый | D56: Да | E56: 1
B57: Управление статусами проектов | C57: Базовый | D57: Да
B58: Рассчитать KPI проектов | C58: Базовый | D58: Да | E58: 1
B59: Планирование KPI проектов, этапов проектов | D59: Нет
B60: Мониторинг состояния показателей | D60: Нет
B61: Технологическе графики проекта | C61: Экспертный | D61: Нет | E61: 10
B62: Шаблоны проектов | C62: Экспертный | D62: Нет | E62: 5
B63: Управление трудоемкостью и прочими ресурсами | C63: ГРУППА | D63: Нет
B64: Сформировать плановые трудозатраты проектов | C64: Базовый | D64: Да | E64: 2
B65: Планирование мощности ролей и подразделений | C65: Базовый | D65: Да
B66: Планирование норм стоимости (ставок) ролей (специальностей) подразделений с учетом уровня квалификации | C66: Базовый | D66: Да
B67: Планирование загрузки подразделений и специальностей по этапам проекта | C67: Базовый | D67: Да
B68: Планирование загрузки сотрудников по задачам проекта (без использования механизма заданий) | C68: Базовый | D68: Да
B69: Планирование загрузки сотрудников по задачам проекта (с использованием механизма заданий) | C69: Базовый | D69: Да
B70: Планирование оперативной загрузки сотрудников по графику в течении периода (день, неделя и т.д.) | C70: Базовый | D70: Да
B71: Сформировать прочие ресурсные планы проектов | C71: Базовый | D71: Да | E71: 1
B72: Планирование материальных ресурсов и оборудования | C72: Базовый | D72: Да
B73: Формирование заказа поставщику | C73: Базовый | D73: Да
B74: Планирование дополнительных затрат | C74: Базовый | D74: Да
B75: Учесть фактические трудозатраты по проектам | C75: Базовый | D75: Да | E75: 1
B76: Учет рабочего времени | C76: Базовый | D76: Да
B77: Анализ фактических трудозатрат | C77: Базовый | D77: Да
B78: План-фактный анализ трудозатрат | C78: Базовый | D78: Да
B79: Учесть фактический расход ресурсов | C79: Базовый | D79: Да | E79: 1
B80: Учет фактического использования материальных ресурсов и оборудования | D80: Нет
B81: Учет факта дополнительных затрат | D81: Нет
B82: План-фактный анализ затрат материальных ресурсов | D82: Нет
B83: План-фактный анализ дополнительных затрат | D83: Нет
B84: S-кривые проектов | C84: ПРОФ | D84: Да | E84: 2
B85: Анализ фактического % готовности проектов, % готовности ожидаемой по сроку на текущую дату, % освоенных трудозатрат и % освоенного объема | C85: ПРОФ | D85: Нет
B86: Анализ отклонений по срокам на S-кривых проектов | C86: ПРОФ | D86: Нет
B87: Анализ отклонений по стоимости на S-кривых проектов | C87: ПРОФ | D87: Нет
B88: KPI проектов по трудоемкости | C88: ПРОФ | D88: Да | E88: 2
B89: Мониторинг KPI сотрудников по трудоемкости | D89: Нет
B90: Нормирование трудозатрат | C90: Экспертный | D90: Нет | E90: 10
B91: Проектное бюджетирование | C91: ГРУППА | D91: Нет
B92: Сформировать планы объемов | C92: Базовый | D92: Да | E92: 1
B93: Планирование объемов доходов и расходов по проекту в стоимостном выражении на основании бюджета доходов и расходов по проектной задаче | C93: Базовый | D93: Да
B94: Планирование выпуска субпродуктов по срокам и стоимости по задачам и актируемым этапам | C94: Базовый | D94: Да
B95: Распределение плановых объемов выпуска по подразделениям, специальностям и с/п | C95: Базовый | D95: Да
B96: Планирование объемов доходов по проекту в натуральном выражении на основании плана выпуска | C96: Базовый | D96: Да
B97: Планирование объемов расходов по проекту в натуральном выражении на основании плана затрат материальных ресурсов | C97: Базовый | D97: Да
B98: Сформировать бюджеты проектов (прямые) | C98: Базовый | D98: Да | E98: 1
B99: Формирование БДР проекта вручную | C99: Базовый | D99: Да
B100: Формирование БДР проекта на основании плана выпуска и ресурсных планов | C100: Базовый | D100: Да
B101: Распределение БДР проекта по подразделениям | C101: Базовый | D101: Да
...

Sheet 2.ФС для Заполнения
AA1: Ставка
B2: 2. Заполнение функционального объема (строго на закладке "ФС для Заполнения") | AA2: 1. Орг объем: Количество пользователей и сотрудников организации всего Заполняются ТОЛЬКО ячейки выделенные желтым цветом. Используется для расчета фаз 5.2,6,7 | AC2: ДО 200 | AF2: =AC2 -> ДО 200 | AI2: =AC2 -> ДО 200 | AL2: =AC2 -> ДО 200
B3: 2.1. Колонка "ДА"/"НЕТ" по принципу Функциональной спецификации На уровне записей устанавливается вручную. Группа определяется по формуле | AA3: Орг. Объем | AC3: Итого | AD3: в т.ч. В городе присутствия | AE3: в т.ч. В регионах (с командировкой) | AF3: Итого | AG3: в т.ч. В городе присутствия | AH3: в т.ч. В регионах (с командировкой) | AI3: Итого | AJ3: в т.ч. В городе присутствия | AK3: в т.ч. В регионах (с командировкой) | AL3: Итого | AM3: в т.ч. В городе присутствия | AN3: в т.ч. В регионах (с командировкой)
B4: 2.2. Необходимость методической проработки в рамках проекта: Первоначально определяется по формуле (Требуется или предоставляется Заказчиком). Если в рамках проекта требуется методическая проработка, то значение меняется вручную на "Необходимо разработать" | AA4: в т.ч. Пользователей | AC4: =AD4+AE4 -> 30 | AD4: =SUM(AD5:AD6) -> 30 | AE4: =SUM(AE5:AE6) -> 0 | AF4: =AG4+AH4 -> 95 | AG4: =SUM(AG5:AG6) -> 95 | AH4: =SUM(AH5:AH6) -> 0 | AI4: =AJ4+AK4 -> 95 | AJ4: =SUM(AJ5:AJ6) -> 95 | AK4: =SUM(AK5:AK6) -> 0 | AL4: =AM4+AN4 -> 0 | AM4: =SUM(AM5:AM6) -> 0 | AN4: =SUM(AN5:AN6) -> 0
B5: 2.3.Объем нагрузочного тестирования: Определяется количество сценариев автоматически Рассчитывается по формуле если функционал отмечен как "Да" | AA5: Количество РП, РПО, Рук. Отделов | AC5: =AD5+AE5 -> 10 | AD5: 10 | AF5: =AG5+AH5 -> 20 | AG5: 20 | AI5: =AJ5+AK5 -> 20 | AJ5: 20 | AL5: =AM5+AN5 -> 0
AA6: Количество Исполнителей Работ | AC6: =AD6+AE6 -> 20 | AD6: 20 | AF6: =AG6+AH6 -> 75 | AG6: 75 | AI6: =AJ6+AK6 -> 75 | AJ6: 75 | AL6: =AM6+AN6 -> 0
AA7: в т.ч. Численность Рабочей Группы Заказчика (Ключевые пользователи к обучению) | AC7: =AD7+AE7 -> 5 | AD7: 5 | AF7: =AG7+AH7 -> 5 | AG7: 5 | AI7: =AJ7+AK7 -> 5 | AJ7: 5 | AL7: =AM7+AN7 -> 0
AC8: БЗ Проеткная дирекция | AF8: Комплексный Заказной проект проект | AI8: БЗ Экономический блок | BW8: Полная рентабельность | BX8: Полная рентабельность | CC8: Полная рентабельность + бюджетирование + казна | CF8: Проектная продукция | CJ8: Упр. Подражделениями | CL8: Тем. План
A9: № п.п | B9: Функциональный объем | C9: Функциональный объем РМ5 и особенности реализации | D9: Аргументы для Заказчика | E9: Функциональный заказчик по блоку (ФИО, должность) | F9: Тип функционала | G9: Тип проекта | H9: PM ПРОФ | I9: УНФ+PM | J9: PM КОРП | K9: ERP+PM | L9: PM5 | M9: Вес функционала Story Points | N9: Story Points Итого | O9: 1 очередь | P9: НМД | Q9: Нагрузочное | R9: 2 очередь | S9: НМД | T9: Нагрузочное | U9: 3 очередь | V9: НМД | W9: Нагрузочное | X9: Развитие | Y9: НМД | Z9: Нагрузочное | AA9: Да/Нет | AB9: Доп. вопросы | AC9: 1 очередь | AD9: НМД | AE9: Комментарий | AF9: 2 очередь | AG9: НМД | AH9: Комментарий | AI9: 3 очередь | AJ9: НМД | AK9: Комментарий | AL9: Развитие | AM9: НМД | AN9: Комментарий | AP9: Шаблоны. Не править | AQ9: Story Points | AR9: По функциональности | AS9: Кейс-проект | AT9: Кейс по готовности PM5 | AU9: БЗ Проеткная дирекция | AV9: БЗ Экономический блок | AW9: Базовый функционал + экономика оптимально (РСП, то, что готово) | AX9: Комплексный ПРОФ проект | AY9: Комплексный Заказной проект проект | AZ9: Заказной+ консалтинг | BA9: По позиционированию | BB9: Акционеры хотят фин.эк. прозрачности (отчеты в сроки через ФД или ПЭО) | BC9: Системный директор /системные ТОПы – комплексная бизнес-система | BD9: Гос.контракты (военные контракты) конструкторов/труд.производства | BE9: Планирование сроков, загрузки и диспетчеризация работ подразделений | BF9: Формирование моделей и физических объектов по моделям в сроки Было: Директор по производству: Результаты (Продукт проекта) в сроки | BG9: Управление сроками, ресурсами и лимитами корпоративных проектов от уровня холдинга до КБ и завода | BH9: Управление корпоративными проектами развития и инвест.проектами | BI9: Руководитель структурного подразделения: сроки, ресурсы, финансы | BJ9: Структурирование проектной деятельности | BK9: Моделирование численности (вкл. Формирование тем. плана) | BL9: Систематизация продаж проектов (вкл. формирование стоимости контракта) | BM9: Операционное управление проектом (пока не наш рынок) | BN9: Технический переход с УПО 1.3 | BO9: ИТ-проект как Большая мечта | BP9: Импортозамещение | BQ9: По функциональности | BS9: Кейс-проект | BT9: Кейс по готовности PM5 | BU9: БЗ Проеткная дирекция | BV9: БЗ Экономический блок | BW9: Инжиниринг | BX9: Базовый функционал + экономика оптимально (РСП, то, что готово) | BY9: Комплексный ПРОФ проект | BZ9: Комплексный Заказной проект проект | CA9: Заказной+ консалтинг | CB9: По позиционированию | CC9: Акционеры хотят фин.эк. прозрачности (отчеты в сроки через ФД или ПЭО) | CD9: Системный директор /системные ТОПы – комплексная бизнес-система | CE9: Гос.контракты (военные контракты) конструкторов/труд.производства | CF9: Планирование сроков, загрузки и диспетчеризация работ подразделений | CG9: Формирование моделей и физических объектов по моделям в сроки Было: Директор по производству: Результаты (Продукт проекта) в сроки | CH9: Управление сроками, ресурсами и лимитами корпоративных проектов от уровня холдинга до КБ и завода | CI9: Управление корпоративными проектами развития и инвест.проектами | CJ9: Руководитель структурного подразделения: сроки, ресурсы, финансы | CK9: Структурирование проектной деятельности | CL9: Моделирование численности (вкл. Формирование тем. плана) | CM9: Систематизация продаж проектов (вкл. формирование стоимости контракта) | CN9: Операционное управление проектом (пока не наш рынок) | CO9: Технический переход с УПО 1.3 | CP9: ИТ-проект как Большая мечта | CQ9: Импортозамещение | CR9: Требуется НМД эталлон
A10: 1. | B10: Тем план и контрактация | F10: ГРУППА | G10: ГРУППА | H10: ГРУППА | I10: ГРУППА | J10: ГРУППА | K10: ГРУППА | L10: ГРУППА | M10: =SUM(M37,M33,M31,M27,M20,M17,M14,M11) -> 28 | N10: =SUM(N37,N33,N31,N27,N20,N17,N14,N11) -> 27 | O10: =SUM(O37,O33,O31,O27,O20,O17,O14,O11) -> 5 | P10: =SUM(P37,P33,P31,P27,P20,P17,P14,P11) -> 0 | Q10: =SUM(Q37,Q33,Q31,Q27,Q20,Q17,Q14,Q11) -> 3 | R10: =SUM(R37,R33,R31,R27,R20,R17,R14,R11) -> 18 | S10: =SUM(S37,S33,S31,S27,S20,S17,S14,S11) -> 0 | T10: =SUM(T37,T33,T31,T27,T20,T17,T14,T11) -> 8 | ... Z10: =SUM(Z37,Z33,Z31,Z27,Z20,Z17,Z14,Z11) -> 0 | AA10: =IF(N10>0,"ДА","НЕТ") -> ДА | AC10: =IF(O10>0,"ДА","НЕТ") -> ДА | AF10: =IF(R10>0,"ДА","НЕТ") -> ДА | AI10: =IF(U10>0,"ДА","НЕТ") -> ДА | AL10: =IF(X10>0,"ДА","НЕТ") -> НЕТ | AS10: =SUM(AS37,AS33,AS31,AS27,AS20,AS17,AS14,AS11) -> 6 | AT10: =SUM(AT37,AT33,AT31,AT27,AT20,AT17,AT14,AT11) -> 5 | AU10: =SUM(AU37,AU33,AU31,AU27,AU20,AU17,AU14,AU11) -> 5 | AV10: =SUM(AV37,AV33,AV31,AV27,AV20,AV17,AV14,AV11) -> 4 | AW10: =SUM(AW37,AW33,AW31,AW27,AW20,AW17,AW14,AW11) -> 8 | AX10: =SUM(AX37,AX33,AX31,AX27,AX20,AX17,AX14,AX11) -> 10 | AY10: =SUM(AY37,AY33,AY31,AY27,AY20,AY17,AY14,AY11) -> 18 | AZ10: =SUM(AZ37,AZ33,AZ31,AZ27,AZ20,AZ17,AZ14,AZ11) -> 28 | BB10: =SUM(BB37,BB33,BB31,BB27,BB20,BB17,BB14,BB11) -> 6 | BC10: =SUM(BC37,BC33,BC31,BC27,BC20,BC17,BC14,BC11) -> 8 | BD10: =SUM(BD37,BD33,BD31,BD27,BD20,BD17,BD14,BD11) -> 3 | BE10: =SUM(BE37,BE33,BE31,BE27,BE20,BE17,BE14,BE11) -> 3 | BF10: =SUM(BF37,BF33,BF31,BF27,BF20,BF17,BF14,BF11) -> 0 | BG10: =SUM(BG37,BG33,BG31,BG27,BG20,BG17,BG14,BG11) -> 16 | BH10: =SUM(BH37,BH33,BH31,BH27,BH20,BH17,BH14,BH11) -> 16 | BI10: =SUM(BI37,BI33,BI31,BI27,BI20,BI17,BI14,BI11) -> 0 | ... BP10: =SUM(BP37,BP33,BP31,BP27,BP20,BP17,BP14,BP11) -> 0 | BS10: =IF(AS10>0,"ДА","НЕТ") -> ДА | BT10: =IF(AT10>0,"ДА","НЕТ") -> ДА | BU10: =IF(AU10>0,"ДА","НЕТ") -> ДА | BV10: =IF(AV10>0,"ДА","НЕТ") -> ДА | BW10: =IF(AS10>0,"ДА","НЕТ") -> ДА | BX10: =IF(AW10>0,"ДА","НЕТ") -> ДА | BY10: =IF(AX10>0,"ДА","НЕТ") -> ДА | BZ10: =IF(AY10>0,"ДА","НЕТ") -> ДА | CA10: =IF(AZ10>0,"ДА","НЕТ") -> ДА | CC10: =IF(BB10>0,"ДА","НЕТ") -> ДА | CD10: =IF(BC10>0,"ДА","НЕТ") -> ДА | CE10: =IF(BD10>0,"ДА","НЕТ") -> ДА | CF10: =IF(BE10>0,"ДА","НЕТ") -> ДА | CG10: =IF(BF10>0,"ДА","НЕТ") -> НЕТ | CH10: =IF(BG10>0,"ДА","НЕТ") -> ДА | CI10: =IF(BH10>0,"ДА","НЕТ") -> ДА | CJ10: =IF(BI10>0,"ДА","НЕТ") -> НЕТ | ... CQ10: =IF(BP10>0,"ДА","НЕТ") -> НЕТ
A11: 1.1. | B11: Производственная программа | F11: Базовый | G11: Кейс-проект | H11: Да | I11: Да | J11: Да | K11: Да | L11: В разработке | M11: 2 | N11: =SUM(O11,R11,U11,X11) -> 6 | O11: =IF(AC11="ДА",$M11,"") -> 2 | Q11: =IF(AC11="ДА",ROUNDUP(O11/5,0),0) -> 1 | R11: =IF(AF11="ДА",$M11,"") -> 2 | T11: =IF(AF11="ДА",ROUNDUP(R11/5,0),0) -> 1 | U11: =IF(AI11="ДА",$M11,"") -> 2 | W11: =IF(AI11="ДА",ROUNDUP(U11/5,0),0) -> 1 | X11: =IF(AL11="ДА",$M11,"") | Z11: =IF(AL11="ДА",ROUNDUP(X11/5,0),0) -> 0 | AA11: =IF(OR(AC11="ДА",AF11="ДА",AI11="ДА",AL11="ДА"),"ДА","НЕТ") -> ДА | AC11: =IF(AC$8=$BT$9,$BT11,IF(AC$8=$BS$9,$BS11,IF(AC$8=$BU$9,$BU11,IF(AC$8=$BV$9,$BV11,IF(AC$8=$BW$9,$BW11,IF(AC$8=$BX$9,$BX11,IF(AC$8=$BY$9,$BY11,IF(AC$8=$BZ$9,$BZ11,IF(AC$8=$CA$9,$CA11,IF(AC$8=$CC$9,$CC11,IF(AC$8=$CD$9,$CD11,IF(AC$8=$CE$9,$CE11,IF(AC$8=$CF$9,$CF11,IF(AC$8=$CG$9,$CG11,IF(AC$8=$CH$9,$CH11,IF(AC$8=$CI$9,$CI11,IF(AC$8=$CJ$9,$CJ11,IF(AC$8=$CK$9,$CK11,IF(AC$8=$CL$9,$CL11,IF(AC$8=$CM$9,$CM11,IF(AC$8=$CN$9,$CN11,IF(AC$8=$CO$9,$CO11,IF(AC$8=$CP$9,$CP11,IF(AC$8=$CQ$9,$CQ11,"НЕТ")))))))))))))))))))))))) -> ДА | AD11: =IF(AC11="НЕТ","Не требуется",$CR11) -> Не требуется | AF11: =IF(AF$8=$BT$9,$BT11,IF(AF$8=$BS$9,$BS11,IF(AF$8=$BU$9,$BU11,IF(AF$8=$BV$9,$BV11,IF(AF$8=$BW$9,$BW11,IF(AF$8=$BX$9,$BX11,IF(AF$8=$BY$9,$BY11,IF(AF$8=$BZ$9,$BZ11,IF(AF$8=$CA$9,$CA11,IF(AF$8=$CC$9,$CC11,IF(AF$8=$CD$9,$CD11,IF(AF$8=$CE$9,$CE11,IF(AF$8=$CF$9,$CF11,IF(AF$8=$CG$9,$CG11,IF(AF$8=$CH$9,$CH11,IF(AF$8=$CI$9,$CI11,IF(AF$8=$CJ$9,$CJ11,IF(AF$8=$CK$9,$CK11,IF(AF$8=$CL$9,$CL11,IF(AF$8=$CM$9,$CM11,IF(AF$8=$CN$9,$CN11,IF(AF$8=$CO$9,$CO11,IF(AF$8=$CP$9,$CP11,IF(AF$8=$CQ$9,$CQ11,"НЕТ")))))))))))))))))))))))) -> ДА | AG11: =IF(AG$8=$BT$9,$BT11,IF(AG$8=$BS$9,$BS11,IF(AG$8=$BU$9,$BU11,IF(AG$8=$BV$9,$BV11,IF(AG$8=$BW$9,$BW11,IF(AG$8=$BX$9,$BX11,IF(AG$8=$BY$9,$BY11,IF(AG$8=$BZ$9,$BZ11,IF(AG$8=$CA$9,$CA11,IF(AG$8=$CC$9,$CC11,IF(AG$8=$CD$9,$CD11,IF(AG$8=$CE$9,$CE11,IF(AG$8=$CF$9,$CF11,IF(AG$8=$CG$9,$CG11,IF(AG$8=$CH$9,$CH11,IF(AG$8=$CI$9,$CI11,IF(AG$8=$CJ$9,$CJ11,IF(AG$8=$CK$9,$CK11,IF(AG$8=$CL$9,$CL11,IF(AG$8=$CM$9,$CM11,IF(AG$8=$CN$9,$CN11,IF(AG$8=$CO$9,$CO11,IF(AG$8=$CP$9,$CP11,IF(AG$8=$CQ$9,$CQ11,"НЕТ")))))))))))))))))))))))) -> НЕТ | AH11: =IF(AH$8=$BT$9,$BT11,IF(AH$8=$BS$9,$BS11,IF(AH$8=$BU$9,$BU11,IF(AH$8=$BV$9,$BV11,IF(AH$8=$BW$9,$BW11,IF(AH$8=$BX$9,$BX11,IF(AH$8=$BY$9,$BY11,IF(AH$8=$BZ$9,$BZ11,IF(AH$8=$CA$9,$CA11,IF(AH$8=$CC$9,$CC11,IF(AH$8=$CD$9,$CD11,IF(AH$8=$CE$9,$CE11,IF(AH$8=$CF$9,$CF11,IF(AH$8=$CG$9,$CG11,IF(AH$8=$CH$9,$CH11,IF(AH$8=$CI$9,$CI11,IF(AH$8=$CJ$9,$CJ11,IF(AH$8=$CK$9,$CK11,IF(AH$8=$CL$9,$CL11,IF(AH$8=$CM$9,$CM11,IF(AH$8=$CN$9,$CN11,IF(AH$8=$CO$9,$CO11,IF(AH$8=$CP$9,$CP11,IF(AH$8=$CQ$9,$CQ11,"НЕТ")))))))))))))))))))))))) -> НЕТ | AI11: =IF(AI$8=$BT$9,$BT11,IF(AI$8=$BS$9,$BS11,IF(AI$8=$BU$9,$BU11,IF(AI$8=$BV$9,$BV11,IF(AI$8=$BW$9,$BW11,IF(AI$8=$BX$9,$BX11,IF(AI$8=$BY$9,$BY11,IF(AI$8=$BZ$9,$BZ11,IF(AI$8=$CA$9,$CA11,IF(AI$8=$CC$9,$CC11,IF(AI$8=$CD$9,$CD11,IF(AI$8=$CE$9,$CE11,IF(AI$8=$CF$9,$CF11,IF(AI$8=$CG$9,$CG11,IF(AI$8=$CH$9,$CH11,IF(AI$8=$CI$9,$CI11,IF(AI$8=$CJ$9,$CJ11,IF(AI$8=$CK$9,$CK11,IF(AI$8=$CL$9,$CL11,IF(AI$8=$CM$9,$CM11,IF(AI$8=$CN$9,$CN11,IF(AI$8=$CO$9,$CO11,IF(AI$8=$CP$9,$CP11,IF(AI$8=$CQ$9,$CQ11,"НЕТ")))))))))))))))))))))))) -> ДА | AJ11: =IF(AJ$8=$BT$9,$BT11,IF(AJ$8=$BS$9,$BS11,IF(AJ$8=$BU$9,$BU11,IF(AJ$8=$BV$9,$BV11,IF(AJ$8=$BW$9,$BW11,IF(AJ$8=$BX$9,$BX11,IF(AJ$8=$BY$9,$BY11,IF(AJ$8=$BZ$9,$BZ11,IF(AJ$8=$CA$9,$CA11,IF(AJ$8=$CC$9,$CC11,IF(AJ$8=$CD$9,$CD11,IF(AJ$8=$CE$9,$CE11,IF(AJ$8=$CF$9,$CF11,IF(AJ$8=$CG$9,$CG11,IF(AJ$8=$CH$9,$CH11,IF(AJ$8=$CI$9,$CI11,IF(AJ$8=$CJ$9,$CJ11,IF(AJ$8=$CK$9,$CK11,IF(AJ$8=$CL$9,$CL11,IF(AJ$8=$CM$9,$CM11,IF(AJ$8=$CN$9,$CN11,IF(AJ$8=$CO$9,$CO11,IF(AJ$8=$CP$9,$CP11,IF(AJ$8=$CQ$9,$CQ11,"НЕТ")))))))))))))))))))))))) -> НЕТ | AK11: =IF(AK$8=$BT$9,$BT11,IF(AK$8=$BS$9,$BS11,IF(AK$8=$BU$9,$BU11,IF(AK$8=$BV$9,$BV11,IF(AK$8=$BW$9,$BW11,IF(AK$8=$BX$9,$BX11,IF(AK$8=$BY$9,$BY11,IF(AK$8=$BZ$9,$BZ11,IF(AK$8=$CA$9,$CA11,IF(AK$8=$CC$9,$CC11,IF(AK$8=$CD$9,$CD11,IF(AK$8=$CE$9,$CE11,IF(AK$8=$CF$9,$CF11,IF(AK$8=$CG$9,$CG11,IF(AK$8=$CH$9,$CH11,IF(AK$8=$CI$9,$CI11,IF(AK$8=$CJ$9,$CJ11,IF(AK$8=$CK$9,$CK11,IF(AK$8=$CL$9,$CL11,IF(AK$8=$CM$9,$CM11,IF(AK$8=$CN$9,$CN11,IF(AK$8=$CO$9,$CO11,IF(AK$8=$CP$9,$CP11,IF(AK$8=$CQ$9,$CQ11,"НЕТ")))))))))))))))))))))))) -> НЕТ | AL11: =IF(AL$8=$BT$9,$BT11,IF(AL$8=$BS$9,$BS11,IF(AL$8=$BU$9,$BU11,IF(AL$8=$BV$9,$BV11,IF(AL$8=$BW$9,$BW11,IF(AL$8=$BX$9,$BX11,IF(AL$8=$BY$9,$BY11,IF(AL$8=$BZ$9,$BZ11,IF(AL$8=$CA$9,$CA11,IF(AL$8=$CC$9,$CC11,IF(AL$8=$CD$9,$CD11,IF(AL$8=$CE$9,$CE11,IF(AL$8=$CF$9,$CF11,IF(AL$8=$CG$9,$CG11,IF(AL$8=$CH$9,$CH11,IF(AL$8=$CI$9,$CI11,IF(AL$8=$CJ$9,$CJ11,IF(AL$8=$CK$9,$CK11,IF(AL$8=$CL$9,$CL11,IF(AL$8=$CM$9,$CM11,IF(AL$8=$CN$9,$CN11,IF(AL$8=$CO$9,$CO11,IF(AL$8=$CP$9,$CP11,IF(AL$8=$CQ$9,$CQ11,"НЕТ")))))))))))))))))))))))) -> НЕТ | AM11: =IF(AL11="НЕТ","Не требуется",$CR11) -> Не требуется | AS11: =IF(BS11="ДА",$M11,"") -> 2 | AT11: =IF(BT11="ДА",$M11,"") -> 2 | AU11: =IF(BU11="ДА",$M11,"") -> 2 | AV11: =IF(BV11="ДА",$M11,"") -> 2 | AW11: =IF(BW11="ДА",$M11,"") -> 2 | AX11: =IF(BY11="ДА",$M11,"") -> 2 | AY11: =IF(BZ11="ДА",$M11,"") -> 2 | AZ11: =IF(CA11="ДА",$M11,"") -> 2 | BB11: =IF(CC11="ДА",$M11,"") -> 2 | BC11: =IF(CD11="ДА",$M11,"") -> 2 | BD11: =IF(CE11="ДА",$M11,"") -> 2 | BE11: =IF(CF11="ДА",$M11,"") -> 2 | BF11: =IF(CG11="ДА",$M11,"") | BG11: =IF(CH11="ДА",$M11,"") -> 2 | BH11: =IF(CI11="ДА",$M11,"") -> 2 | BI11: =IF(CJ11="ДА",$M11,"") | ... BP11: =IF(CQ11="ДА",$M11,"") | BS11: ДА | BT11: ДА | BU11: ДА | BV11: ДА | BW11: ДА | BX11: ДА | BY11: ДА | BZ11: ДА | CA11: ДА | CC11: ДА | CD11: ДА | CE11: ДА | CF11: ДА | CG11: НЕТ | CH11: ДА | CI11: ДА | CJ11: НЕТ | CK11: ДА | CL11: ДА | CM11: ДА | CN11: НЕТ | CO11: НЕТ | CP11: НЕТ | CQ11: НЕТ | CR11: Не требуется | CS11: НЕТ | CT11: НЕТ
B12: Формирование производственной программы | C12: Частично! Свод по производственной программе- в панели руководителя и отчетах, отдельной сущности нет. Есть доходные объемы, а доходов собственно нет. Есть БДР и БДДС в структуре, а так же в табличном редакторе, так же есть доходные объемы и расходные (ресурсы)
B13: План-фактный анализ по программе | C13: Пока не весь функционал ПФА по программе есть как в РМ4. Нет необходимости в полном повторении РМ4, потому что по сценарию РМ5 он такой не нужен. ПФА существует в виде отчетов, а так же с помощью таблиных редакторов, где присутствует план, а так же факт+прогноз.
A14: 1.2. | B14: Сводная загрузка | F14: Базовый | G14: Кейс-проект | H14: Да | I14: Да | J14: Да | K14: Да | L14: Да | M14: 1 | N14: =SUM(O14,R14,U14,X14) -> 2 | O14: =IF(AC14="ДА",$M14,"") -> 1 | Q14: =IF(AC14="ДА",ROUNDUP(O14/5,0),0) -> 1 | R14: =IF(AF14="ДА",$M14,"") -> 1 | T14: =IF(AF14="ДА",ROUNDUP(R14/5,0),0) -> 1 | U14: =IF(AI14="ДА",$M14,"") | W14: =IF(AI14="ДА",ROUNDUP(U14/5,0),0) -> 0 | X14: =IF(AL14="ДА",$M14,"") | Z14: =IF(AL14="ДА",ROUNDUP(X14/5,0),0) -> 0 | AA14: =IF(OR(AC14="ДА",AF14="ДА",AI14="ДА",AL14="ДА"),"ДА","НЕТ") -> ДА | AC14: =IF(AC$8=$BT$9,$BT14,IF(AC$8=$BS$9,$BS14,IF(AC$8=$BU$9,$BU14,IF(AC$8=$BV$9,$BV14,IF(AC$8=$BW$9,$BW14,IF(AC$8=$BX$9,$BX14,IF(AC$8=$BY$9,$BY14,IF(AC$8=$BZ$9,$BZ14,IF(AC$8=$CA$9,$CA14,IF(AC$8=$CC$9,$CC14,IF(AC$8=$CD$9,$CD14,IF(AC$8=$CE$9,$CE14,IF(AC$8=$CF$9,$CF14,IF(AC$8=$CG$9,$CG14,IF(AC$8=$CH$9,$CH14,IF(AC$8=$CI$9,$CI14,IF(AC$8=$CJ$9,$CJ14,IF(AC$8=$CK$9,$CK14,IF(AC$8=$CL$9,$CL14,IF(AC$8=$CM$9,$CM14,IF(AC$8=$CN$9,$CN14,IF(AC$8=$CO$9,$CO14,IF(AC$8=$CP$9,$CP14,IF(AC$8=$CQ$9,$CQ14,"НЕТ")))))))))))))))))))))))) -> ДА | AD14: =IF(AC14="НЕТ","Не требуется",$CR14) -> Не требуется | AF14: =IF(AF$8=$BT$9,$BT14,IF(AF$8=$BS$9,$BS14,IF(AF$8=$BU$9,$BU14,IF(AF$8=$BV$9,$BV14,IF(AF$8=$BW$9,$BW14,IF(AF$8=$BX$9,$BX14,IF(AF$8=$BY$9,$BY14,IF(AF$8=$BZ$9,$BZ14,IF(AF$8=$CA$9,$CA14,IF(AF$8=$CC$9,$CC14,IF(AF$8=$CD$9,$CD14,IF(AF$8=$CE$9,$CE14,IF(AF$8=$CF$9,$CF14,IF(AF$8=$CG$9,$CG14,IF(AF$8=$CH$9,$CH14,IF(AF$8=$CI$9,$CI14,IF(AF$8=$CJ$9,$CJ14,IF(AF$8=$CK$9,$CK14,IF(AF$8=$CL$9,$CL14,IF(AF$8=$CM$9,$CM14,IF(AF$8=$CN$9,$CN14,IF(AF$8=$CO$9,$CO14,IF(AF$8=$CP$9,$CP14,IF(AF$8=$CQ$9,$CQ14,"НЕТ")))))))))))))))))))))))) -> ДА | AG14: =IF(AG$8=$BT$9,$BT14,IF(AG$8=$BS$9,$BS14,IF(AG$8=$BU$9,$BU14,IF(AG$8=$BV$9,$BV14,IF(AG$8=$BW$9,$BW14,IF(AG$8=$BX$9,$BX14,IF(AG$8=$BY$9,$BY14,IF(AG$8=$BZ$9,$BZ14,IF(AG$8=$CA$9,$CA14,IF(AG$8=$CC$9,$CC14,IF(AG$8=$CD$9,$CD14,IF(AG$8=$CE$9,$CE14,IF(AG$8=$CF$9,$CF14,IF(AG$8=$CG$9,$CG14,IF(AG$8=$CH$9,$CH14,IF(AG$8=$CI$9,$CI14,IF(AG$8=$CJ$9,$CJ14,IF(AG$8=$CK$9,$CK14,IF(AG$8=$CL$9,$CL14,IF(AG$8=$CM$9,$CM14,IF(AG$8=$CN$9,$CN14,IF(AG$8=$CO$9,$CO14,IF(AG$8=$CP$9,$CP14,IF(AG$8=$CQ$9,$CQ14,"НЕТ")))))))))))))))))))))))) -> НЕТ | AH14: =IF(AH$8=$BT$9,$BT14,IF(AH$8=$BS$9,$BS14,IF(AH$8=$BU$9,$BU14,IF(AH$8=$BV$9,$BV14,IF(AH$8=$BW$9,$BW14,IF(AH$8=$BX$9,$BX14,IF(AH$8=$BY$9,$BY14,IF(AH$8=$BZ$9,$BZ14,IF(AH$8=$CA$9,$CA14,IF(AH$8=$CC$9,$CC14,IF(AH$8=$CD$9,$CD14,IF(AH$8=$CE$9,$CE14,IF(AH$8=$CF$9,$CF14,IF(AH$8=$CG$9,$CG14,IF(AH$8=$CH$9,$CH14,IF(AH$8=$CI$9,$CI14,IF(AH$8=$CJ$9,$CJ14,IF(AH$8=$CK$9,$CK14,IF(AH$8=$CL$9,$CL14,IF(AH$8=$CM$9,$CM14,IF(AH$8=$CN$9,$CN14,IF(AH$8=$CO$9,$CO14,IF(AH$8=$CP$9,$CP14,IF(AH$8=$CQ$9,$CQ14,"НЕТ")))))))))))))))))))))))) -> НЕТ | AI14: =IF(AI$8=$BT$9,$BT14,IF(AI$8=$BS$9,$BS14,IF(AI$8=$BU$9,$BU14,IF(AI$8=$BV$9,$BV14,IF(AI$8=$BW$9,$BW14,IF(AI$8=$BX$9,$BX14,IF(AI$8=$BY$9,$BY14,IF(AI$8=$BZ$9,$BZ14,IF(AI$8=$CA$9,$CA14,IF(AI$8=$CC$9,$CC14,IF(AI$8=$CD$9,$CD14,IF(AI$8=$CE$9,$CE14,IF(AI$8=$CF$9,$CF14,IF(AI$8=$CG$9,$CG14,IF(AI$8=$CH$9,$CH14,IF(AI$8=$CI$9,$CI14,IF(AI$8=$CJ$9,$CJ14,IF(AI$8=$CK$9,$CK14,IF(AI$8=$CL$9,$CL14,IF(AI$8=$CM$9,$CM14,IF(AI$8=$CN$9,$CN14,IF(AI$8=$CO$9,$CO14,IF(AI$8=$CP$9,$CP14,IF(AI$8=$CQ$9,$CQ14,"НЕТ")))))))))))))))))))))))) -> НЕТ | AJ14: =IF(AJ$8=$BT$9,$BT14,IF(AJ$8=$BS$9,$BS14,IF(AJ$8=$BU$9,$BU14,IF(AJ$8=$BV$9,$BV14,IF(AJ$8=$BW$9,$BW14,IF(AJ$8=$BX$9,$BX14,IF(AJ$8=$BY$9,$BY14,IF(AJ$8=$BZ$9,$BZ14,IF(AJ$8=$CA$9,$CA14,IF(AJ$8=$CC$9,$CC14,IF(AJ$8=$CD$9,$CD14,IF(AJ$8=$CE$9,$CE14,IF(AJ$8=$CF$9,$CF14,IF(AJ$8=$CG$9,$CG14,IF(AJ$8=$CH$9,$CH14,IF(AJ$8=$CI$9,$CI14,IF(AJ$8=$CJ$9,$CJ14,IF(AJ$8=$CK$9,$CK14,IF(AJ$8=$CL$9,$CL14,IF(AJ$8=$CM$9,$CM14,IF(AJ$8=$CN$9,$CN14,IF(AJ$8=$CO$9,$CO14,IF(AJ$8=$CP$9,$CP14,IF(AJ$8=$CQ$9,$CQ14,"НЕТ")))))))))))))))))))))))) -> НЕТ | AK14: =IF(AK$8=$BT$9,$BT14,IF(AK$8=$BS$9,$BS14,IF(AK$8=$BU$9,$BU14,IF(AK$8=$BV$9,$BV14,IF(AK$8=$BW$9,$BW14,IF(AK$8=$BX$9,$BX14,IF(AK$8=$BY$9,$BY14,IF(AK$8=$BZ$9,$BZ14,IF(AK$8=$CA$9,$CA14,IF(AK$8=$CC$9,$CC14,IF(AK$8=$CD$9,$CD14,IF(AK$8=$CE$9,$CE14,IF(AK$8=$CF$9,$CF14,IF(AK$8=$CG$9,$CG14,IF(AK$8=$CH$9,$CH14,IF(AK$8=$CI$9,$CI14,IF(AK$8=$CJ$9,$CJ14,IF(AK$8=$CK$9,$CK14,IF(AK$8=$CL$9,$CL14,IF(AK$8=$CM$9,$CM14,IF(AK$8=$CN$9,$CN14,IF(AK$8=$CO$9,$CO14,IF(AK$8=$CP$9,$CP14,IF(AK$8=$CQ$9,$CQ14,"НЕТ")))))))))))))))))))))))) -> НЕТ | AL14: =IF(AL$8=$BT$9,$BT14,IF(AL$8=$BS$9,$BS14,IF(AL$8=$BU$9,$BU14,IF(AL$8=$BV$9,$BV14,IF(AL$8=$BW$9,$BW14,IF(AL$8=$BX$9,$BX14,IF(AL$8=$BY$9,$BY14,IF(AL$8=$BZ$9,$BZ14,IF(AL$8=$CA$9,$CA14,IF(AL$8=$CC$9,$CC14,IF(AL$8=$CD$9,$CD14,IF(AL$8=$CE$9,$CE14,IF(AL$8=$CF$9,$CF14,IF(AL$8=$CG$9,$CG14,IF(AL$8=$CH$9,$CH14,IF(AL$8=$CI$9,$CI14,IF(AL$8=$CJ$9,$CJ14,IF(AL$8=$CK$9,$CK14,IF(AL$8=$CL$9,$CL14,IF(AL$8=$CM$9,$CM14,IF(AL$8=$CN$9,$CN14,IF(AL$8=$CO$9,$CO14,IF(AL$8=$CP$9,$CP14,IF(AL$8=$CQ$9,$CQ14,"НЕТ")))))))))))))))))))))))) -> НЕТ | AM14: =IF(AL14="НЕТ","Не требуется",$CR14) -> Не требуется | AS14: =IF(BS14="ДА",$M14,"") -> 1 | AT14: =IF(BT14="ДА",$M14,"") -> 1 | AU14: =IF(BU14="ДА",$M14,"") -> 1 | AV14: =IF(BV14="ДА",$M14,"") | AW14: =IF(BX14="ДА",$M14,"") -> 1 | AX14: =IF(BY14="ДА",$M14,"") -> 1 | AY14: =IF(BZ14="ДА",$M14,"") -> 1 | AZ14: =IF(CA14="ДА",$M14,"") -> 1 | BB14: =IF(CC14="ДА",$M14,"") -> 1 | BC14: =IF(CD14="ДА",$M14,"") -> 1 | BD14: =IF(CE14="ДА",$M14,"") -> 1 | BE14: =IF(CF14="ДА",$M14,"") -> 1 | BF14: =IF(CG14="ДА",$M14,"") | BG14: =IF(CH14="ДА",$M14,"") -> 1 | BH14: =IF(CI14="ДА",$M14,"") -> 1 | BI14: =IF(CJ14="ДА",$M14,"") | ... BP14: =IF(CQ14="ДА",$M14,"") | BS14: ДА | BT14: ДА | BU14: ДА | BV14: НЕТ | BW14: ДА | BX14: ДА | BY14: ДА | BZ14: ДА | CA14: ДА | CC14: ДА | CD14: ДА | CE14: ДА | CF14: ДА | CG14: НЕТ | CH14: ДА | CI14: ДА | CJ14: НЕТ | CK14: ДА | CL14: ДА | CM14: ДА | CN14: НЕТ | CO14: НЕТ | CP14: НЕТ | CQ14: НЕТ | CR14: Не требуется
B15: Анализ загрузки подразделений и специальностей по задачам производственной программы | C15: Как в РМ4 нет, но есть табличный редактор. Текущая реализация - очень неудобная. Технология ПРОФ-мини. С помощью настройки табличного редактора (выбрав подразделение операции или ресурса) | N15: =SUM(O15,R15,U15,X15) -> 0
B16: Ручное выравнивание загрузки подразделений по задачам портфеля проектов в т.ч. С помощью документа "Прогноз трудозатрат по ролям" | C16: Как в РМ4 нет, но есть табличный редактор. Текущая реализация - очень неудобная. Технология ПРОФ-мини. С помощью настройки табличного редактора (выбрав подразделение операции или ресурса) | N16: =SUM(O16,R16,U16,X16) -> 0
A17: 1.3. | B17: Расчет цены контракта (Возможно включение в Кейс с увеличением стоимости) Нужно зафиксировать сценарий в материалах Кейса | C17: Нет | F17: Проф | G17: Проф/мини | H17: Нет | I17: Нет | J17: Да | K17: Да | L17: Под проект | M17: 2 | N17: =SUM(O17,R17,U17,X17) -> 2 | O17: =IF(AC17="ДА",$M17,"") | Q17: =IF(AC17="ДА",ROUNDUP(O17/5,0),0) -> 0 | R17: =IF(AF17="ДА",$M17,"") -> 2 | T17: =IF(AF17="ДА",ROUNDUP(R17/5,0),0) -> 1 | U17: =IF(AI17="ДА",$M17,"") | W17: =IF(AI17="ДА",ROUNDUP(U17/5,0),0) -> 0 | X17: =IF(AL17="ДА",$M17,"") | Z17: =IF(AL17="ДА",ROUNDUP(X17/5,0),0) -> 0 | AA17: =IF(OR(AC17="ДА",AF17="ДА",AI17="ДА",AL17="ДА"),"ДА","НЕТ") -> ДА | AC17: =IF(AC$8=$BT$9,$BT17,IF(AC$8=$BS$9,$BS17,IF(AC$8=$BU$9,$BU17,IF(AC$8=$BV$9,$BV17,IF(AC$8=$BW$9,$BW17,IF(AC$8=$BX$9,$BX17,IF(AC$8=$BY$9,$BY17,IF(AC$8=$BZ$9,$BZ17,IF(AC$8=$CA$9,$CA17,IF(AC$8=$CC$9,$CC17,IF(AC$8=$CD$9,$CD17,IF(AC$8=$CE$9,$CE17,IF(AC$8=$CF$9,$CF17,IF(AC$8=$CG$9,$CG17,IF(AC$8=$CH$9,$CH17,IF(AC$8=$CI$9,$CI17,IF(AC$8=$CJ$9,$CJ17,IF(AC$8=$CK$9,$CK17,IF(AC$8=$CL$9,$CL17,IF(AC$8=$CM$9,$CM17,IF(AC$8=$CN$9,$CN17,IF(AC$8=$CO$9,$CO17,IF(AC$8=$CP$9,$CP17,IF(AC$8=$CQ$9,$CQ17,"НЕТ")))))))))))))))))))))))) -> НЕТ | AD17: =IF(AC17="НЕТ","Не требуется",$CR17) -> Не требуется | AF17: =IF(AF$8=$BT$9,$BT17,IF(AF$8=$BS$9,$BS17,IF(AF$8=$BU$9,$BU17,IF(AF$8=$BV$9,$BV17,IF(AF$8=$BW$9,$BW17,IF(AF$8=$BX$9,$BX17,IF(AF$8=$BY$9,$BY17,IF(AF$8=$BZ$9,$BZ17,IF(AF$8=$CA$9,$CA17,IF(AF$8=$CC$9,$CC17,IF(AF$8=$CD$9,$CD17,IF(AF$8=$CE$9,$CE17,IF(AF$8=$CF$9,$CF17,IF(AF$8=$CG$9,$CG17,IF(AF$8=$CH$9,$CH17,IF(AF$8=$CI$9,$CI17,IF(AF$8=$CJ$9,$CJ17,IF(AF$8=$CK$9,$CK17,IF(AF$8=$CL$9,$CL17,IF(AF$8=$CM$9,$CM17,IF(AF$8=$CN$9,$CN17,IF(AF$8=$CO$9,$CO17,IF(AF$8=$CP$9,$CP17,IF(AF$8=$CQ$9,$CQ17,"НЕТ")))))))))))))))))))))))) -> ДА | AG17: =IF(AG$8=$BT$9,$BT17,IF(AG$8=$BS$9,$BS17,IF(AG$8=$BU$9,$BU17,IF(AG$8=$BV$9,$BV17,IF(AG$8=$BW$9,$BW17,IF(AG$8=$BX$9,$BX17,IF(AG$8=$BY$9,$BY17,IF(AG$8=$BZ$9,$BZ17,IF(AG$8=$CA$9,$CA17,IF(AG$8=$CC$9,$CC17,IF(AG$8=$CD$9,$CD17,IF(AG$8=$CE$9,$CE17,IF(AG$8=$CF$9,$CF17,IF(AG$8=$CG$9,$CG17,IF(AG$8=$CH$9,$CH17,IF(AG$8=$CI$9,$CI17,IF(AG$8=$CJ$9,$CJ17,IF(AG$8=$CK$9,$CK17,IF(AG$8=$CL$9,$CL17,IF(AG$8=$CM$9,$CM17,IF(AG$8=$CN$9,$CN17,IF(AG$8=$CO$9,$CO17,IF(AG$8=$CP$9,$CP17,IF(AG$8=$CQ$9,$CQ17,"НЕТ")))))))))))))))))))))))) -> НЕТ | AH17: =IF(AH$8=$BT$9,$BT17,IF(AH$8=$BS$9,$BS17,IF(AH$8=$BU$9,$BU17,IF(AH$8=$BV$9,$BV17,IF(AH$8=$BW$9,$BW17,IF(AH$8=$BX$9,$BX17,IF(AH$8=$BY$9,$BY17,IF(AH$8=$BZ$9,$BZ17,IF(AH$8=$CA$9,$CA17,IF(AH$8=$CC$9,$CC17,IF(AH$8=$CD$9,$CD17,IF(AH$8=$CE$9,$CE17,IF(AH$8=$CF$9,$CF17,IF(AH$8=$CG$9,$CG17,IF(AH$8=$CH$9,$CH17,IF(AH$8=$CI$9,$CI17,IF(AH$8=$CJ$9,$CJ17,IF(AH$8=$CK$9,$CK17,IF(AH$8=$CL$9,$CL17,IF(AH$8=$CM$9,$CM17,IF(AH$8=$CN$9,$CN17,IF(AH$8=$CO$9,$CO17,IF(AH$8=$CP$9,$CP17,IF(AH$8=$CQ$9,$CQ17,"НЕТ")))))))))))))))))))))))) -> НЕТ | AI17: =IF(AI$8=$BT$9,$BT17,IF(AI$8=$BS$9,$BS17,IF(AI$8=$BU$9,$BU17,IF(AI$8=$BV$9,$BV17,IF(AI$8=$BW$9,$BW17,IF(AI$8=$BX$9,$BX17,IF(AI$8=$BY$9,$BY17,IF(AI$8=$BZ$9,$BZ17,IF(AI$8=$CA$9,$CA17,IF(AI$8=$CC$9,$CC17,IF(AI$8=$CD$9,$CD17,IF(AI$8=$CE$9,$CE17,IF(AI$8=$CF$9,$CF17,IF(AI$8=$CG$9,$CG17,IF(AI$8=$CH$9,$CH17,IF(AI$8=$CI$9,$CI17,IF(AI$8=$CJ$9,$CJ17,IF(AI$8=$CK$9,$CK17,IF(AI$8=$CL$9,$CL17,IF(AI$8=$CM$9,$CM17,IF(AI$8=$CN$9,$CN17,IF(AI$8=$CO$9,$CO17,IF(AI$8=$CP$9,$CP17,IF(AI$8=$CQ$9,$CQ17,"НЕТ")))))))))))))))))))))))) -> НЕТ | AJ17: =IF(AJ$8=$BT$9,$BT17,IF(AJ$8=$BS$9,$BS17,IF(AJ$8=$BU$9,$BU17,IF(AJ$8=$BV$9,$BV17,IF(AJ$8=$BW$9,$BW17,IF(AJ$8=$BX$9,$BX17,IF(AJ$8=$BY$9,$BY17,IF(AJ$8=$BZ$9,$BZ17,IF(AJ$8=$CA$9,$CA17,IF(AJ$8=$CC$9,$CC17,IF(AJ$8=$CD$9,$CD17,IF(AJ$8=$CE$9,$CE17,IF(AJ$8=$CF$9,$CF17,IF(AJ$8=$CG$9,$CG17,IF(AJ$8=$CH$9,$CH17,IF(AJ$8=$CI$9,$CI17,IF(AJ$8=$CJ$9,$CJ17,IF(AJ$8=$CK$9,$CK17,IF(AJ$8=$CL$9,$CL17,IF(AJ$8=$CM$9,$CM17,IF(AJ$8=$CN$9,$CN17,IF(AJ$8=$CO$9,$CO17,IF(AJ$8=$CP$9,$CP17,IF(AJ$8=$CQ$9,$CQ17,"НЕТ")))))))))))))))))))))))) -> НЕТ | AK17: =IF(AK$8=$BT$9,$BT17,IF(AK$8=$BS$9,$BS17,IF(AK$8=$BU$9,$BU17,IF(AK$8=$BV$9,$BV17,IF(AK$8=$BW$9,$BW17,IF(AK$8=$BX$9,$BX17,IF(AK$8=$BY$9,$BY17,IF(AK$8=$BZ$9,$BZ17,IF(AK$8=$CA$9,$CA17,IF(AK$8=$CC$9,$CC17,IF(AK$8=$CD$9,$CD17,IF(AK$8=$CE$9,$CE17,IF(AK$8=$CF$9,$CF17,IF(AK$8=$CG$9,$CG17,IF(AK$8=$CH$9,$CH17,IF(AK$8=$CI$9,$CI17,IF(AK$8=$CJ$9,$CJ17,IF(AK$8=$CK$9,$CK17,IF(AK$8=$CL$9,$CL17,IF(AK$8=$CM$9,$CM17,IF(AK$8=$CN$9,$CN17,IF(AK$8=$CO$9,$CO17,IF(AK$8=$CP$9,$CP17,IF(AK$8=$CQ$9,$CQ17,"НЕТ")))))))))))))))))))))))) -> НЕТ | AL17: =IF(AL$8=$BT$9,$BT17,IF(AL$8=$BS$9,$BS17,IF(AL$8=$BU$9,$BU17,IF(AL$8=$BV$9,$BV17,IF(AL$8=$BW$9,$BW17,IF(AL$8=$BX$9,$BX17,IF(AL$8=$BY$9,$BY17,IF(AL$8=$BZ$9,$BZ17,IF(AL$8=$CA$9,$CA17,IF(AL$8=$CC$9,$CC17,IF(AL$8=$CD$9,$CD17,IF(AL$8=$CE$9,$CE17,IF(AL$8=$CF$9,$CF17,IF(AL$8=$CG$9,$CG17,IF(AL$8=$CH$9,$CH17,IF(AL$8=$CI$9,$CI17,IF(AL$8=$CJ$9,$CJ17,IF(AL$8=$CK$9,$CK17,IF(AL$8=$CL$9,$CL17,IF(AL$8=$CM$9,$CM17,IF(AL$8=$CN$9,$CN17,IF(AL$8=$CO$9,$CO17,IF(AL$8=$CP$9,$CP17,IF(AL$8=$CQ$9,$CQ17,"НЕТ")))))))))))))))))))))))) -> НЕТ | AM17: =IF(AL17="НЕТ","Не требуется",$CR17) -> Не требуется | AS17: =IF(BT17="ДА",$M17,"") | AT17: =IF(BU17="ДА",$M17,"") | AU17: =IF(BV17="ДА",$M17,"") | AV17: =IF(BW17="ДА",$M17,"") | AW17: =IF(BX17="ДА",$M17,"") -> 2 | AX17: =IF(BY17="ДА",$M17,"") -> 2 | AY17: =IF(BZ17="ДА",$M17,"") -> 2 | AZ17: =IF(CA17="ДА",$M17,"") -> 2 | BB17: =IF(CC17="ДА",$M17,"") | BC17: =IF(CD17="ДА",$M17,"") | BD17: =IF(CE17="ДА",$M17,"") | BE17: =IF(CF17="ДА",$M17,"") | BF17: =IF(CG17="ДА",$M17,"") | BG17: =IF(CH17="ДА",$M17,"") | BH17: =IF(CI17="ДА",$M17,"") | BI17: =IF(CJ17="ДА",$M17,"") | ... BP17: =IF(CQ17="ДА",$M17,"") | BS17: НЕТ | BT17: НЕТ | BU17: НЕТ | BV17: НЕТ | BW17: НЕТ | BX17: ДА | BY17: ДА | BZ17: ДА | CA17: ДА | CC17: НЕТ | CD17: НЕТ | CE17: НЕТ | CF17: НЕТ | CG17: НЕТ | CH17: НЕТ | CI17: НЕТ | CJ17: НЕТ | CK17: НЕТ | CL17: НЕТ | CM17: ДА | CN17: НЕТ | CO17: НЕТ | CP17: НЕТ | CQ17: НЕТ | CR17: Предоставляется Заказчиком
B18: Расчет цены контракта | C18: Нет | N18: =SUM(O18,R18,U18,X18) -> 0
B19: Планирование и мониторинг процесса продажи как проекта | C19: Нет | N19: =SUM(O19,R19,U19,X19) -> 0
A20: 1.4. | B20: Моделирование инвест. портфеля. Ранжирование заявок на проекты. | C20: Нет | F20: Проф | G20: КОРП-проект | H20: Нет | I20: Нет | J20: Да | K20: Да | L20: Под проект | M20: 8 | N20: =SUM(O20,R20,U20,X20) -> 8 | O20: =IF(AC20="ДА",$M20,"") | Q20: =IF(AC20="ДА",ROUNDUP(O20/5,0),0) -> 0 | R20: =IF(AF20="ДА",$M20,"") -> 8 | T20: =IF(AF20="ДА",ROUNDUP(R20/5,0),0) -> 2 | U20: =IF(AI20="ДА",$M20,"") | W20: =IF(AI20="ДА",ROUNDUP(U20/5,0),0) -> 0 | X20: =IF(AL20="ДА",$M20,"") | Z20: =IF(AL20="ДА",ROUNDUP(X20/5,0),0) -> 0 | AA20: =IF(OR(AC20="ДА",AF20="ДА",AI20="ДА",AL20="ДА"),"ДА","НЕТ") -> ДА | AC20: =IF(AC$8=$BT$9,$BT20,IF(AC$8=$BS$9,$BS20,IF(AC$8=$BU$9,$BU20,IF(AC$8=$BV$9,$BV20,IF(AC$8=$BW$9,$BW20,IF(AC$8=$BX$9,$BX20,IF(AC$8=$BY$9,$BY20,IF(AC$8=$BZ$9,$BZ20,IF(AC$8=$CA$9,$CA20,IF(AC$8=$CC$9,$CC20,IF(AC$8=$CD$9,$CD20,IF(AC$8=$CE$9,$CE20,IF(AC$8=$CF$9,$CF20,IF(AC$8=$CG$9,$CG20,IF(AC$8=$CH$9,$CH20,IF(AC$8=$CI$9,$CI20,IF(AC$8=$CJ$9,$CJ20,IF(AC$8=$CK$9,$CK20,IF(AC$8=$CL$9,$CL20,IF(AC$8=$CM$9,$CM20,IF(AC$8=$CN$9,$CN20,IF(AC$8=$CO$9,$CO20,IF(AC$8=$CP$9,$CP20,IF(AC$8=$CQ$9,$CQ20,"НЕТ")))))))))))))))))))))))) -> НЕТ | AD20: =IF(AC20="НЕТ","Не требуется",$CR20) -> Не требуется | AF20: =IF(AF$8=$BT$9,$BT20,IF(AF$8=$BS$9,$BS20,IF(AF$8=$BU$9,$BU20,IF(AF$8=$BV$9,$BV20,IF(AF$8=$BW$9,$BW20,IF(AF$8=$BX$9,$BX20,IF(AF$8=$BY$9,$BY20,IF(AF$8=$BZ$9,$BZ20,IF(AF$8=$CA$9,$CA20,IF(AF$8=$CC$9,$CC20,IF(AF$8=$CD$9,$CD20,IF(AF$8=$CE$9,$CE20,IF(AF$8=$CF$9,$CF20,IF(AF$8=$CG$9,$CG20,IF(AF$8=$CH$9,$CH20,IF(AF$8=$CI$9,$CI20,IF(AF$8=$CJ$9,$CJ20,IF(AF$8=$CK$9,$CK20,IF(AF$8=$CL$9,$CL20,IF(AF$8=$CM$9,$CM20,IF(AF$8=$CN$9,$CN20,IF(AF$8=$CO$9,$CO20,IF(AF$8=$CP$9,$CP20,IF(AF$8=$CQ$9,$CQ20,"НЕТ")))))))))))))))))))))))) -> ДА | AG20: =IF(AG$8=$BT$9,$BT20,IF(AG$8=$BS$9,$BS20,IF(AG$8=$BU$9,$BU20,IF(AG$8=$BV$9,$BV20,IF(AG$8=$BW$9,$BW20,IF(AG$8=$BX$9,$BX20,IF(AG$8=$BY$9,$BY20,IF(AG$8=$BZ$9,$BZ20,IF(AG$8=$CA$9,$CA20,IF(AG$8=$CC$9,$CC20,IF(AG$8=$CD$9,$CD20,IF(AG$8=$CE$9,$CE20,IF(AG$8=$CF$9,$CF20,IF(AG$8=$CG$9,$CG20,IF(AG$8=$CH$9,$CH20,IF(AG$8=$CI$9,$CI20,IF(AG$8=$CJ$9,$CJ20,IF(AG$8=$CK$9,$CK20,IF(AG$8=$CL$9,$CL20,IF(AG$8=$CM$9,$CM20,IF(AG$8=$CN$9,$CN20,IF(AG$8=$CO$9,$CO20,IF(AG$8=$CP$9,$CP20,IF(AG$8=$CQ$9,$CQ20,"НЕТ")))))))))))))))))))))))) -> НЕТ | AH20: =IF(AH$8=$BT$9,$BT20,IF(AH$8=$BS$9,$BS20,IF(AH$8=$BU$9,$BU20,IF(AH$8=$BV$9,$BV20,IF(AH$8=$BW$9,$BW20,IF(AH$8=$BX$9,$BX20,IF(AH$8=$BY$9,$BY20,IF(AH$8=$BZ$9,$BZ20,IF(AH$8=$CA$9,$CA20,IF(AH$8=$CC$9,$CC20,IF(AH$8=$CD$9,$CD20,IF(AH$8=$CE$9,$CE20,IF(AH$8=$CF$9,$CF20,IF(AH$8=$CG$9,$CG20,IF(AH$8=$CH$9,$CH20,IF(AH$8=$CI$9,$CI20,IF(AH$8=$CJ$9,$CJ20,IF(AH$8=$CK$9,$CK20,IF(AH$8=$CL$9,$CL20,IF(AH$8=$CM$9,$CM20,IF(AH$8=$CN$9,$CN20,IF(AH$8=$CO$9,$CO20,IF(AH$8=$CP$9,$CP20,IF(AH$8=$CQ$9,$CQ20,"НЕТ")))))))))))))))))))))))) -> НЕТ | AI20: =IF(AI$8=$BT$9,$BT20,IF(AI$8=$BS$9,$BS20,IF(AI$8=$BU$9,$BU20,IF(AI$8=$BV$9,$BV20,IF(AI$8=$BW$9,$BW20,IF(AI$8=$BX$9,$BX20,IF(AI$8=$BY$9,$BY20,IF(AI$8=$BZ$9,$BZ20,IF(AI$8=$CA$9,$CA20,IF(AI$8=$CC$9,$CC20,IF(AI$8=$CD$9,$CD20,IF(AI$8=$CE$9,$CE20,IF(AI$8=$CF$9,$CF20,IF(AI$8=$CG$9,$CG20,IF(AI$8=$CH$9,$CH20,IF(AI$8=$CI$9,$CI20,IF(AI$8=$CJ$9,$CJ20,IF(AI$8=$CK$9,$CK20,IF(AI$8=$CL$9,$CL20,IF(AI$8=$CM$9,$CM20,IF(AI$8=$CN$9,$CN20,IF(AI$8=$CO$9,$CO20,IF(AI$8=$CP$9,$CP20,IF(AI$8=$CQ$9,$CQ20,"НЕТ")))))))))))))))))))))))) -> НЕТ | AJ20: =IF(AJ$8=$BT$9,$BT20,IF(AJ$8=$BS$9,$BS20,IF(AJ$8=$BU$9,$BU20,IF(AJ$8=$BV$9,$BV20,IF(AJ$8=$BW$9,$BW20,IF(AJ$8=$BX$9,$BX20,IF(AJ$8=$BY$9,$BY20,IF(AJ$8=$BZ$9,$BZ20,IF(AJ$8=$CA$9,$CA20,IF(AJ$8=$CC$9,$CC20,IF(AJ$8=$CD$9,$CD20,IF(AJ$8=$CE$9,$CE20,IF(AJ$8=$CF$9,$CF20,IF(AJ$8=$CG$9,$CG20,IF(AJ$8=$CH$9,$CH20,IF(AJ$8=$CI$9,$CI20,IF(AJ$8=$CJ$9,$CJ20,IF(AJ$8=$CK$9,$CK20,IF(AJ$8=$CL$9,$CL20,IF(AJ$8=$CM$9,$CM20,IF(AJ$8=$CN$9,$CN20,IF(AJ$8=$CO$9,$CO20,IF(AJ$8=$CP$9,$CP20,IF(AJ$8=$CQ$9,$CQ20,"НЕТ")))))))))))))))))))))))) -> НЕТ | AK20: =IF(AK$8=$BT$9,$BT20,IF(AK$8=$BS$9,$BS20,IF(AK$8=$BU$9,$BU20,IF(AK$8=$BV$9,$BV20,IF(AK$8=$BW$9,$BW20,IF(AK$8=$BX$9,$BX20,IF(AK$8=$BY$9,$BY20,IF(AK$8=$BZ$9,$BZ20,IF(AK$8=$CA$9,$CA20,IF(AK$8=$CC$9,$CC20,IF(AK$8=$CD$9,$CD20,IF(AK$8=$CE$9,$CE20,IF(AK$8=$CF$9,$CF20,IF(AK$8=$CG$9,$CG20,IF(AK$8=$CH$9,$CH20,IF(AK$8=$CI$9,$CI20,IF(AK$8=$CJ$9,$CJ20,IF(AK$8=$CK$9,$CK20,IF(AK$8=$CL$9,$CL20,IF(AK$8=$CM$9,$CM20,IF(AK$8=$CN$9,$CN20,IF(AK$8=$CO$9,$CO20,IF(AK$8=$CP$9,$CP20,IF(AK$8=$CQ$9,$CQ20,"НЕТ")))))))))))))))))))))))) -> НЕТ | AL20: =IF(AL$8=$BT$9,$BT20,IF(AL$8=$BS$9,$BS20,IF(AL$8=$BU$9,$BU20,IF(AL$8=$BV$9,$BV20,IF(AL$8=$BW$9,$BW20,IF(AL$8=$BX$9,$BX20,IF(AL$8=$BY$9,$BY20,IF(AL$8=$BZ$9,$BZ20,IF(AL$8=$CA$9,$CA20,IF(AL$8=$CC$9,$CC20,IF(AL$8=$CD$9,$CD20,IF(AL$8=$CE$9,$CE20,IF(AL$8=$CF$9,$CF20,IF(AL$8=$CG$9,$CG20,IF(AL$8=$CH$9,$CH20,IF(AL$8=$CI$9,$CI20,IF(AL$8=$CJ$9,$CJ20,IF(AL$8=$CK$9,$CK20,IF(AL$8=$CL$9,$CL20,IF(AL$8=$CM$9,$CM20,IF(AL$8=$CN$9,$CN20,IF(AL$8=$CO$9,$CO20,IF(AL$8=$CP$9,$CP20,IF(AL$8=$CQ$9,$CQ20,"НЕТ")))))))))))))))))))))))) -> НЕТ | AM20: =IF(AL20="НЕТ","Не требуется",$CR20) -> Не требуется | AS20: =IF(BS20="ДА",$M20,"") | AT20: =IF(BT20="ДА",$M20,"") | AU20: =IF(BU20="ДА",$M20,"") | AV20: =IF(BV20="ДА",$M20,"") | AW20: =IF(BX20="ДА",$M20,"") | AX20: =IF(BY20="ДА",$M20,"") | AY20: =IF(BZ20="ДА",$M20,"") -> 8 | AZ20: =IF(CA20="ДА",$M20,"") -> 8 | BB20: =IF(CC20="ДА",$M20,"") | BC20: =IF(CD20="ДА",$M20,"") | BD20: =IF(CE20="ДА",$M20,"") | BE20: =IF(CF20="ДА",$M20,"") | BF20: =IF(CG20="ДА",$M20,"") | BG20: =IF(CH20="ДА",$M20,"") -> 8 | BH20: =IF(CI20="ДА",$M20,"") -> 8 | BI20: =IF(CJ20="ДА",$M20,"") | ... BP20: =IF(CQ20="ДА",$M20,"") | BS20: НЕТ | BT20: НЕТ | BU20: НЕТ | BV20: НЕТ | BW20: НЕТ | BX20: НЕТ | BY20: НЕТ | BZ20: ДА | CA20: ДА | CC20: НЕТ | CD20: НЕТ | CE20: НЕТ | CF20: НЕТ | CG20: НЕТ | CH20: ДА | CI20: ДА | CJ20: НЕТ | CK20: ДА | CL20: ДА | CM20: НЕТ | CN20: НЕТ | CO20: НЕТ | CP20: НЕТ | CQ20: НЕТ | CR20: Предоставляется Заказчиком
B21: Формирование заявок на проект. Мониторинг состояния заявок. | C21: нет | N21: =SUM(O21,R21,U21,X21) -> 0
B22: Регистрация значений показателей эффективности проектов (Внутренняя ставка доходности, срок окупаемости, индекс прибыльности, чистый денежный поток, чистая приведенная стоимость) | C22: нет | N22: =SUM(O22,R22,U22,X22) -> 0
B23: Оценка соответствия портфеля инвестиционных проектов стратегическим целям компании | C23: нет | N23: =SUM(O23,R23,U23,X23) -> 0
B24: Расчет итогового балла проектов | C24: нет | N24: =SUM(O24,R24,U24,X24) -> 0
B25: Ранжирование проектов по показателям эффективности и формирование бизнес плана по портфелю проектов. | C25: нет | N25: =SUM(O25,R25,U25,X25) -> 0
B26: Формирование портфеля инвестиционных проектов (проекта с компонентой "Портфель проектов") | C26: нет | N26: =SUM(O26,R26,U26,X26) -> 0
A27: 1.5. | B27: Мониторинг договорной кампании | F27: Базовый | G27: Кейс-проект | H27: Да | I27: Да | J27: Да | K27: Да | L27: В разработке | M27: 2 | N27: =SUM(O27,R27,U27,X27) -> 6 | O27: =IF(AC27="ДА",$M27,"") -> 2 | Q27: =IF(AC27="ДА",ROUNDUP(O27/5,0),0) -> 1 | R27: =IF(AF27="ДА",$M27,"") -> 2 | T27: =IF(AF27="ДА",ROUNDUP(R27/5,0),0) -> 1 | U27: =IF(AI27="ДА",$M27,"") -> 2 | W27: =IF(AI27="ДА",ROUNDUP(U27/5,0),0) -> 1 | X27: =IF(AL27="ДА",$M27,"") | Z27: =IF(AL27="ДА",ROUNDUP(X27/5,0),0) -> 0 | AA27: =IF(OR(AC27="ДА",AF27="ДА",AI27="ДА",AL27="ДА"),"ДА","НЕТ") -> ДА | AC27: =IF(AC$8=$BT$9,$BT27,IF(AC$8=$BS$9,$BS27,IF(AC$8=$BU$9,$BU27,IF(AC$8=$BV$9,$BV27,IF(AC$8=$BW$9,$BW27,IF(AC$8=$BX$9,$BX27,IF(AC$8=$BY$9,$BY27,IF(AC$8=$BZ$9,$BZ27,IF(AC$8=$CA$9,$CA27,IF(AC$8=$CC$9,$CC27,IF(AC$8=$CD$9,$CD27,IF(AC$8=$CE$9,$CE27,IF(AC$8=$CF$9,$CF27,IF(AC$8=$CG$9,$CG27,IF(AC$8=$CH$9,$CH27,IF(AC$8=$CI$9,$CI27,IF(AC$8=$CJ$9,$CJ27,IF(AC$8=$CK$9,$CK27,IF(AC$8=$CL$9,$CL27,IF(AC$8=$CM$9,$CM27,IF(AC$8=$CN$9,$CN27,IF(AC$8=$CO$9,$CO27,IF(AC$8=$CP$9,$CP27,IF(AC$8=$CQ$9,$CQ27,"НЕТ")))))))))))))))))))))))) -> ДА | AD27: =IF(AC27="НЕТ","Не требуется",$CR27) -> Предоставляется Заказчиком | AF27: =IF(AF$8=$BT$9,$BT27,IF(AF$8=$BS$9,$BS27,IF(AF$8=$BU$9,$BU27,IF(AF$8=$BV$9,$BV27,IF(AF$8=$BW$9,$BW27,IF(AF$8=$BX$9,$BX27,IF(AF$8=$BY$9,$BY27,IF(AF$8=$BZ$9,$BZ27,IF(AF$8=$CA$9,$CA27,IF(AF$8=$CC$9,$CC27,IF(AF$8=$CD$9,$CD27,IF(AF$8=$CE$9,$CE27,IF(AF$8=$CF$9,$CF27,IF(AF$8=$CG$9,$CG27,IF(AF$8=$CH$9,$CH27,IF(AF$8=$CI$9,$CI27,IF(AF$8=$CJ$9,$CJ27,IF(AF$8=$CK$9,$CK27,IF(AF$8=$CL$9,$CL27,IF(AF$8=$CM$9,$CM27,IF(AF$8=$CN$9,$CN27,IF(AF$8=$CO$9,$CO27,IF(AF$8=$CP$9,$CP27,IF(AF$8=$CQ$9,$CQ27,"НЕТ")))))))))))))))))))))))) -> ДА | AG27: =IF(AG$8=$BT$9,$BT27,IF(AG$8=$BS$9,$BS27,IF(AG$8=$BU$9,$BU27,IF(AG$8=$BV$9,$BV27,IF(AG$8=$BW$9,$BW27,IF(AG$8=$BX$9,$BX27,IF(AG$8=$BY$9,$BY27,IF(AG$8=$BZ$9,$BZ27,IF(AG$8=$CA$9,$CA27,IF(AG$8=$CC$9,$CC27,IF(AG$8=$CD$9,$CD27,IF(AG$8=$CE$9,$CE27,IF(AG$8=$CF$9,$CF27,IF(AG$8=$CG$9,$CG27,IF(AG$8=$CH$9,$CH27,IF(AG$8=$CI$9,$CI27,IF(AG$8=$CJ$9,$CJ27,IF(AG$8=$CK$9,$CK27,IF(AG$8=$CL$9,$CL27,IF(AG$8=$CM$9,$CM27,IF(AG$8=$CN$9,$CN27,IF(AG$8=$CO$9,$CO27,IF(AG$8=$CP$9,$CP27,IF(AG$8=$CQ$9,$CQ27,"НЕТ")))))))))))))))))))))))) -> НЕТ | AH27: =IF(AH$8=$BT$9,$BT27,IF(AH$8=$BS$9,$BS27,IF(AH$8=$BU$9,$BU27,IF(AH$8=$BV$9,$BV27,IF(AH$8=$BW$9,$BW27,IF(AH$8=$BX$9,$BX27,IF(AH$8=$BY$9,$BY27,IF(AH$8=$BZ$9,$BZ27,IF(AH$8=$CA$9,$CA27,IF(AH$8=$CC$9,$CC27,IF(AH$8=$CD$9,$CD27,IF(AH$8=$CE$9,$CE27,IF(AH$8=$CF$9,$CF27,IF(AH$8=$CG$9,$CG27,IF(AH$8=$CH$9,$CH27,IF(AH$8=$CI$9,$CI27,IF(AH$8=$CJ$9,$CJ27,IF(AH$8=$CK$9,$CK27,IF(AH$8=$CL$9,$CL27,IF(AH$8=$CM$9,$CM27,IF(AH$8=$CN$9,$CN27,IF(AH$8=$CO$9,$CO27,IF(AH$8=$CP$9,$CP27,IF(AH$8=$CQ$9,$CQ27,"НЕТ")))))))))))))))))))))))) -> НЕТ | AI27: =IF(AI$8=$BT$9,$BT27,IF(AI$8=$BS$9,$BS27,IF(AI$8=$BU$9,$BU27,IF(AI$8=$BV$9,$BV27,IF(AI$8=$BW$9,$BW27,IF(AI$8=$BX$9,$BX27,IF(AI$8=$BY$9,$BY27,IF(AI$8=$BZ$9,$BZ27,IF(AI$8=$CA$9,$CA27,IF(AI$8=$CC$9,$CC27,IF(AI$8=$CD$9,$CD27,IF(AI$8=$CE$9,$CE27,IF(AI$8=$CF$9,$CF27,IF(AI$8=$CG$9,$CG27,IF(AI$8=$CH$9,$CH27,IF(AI$8=$CI$9,$CI27,IF(AI$8=$CJ$9,$CJ27,IF(AI$8=$CK$9,$CK27,IF(AI$8=$CL$9,$CL27,IF(AI$8=$CM$9,$CM27,IF(AI$8=$CN$9,$CN27,IF(AI$8=$CO$9,$CO27,IF(AI$8=$CP$9,$CP27,IF(AI$8=$CQ$9,$CQ27,"НЕТ")))))))))))))))))))))))) -> ДА | AJ27: =IF(AJ$8=$BT$9,$BT27,IF(AJ$8=$BS$9,$BS27,IF(AJ$8=$BU$9,$BU27,IF(AJ$8=$BV$9,$BV27,IF(AJ$8=$BW$9,$BW27,IF(AJ$8=$BX$9,$BX27,IF(AJ$8=$BY$9,$BY27,IF(AJ$8=$BZ$9,$BZ27,IF(AJ$8=$CA$9,$CA27,IF(AJ$8=$CC$9,$CC27,IF(AJ$8=$CD$9,$CD27,IF(AJ$8=$CE$9,$CE27,IF(AJ$8=$CF$9,$CF27,IF(AJ$8=$CG$9,$CG27,IF(AJ$8=$CH$9,$CH27,IF(AJ$8=$CI$9,$CI27,IF(AJ$8=$CJ$9,$CJ27,IF(AJ$8=$CK$9,$CK27,IF(AJ$8=$CL$9,$CL27,IF(AJ$8=$CM$9,$CM27,IF(AJ$8=$CN$9,$CN27,IF(AJ$8=$CO$9,$CO27,IF(AJ$8=$CP$9,$CP27,IF(AJ$8=$CQ$9,$CQ27,"НЕТ")))))))))))))))))))))))) -> НЕТ | AK27: =IF(AK$8=$BT$9,$BT27,IF(AK$8=$BS$9,$BS27,IF(AK$8=$BU$9,$BU27,IF(AK$8=$BV$9,$BV27,IF(AK$8=$BW$9,$BW27,IF(AK$8=$BX$9,$BX27,IF(AK$8=$BY$9,$BY27,IF(AK$8=$BZ$9,$BZ27,IF(AK$8=$CA$9,$CA27,IF(AK$8=$CC$9,$CC27,IF(AK$8=$CD$9,$CD27,IF(AK$8=$CE$9,$CE27,IF(AK$8=$CF$9,$CF27,IF(AK$8=$CG$9,$CG27,IF(AK$8=$CH$9,$CH27,IF(AK$8=$CI$9,$CI27,IF(AK$8=$CJ$9,$CJ27,IF(AK$8=$CK$9,$CK27,IF(AK$8=$CL$9,$CL27,IF(AK$8=$CM$9,$CM27,IF(AK$8=$CN$9,$CN27,IF(AK$8=$CO$9,$CO27,IF(AK$8=$CP$9,$CP27,IF(AK$8=$CQ$9,$CQ27,"НЕТ")))))))))))))))))))))))) -> НЕТ | AL27: =IF(AL$8=$BT$9,$BT27,IF(AL$8=$BS$9,$BS27,IF(AL$8=$BU$9,$BU27,IF(AL$8=$BV$9,$BV27,IF(AL$8=$BW$9,$BW27,IF(AL$8=$BX$9,$BX27,IF(AL$8=$BY$9,$BY27,IF(AL$8=$BZ$9,$BZ27,IF(AL$8=$CA$9,$CA27,IF(AL$8=$CC$9,$CC27,IF(AL$8=$CD$9,$CD27,IF(AL$8=$CE$9,$CE27,IF(AL$8=$CF$9,$CF27,IF(AL$8=$CG$9,$CG27,IF(AL$8=$CH$9,$CH27,IF(AL$8=$CI$9,$CI27,IF(AL$8=$CJ$9,$CJ27,IF(AL$8=$CK$9,$CK27,IF(AL$8=$CL$9,$CL27,IF(AL$8=$CM$9,$CM27,IF(AL$8=$CN$9,$CN27,IF(AL$8=$CO$9,$CO27,IF(AL$8=$CP$9,$CP27,IF(AL$8=$CQ$9,$CQ27,"НЕТ")))))))))))))))))))))))) -> НЕТ | AM27: =IF(AL27="НЕТ","Не требуется",$CR27) -> Не требуется | AS27: =IF(BS27="ДА",$M27,"") -> 2 | AT27: =IF(BT27="ДА",$M27,"") -> 2 | AU27: =IF(BU27="ДА",$M27,"") -> 2 | AV27: =IF(BV27="ДА",$M27,"") -> 2 | AW27: =IF(BX27="ДА",$M27,"") -> 2 | AX27: =IF(BY27="ДА",$M27,"") -> 2 | AY27: =IF(BZ27="ДА",$M27,"") -> 2 | AZ27: =IF(CA27="ДА",$M27,"") -> 2 | BB27: =IF(CC27="ДА",$M27,"") -> 2 | BC27: =IF(CD27="ДА",$M27,"") -> 2 | BD27: =IF(CE27="ДА",$M27,"") | BE27: =IF(CF27="ДА",$M27,"") | BF27: =IF(CG27="ДА",$M27,"") | BG27: =IF(CH27="ДА",$M27,"") -> 2 | BH27: =IF(CI27="ДА",$M27,"") -> 2 | BI27: =IF(CJ27="ДА",$M27,"") | ... BP27: =IF(CQ27="ДА",$M27,"") | BS27: ДА | BT27: ДА | BU27: ДА | BV27: ДА | BW27: ДА | BX27: ДА | BY27: ДА | BZ27: ДА | CA27: ДА | CC27: ДА | CD27: ДА | CE27: НЕТ | CF27: НЕТ | CG27: НЕТ | CH27: ДА | CI27: ДА | CJ27: НЕТ | CK27: ДА | CL27: НЕТ | CM27: ДА | CN27: НЕТ | CO27: НЕТ | CP27: НЕТ | CQ27: НЕТ | CR27: Предоставляется Заказчиком
B28: Установка статуса договора в карточке договора вручную | C28: не нужно в сценарии. Можно поставить допреквизитом | N28: =SUM(O28,R28,U28,X28) -> 0
B29: Анализ тематического плана | N29: =SUM(O29,R29,U29,X29) -> 0
B30: Хранение файлов и отсканированных копий договора без использования 1С: Документооборот 8 | C30: Можно прикреплять файлы к объектам системы | N30: =SUM(O30,R30,U30,X30) -> 0
A31: 1.6. | B31: Мониторинг фаз проектов портфеля (Gate) | F31: Базовый | G31: Кейс-проект | H31: Нет | I31: Нет | J31: Да | K31: Да | L31: В разработке | M31: 1 | N31: =SUM(O31,R31,U31,X31) -> 1 | O31: =IF(AC31="ДА",$M31,"") | Q31: =IF(AC31="ДА",ROUNDUP(O31/5,0),0) -> 0 | R31: =IF(AF31="ДА",$M31,"") -> 1 | T31: =IF(AF31="ДА",ROUNDUP(R31/5,0),0) -> 1 | U31: =IF(AI31="ДА",$M31,"") | W31: =IF(AI31="ДА",ROUNDUP(U31/5,0),0) -> 0 | X31: =IF(AL31="ДА",$M31,"") | Z31: =IF(AL31="ДА",ROUNDUP(X31/5,0),0) -> 0 | AA31: =IF(OR(AC31="ДА",AF31="ДА",AI31="ДА",AL31="ДА"),"ДА","НЕТ") -> ДА | AC31: =IF(AC$8=$BT$9,$BT31,IF(AC$8=$BS$9,$BS31,IF(AC$8=$BU$9,$BU31,IF(AC$8=$BV$9,$BV31,IF(AC$8=$BW$9,$BW31,IF(AC$8=$BX$9,$BX31,IF(AC$8=$BY$9,$BY31,IF(AC$8=$BZ$9,$BZ31,IF(AC$8=$CA$9,$CA31,IF(AC$8=$CC$9,$CC31,IF(AC$8=$CD$9,$CD31,IF(AC$8=$CE$9,$CE31,IF(AC$8=$CF$9,$CF31,IF(AC$8=$CG$9,$CG31,IF(AC$8=$CH$9,$CH31,IF(AC$8=$CI$9,$CI31,IF(AC$8=$CJ$9,$CJ31,IF(AC$8=$CK$9,$CK31,IF(AC$8=$CL$9,$CL31,IF(AC$8=$CM$9,$CM31,IF(AC$8=$CN$9,$CN31,IF(AC$8=$CO$9,$CO31,IF(AC$8=$CP$9,$CP31,IF(AC$8=$CQ$9,$CQ31,"НЕТ")))))))))))))))))))))))) -> НЕТ | AD31: =IF(AC31="НЕТ","Не требуется",$CR31) -> Не требуется | AF31: =IF(AF$8=$BT$9,$BT31,IF(AF$8=$BS$9,$BS31,IF(AF$8=$BU$9,$BU31,IF(AF$8=$BV$9,$BV31,IF(AF$8=$BW$9,$BW31,IF(AF$8=$BX$9,$BX31,IF(AF$8=$BY$9,$BY31,IF(AF$8=$BZ$9,$BZ31,IF(AF$8=$CA$9,$CA31,IF(AF$8=$CC$9,$CC31,IF(AF$8=$CD$9,$CD31,IF(AF$8=$CE$9,$CE31,IF(AF$8=$CF$9,$CF31,IF(AF$8=$CG$9,$CG31,IF(AF$8=$CH$9,$CH31,IF(AF$8=$CI$9,$CI31,IF(AF$8=$CJ$9,$CJ31,IF(AF$8=$CK$9,$CK31,IF(AF$8=$CL$9,$CL31,IF(AF$8=$CM$9,$CM31,IF(AF$8=$CN$9,$CN31,IF(AF$8=$CO$9,$CO31,IF(AF$8=$CP$9,$CP31,IF(AF$8=$CQ$9,$CQ31,"НЕТ")))))))))))))))))))))))) -> ДА | AG31: =IF(AG$8=$BT$9,$BT31,IF(AG$8=$BS$9,$BS31,IF(AG$8=$BU$9,$BU31,IF(AG$8=$BV$9,$BV31,IF(AG$8=$BW$9,$BW31,IF(AG$8=$BX$9,$BX31,IF(AG$8=$BY$9,$BY31,IF(AG$8=$BZ$9,$BZ31,IF(AG$8=$CA$9,$CA31,IF(AG$8=$CC$9,$CC31,IF(AG$8=$CD$9,$CD31,IF(AG$8=$CE$9,$CE31,IF(AG$8=$CF$9,$CF31,IF(AG$8=$CG$9,$CG31,IF(AG$8=$CH$9,$CH31,IF(AG$8=$CI$9,$CI31,IF(AG$8=$CJ$9,$CJ31,IF(AG$8=$CK$9,$CK31,IF(AG$8=$CL$9,$CL31,IF(AG$8=$CM$9,$CM31,IF(AG$8=$CN$9,$CN31,IF(AG$8=$CO$9,$CO31,IF(AG$8=$CP$9,$CP31,IF(AG$8=$CQ$9,$CQ31,"НЕТ")))))))))))))))))))))))) -> НЕТ | AH31: =IF(AH$8=$BT$9,$BT31,IF(AH$8=$BS$9,$BS31,IF(AH$8=$BU$9,$BU31,IF(AH$8=$BV$9,$BV31,IF(AH$8=$BW$9,$BW31,IF(AH$8=$BX$9,$BX31,IF(AH$8=$BY$9,$BY31,IF(AH$8=$BZ$9,$BZ31,IF(AH$8=$CA$9,$CA31,IF(AH$8=$CC$9,$CC31,IF(AH$8=$CD$9,$CD31,IF(AH$8=$CE$9,$CE31,IF(AH$8=$CF$9,$CF31,IF(AH$8=$CG$9,$CG31,IF(AH$8=$CH$9,$CH31,IF(AH$8=$CI$9,$CI31,IF(AH$8=$CJ$9,$CJ31,IF(AH$8=$CK$9,$CK31,IF(AH$8=$CL$9,$CL31,IF(AH$8=$CM$9,$CM31,IF(AH$8=$CN$9,$CN31,IF(AH$8=$CO$9,$CO31,IF(AH$8=$CP$9,$CP31,IF(AH$8=$CQ$9,$CQ31,"НЕТ")))))))))))))))))))))))) -> НЕТ | AI31: =IF(AI$8=$BT$9,$BT31,IF(AI$8=$BS$9,$BS31,IF(AI$8=$BU$9,$BU31,IF(AI$8=$BV$9,$BV31,IF(AI$8=$BW$9,$BW31,IF(AI$8=$BX$9,$BX31,IF(AI$8=$BY$9,$BY31,IF(AI$8=$BZ$9,$BZ31,IF(AI$8=$CA$9,$CA31,IF(AI$8=$CC$9,$CC31,IF(AI$8=$CD$9,$CD31,IF(AI$8=$CE$9,$CE31,IF(AI$8=$CF$9,$CF31,IF(AI$8=$CG$9,$CG31,IF(AI$8=$CH$9,$CH31,IF(AI$8=$CI$9,$CI31,IF(AI$8=$CJ$9,$CJ31,IF(AI$8=$CK$9,$CK31,IF(AI$8=$CL$9,$CL31,IF(AI$8=$CM$9,$CM31,IF(AI$8=$CN$9,$CN31,IF(AI$8=$CO$9,$CO31,IF(AI$8=$CP$9,$CP31,IF(AI$8=$CQ$9,$CQ31,"НЕТ")))))))))))))))))))))))) -> НЕТ | AJ31: =IF(AJ$8=$BT$9,$BT31,IF(AJ$8=$BS$9,$BS31,IF(AJ$8=$BU$9,$BU31,IF(AJ$8=$BV$9,$BV31,IF(AJ$8=$BW$9,$BW31,IF(AJ$8=$BX$9,$BX31,IF(AJ$8=$BY$9,$BY31,IF(AJ$8=$BZ$9,$BZ31,IF(AJ$8=$CA$9,$CA31,IF(AJ$8=$CC$9,$CC31,IF(AJ$8=$CD$9,$CD31,IF(AJ$8=$CE$9,$CE31,IF(AJ$8=$CF$9,$CF31,IF(AJ$8=$CG$9,$CG31,IF(AJ$8=$CH$9,$CH31,IF(AJ$8=$CI$9,$CI31,IF(AJ$8=$CJ$9,$CJ31,IF(AJ$8=$CK$9,$CK31,IF(AJ$8=$CL$9,$CL31,IF(AJ$8=$CM$9,$CM31,IF(AJ$8=$CN$9,$CN31,IF(AJ$8=$CO$9,$CO31,IF(AJ$8=$CP$9,$CP31,IF(AJ$8=$CQ$9,$CQ31,"НЕТ")))))))))))))))))))))))) -> НЕТ | AK31: =IF(AK$8=$BT$9,$BT31,IF(AK$8=$BS$9,$BS31,IF(AK$8=$BU$9,$BU31,IF(AK$8=$BV$9,$BV31,IF(AK$8=$BW$9,$BW31,IF(AK$8=$BX$9,$BX31,IF(AK$8=$BY$9,$BY31,IF(AK$8=$BZ$9,$BZ31,IF(AK$8=$CA$9,$CA31,IF(AK$8=$CC$9,$CC31,IF(AK$8=$CD$9,$CD31,IF(AK$8=$CE$9,$CE31,IF(AK$8=$CF$9,$CF31,IF(AK$8=$CG$9,$CG31,IF(AK$8=$CH$9,$CH31,IF(AK$8=$CI$9,$CI31,IF(AK$8=$CJ$9,$CJ31,IF(AK$8=$CK$9,$CK31,IF(AK$8=$CL$9,$CL31,IF(AK$8=$CM$9,$CM31,IF(AK$8=$CN$9,$CN31,IF(AK$8=$CO$9,$CO31,IF(AK$8=$CP$9,$CP31,IF(AK$8=$CQ$9,$CQ31,"НЕТ")))))))))))))))))))))))) -> НЕТ | AL31: =IF(AL$8=$BT$9,$BT31,IF(AL$8=$BS$9,$BS31,IF(AL$8=$BU$9,$BU31,IF(AL$8=$BV$9,$BV31,IF(AL$8=$BW$9,$BW31,IF(AL$8=$BX$9,$BX31,IF(AL$8=$BY$9,$BY31,IF(AL$8=$BZ$9,$BZ31,IF(AL$8=$CA$9,$CA31,IF(AL$8=$CC$9,$CC31,IF(AL$8=$CD$9,$CD31,IF(AL$8=$CE$9,$CE31,IF(AL$8=$CF$9,$CF31,IF(AL$8=$CG$9,$CG31,IF(AL$8=$CH$9,$CH31,IF(AL$8=$CI$9,$CI31,IF(AL$8=$CJ$9,$CJ31,IF(AL$8=$CK$9,$CK31,IF(AL$8=$CL$9,$CL31,IF(AL$8=$CM$9,$CM31,IF(AL$8=$CN$9,$CN31,IF(AL$8=$CO$9,$CO31,IF(AL$8=$CP$9,$CP31,IF(AL$8=$CQ$9,$CQ31,"НЕТ")))))))))))))))))))))))) -> НЕТ | AM31: =IF(AL31="НЕТ","Не требуется",$CR31) -> Не требуется | AS31: =IF(BS31="ДА",$M31,"") -> 1 | AT31: =IF(BT31="ДА",$M31,"") | AU31: =IF(BU31="ДА",$M31,"") | AV31: =IF(BV31="ДА",$M31,"") | AW31: =IF(BX31="ДА",$M31,"") -> 1 | AX31: =IF(BY31="ДА",$M31,"") -> 1 | AY31: =IF(BZ31="ДА",$M31,"") -> 1 | AZ31: =IF(CA31="ДА",$M31,"") -> 1 | BB31: =IF(CC31="ДА",$M31,"") -> 1 | BC31: =IF(CD31="ДА",$M31,"") -> 1 | BD31: =IF(CE31="ДА",$M31,"") | BE31: =IF(CF31="ДА",$M31,"") | BF31: =IF(CG31="ДА",$M31,"") | BG31: =IF(CH31="ДА",$M31,"") -> 1 | BH31: =IF(CI31="ДА",$M31,"") -> 1 | BI31: =IF(CJ31="ДА",$M31,"") | ... BP31: =IF(CQ31="ДА",$M31,"") | BS31: ДА | BT31: НЕТ | BU31: НЕТ | BV31: НЕТ | BW31: ДА | BX31: ДА | BY31: ДА | BZ31: ДА | CA31: ДА | CC31: ДА | CD31: ДА | CE31: НЕТ | CF31: НЕТ | CG31: НЕТ | CH31: ДА | CI31: ДА | CJ31: НЕТ | CK31: ДА | CL31: ДА | CM31: НЕТ | CN31: НЕТ | CO31: НЕТ | CP31: НЕТ | CQ31: НЕТ | CR31: Предоставляется Заказчиком
B32: Контроль исполнения проектов портфеля по методике ворот качества | C32: Признак "Ворота качества" у вехи имеется, фаз на данный момент нет | N32: =SUM(O32,R32,U32,X32) -> 0
A33: 1.7. | B33: KPI портфеля проектов | F33: Проф | G33: ПРОФ-проект | H33: Нет | I33: Нет | J33: Да | K33: Да | L33: В разработке | M33: 2 | N33: =SUM(O33,R33,U33,X33) -> 2 | O33: =IF(AC33="ДА",$M33,"") | Q33: =IF(AC33="ДА",ROUNDUP(O33/5,0),0) -> 0 | R33: =IF(AF33="ДА",$M33,"") -> 2 | T33: =IF(AF33="ДА",ROUNDUP(R33/5,0),0) -> 1 | U33: =IF(AI33="ДА",$M33,"") | W33: =IF(AI33="ДА",ROUNDUP(U33/5,0),0) -> 0 | X33: =IF(AL33="ДА",$M33,"") | Z33: =IF(AL33="ДА",ROUNDUP(X33/5,0),0) -> 0 | AA33: =IF(OR(AC33="ДА",AF33="ДА",AI33="ДА",AL33="ДА"),"ДА","НЕТ") -> ДА | AC33: =IF(AC$8=$BT$9,$BT33,IF(AC$8=$BS$9,$BS33,IF(AC$8=$BU$9,$BU33,IF(AC$8=$BV$9,$BV33,IF(AC$8=$BW$9,$BW33,IF(AC$8=$BX$9,$BX33,IF(AC$8=$BY$9,$BY33,IF(AC$8=$BZ$9,$BZ33,IF(AC$8=$CA$9,$CA33,IF(AC$8=$CC$9,$CC33,IF(AC$8=$CD$9,$CD33,IF(AC$8=$CE$9,$CE33,IF(AC$8=$CF$9,$CF33,IF(AC$8=$CG$9,$CG33,IF(AC$8=$CH$9,$CH33,IF(AC$8=$CI$9,$CI33,IF(AC$8=$CJ$9,$CJ33,IF(AC$8=$CK$9,$CK33,IF(AC$8=$CL$9,$CL33,IF(AC$8=$CM$9,$CM33,IF(AC$8=$CN$9,$CN33,IF(AC$8=$CO$9,$CO33,IF(AC$8=$CP$9,$CP33,IF(AC$8=$CQ$9,$CQ33,"НЕТ")))))))))))))))))))))))) -> НЕТ | AD33: =IF(AC33="НЕТ","Не требуется",$CR33) -> Не требуется | AF33: =IF(AF$8=$BT$9,$BT33,IF(AF$8=$BS$9,$BS33,IF(AF$8=$BU$9,$BU33,IF(AF$8=$BV$9,$BV33,IF(AF$8=$BW$9,$BW33,IF(AF$8=$BX$9,$BX33,IF(AF$8=$BY$9,$BY33,IF(AF$8=$BZ$9,$BZ33,IF(AF$8=$CA$9,$CA33,IF(AF$8=$CC$9,$CC33,IF(AF$8=$CD$9,$CD33,IF(AF$8=$CE$9,$CE33,IF(AF$8=$CF$9,$CF33,IF(AF$8=$CG$9,$CG33,IF(AF$8=$CH$9,$CH33,IF(AF$8=$CI$9,$CI33,IF(AF$8=$CJ$9,$CJ33,IF(AF$8=$CK$9,$CK33,IF(AF$8=$CL$9,$CL33,IF(AF$8=$CM$9,$CM33,IF(AF$8=$CN$9,$CN33,IF(AF$8=$CO$9,$CO33,IF(AF$8=$CP$9,$CP33,IF(AF$8=$CQ$9,$CQ33,"НЕТ")))))))))))))))))))))))) -> ДА | AG33: =IF(AG$8=$BT$9,$BT33,IF(AG$8=$BS$9,$BS33,IF(AG$8=$BU$9,$BU33,IF(AG$8=$BV$9,$BV33,IF(AG$8=$BW$9,$BW33,IF(AG$8=$BX$9,$BX33,IF(AG$8=$BY$9,$BY33,IF(AG$8=$BZ$9,$BZ33,IF(AG$8=$CA$9,$CA33,IF(AG$8=$CC$9,$CC33,IF(AG$8=$CD$9,$CD33,IF(AG$8=$CE$9,$CE33,IF(AG$8=$CF$9,$CF33,IF(AG$8=$CG$9,$CG33,IF(AG$8=$CH$9,$CH33,IF(AG$8=$CI$9,$CI33,IF(AG$8=$CJ$9,$CJ33,IF(AG$8=$CK$9,$CK33,IF(AG$8=$CL$9,$CL33,IF(AG$8=$CM$9,$CM33,IF(AG$8=$CN$9,$CN33,IF(AG$8=$CO$9,$CO33,IF(AG$8=$CP$9,$CP33,IF(AG$8=$CQ$9,$CQ33,"НЕТ")))))))))))))))))))))))) -> НЕТ | AH33: =IF(AH$8=$BT$9,$BT33,IF(AH$8=$BS$9,$BS33,IF(AH$8=$BU$9,$BU33,IF(AH$8=$BV$9,$BV33,IF(AH$8=$BW$9,$BW33,IF(AH$8=$BX$9,$BX33,IF(AH$8=$BY$9,$BY33,IF(AH$8=$BZ$9,$BZ33,IF(AH$8=$CA$9,$CA33,IF(AH$8=$CC$9,$CC33,IF(AH$8=$CD$9,$CD33,IF(AH$8=$CE$9,$CE33,IF(AH$8=$CF$9,$CF33,IF(AH$8=$CG$9,$CG33,IF(AH$8=$CH$9,$CH33,IF(AH$8=$CI$9,$CI33,IF(AH$8=$CJ$9,$CJ33,IF(AH$8=$CK$9,$CK33,IF(AH$8=$CL$9,$CL33,IF(AH$8=$CM$9,$CM33,IF(AH$8=$CN$9,$CN33,IF(AH$8=$CO$9,$CO33,IF(AH$8=$CP$9,$CP33,IF(AH$8=$CQ$9,$CQ33,"НЕТ")))))))))))))))))))))))) -> НЕТ | AI33: =IF(AI$8=$BT$9,$BT33,IF(AI$8=$BS$9,$BS33,IF(AI$8=$BU$9,$BU33,IF(AI$8=$BV$9,$BV33,IF(AI$8=$BW$9,$BW33,IF(AI$8=$BX$9,$BX33,IF(AI$8=$BY$9,$BY33,IF(AI$8=$BZ$9,$BZ33,IF(AI$8=$CA$9,$CA33,IF(AI$8=$CC$9,$CC33,IF(AI$8=$CD$9,$CD33,IF(AI$8=$CE$9,$CE33,IF(AI$8=$CF$9,$CF33,IF(AI$8=$CG$9,$CG33,IF(AI$8=$CH$9,$CH33,IF(AI$8=$CI$9,$CI33,IF(AI$8=$CJ$9,$CJ33,IF(AI$8=$CK$9,$CK33,IF(AI$8=$CL$9,$CL33,IF(AI$8=$CM$9,$CM33,IF(AI$8=$CN$9,$CN33,IF(AI$8=$CO$9,$CO33,IF(AI$8=$CP$9,$CP33,IF(AI$8=$CQ$9,$CQ33,"НЕТ")))))))))))))))))))))))) -> НЕТ | AJ33: =IF(AJ$8=$BT$9,$BT33,IF(AJ$8=$BS$9,$BS33,IF(AJ$8=$BU$9,$BU33,IF(AJ$8=$BV$9,$BV33,IF(AJ$8=$BW$9,$BW33,IF(AJ$8=$BX$9,$BX33,IF(AJ$8=$BY$9,$BY33,IF(AJ$8=$BZ$9,$BZ33,IF(AJ$8=$CA$9,$CA33,IF(AJ$8=$CC$9,$CC33,IF(AJ$8=$CD$9,$CD33,IF(AJ$8=$CE$9,$CE33,IF(AJ$8=$CF$9,$CF33,IF(AJ$8=$CG$9,$CG33,IF(AJ$8=$CH$9,$CH33,IF(AJ$8=$CI$9,$CI33,IF(AJ$8=$CJ$9,$CJ33,IF(AJ$8=$CK$9,$CK33,IF(AJ$8=$CL$9,$CL33,IF(AJ$8=$CM$9,$CM33,IF(AJ$8=$CN$9,$CN33,IF(AJ$8=$CO$9,$CO33,IF(AJ$8=$CP$9,$CP33,IF(AJ$8=$CQ$9,$CQ33,"НЕТ")))))))))))))))))))))))) -> НЕТ | AK33: =IF(AK$8=$BT$9,$BT33,IF(AK$8=$BS$9,$BS33,IF(AK$8=$BU$9,$BU33,IF(AK$8=$BV$9,$BV33,IF(AK$8=$BW$9,$BW33,IF(AK$8=$BX$9,$BX33,IF(AK$8=$BY$9,$BY33,IF(AK$8=$BZ$9,$BZ33,IF(AK$8=$CA$9,$CA33,IF(AK$8=$CC$9,$CC33,IF(AK$8=$CD$9,$CD33,IF(AK$8=$CE$9,$CE33,IF(AK$8=$CF$9,$CF33,IF(AK$8=$CG$9,$CG33,IF(AK$8=$CH$9,$CH33,IF(AK$8=$CI$9,$CI33,IF(AK$8=$CJ$9,$CJ33,IF(AK$8=$CK$9,$CK33,IF(AK$8=$CL$9,$CL33,IF(AK$8=$CM$9,$CM33,IF(AK$8=$CN$9,$CN33,IF(AK$8=$CO$9,$CO33,IF(AK$8=$CP$9,$CP33,IF(AK$8=$CQ$9,$CQ33,"НЕТ")))))))))))))))))))))))) -> НЕТ | AL33: =IF(AL$8=$BT$9,$BT33,IF(AL$8=$BS$9,$BS33,IF(AL$8=$BU$9,$BU33,IF(AL$8=$BV$9,$BV33,IF(AL$8=$BW$9,$BW33,IF(AL$8=$BX$9,$BX33,IF(AL$8=$BY$9,$BY33,IF(AL$8=$BZ$9,$BZ33,IF(AL$8=$CA$9,$CA33,IF(AL$8=$CC$9,$CC33,IF(AL$8=$CD$9,$CD33,IF(AL$8=$CE$9,$CE33,IF(AL$8=$CF$9,$CF33,IF(AL$8=$CG$9,$CG33,IF(AL$8=$CH$9,$CH33,IF(AL$8=$CI$9,$CI33,IF(AL$8=$CJ$9,$CJ33,IF(AL$8=$CK$9,$CK33,IF(AL$8=$CL$9,$CL33,IF(AL$8=$CM$9,$CM33,IF(AL$8=$CN$9,$CN33,IF(AL$8=$CO$9,$CO33,IF(AL$8=$CP$9,$CP33,IF(AL$8=$CQ$9,$CQ33,"НЕТ")))))))))))))))))))))))) -> НЕТ | AM33: =IF(AL33="НЕТ","Не требуется",$CR33) -> Не требуется | AS33: =IF(BS33="ДА",$M33,"") | AT33: =IF(BT33="ДА",$M33,"") | AU33: =IF(BU33="ДА",$M33,"") | AV33: =IF(BV33="ДА",$M33,"") | AW33: =IF(BX33="ДА",$M33,"") | AX33: =IF(BY33="ДА",$M33,"") -> 2 | AY33: =IF(BZ33="ДА",$M33,"") -> 2 | AZ33: =IF(CA33="ДА",$M33,"") -> 2 | BB33: =IF(CC33="ДА",$M33,"") | BC33: =IF(CD33="ДА",$M33,"") -> 2 | BD33: =IF(CE33="ДА",$M33,"") | BE33: =IF(CF33="ДА",$M33,"") | BF33: =IF(CG33="ДА",$M33,"") | BG33: =IF(CH33="ДА",$M33,"") -> 2 | BH33: =IF(CI33="ДА",$M33,"") -> 2 | BI33: =IF(CJ33="ДА",$M33,"") | ... BP33: =IF(CQ33="ДА",$M33,"") | BS33: НЕТ | BT33: НЕТ | BU33: НЕТ | BV33: НЕТ | BW33: НЕТ | BX33: НЕТ | BY33: ДА | BZ33: ДА | CA33: ДА | CC33: НЕТ | CD33: ДА | CE33: НЕТ | CF33: НЕТ | CG33: НЕТ | CH33: ДА | CI33: ДА | CJ33: НЕТ | CK33: ДА | CL33: ДА | CM33: ДА | CN33: НЕТ | CO33: НЕТ | CP33: НЕТ | CQ33: НЕТ | CR33: Предоставляется Заказчиком
B34: Мониторинг KPI портфеля проектов (проекта с компонентой "Портфель проектов") | C34: с помощью панели руководителя, а так же отчетов (ПФА БДР, ПФА БДДС, ПФА Ресурсов) | N34: =SUM(O34,R34,U34,X34) -> 0
B35: Мониторинг показателей трудоемкости, бюджетов и объемов работ запланированных по портфелю и соответствующих плановых и фактических показателей проектов входящих в портфель | C35: с помощью панели руководителя, а так же отчетов (ПФА БДР, ПФА БДДС, ПФА Ресурсов) | N35: =SUM(O35,R35,U35,X35) -> 0
B36: План-фактный анализ по портфелю | C36: с помощью панели руководителя, а так же отчетов (ПФА БДР, ПФА БДДС, ПФА Ресурсов) | N36: =SUM(O36,R36,U36,X36) -> 0
A37: 1.8. | B37: Оптимизация тематического плана | C37: Нет | F37: Экспертный | G37: КОРП-проект | H37: Под проект | I37: Под проект | J37: Под проект | K37: Под проект | L37: Под проект | M37: 10 | N37: =SUM(O37,R37,U37,X37) -> 0 | O37: =IF(AC37="ДА",$M37,"") | Q37: =IF(AC37="ДА",ROUNDUP(O37/5,0),0) -> 0 | R37: =IF(AF37="ДА",$M37,"") | T37: =IF(AF37="ДА",ROUNDUP(R37/5,0),0) -> 0 | U37: =IF(AI37="ДА",$M37,"") | W37: =IF(AI37="ДА",ROUNDUP(U37/5,0),0) -> 0 | X37: =IF(AL37="ДА",$M37,"") | Z37: =IF(AL37="ДА",ROUNDUP(X37/5,0),0) -> 0 | AA37: =IF(OR(AC37="ДА",AF37="ДА",AI37="ДА",AL37="ДА"),"ДА","НЕТ") -> НЕТ | AC37: =IF(AC$8=$BT$9,$BT37,IF(AC$8=$BS$9,$BS37,IF(AC$8=$BU$9,$BU37,IF(AC$8=$BV$9,$BV37,IF(AC$8=$BW$9,$BW37,IF(AC$8=$BX$9,$BX37,IF(AC$8=$BY$9,$BY37,IF(AC$8=$BZ$9,$BZ37,IF(AC$8=$CA$9,$CA37,IF(AC$8=$CC$9,$CC37,IF(AC$8=$CD$9,$CD37,IF(AC$8=$CE$9,$CE37,IF(AC$8=$CF$9,$CF37,IF(AC$8=$CG$9,$CG37,IF(AC$8=$CH$9,$CH37,IF(AC$8=$CI$9,$CI37,IF(AC$8=$CJ$9,$CJ37,IF(AC$8=$CK$9,$CK37,IF(AC$8=$CL$9,$CL37,IF(AC$8=$CM$9,$CM37,IF(AC$8=$CN$9,$CN37,IF(AC$8=$CO$9,$CO37,IF(AC$8=$CP$9,$CP37,IF(AC$8=$CQ$9,$CQ37,"НЕТ")))))))))))))))))))))))) -> НЕТ | AD37: =IF(AC37="НЕТ","Не требуется",$CR37) -> Не требуется | AF37: =IF(AF$8=$BT$9,$BT37,IF(AF$8=$BS$9,$BS37,IF(AF$8=$BU$9,$BU37,IF(AF$8=$BV$9,$BV37,IF(AF$8=$BW$9,$BW37,IF(AF$8=$BX$9,$BX37,IF(AF$8=$BY$9,$BY37,IF(AF$8=$BZ$9,$BZ37,IF(AF$8=$CA$9,$CA37,IF(AF$8=$CC$9,$CC37,IF(AF$8=$CD$9,$CD37,IF(AF$8=$CE$9,$CE37,IF(AF$8=$CF$9,$CF37,IF(AF$8=$CG$9,$CG37,IF(AF$8=$CH$9,$CH37,IF(AF$8=$CI$9,$CI37,IF(AF$8=$CJ$9,$CJ37,IF(AF$8=$CK$9,$CK37,IF(AF$8=$CL$9,$CL37,IF(AF$8=$CM$9,$CM37,IF(AF$8=$CN$9,$CN37,IF(AF$8=$CO$9,$CO37,IF(AF$8=$CP$9,$CP37,IF(AF$8=$CQ$9,$CQ37,"НЕТ")))))))))))))))))))))))) -> НЕТ | AG37: =IF(AG$8=$BT$9,$BT37,IF(AG$8=$BS$9,$BS37,IF(AG$8=$BU$9,$BU37,IF(AG$8=$BV$9,$BV37,IF(AG$8=$BW$9,$BW37,IF(AG$8=$BX$9,$BX37,IF(AG$8=$BY$9,$BY37,IF(AG$8=$BZ$9,$BZ37,IF(AG$8=$CA$9,$CA37,IF(AG$8=$CC$9,$CC37,IF(AG$8=$CD$9,$CD37,IF(AG$8=$CE$9,$CE37,IF(AG$8=$CF$9,$CF37,IF(AG$8=$CG$9,$CG37,IF(AG$8=$CH$9,$CH37,IF(AG$8=$CI$9,$CI37,IF(AG$8=$CJ$9,$CJ37,IF(AG$8=$CK$9,$CK37,IF(AG$8=$CL$9,$CL37,IF(AG$8=$CM$9,$CM37,IF(AG$8=$CN$9,$CN37,IF(AG$8=$CO$9,$CO37,IF(AG$8=$CP$9,$CP37,IF(AG$8=$CQ$9,$CQ37,"НЕТ")))))))))))))))))))))))) -> НЕТ | AH37: =IF(AH$8=$BT$9,$BT37,IF(AH$8=$BS$9,$BS37,IF(AH$8=$BU$9,$BU37,IF(AH$8=$BV$9,$BV37,IF(AH$8=$BW$9,$BW37,IF(AH$8=$BX$9,$BX37,IF(AH$8=$BY$9,$BY37,IF(AH$8=$BZ$9,$BZ37,IF(AH$8=$CA$9,$CA37,IF(AH$8=$CC$9,$CC37,IF(AH$8=$CD$9,$CD37,IF(AH$8=$CE$9,$CE37,IF(AH$8=$CF$9,$CF37,IF(AH$8=$CG$9,$CG37,IF(AH$8=$CH$9,$CH37,IF(AH$8=$CI$9,$CI37,IF(AH$8=$CJ$9,$CJ37,IF(AH$8=$CK$9,$CK37,IF(AH$8=$CL$9,$CL37,IF(AH$8=$CM$9,$CM37,IF(AH$8=$CN$9,$CN37,IF(AH$8=$CO$9,$CO37,IF(AH$8=$CP$9,$CP37,IF(AH$8=$CQ$9,$CQ37,"НЕТ")))))))))))))))))))))))) -> НЕТ | AI37: =IF(AI$8=$BT$9,$BT37,IF(AI$8=$BS$9,$BS37,IF(AI$8=$BU$9,$BU37,IF(AI$8=$BV$9,$BV37,IF(AI$8=$BW$9,$BW37,IF(AI$8=$BX$9,$BX37,IF(AI$8=$BY$9,$BY37,IF(AI$8=$BZ$9,$BZ37,IF(AI$8=$CA$9,$CA37,IF(AI$8=$CC$9,$CC37,IF(AI$8=$CD$9,$CD37,IF(AI$8=$CE$9,$CE37,IF(AI$8=$CF$9,$CF37,IF(AI$8=$CG$9,$CG37,IF(AI$8=$CH$9,$CH37,IF(AI$8=$CI$9,$CI37,IF(AI$8=$CJ$9,$CJ37,IF(AI$8=$CK$9,$CK37,IF(AI$8=$CL$9,$CL37,IF(AI$8=$CM$9,$CM37,IF(AI$8=$CN$9,$CN37,IF(AI$8=$CO$9,$CO37,IF(AI$8=$CP$9,$CP37,IF(AI$8=$CQ$9,$CQ37,"НЕТ")))))))))))))))))))))))) -> НЕТ | AJ37: =IF(AJ$8=$BT$9,$BT37,IF(AJ$8=$BS$9,$BS37,IF(AJ$8=$BU$9,$BU37,IF(AJ$8=$BV$9,$BV37,IF(AJ$8=$BW$9,$BW37,IF(AJ$8=$BX$9,$BX37,IF(AJ$8=$BY$9,$BY37,IF(AJ$8=$BZ$9,$BZ37,IF(AJ$8=$CA$9,$CA37,IF(AJ$8=$CC$9,$CC37,IF(AJ$8=$CD$9,$CD37,IF(AJ$8=$CE$9,$CE37,IF(AJ$8=$CF$9,$CF37,IF(AJ$8=$CG$9,$CG37,IF(AJ$8=$CH$9,$CH37,IF(AJ$8=$CI$9,$CI37,IF(AJ$8=$CJ$9,$CJ37,IF(AJ$8=$CK$9,$CK37,IF(AJ$8=$CL$9,$CL37,IF(AJ$8=$CM$9,$CM37,IF(AJ$8=$CN$9,$CN37,IF(AJ$8=$CO$9,$CO37,IF(AJ$8=$CP$9,$CP37,IF(AJ$8=$CQ$9,$CQ37,"НЕТ")))))))))))))))))))))))) -> НЕТ | AK37: =IF(AK$8=$BT$9,$BT37,IF(AK$8=$BS$9,$BS37,IF(AK$8=$BU$9,$BU37,IF(AK$8=$BV$9,$BV37,IF(AK$8=$BW$9,$BW37,IF(AK$8=$BX$9,$BX37,IF(AK$8=$BY$9,$BY37,IF(AK$8=$BZ$9,$BZ37,IF(AK$8=$CA$9,$CA37,IF(AK$8=$CC$9,$CC37,IF(AK$8=$CD$9,$CD37,IF(AK$8=$CE$9,$CE37,IF(AK$8=$CF$9,$CF37,IF(AK$8=$CG$9,$CG37,IF(AK$8=$CH$9,$CH37,IF(AK$8=$CI$9,$CI37,IF(AK$8=$CJ$9,$CJ37,IF(AK$8=$CK$9,$CK37,IF(AK$8=$CL$9,$CL37,IF(AK$8=$CM$9,$CM37,IF(AK$8=$CN$9,$CN37,IF(AK$8=$CO$9,$CO37,IF(AK$8=$CP$9,$CP37,IF(AK$8=$CQ$9,$CQ37,"НЕТ")))))))))))))))))))))))) -> НЕТ | AL37: =IF(AL$8=$BT$9,$BT37,IF(AL$8=$BS$9,$BS37,IF(AL$8=$BU$9,$BU37,IF(AL$8=$BV$9,$BV37,IF(AL$8=$BW$9,$BW37,IF(AL$8=$BX$9,$BX37,IF(AL$8=$BY$9,$BY37,IF(AL$8=$BZ$9,$BZ37,IF(AL$8=$CA$9,$CA37,IF(AL$8=$CC$9,$CC37,IF(AL$8=$CD$9,$CD37,IF(AL$8=$CE$9,$CE37,IF(AL$8=$CF$9,$CF37,IF(AL$8=$CG$9,$CG37,IF(AL$8=$CH$9,$CH37,IF(AL$8=$CI$9,$CI37,IF(AL$8=$CJ$9,$CJ37,IF(AL$8=$CK$9,$CK37,IF(AL$8=$CL$9,$CL37,IF(AL$8=$CM$9,$CM37,IF(AL$8=$CN$9,$CN37,IF(AL$8=$CO$9,$CO37,IF(AL$8=$CP$9,$CP37,IF(AL$8=$CQ$9,$CQ37,"НЕТ")))))))))))))))))))))))) -> НЕТ | AM37: =IF(AL37="НЕТ","Не требуется",$CR37) -> Не требуется | AS37: =IF(BS37="ДА",$M37,"") | AT37: =IF(BT37="ДА",$M37,"") | AU37: =IF(BU37="ДА",$M37,"") | AV37: =IF(BV37="ДА",$M37,"") | AW37: =IF(BX37="ДА",$M37,"") | AX37: =IF(BY37="ДА",$M37,"") | AY37: =IF(BZ37="ДА",$M37,"") | AZ37: =IF(CA37="ДА",$M37,"") -> 10 | BB37: =IF(CC37="ДА",$M37,"") | BC37: =IF(CD37="ДА",$M37,"") | BD37: =IF(CE37="ДА",$M37,"") | BE37: =IF(CF37="ДА",$M37,"") | BF37: =IF(CG37="ДА",$M37,"") | BG37: =IF(CH37="ДА",$M37,"") | BH37: =IF(CI37="ДА",$M37,"") | BI37: =IF(CJ37="ДА",$M37,"") | ... BP37: =IF(CQ37="ДА",$M37,"") | BS37: НЕТ | BT37: НЕТ | BU37: НЕТ | BV37: НЕТ | BW37: НЕТ | BX37: НЕТ | BY37: НЕТ | BZ37: НЕТ | CA37: ДА | CC37: НЕТ | CD37: НЕТ | CE37: НЕТ | CF37: НЕТ | CG37: НЕТ | CH37: НЕТ | CI37: НЕТ | CJ37: НЕТ | CK37: ДА | CL37: НЕТ | CM37: НЕТ | CN37: НЕТ | CO37: НЕТ | CP37: НЕТ | CQ37: НЕТ | CR37: Предоставляется Заказчиком
A38: 2. | B38: Управление работами и сроками | F38: ГРУППА | G38: ГРУППА | H38: ГРУППА | I38: ГРУППА | J38: ГРУППА | K38: ГРУППА | L38: ГРУППА | M38: =SUM(M39,M50,M54,M59,M61,M64,M65,M66) -> 26 | N38: =SUM(N39,N50,N54,N59,N61,N64,N65,N66) -> 33 | O38: =SUM(O39,O50,O54,O59,O61,O64,O65,O66) -> 6 | P38: =SUM(P39,P50,P54,P59,P61,P64,P65,P66) -> 0 | Q38: =SUM(Q39,Q50,Q54,Q59,Q61,Q64,Q65,Q66) -> 5 | R38: =SUM(R39,R50,R54,R59,R61,R64,R65,R66) -> 21 | S38: =SUM(S39,S50,S54,S59,S61,S64,S65,S66) -> 0 | T38: =SUM(T39,T50,T54,T59,T61,T64,T65,T66) -> 8 | ... Z38: =SUM(Z39,Z50,Z54,Z59,Z61,Z64,Z65,Z66) -> 0 | AA38: =IF(N38>0,"ДА","НЕТ") -> ДА | AC38: =IF(O38>0,"ДА","НЕТ") -> ДА | AF38: =IF(R38>0,"ДА","НЕТ") -> ДА | AI38: =IF(U38>0,"ДА","НЕТ") -> ДА | AL38: =IF(X38>0,"ДА","НЕТ") -> НЕТ | AS38: =SUM(AS39,AS50,AS54,AS59,AS61,AS64,AS65,AS66) -> 6 | AT38: =SUM(AT39,AT50,AT54,AT59,AT61,AT64,AT65,AT66) -> 5 | AU38: =SUM(AU39,AU50,AU54,AU59,AU61,AU64,AU65,AU66) -> 6 | AV38: =SUM(AV39,AV50,AV54,AV59,AV61,AV64,AV65,AV66) -> 6 | AW38: =SUM(AW39,AW50,AW54,AW59,AW61,AW64,AW65,AW66) -> 6 | AX38: =SUM(AX39,AX50,AX54,AX59,AX61,AX64,AX65,AX66) -> 16 | AY38: =SUM(AY39,AY50,AY54,AY59,AY61,AY64,AY65,AY66) -> 21 | AZ38: =SUM(AZ39,AZ50,AZ54,AZ59,AZ61,AZ64,AZ65,AZ66) -> 26 | BB38: =SUM(BB39,BB50,BB54,BB59,BB61,BB64,BB65,BB66) -> 4 | BC38: =SUM(BC39,BC50,BC54,BC59,BC61,BC64,BC65,BC66) -> 10 | BD38: =SUM(BD39,BD50,BD54,BD59,BD61,BD64,BD65,BD66) -> 3 | BE38: =SUM(BE39,BE50,BE54,BE59,BE61,BE64,BE65,BE66) -> 25 | BF38: =SUM(BF39,BF50,BF54,BF59,BF61,BF64,BF65,BF66) -> 24 | BG38: =SUM(BG39,BG50,BG54,BG59,BG61,BG64,BG65,BG66) -> 6 | BH38: =SUM(BH39,BH50,BH54,BH59,BH61,BH64,BH65,BH66) -> 10 | BI38: =SUM(BI39,BI50,BI54,BI59,BI61,BI64,BI65,BI66) -> 16 | ... BP38: =SUM(BP39,BP50,BP54,BP59,BP61,BP64,BP65,BP66) -> 0 | BS38: =IF(AS38>0,"ДА","НЕТ") -> ДА | BT38: =IF(AT38>0,"ДА","НЕТ") -> ДА | BU38: =IF(AU38>0,"ДА","НЕТ") -> ДА | BV38: =IF(AV38>0,"ДА","НЕТ") -> ДА | BW38: =IF(AS38>0,"ДА","НЕТ") -> ДА | BX38: =IF(AW38>0,"ДА","НЕТ") -> ДА | BY38: =IF(AX38>0,"ДА","НЕТ") -> ДА | BZ38: =IF(AY38>0,"ДА","НЕТ") -> ДА | CA38: =IF(AZ38>0,"ДА","НЕТ") -> ДА | CC38: =IF(BB38>0,"ДА","НЕТ") -> ДА | CD38: =IF(BC38>0,"ДА","НЕТ") -> ДА | CE38: =IF(BD38>0,"ДА","НЕТ") -> ДА | CF38: =IF(BE38>0,"ДА","НЕТ") -> ДА | CG38: =IF(BF38>0,"ДА","НЕТ") -> ДА | CH38: =IF(BG38>0,"ДА","НЕТ") -> ДА | CI38: =IF(BH38>0,"ДА","НЕТ") -> ДА | CJ38: =IF(BI38>0,"ДА","НЕТ") -> ДА | ... CQ38: =IF(BP38>0,"ДА","НЕТ") -> НЕТ
A39: 2.1. | B39: Сформировать календарные планы проектов | F39: Базовый | G39: Кейс-проект | H39: Да | I39: Да | J39: Да | K39: Да | L39: Да | M39: 2 | N39: =SUM(O39,R39,U39,X39) -> 6 | O39: =IF(AC39="ДА",$M39,"") -> 2 | Q39: =IF(AC39="ДА",ROUNDUP(O39/5,0),0) -> 1 | R39: =IF(AF39="ДА",$M39,"") -> 2 | T39: =IF(AF39="ДА",ROUNDUP(R39/5,0),0) -> 1 | U39: =IF(AI39="ДА",$M39,"") -> 2 | W39: =IF(AI39="ДА",ROUNDUP(U39/5,0),0) -> 1 | X39: =IF(AL39="ДА",$M39,"") | Z39: =IF(AL39="ДА",ROUNDUP(X39/5,0),0) -> 0 | AA39: =IF(OR(AC39="ДА",AF39="ДА",AI39="ДА",AL39="ДА"),"ДА","НЕТ") -> ДА | AC39: =IF(AC$8=$BT$9,$BT39,IF(AC$8=$BS$9,$BS39,IF(AC$8=$BU$9,$BU39,IF(AC$8=$BV$9,$BV39,IF(AC$8=$BW$9,$BW39,IF(AC$8=$BX$9,$BX39,IF(AC$8=$BY$9,$BY39,IF(AC$8=$BZ$9,$BZ39,IF(AC$8=$CA$9,$CA39,IF(AC$8=$CC$9,$CC39,IF(AC$8=$CD$9,$CD39,IF(AC$8=$CE$9,$CE39,IF(AC$8=$CF$9,$CF39,IF(AC$8=$CG$9,$CG39,IF(AC$8=$CH$9,$CH39,IF(AC$8=$CI$9,$CI39,IF(AC$8=$CJ$9,$CJ39,IF(AC$8=$CK$9,$CK39,IF(AC$8=$CL$9,$CL39,IF(AC$8=$CM$9,$CM39,IF(AC$8=$CN$9,$CN39,IF(AC$8=$CO$9,$CO39,IF(AC$8=$CP$9,$CP39,IF(AC$8=$CQ$9,$CQ39,"НЕТ")))))))))))))))))))))))) -> ДА | AD39: =IF(AC39="НЕТ","Не требуется",$CR39) -> Не требуется | AF39: =IF(AF$8=$BT$9,$BT39,IF(AF$8=$BS$9,$BS39,IF(AF$8=$BU$9,$BU39,IF(AF$8=$BV$9,$BV39,IF(AF$8=$BW$9,$BW39,IF(AF$8=$BX$9,$BX39,IF(AF$8=$BY$9,$BY39,IF(AF$8=$BZ$9,$BZ39,IF(AF$8=$CA$9,$CA39,IF(AF$8=$CC$9,$CC39,IF(AF$8=$CD$9,$CD39,IF(AF$8=$CE$9,$CE39,IF(AF$8=$CF$9,$CF39,IF(AF$8=$CG$9,$CG39,IF(AF$8=$CH$9,$CH39,IF(AF$8=$CI$9,$CI39,IF(AF$8=$CJ$9,$CJ39,IF(AF$8=$CK$9,$CK39,IF(AF$8=$CL$9,$CL39,IF(AF$8=$CM$9,$CM39,IF(AF$8=$CN$9,$CN39,IF(AF$8=$CO$9,$CO39,IF(AF$8=$CP$9,$CP39,IF(AF$8=$CQ$9,$CQ39,"НЕТ")))))))))))))))))))))))) -> ДА | AG39: =IF(AG$8=$BT$9,$BT39,IF(AG$8=$BS$9,$BS39,IF(AG$8=$BU$9,$BU39,IF(AG$8=$BV$9,$BV39,IF(AG$8=$BW$9,$BW39,IF(AG$8=$BX$9,$BX39,IF(AG$8=$BY$9,$BY39,IF(AG$8=$BZ$9,$BZ39,IF(AG$8=$CA$9,$CA39,IF(AG$8=$CC$9,$CC39,IF(AG$8=$CD$9,$CD39,IF(AG$8=$CE$9,$CE39,IF(AG$8=$CF$9,$CF39,IF(AG$8=$CG$9,$CG39,IF(AG$8=$CH$9,$CH39,IF(AG$8=$CI$9,$CI39,IF(AG$8=$CJ$9,$CJ39,IF(AG$8=$CK$9,$CK39,IF(AG$8=$CL$9,$CL39,IF(AG$8=$CM$9,$CM39,IF(AG$8=$CN$9,$CN39,IF(AG$8=$CO$9,$CO39,IF(AG$8=$CP$9,$CP39,IF(AG$8=$CQ$9,$CQ39,"НЕТ")))))))))))))))))))))))) -> НЕТ | AH39: =IF(AH$8=$BT$9,$BT39,IF(AH$8=$BS$9,$BS39,IF(AH$8=$BU$9,$BU39,IF(AH$8=$BV$9,$BV39,IF(AH$8=$BW$9,$BW39,IF(AH$8=$BX$9,$BX39,IF(AH$8=$BY$9,$BY39,IF(AH$8=$BZ$9,$BZ39,IF(AH$8=$CA$9,$CA39,IF(AH$8=$CC$9,$CC39,IF(AH$8=$CD$9,$CD39,IF(AH$8=$CE$9,$CE39,IF(AH$8=$CF$9,$CF39,IF(AH$8=$CG$9,$CG39,IF(AH$8=$CH$9,$CH39,IF(AH$8=$CI$9,$CI39,IF(AH$8=$CJ$9,$CJ39,IF(AH$8=$CK$9,$CK39,IF(AH$8=$CL$9,$CL39,IF(AH$8=$CM$9,$CM39,IF(AH$8=$CN$9,$CN39,IF(AH$8=$CO$9,$CO39,IF(AH$8=$CP$9,$CP39,IF(AH$8=$CQ$9,$CQ39,"НЕТ")))))))))))))))))))))))) -> НЕТ | AI39: =IF(AI$8=$BT$9,$BT39,IF(AI$8=$BS$9,$BS39,IF(AI$8=$BU$9,$BU39,IF(AI$8=$BV$9,$BV39,IF(AI$8=$BW$9,$BW39,IF(AI$8=$BX$9,$BX39,IF(AI$8=$BY$9,$BY39,IF(AI$8=$BZ$9,$BZ39,IF(AI$8=$CA$9,$CA39,IF(AI$8=$CC$9,$CC39,IF(AI$8=$CD$9,$CD39,IF(AI$8=$CE$9,$CE39,IF(AI$8=$CF$9,$CF39,IF(AI$8=$CG$9,$CG39,IF(AI$8=$CH$9,$CH39,IF(AI$8=$CI$9,$CI39,IF(AI$8=$CJ$9,$CJ39,IF(AI$8=$CK$9,$CK39,IF(AI$8=$CL$9,$CL39,IF(AI$8=$CM$9,$CM39,IF(AI$8=$CN$9,$CN39,IF(AI$8=$CO$9,$CO39,IF(AI$8=$CP$9,$CP39,IF(AI$8=$CQ$9,$CQ39,"НЕТ")))))))))))))))))))))))) -> ДА | AJ39: =IF(AJ$8=$BT$9,$BT39,IF(AJ$8=$BS$9,$BS39,IF(AJ$8=$BU$9,$BU39,IF(AJ$8=$BV$9,$BV39,IF(AJ$8=$BW$9,$BW39,IF(AJ$8=$BX$9,$BX39,IF(AJ$8=$BY$9,$BY39,IF(AJ$8=$BZ$9,$BZ39,IF(AJ$8=$CA$9,$CA39,IF(AJ$8=$CC$9,$CC39,IF(AJ$8=$CD$9,$CD39,IF(AJ$8=$CE$9,$CE39,IF(AJ$8=$CF$9,$CF39,IF(AJ$8=$CG$9,$CG39,IF(AJ$8=$CH$9,$CH39,IF(AJ$8=$CI$9,$CI39,IF(AJ$8=$CJ$9,$CJ39,IF(AJ$8=$CK$9,$CK39,IF(AJ$8=$CL$9,$CL39,IF(AJ$8=$CM$9,$CM39,IF(AJ$8=$CN$9,$CN39,IF(AJ$8=$CO$9,$CO39,IF(AJ$8=$CP$9,$CP39,IF(AJ$8=$CQ$9,$CQ39,"НЕТ")))))))))))))))))))))))) -> НЕТ | AK39: =IF(AK$8=$BT$9,$BT39,IF(AK$8=$BS$9,$BS39,IF(AK$8=$BU$9,$BU39,IF(AK$8=$BV$9,$BV39,IF(AK$8=$BW$9,$BW39,IF(AK$8=$BX$9,$BX39,IF(AK$8=$BY$9,$BY39,IF(AK$8=$BZ$9,$BZ39,IF(AK$8=$CA$9,$CA39,IF(AK$8=$CC$9,$CC39,IF(AK$8=$CD$9,$CD39,IF(AK$8=$CE$9,$CE39,IF(AK$8=$CF$9,$CF39,IF(AK$8=$CG$9,$CG39,IF(AK$8=$CH$9,$CH39,IF(AK$8=$CI$9,$CI39,IF(AK$8=$CJ$9,$CJ39,IF(AK$8=$CK$9,$CK39,IF(AK$8=$CL$9,$CL39,IF(AK$8=$CM$9,$CM39,IF(AK$8=$CN$9,$CN39,IF(AK$8=$CO$9,$CO39,IF(AK$8=$CP$9,$CP39,IF(AK$8=$CQ$9,$CQ39,"НЕТ")))))))))))))))))))))))) -> НЕТ | AL39: =IF(AL$8=$BT$9,$BT39,IF(AL$8=$BS$9,$BS39,IF(AL$8=$BU$9,$BU39,IF(AL$8=$BV$9,$BV39,IF(AL$8=$BW$9,$BW39,IF(AL$8=$BX$9,$BX39,IF(AL$8=$BY$9,$BY39,IF(AL$8=$BZ$9,$BZ39,IF(AL$8=$CA$9,$CA39,IF(AL$8=$CC$9,$CC39,IF(AL$8=$CD$9,$CD39,IF(AL$8=$CE$9,$CE39,IF(AL$8=$CF$9,$CF39,IF(AL$8=$CG$9,$CG39,IF(AL$8=$CH$9,$CH39,IF(AL$8=$CI$9,$CI39,IF(AL$8=$CJ$9,$CJ39,IF(AL$8=$CK$9,$CK39,IF(AL$8=$CL$9,$CL39,IF(AL$8=$CM$9,$CM39,IF(AL$8=$CN$9,$CN39,IF(AL$8=$CO$9,$CO39,IF(AL$8=$CP$9,$CP39,IF(AL$8=$CQ$9,$CQ39,"НЕТ")))))))))))))))))))))))) -> НЕТ | AM39: =IF(AL39="НЕТ","Не требуется",$CR39) -> Не требуется | AS39: =IF(BS39="ДА",$M39,"") -> 2 | AT39: =IF(BT39="ДА",$M39,"") -> 2 | AU39: =IF(BU39="ДА",$M39,"") -> 2 | AV39: =IF(BV39="ДА",$M39,"") -> 2 | AW39: =IF(BX39="ДА",$M39,"") -> 2 | AX39: =IF(BY39="ДА",$M39,"") -> 2 | AY39: =IF(BZ39="ДА",$M39,"") -> 2 | AZ39: =IF(CA39="ДА",$M39,"") -> 2 | BB39: =IF(CC39="ДА",$M39,"") -> 2 | BC39: =IF(CD39="ДА",$M39,"") -> 2 | BD39: =IF(CE39="ДА",$M39,"") -> 2 | BE39: =IF(CF39="ДА",$M39,"") -> 2 | BF39: =IF(CG39="ДА",$M39,"") -> 2 | BG39: =IF(CH39="ДА",$M39,"") -> 2 | BH39: =IF(CI39="ДА",$M39,"") -> 2 | BI39: =IF(CJ39="ДА",$M39,"") -> 2 | ... BP39: =IF(CQ39="ДА",$M39,"") | BS39: ДА | BT39: ДА | BU39: ДА | BV39: ДА | BW39: ДА | BX39: ДА | BY39: ДА | BZ39: ДА | CA39: ДА | CC39: ДА | CD39: ДА | CE39: ДА | CF39: ДА | CG39: ДА | CH39: ДА | CI39: ДА | CJ39: ДА | CK39: ДА | CL39: ДА | CM39: ДА | CN39: НЕТ | CO39: НЕТ | CP39: НЕТ | CQ39: НЕТ | CR39: Не требуется
B40: Регистрация паспорта проекта | C40: Карточка проекта/Карточка плана проекта | N40: =SUM(O40,R40,U40,X40) -> 0
B41: Декомпозиция проекта до этапов, определенных договором | C41: Декомпозиция проекта до этапов, определенных договором | N41: =SUM(O41,R41,U41,X41) -> 0
B42: Декомпозиция этапов работ до подэтапов и задач. Определение сроков и длительности выполнения задач и подэтапов. | C42: Декомпозиция этапов работ до подэтапов и задач. Определение сроков и длительности выполнения задач и подэтапов. | N42: =SUM(O42,R42,U42,X42) -> 0
B43: Планирование ключевых и технологических событий («вех») проектов | C43: Планирование ключевых и технологических событий («вех») проектов | N43: =SUM(O43,R43,U43,X43) -> 0
B44: Расчет «критического пути» проекта | C44: Расчет «критического пути» проекта. Реализовано как в РМ4, без сложных расчетов как в Примавере | N44: =SUM(O44,R44,U44,X44) -> 0
B45: Использование диаграмм Ганта | C45: Использование диаграмм Ганта | N45: =SUM(O45,R45,U45,X45) -> 0
B46: Формирование сетевого график проектов | C46: Возможность добавить несколько планов и вывести в виде ДГ | N46: =SUM(O46,R46,U46,X46) -> 0
B47: Версионирование календарного плана проекта | C47: Все данные хранятся именно в версии, а не плане | N47: =SUM(O47,R47,U47,X47) -> 0
B48: План-фактный анализ сроков проекта (в ТЗ в другом разделе "выполнение работ проекта" из этого раздела переносим?) | C48: Сравнение версий планов | N48: =SUM(O48,R48,U48,X48) -> 0
B49: Анализ отклонений сроков текущего плана проекта от сроков версий плана проекта | C49: Сравнение версий планов | N49: =SUM(O49,R49,U49,X49) -> 0
A50: 2.2. | B50: Работа с шаблонами в проектах | F50: Базовый | G50: Кейс-проект | H50: Да | I50: Да | J50: Да | K50: Да | L50: В разработке | M50: 1 | N50: =SUM(O50,R50,U50,X50) -> 3 | O50: =IF(AC50="ДА",$M50,"") -> 1 | Q50: =IF(AC50="ДА",ROUNDUP(O50/5,0),0) -> 1 | R50: =IF(AF50="ДА",$M50,"") -> 1 | T50: =IF(AF50="ДА",ROUNDUP(R50/5,0),0) -> 1 | U50: =IF(AI50="ДА",$M50,"") -> 1 | W50: =IF(AI50="ДА",ROUNDUP(U50/5,0),0) -> 1 | X50: =IF(AL50="ДА",$M50,"") | Z50: =IF(AL50="ДА",ROUNDUP(X50/5,0),0) -> 0 | AA50: =IF(OR(AC50="ДА",AF50="ДА",AI50="ДА",AL50="ДА"),"ДА","НЕТ") -> ДА | AC50: =IF(AC$8=$BT$9,$BT50,IF(AC$8=$BS$9,$BS50,IF(AC$8=$BU$9,$BU50,IF(AC$8=$BV$9,$BV50,IF(AC$8=$BW$9,$BW50,IF(AC$8=$BX$9,$BX50,IF(AC$8=$BY$9,$BY50,IF(AC$8=$BZ$9,$BZ50,IF(AC$8=$CA$9,$CA50,IF(AC$8=$CC$9,$CC50,IF(AC$8=$CD$9,$CD50,IF(AC$8=$CE$9,$CE50,IF(AC$8=$CF$9,$CF50,IF(AC$8=$CG$9,$CG50,IF(AC$8=$CH$9,$CH50,IF(AC$8=$CI$9,$CI50,IF(AC$8=$CJ$9,$CJ50,IF(AC$8=$CK$9,$CK50,IF(AC$8=$CL$9,$CL50,IF(AC$8=$CM$9,$CM50,IF(AC$8=$CN$9,$CN50,IF(AC$8=$CO$9,$CO50,IF(AC$8=$CP$9,$CP50,IF(AC$8=$CQ$9,$CQ50,"НЕТ")))))))))))))))))))))))) -> ДА | AD50: =IF(AC50="НЕТ","Не требуется",$CR50) -> Не требуется | AF50: =IF(AF$8=$BT$9,$BT50,IF(AF$8=$BS$9,$BS50,IF(AF$8=$BU$9,$BU50,IF(AF$8=$BV$9,$BV50,IF(AF$8=$BW$9,$BW50,IF(AF$8=$BX$9,$BX50,IF(AF$8=$BY$9,$BY50,IF(AF$8=$BZ$9,$BZ50,IF(AF$8=$CA$9,$CA50,IF(AF$8=$CC$9,$CC50,IF(AF$8=$CD$9,$CD50,IF(AF$8=$CE$9,$CE50,IF(AF$8=$CF$9,$CF50,IF(AF$8=$CG$9,$CG50,IF(AF$8=$CH$9,$CH50,IF(AF$8=$CI$9,$CI50,IF(AF$8=$CJ$9,$CJ50,IF(AF$8=$CK$9,$CK50,IF(AF$8=$CL$9,$CL50,IF(AF$8=$CM$9,$CM50,IF(AF$8=$CN$9,$CN50,IF(AF$8=$CO$9,$CO50,IF(AF$8=$CP$9,$CP50,IF(AF$8=$CQ$9,$CQ50,"НЕТ")))))))))))))))))))))))) -> ДА | AG50: =IF(AG$8=$BT$9,$BT50,IF(AG$8=$BS$9,$BS50,IF(AG$8=$BU$9,$BU50,IF(AG$8=$BV$9,$BV50,IF(AG$8=$BW$9,$BW50,IF(AG$8=$BX$9,$BX50,IF(AG$8=$BY$9,$BY50,IF(AG$8=$BZ$9,$BZ50,IF(AG$8=$CA$9,$CA50,IF(AG$8=$CC$9,$CC50,IF(AG$8=$CD$9,$CD50,IF(AG$8=$CE$9,$CE50,IF(AG$8=$CF$9,$CF50,IF(AG$8=$CG$9,$CG50,IF(AG$8=$CH$9,$CH50,IF(AG$8=$CI$9,$CI50,IF(AG$8=$CJ$9,$CJ50,IF(AG$8=$CK$9,$CK50,IF(AG$8=$CL$9,$CL50,IF(AG$8=$CM$9,$CM50,IF(AG$8=$CN$9,$CN50,IF(AG$8=$CO$9,$CO50,IF(AG$8=$CP$9,$CP50,IF(AG$8=$CQ$9,$CQ50,"НЕТ")))))))))))))))))))))))) -> НЕТ | AH50: =IF(AH$8=$BT$9,$BT50,IF(AH$8=$BS$9,$BS50,IF(AH$8=$BU$9,$BU50,IF(AH$8=$BV$9,$BV50,IF(AH$8=$BW$9,$BW50,IF(AH$8=$BX$9,$BX50,IF(AH$8=$BY$9,$BY50,IF(AH$8=$BZ$9,$BZ50,IF(AH$8=$CA$9,$CA50,IF(AH$8=$CC$9,$CC50,IF(AH$8=$CD$9,$CD50,IF(AH$8=$CE$9,$CE50,IF(AH$8=$CF$9,$CF50,IF(AH$8=$CG$9,$CG50,IF(AH$8=$CH$9,$CH50,IF(AH$8=$CI$9,$CI50,IF(AH$8=$CJ$9,$CJ50,IF(AH$8=$CK$9,$CK50,IF(AH$8=$CL$9,$CL50,IF(AH$8=$CM$9,$CM50,IF(AH$8=$CN$9,$CN50,IF(AH$8=$CO$9,$CO50,IF(AH$8=$CP$9,$CP50,IF(AH$8=$CQ$9,$CQ50,"НЕТ")))))))))))))))))))))))) -> НЕТ | AI50: =IF(AI$8=$BT$9,$BT50,IF(AI$8=$BS$9,$BS50,IF(AI$8=$BU$9,$BU50,IF(AI$8=$BV$9,$BV50,IF(AI$8=$BW$9,$BW50,IF(AI$8=$BX$9,$BX50,IF(AI$8=$BY$9,$BY50,IF(AI$8=$BZ$9,$BZ50,IF(AI$8=$CA$9,$CA50,IF(AI$8=$CC$9,$CC50,IF(AI$8=$CD$9,$CD50,IF(AI$8=$CE$9,$CE50,IF(AI$8=$CF$9,$CF50,IF(AI$8=$CG$9,$CG50,IF(AI$8=$CH$9,$CH50,IF(AI$8=$CI$9,$CI50,IF(AI$8=$CJ$9,$CJ50,IF(AI$8=$CK$9,$CK50,IF(AI$8=$CL$9,$CL50,IF(AI$8=$CM$9,$CM50,IF(AI$8=$CN$9,$CN50,IF(AI$8=$CO$9,$CO50,IF(AI$8=$CP$9,$CP50,IF(AI$8=$CQ$9,$CQ50,"НЕТ")))))))))))))))))))))))) -> ДА | AJ50: =IF(AJ$8=$BT$9,$BT50,IF(AJ$8=$BS$9,$BS50,IF(AJ$8=$BU$9,$BU50,IF(AJ$8=$BV$9,$BV50,IF(AJ$8=$BW$9,$BW50,IF(AJ$8=$BX$9,$BX50,IF(AJ$8=$BY$9,$BY50,IF(AJ$8=$BZ$9,$BZ50,IF(AJ$8=$CA$9,$CA50,IF(AJ$8=$CC$9,$CC50,IF(AJ$8=$CD$9,$CD50,IF(AJ$8=$CE$9,$CE50,IF(AJ$8=$CF$9,$CF50,IF(AJ$8=$CG$9,$CG50,IF(AJ$8=$CH$9,$CH50,IF(AJ$8=$CI$9,$CI50,IF(AJ$8=$CJ$9,$CJ50,IF(AJ$8=$CK$9,$CK50,IF(AJ$8=$CL$9,$CL50,IF(AJ$8=$CM$9,$CM50,IF(AJ$8=$CN$9,$CN50,IF(AJ$8=$CO$9,$CO50,IF(AJ$8=$CP$9,$CP50,IF(AJ$8=$CQ$9,$CQ50,"НЕТ")))))))))))))))))))))))) -> НЕТ | AK50: =IF(AK$8=$BT$9,$BT50,IF(AK$8=$BS$9,$BS50,IF(AK$8=$BU$9,$BU50,IF(AK$8=$BV$9,$BV50,IF(AK$8=$BW$9,$BW50,IF(AK$8=$BX$9,$BX50,IF(AK$8=$BY$9,$BY50,IF(AK$8=$BZ$9,$BZ50,IF(AK$8=$CA$9,$CA50,IF(AK$8=$CC$9,$CC50,IF(AK$8=$CD$9,$CD50,IF(AK$8=$CE$9,$CE50,IF(AK$8=$CF$9,$CF50,IF(AK$8=$CG$9,$CG50,IF(AK$8=$CH$9,$CH50,IF(AK$8=$CI$9,$CI50,IF(AK$8=$CJ$9,$CJ50,IF(AK$8=$CK$9,$CK50,IF(AK$8=$CL$9,$CL50,IF(AK$8=$CM$9,$CM50,IF(AK$8=$CN$9,$CN50,IF(AK$8=$CO$9,$CO50,IF(AK$8=$CP$9,$CP50,IF(AK$8=$CQ$9,$CQ50,"НЕТ")))))))))))))))))))))))) -> НЕТ | AL50: =IF(AL$8=$BT$9,$BT50,IF(AL$8=$BS$9,$BS50,IF(AL$8=$BU$9,$BU50,IF(AL$8=$BV$9,$BV50,IF(AL$8=$BW$9,$BW50,IF(AL$8=$BX$9,$BX50,IF(AL$8=$BY$9,$BY50,IF(AL$8=$BZ$9,$BZ50,IF(AL$8=$CA$9,$CA50,IF(AL$8=$CC$9,$CC50,IF(AL$8=$CD$9,$CD50,IF(AL$8=$CE$9,$CE50,IF(AL$8=$CF$9,$CF50,IF(AL$8=$CG$9,$CG50,IF(AL$8=$CH$9,$CH50,IF(AL$8=$CI$9,$CI50,IF(AL$8=$CJ$9,$CJ50,IF(AL$8=$CK$9,$CK50,IF(AL$8=$CL$9,$CL50,IF(AL$8=$CM$9,$CM50,IF(AL$8=$CN$9,$CN50,IF(AL$8=$CO$9,$CO50,IF(AL$8=$CP$9,$CP50,IF(AL$8=$CQ$9,$CQ50,"НЕТ")))))))))))))))))))))))) -> НЕТ | AM50: =IF(AL50="НЕТ","Не требуется",$CR50) -> Не требуется | AS50: =IF(BS50="ДА",$M50,"") -> 1 | AT50: =IF(BT50="ДА",$M50,"") -> 1 | AU50: =IF(BU50="ДА",$M50,"") -> 1 | AV50: =IF(BV50="ДА",$M50,"") -> 1 | AW50: =IF(BX50="ДА",$M50,"") -> 1 | AX50: =IF(BY50="ДА",$M50,"") -> 1 | AY50: =IF(BZ50="ДА",$M50,"") -> 1 | AZ50: =IF(CA50="ДА",$M50,"") -> 1 | BB50: =IF(CC50="ДА",$M50,"") | BC50: =IF(CD50="ДА",$M50,"") | BD50: =IF(CE50="ДА",$M50,"") | BE50: =IF(CF50="ДА",$M50,"") -> 1 | BF50: =IF(CG50="ДА",$M50,"") -> 1 | BG50: =IF(CH50="ДА",$M50,"") -> 1 | BH50: =IF(CI50="ДА",$M50,"") | BI50: =IF(CJ50="ДА",$M50,"") -> 1 | ... BP50: =IF(CQ50="ДА",$M50,"") | BS50: ДА | BT50: ДА | BU50: ДА | BV50: ДА | BW50: ДА | BX50: ДА | BY50: ДА | BZ50: ДА | CA50: ДА | CC50: НЕТ | CD50: НЕТ | CE50: НЕТ | CF50: ДА | CG50: ДА | CH50: ДА | CI50: НЕТ | CJ50: ДА | CK50: ДА | CL50: НЕТ | CM50: ДА | CN50: НЕТ | CO50: НЕТ | CP50: НЕТ | CQ50: НЕТ | CR50: Не требуется
B51: Сохранение проекта в Шаблон | C51: Нет отдельного объекта = Шаблон. Эталонный проект такой же проект как и другие. Любой план можно назначить шаблоном | N51: =SUM(O51,R51,U51,X51) -> 0
B52: Панель шаблона проекта | C52: Нет отдельного объекта = Шаблон. Эталонный проект такой же проект как и другие. | N52: =SUM(O52,R52,U52,X52) -> 0
B53: Создание проекта из Шаблона | C53: Нет возможности предварительного моделирования проекта. Нет возможности заполнить НСИ и тд из шаблона | N53: =SUM(O53,R53,U53,X53) -> 0
A54: 2.3. | B54: Учесть выполнение работ проектов | F54: Базовый | G54: Кейс-проект | H54: Да | I54: Да | J54: Да | K54: Да | L54: Да | M54: 1 | N54: =SUM(O54,R54,U54,X54) -> 3 | O54: =IF(AC54="ДА",$M54,"") -> 1 | Q54: =IF(AC54="ДА",ROUNDUP(O54/5,0),0) -> 1 | R54: =IF(AF54="ДА",$M54,"") -> 1 | T54: =IF(AF54="ДА",ROUNDUP(R54/5,0),0) -> 1 | U54: =IF(AI54="ДА",$M54,"") -> 1 | W54: =IF(AI54="ДА",ROUNDUP(U54/5,0),0) -> 1 | X54: =IF(AL54="ДА",$M54,"") | Z54: =IF(AL54="ДА",ROUNDUP(X54/5,0),0) -> 0 | AA54: =IF(OR(AC54="ДА",AF54="ДА",AI54="ДА",AL54="ДА"),"ДА","НЕТ") -> ДА | AC54: =IF(AC$8=$BT$9,$BT54,IF(AC$8=$BS$9,$BS54,IF(AC$8=$BU$9,$BU54,IF(AC$8=$BV$9,$BV54,IF(AC$8=$BW$9,$BW54,IF(AC$8=$BX$9,$BX54,IF(AC$8=$BY$9,$BY54,IF(AC$8=$BZ$9,$BZ54,IF(AC$8=$CA$9,$CA54,IF(AC$8=$CC$9,$CC54,IF(AC$8=$CD$9,$CD54,IF(AC$8=$CE$9,$CE54,IF(AC$8=$CF$9,$CF54,IF(AC$8=$CG$9,$CG54,IF(AC$8=$CH$9,$CH54,IF(AC$8=$CI$9,$CI54,IF(AC$8=$CJ$9,$CJ54,IF(AC$8=$CK$9,$CK54,IF(AC$8=$CL$9,$CL54,IF(AC$8=$CM$9,$CM54,IF(AC$8=$CN$9,$CN54,IF(AC$8=$CO$9,$CO54,IF(AC$8=$CP$9,$CP54,IF(AC$8=$CQ$9,$CQ54,"НЕТ")))))))))))))))))))))))) -> ДА | AD54: =IF(AC54="НЕТ","Не требуется",$CR54) -> Не требуется | AF54: =IF(AF$8=$BT$9,$BT54,IF(AF$8=$BS$9,$BS54,IF(AF$8=$BU$9,$BU54,IF(AF$8=$BV$9,$BV54,IF(AF$8=$BW$9,$BW54,IF(AF$8=$BX$9,$BX54,IF(AF$8=$BY$9,$BY54,IF(AF$8=$BZ$9,$BZ54,IF(AF$8=$CA$9,$CA54,IF(AF$8=$CC$9,$CC54,IF(AF$8=$CD$9,$CD54,IF(AF$8=$CE$9,$CE54,IF(AF$8=$CF$9,$CF54,IF(AF$8=$CG$9,$CG54,IF(AF$8=$CH$9,$CH54,IF(AF$8=$CI$9,$CI54,IF(AF$8=$CJ$9,$CJ54,IF(AF$8=$CK$9,$CK54,IF(AF$8=$CL$9,$CL54,IF(AF$8=$CM$9,$CM54,IF(AF$8=$CN$9,$CN54,IF(AF$8=$CO$9,$CO54,IF(AF$8=$CP$9,$CP54,IF(AF$8=$CQ$9,$CQ54,"НЕТ")))))))))))))))))))))))) -> ДА | AG54: =IF(AG$8=$BT$9,$BT54,IF(AG$8=$BS$9,$BS54,IF(AG$8=$BU$9,$BU54,IF(AG$8=$BV$9,$BV54,IF(AG$8=$BW$9,$BW54,IF(AG$8=$BX$9,$BX54,IF(AG$8=$BY$9,$BY54,IF(AG$8=$BZ$9,$BZ54,IF(AG$8=$CA$9,$CA54,IF(AG$8=$CC$9,$CC54,IF(AG$8=$CD$9,$CD54,IF(AG$8=$CE$9,$CE54,IF(AG$8=$CF$9,$CF54,IF(AG$8=$CG$9,$CG54,IF(AG$8=$CH$9,$CH54,IF(AG$8=$CI$9,$CI54,IF(AG$8=$CJ$9,$CJ54,IF(AG$8=$CK$9,$CK54,IF(AG$8=$CL$9,$CL54,IF(AG$8=$CM$9,$CM54,IF(AG$8=$CN$9,$CN54,IF(AG$8=$CO$9,$CO54,IF(AG$8=$CP$9,$CP54,IF(AG$8=$CQ$9,$CQ54,"НЕТ")))))))))))))))))))))))) -> НЕТ | AH54: =IF(AH$8=$BT$9,$BT54,IF(AH$8=$BS$9,$BS54,IF(AH$8=$BU$9,$BU54,IF(AH$8=$BV$9,$BV54,IF(AH$8=$BW$9,$BW54,IF(AH$8=$BX$9,$BX54,IF(AH$8=$BY$9,$BY54,IF(AH$8=$BZ$9,$BZ54,IF(AH$8=$CA$9,$CA54,IF(AH$8=$CC$9,$CC54,IF(AH$8=$CD$9,$CD54,IF(AH$8=$CE$9,$CE54,IF(AH$8=$CF$9,$CF54,IF(AH$8=$CG$9,$CG54,IF(AH$8=$CH$9,$CH54,IF(AH$8=$CI$9,$CI54,IF(AH$8=$CJ$9,$CJ54,IF(AH$8=$CK$9,$CK54,IF(AH$8=$CL$9,$CL54,IF(AH$8=$CM$9,$CM54,IF(AH$8=$CN$9,$CN54,IF(AH$8=$CO$9,$CO54,IF(AH$8=$CP$9,$CP54,IF(AH$8=$CQ$9,$CQ54,"НЕТ")))))))))))))))))))))))) -> НЕТ | AI54: =IF(AI$8=$BT$9,$BT54,IF(AI$8=$BS$9,$BS54,IF(AI$8=$BU$9,$BU54,IF(AI$8=$BV$9,$BV54,IF(AI$8=$BW$9,$BW54,IF(AI$8=$BX$9,$BX54,IF(AI$8=$BY$9,$BY54,IF(AI$8=$BZ$9,$BZ54,IF(AI$8=$CA$9,$CA54,IF(AI$8=$CC$9,$CC54,IF(AI$8=$CD$9,$CD54,IF(AI$8=$CE$9,$CE54,IF(AI$8=$CF$9,$CF54,IF(AI$8=$CG$9,$CG54,IF(AI$8=$CH$9,$CH54,IF(AI$8=$CI$9,$CI54,IF(AI$8=$CJ$9,$CJ54,IF(AI$8=$CK$9,$CK54,IF(AI$8=$CL$9,$CL54,IF(AI$8=$CM$9,$CM54,IF(AI$8=$CN$9,$CN54,IF(AI$8=$CO$9,$CO54,IF(AI$8=$CP$9,$CP54,IF(AI$8=$CQ$9,$CQ54,"НЕТ")))))))))))))))))))))))) -> ДА | AJ54: =IF(AJ$8=$BT$9,$BT54,IF(AJ$8=$BS$9,$BS54,IF(AJ$8=$BU$9,$BU54,IF(AJ$8=$BV$9,$BV54,IF(AJ$8=$BW$9,$BW54,IF(AJ$8=$BX$9,$BX54,IF(AJ$8=$BY$9,$BY54,IF(AJ$8=$BZ$9,$BZ54,IF(AJ$8=$CA$9,$CA54,IF(AJ$8=$CC$9,$CC54,IF(AJ$8=$CD$9,$CD54,IF(AJ$8=$CE$9,$CE54,IF(AJ$8=$CF$9,$CF54,IF(AJ$8=$CG$9,$CG54,IF(AJ$8=$CH$9,$CH54,IF(AJ$8=$CI$9,$CI54,IF(AJ$8=$CJ$9,$CJ54,IF(AJ$8=$CK$9,$CK54,IF(AJ$8=$CL$9,$CL54,IF(AJ$8=$CM$9,$CM54,IF(AJ$8=$CN$9,$CN54,IF(AJ$8=$CO$9,$CO54,IF(AJ$8=$CP$9,$CP54,IF(AJ$8=$CQ$9,$CQ54,"НЕТ")))))))))))))))))))))))) -> НЕТ | AK54: =IF(AK$8=$BT$9,$BT54,IF(AK$8=$BS$9,$BS54,IF(AK$8=$BU$9,$BU54,IF(AK$8=$BV$9,$BV54,IF(AK$8=$BW$9,$BW54,IF(AK$8=$BX$9,$BX54,IF(AK$8=$BY$9,$BY54,IF(AK$8=$BZ$9,$BZ54,IF(AK$8=$CA$9,$CA54,IF(AK$8=$CC$9,$CC54,IF(AK$8=$CD$9,$CD54,IF(AK$8=$CE$9,$CE54,IF(AK$8=$CF$9,$CF54,IF(AK$8=$CG$9,$CG54,IF(AK$8=$CH$9,$CH54,IF(AK$8=$CI$9,$CI54,IF(AK$8=$CJ$9,$CJ54,IF(AK$8=$CK$9,$CK54,IF(AK$8=$CL$9,$CL54,IF(AK$8=$CM$9,$CM54,IF(AK$8=$CN$9,$CN54,IF(AK$8=$CO$9,$CO54,IF(AK$8=$CP$9,$CP54,IF(AK$8=$CQ$9,$CQ54,"НЕТ")))))))))))))))))))))))) -> НЕТ | AL54: =IF(AL$8=$BT$9,$BT54,IF(AL$8=$BS$9,$BS54,IF(AL$8=$BU$9,$BU54,IF(AL$8=$BV$9,$BV54,IF(AL$8=$BW$9,$BW54,IF(AL$8=$BX$9,$BX54,IF(AL$8=$BY$9,$BY54,IF(AL$8=$BZ$9,$BZ54,IF(AL$8=$CA$9,$CA54,IF(AL$8=$CC$9,$CC54,IF(AL$8=$CD$9,$CD54,IF(AL$8=$CE$9,$CE54,IF(AL$8=$CF$9,$CF54,IF(AL$8=$CG$9,$CG54,IF(AL$8=$CH$9,$CH54,IF(AL$8=$CI$9,$CI54,IF(AL$8=$CJ$9,$CJ54,IF(AL$8=$CK$9,$CK54,IF(AL$8=$CL$9,$CL54,IF(AL$8=$CM$9,$CM54,IF(AL$8=$CN$9,$CN54,IF(AL$8=$CO$9,$CO54,IF(AL$8=$CP$9,$CP54,IF(AL$8=$CQ$9,$CQ54,"НЕТ")))))))))))))))))))))))) -> НЕТ | AM54: =IF(AL54="НЕТ","Не требуется",$CR54) -> Не требуется | AS54: =IF(BS54="ДА",$M54,"") -> 1 | AT54: =IF(BT54="ДА",$M54,"") -> 1 | AU54: =IF(BU54="ДА",$M54,"") -> 1 | AV54: =IF(BV54="ДА",$M54,"") -> 1 | AW54: =IF(BX54="ДА",$M54,"") -> 1 | AX54: =IF(BY54="ДА",$M54,"") -> 1 | AY54: =IF(BZ54="ДА",$M54,"") -> 1 | AZ54: =IF(CA54="ДА",$M54,"") -> 1 | BB54: =IF(CC54="ДА",$M54,"") -> 1 | BC54: =IF(CD54="ДА",$M54,"") -> 1 | BD54: =IF(CE54="ДА",$M54,"") -> 1 | BE54: =IF(CF54="ДА",$M54,"") -> 1 | BF54: =IF(CG54="ДА",$M54,"") -> 1 | BG54: =IF(CH54="ДА",$M54,"") -> 1 | BH54: =IF(CI54="ДА",$M54,"") -> 1 | BI54: =IF(CJ54="ДА",$M54,"") -> 1 | ... BP54: =IF(CQ54="ДА",$M54,"") | BS54: ДА | BT54: ДА | BU54: ДА | BV54: ДА | BW54: ДА | BX54: ДА | BY54: ДА | BZ54: ДА | CA54: ДА | CC54: ДА | CD54: ДА | CE54: ДА | CF54: ДА | CG54: ДА | CH54: ДА | CI54: ДА | CJ54: ДА | CK54: ДА | CL54: НЕТ | CM54: НЕТ | CN54: НЕТ | CO54: НЕТ | CP54: НЕТ | CQ54: НЕТ | CR54: Не требуется
B55: Отражение выполнение работ по задачам проекта | C55: В проработке концепция ограничений на действия с элементами плана в разных статусах. Вручную устанавливаем % и статусы задач | N55: =SUM(O55,R55,U55,X55) -> 0
B56: Прохождение технологических событий проекта | C56: Прохождение технологических событий проекта | N56: =SUM(O56,R56,U56,X56) -> 0
B57: Прохождение ключевых событий проекта | C57: Прохождение ключевых событий проекта | N57: =SUM(O57,R57,U57,X57) -> 0
B58: План-фактный анализ выполнения работ проекта и прохождения ключевых событий и технологических операций | C58: Частично есть, требует уточнения | N58: =SUM(O58,R58,U58,X58) -> 0
A59: 2.4. | B59: Управлять ЖЦ проектов | F59: Базовый | G59: Кейс-проект | H59: Да | I59: Да | J59: Да | K59: Да | L59: В разработке | M59: 1 | N59: =SUM(O59,R59,U59,X59) -> 3 | O59: =IF(AC59="ДА",$M59,"") -> 1 | Q59: =IF(AC59="ДА",ROUNDUP(O59/5,0),0) -> 1 | R59: =IF(AF59="ДА",$M59,"") -> 1 | T59: =IF(AF59="ДА",ROUNDUP(R59/5,0),0) -> 1 | U59: =IF(AI59="ДА",$M59,"") -> 1 | W59: =IF(AI59="ДА",ROUNDUP(U59/5,0),0) -> 1 | X59: =IF(AL59="ДА",$M59,"") | Z59: =IF(AL59="ДА",ROUNDUP(X59/5,0),0) -> 0 | AA59: =IF(OR(AC59="ДА",AF59="ДА",AI59="ДА",AL59="ДА"),"ДА","НЕТ") -> ДА | AC59: =IF(AC$8=$BT$9,$BT59,IF(AC$8=$BS$9,$BS59,IF(AC$8=$BU$9,$BU59,IF(AC$8=$BV$9,$BV59,IF(AC$8=$BW$9,$BW59,IF(AC$8=$BX$9,$BX59,IF(AC$8=$BY$9,$BY59,IF(AC$8=$BZ$9,$BZ59,IF(AC$8=$CA$9,$CA59,IF(AC$8=$CC$9,$CC59,IF(AC$8=$CD$9,$CD59,IF(AC$8=$CE$9,$CE59,IF(AC$8=$CF$9,$CF59,IF(AC$8=$CG$9,$CG59,IF(AC$8=$CH$9,$CH59,IF(AC$8=$CI$9,$CI59,IF(AC$8=$CJ$9,$CJ59,IF(AC$8=$CK$9,$CK59,IF(AC$8=$CL$9,$CL59,IF(AC$8=$CM$9,$CM59,IF(AC$8=$CN$9,$CN59,IF(AC$8=$CO$9,$CO59,IF(AC$8=$CP$9,$CP59,IF(AC$8=$CQ$9,$CQ59,"НЕТ")))))))))))))))))))))))) -> ДА | AD59: =IF(AC59="НЕТ","Не требуется",$CR59) -> Не требуется | AF59: =IF(AF$8=$BT$9,$BT59,IF(AF$8=$BS$9,$BS59,IF(AF$8=$BU$9,$BU59,IF(AF$8=$BV$9,$BV59,IF(AF$8=$BW$9,$BW59,IF(AF$8=$BX$9,$BX59,IF(AF$8=$BY$9,$BY59,IF(AF$8=$BZ$9,$BZ59,IF(AF$8=$CA$9,$CA59,IF(AF$8=$CC$9,$CC59,IF(AF$8=$CD$9,$CD59,IF(AF$8=$CE$9,$CE59,IF(AF$8=$CF$9,$CF59,IF(AF$8=$CG$9,$CG59,IF(AF$8=$CH$9,$CH59,IF(AF$8=$CI$9,$CI59,IF(AF$8=$CJ$9,$CJ59,IF(AF$8=$CK$9,$CK59,IF(AF$8=$CL$9,$CL59,IF(AF$8=$CM$9,$CM59,IF(AF$8=$CN$9,$CN59,IF(AF$8=$CO$9,$CO59,IF(AF$8=$CP$9,$CP59,IF(AF$8=$CQ$9,$CQ59,"НЕТ")))))))))))))))))))))))) -> ДА | AG59: =IF(AG$8=$BT$9,$BT59,IF(AG$8=$BS$9,$BS59,IF(AG$8=$BU$9,$BU59,IF(AG$8=$BV$9,$BV59,IF(AG$8=$BW$9,$BW59,IF(AG$8=$BX$9,$BX59,IF(AG$8=$BY$9,$BY59,IF(AG$8=$BZ$9,$BZ59,IF(AG$8=$CA$9,$CA59,IF(AG$8=$CC$9,$CC59,IF(AG$8=$CD$9,$CD59,IF(AG$8=$CE$9,$CE59,IF(AG$8=$CF$9,$CF59,IF(AG$8=$CG$9,$CG59,IF(AG$8=$CH$9,$CH59,IF(AG$8=$CI$9,$CI59,IF(AG$8=$CJ$9,$CJ59,IF(AG$8=$CK$9,$CK59,IF(AG$8=$CL$9,$CL59,IF(AG$8=$CM$9,$CM59,IF(AG$8=$CN$9,$CN59,IF(AG$8=$CO$9,$CO59,IF(AG$8=$CP$9,$CP59,IF(AG$8=$CQ$9,$CQ59,"НЕТ")))))))))))))))))))))))) -> НЕТ | AH59: =IF(AH$8=$BT$9,$BT59,IF(AH$8=$BS$9,$BS59,IF(AH$8=$BU$9,$BU59,IF(AH$8=$BV$9,$BV59,IF(AH$8=$BW$9,$BW59,IF(AH$8=$BX$9,$BX59,IF(AH$8=$BY$9,$BY59,IF(AH$8=$BZ$9,$BZ59,IF(AH$8=$CA$9,$CA59,IF(AH$8=$CC$9,$CC59,IF(AH$8=$CD$9,$CD59,IF(AH$8=$CE$9,$CE59,IF(AH$8=$CF$9,$CF59,IF(AH$8=$CG$9,$CG59,IF(AH$8=$CH$9,$CH59,IF(AH$8=$CI$9,$CI59,IF(AH$8=$CJ$9,$CJ59,IF(AH$8=$CK$9,$CK59,IF(AH$8=$CL$9,$CL59,IF(AH$8=$CM$9,$CM59,IF(AH$8=$CN$9,$CN59,IF(AH$8=$CO$9,$CO59,IF(AH$8=$CP$9,$CP59,IF(AH$8=$CQ$9,$CQ59,"НЕТ")))))))))))))))))))))))) -> НЕТ | AI59: =IF(AI$8=$BT$9,$BT59,IF(AI$8=$BS$9,$BS59,IF(AI$8=$BU$9,$BU59,IF(AI$8=$BV$9,$BV59,IF(AI$8=$BW$9,$BW59,IF(AI$8=$BX$9,$BX59,IF(AI$8=$BY$9,$BY59,IF(AI$8=$BZ$9,$BZ59,IF(AI$8=$CA$9,$CA59,IF(AI$8=$CC$9,$CC59,IF(AI$8=$CD$9,$CD59,IF(AI$8=$CE$9,$CE59,IF(AI$8=$CF$9,$CF59,IF(AI$8=$CG$9,$CG59,IF(AI$8=$CH$9,$CH59,IF(AI$8=$CI$9,$CI59,IF(AI$8=$CJ$9,$CJ59,IF(AI$8=$CK$9,$CK59,IF(AI$8=$CL$9,$CL59,IF(AI$8=$CM$9,$CM59,IF(AI$8=$CN$9,$CN59,IF(AI$8=$CO$9,$CO59,IF(AI$8=$CP$9,$CP59,IF(AI$8=$CQ$9,$CQ59,"НЕТ")))))))))))))))))))))))) -> ДА | AJ59: =IF(AJ$8=$BT$9,$BT59,IF(AJ$8=$BS$9,$BS59,IF(AJ$8=$BU$9,$BU59,IF(AJ$8=$BV$9,$BV59,IF(AJ$8=$BW$9,$BW59,IF(AJ$8=$BX$9,$BX59,IF(AJ$8=$BY$9,$BY59,IF(AJ$8=$BZ$9,$BZ59,IF(AJ$8=$CA$9,$CA59,IF(AJ$8=$CC$9,$CC59,IF(AJ$8=$CD$9,$CD59,IF(AJ$8=$CE$9,$CE59,IF(AJ$8=$CF$9,$CF59,IF(AJ$8=$CG$9,$CG59,IF(AJ$8=$CH$9,$CH59,IF(AJ$8=$CI$9,$CI59,IF(AJ$8=$CJ$9,$CJ59,IF(AJ$8=$CK$9,$CK59,IF(AJ$8=$CL$9,$CL59,IF(AJ$8=$CM$9,$CM59,IF(AJ$8=$CN$9,$CN59,IF(AJ$8=$CO$9,$CO59,IF(AJ$8=$CP$9,$CP59,IF(AJ$8=$CQ$9,$CQ59,"НЕТ")))))))))))))))))))))))) -> НЕТ | AK59: =IF(AK$8=$BT$9,$BT59,IF(AK$8=$BS$9,$BS59,IF(AK$8=$BU$9,$BU59,IF(AK$8=$BV$9,$BV59,IF(AK$8=$BW$9,$BW59,IF(AK$8=$BX$9,$BX59,IF(AK$8=$BY$9,$BY59,IF(AK$8=$BZ$9,$BZ59,IF(AK$8=$CA$9,$CA59,IF(AK$8=$CC$9,$CC59,IF(AK$8=$CD$9,$CD59,IF(AK$8=$CE$9,$CE59,IF(AK$8=$CF$9,$CF59,IF(AK$8=$CG$9,$CG59,IF(AK$8=$CH$9,$CH59,IF(AK$8=$CI$9,$CI59,IF(AK$8=$CJ$9,$CJ59,IF(AK$8=$CK$9,$CK59,IF(AK$8=$CL$9,$CL59,IF(AK$8=$CM$9,$CM59,IF(AK$8=$CN$9,$CN59,IF(AK$8=$CO$9,$CO59,IF(AK$8=$CP$9,$CP59,IF(AK$8=$CQ$9,$CQ59,"НЕТ")))))))))))))))))))))))) -> НЕТ | AL59: =IF(AL$8=$BT$9,$BT59,IF(AL$8=$BS$9,$BS59,IF(AL$8=$BU$9,$BU59,IF(AL$8=$BV$9,$BV59,IF(AL$8=$BW$9,$BW59,IF(AL$8=$BX$9,$BX59,IF(AL$8=$BY$9,$BY59,IF(AL$8=$BZ$9,$BZ59,IF(AL$8=$CA$9,$CA59,IF(AL$8=$CC$9,$CC59,IF(AL$8=$CD$9,$CD59,IF(AL$8=$CE$9,$CE59,IF(AL$8=$CF$9,$CF59,IF(AL$8=$CG$9,$CG59,IF(AL$8=$CH$9,$CH59,IF(AL$8=$CI$9,$CI59,IF(AL$8=$CJ$9,$CJ59,IF(AL$8=$CK$9,$CK59,IF(AL$8=$CL$9,$CL59,IF(AL$8=$CM$9,$CM59,IF(AL$8=$CN$9,$CN59,IF(AL$8=$CO$9,$CO59,IF(AL$8=$CP$9,$CP59,IF(AL$8=$CQ$9,$CQ59,"НЕТ")))))))))))))))))))))))) -> НЕТ | AM59: =IF(AL59="НЕТ","Не требуется",$CR59) -> Не требуется | AS59: =IF(BS59="ДА",$M59,"") -> 1 | AT59: =IF(BT59="ДА",$M59,"") | AU59: =IF(BU59="ДА",$M59,"") -> 1 | AV59: =IF(BV59="ДА",$M59,"") -> 1 | AW59: =IF(BX59="ДА",$M59,"") -> 1 | AX59: =IF(BY59="ДА",$M59,"") -> 1 | AY59: =IF(BZ59="ДА",$M59,"") -> 1 | AZ59: =IF(CA59="ДА",$M59,"") -> 1 | BB59: =IF(CC59="ДА",$M59,"") | BC59: =IF(CD59="ДА",$M59,"") -> 1 | BD59: =IF(CE59="ДА",$M59,"") | BE59: =IF(CF59="ДА",$M59,"") -> 1 | BF59: =IF(CG59="ДА",$M59,"") | BG59: =IF(CH59="ДА",$M59,"") -> 1 | BH59: =IF(CI59="ДА",$M59,"") -> 1 | BI59: =IF(CJ59="ДА",$M59,"") -> 1 | ... BP59: =IF(CQ59="ДА",$M59,"") | BS59: ДА | BT59: НЕТ | BU59: ДА | BV59: ДА | BW59: ДА | BX59: ДА | BY59: ДА | BZ59: ДА | CA59: ДА | CC59: НЕТ | CD59: ДА | CE59: НЕТ | CF59: ДА | CG59: НЕТ | CH59: ДА | CI59: ДА | CJ59: ДА | CK59: ДА | CL59: НЕТ | CM59: НЕТ | CN59: НЕТ | CO59: НЕТ | CP59: НЕТ | CQ59: НЕТ | CR59: Не требуется
B60: Управление статусами проектов | C60: Статус имеет как проект, так и план. Требует уточнения реализации! | N60: =SUM(O60,R60,U60,X60) -> 0
A61: 2.5. | B61: Рассчитать KPI проектов | F61: Базовый | G61: Кейс-проект | H61: Да | I61: Да | J61: Да | K61: Да | L61: В разработке | M61: 1 | N61: =SUM(O61,R61,U61,X61) -> 3 | O61: =IF(AC61="ДА",$M61,"") -> 1 | Q61: =IF(AC61="ДА",ROUNDUP(O61/5,0),0) -> 1 | R61: =IF(AF61="ДА",$M61,"") -> 1 | T61: =IF(AF61="ДА",ROUNDUP(R61/5,0),0) -> 1 | U61: =IF(AI61="ДА",$M61,"") -> 1 | W61: =IF(AI61="ДА",ROUNDUP(U61/5,0),0) -> 1 | X61: =IF(AL61="ДА",$M61,"") | Z61: =IF(AL61="ДА",ROUNDUP(X61/5,0),0) -> 0 | AA61: =IF(OR(AC61="ДА",AF61="ДА",AI61="ДА",AL61="ДА"),"ДА","НЕТ") -> ДА | AC61: =IF(AC$8=$BT$9,$BT61,IF(AC$8=$BS$9,$BS61,IF(AC$8=$BU$9,$BU61,IF(AC$8=$BV$9,$BV61,IF(AC$8=$BW$9,$BW61,IF(AC$8=$BX$9,$BX61,IF(AC$8=$BY$9,$BY61,IF(AC$8=$BZ$9,$BZ61,IF(AC$8=$CA$9,$CA61,IF(AC$8=$CC$9,$CC61,IF(AC$8=$CD$9,$CD61,IF(AC$8=$CE$9,$CE61,IF(AC$8=$CF$9,$CF61,IF(AC$8=$CG$9,$CG61,IF(AC$8=$CH$9,$CH61,IF(AC$8=$CI$9,$CI61,IF(AC$8=$CJ$9,$CJ61,IF(AC$8=$CK$9,$CK61,IF(AC$8=$CL$9,$CL61,IF(AC$8=$CM$9,$CM61,IF(AC$8=$CN$9,$CN61,IF(AC$8=$CO$9,$CO61,IF(AC$8=$CP$9,$CP61,IF(AC$8=$CQ$9,$CQ61,"НЕТ")))))))))))))))))))))))) -> ДА | AD61: =IF(AC61="НЕТ","Не требуется",$CR61) -> Не требуется | AF61: =IF(AF$8=$BT$9,$BT61,IF(AF$8=$BS$9,$BS61,IF(AF$8=$BU$9,$BU61,IF(AF$8=$BV$9,$BV61,IF(AF$8=$BW$9,$BW61,IF(AF$8=$BX$9,$BX61,IF(AF$8=$BY$9,$BY61,IF(AF$8=$BZ$9,$BZ61,IF(AF$8=$CA$9,$CA61,IF(AF$8=$CC$9,$CC61,IF(AF$8=$CD$9,$CD61,IF(AF$8=$CE$9,$CE61,IF(AF$8=$CF$9,$CF61,IF(AF$8=$CG$9,$CG61,IF(AF$8=$CH$9,$CH61,IF(AF$8=$CI$9,$CI61,IF(AF$8=$CJ$9,$CJ61,IF(AF$8=$CK$9,$CK61,IF(AF$8=$CL$9,$CL61,IF(AF$8=$CM$9,$CM61,IF(AF$8=$CN$9,$CN61,IF(AF$8=$CO$9,$CO61,IF(AF$8=$CP$9,$CP61,IF(AF$8=$CQ$9,$CQ61,"НЕТ")))))))))))))))))))))))) -> ДА | AG61: =IF(AG$8=$BT$9,$BT61,IF(AG$8=$BS$9,$BS61,IF(AG$8=$BU$9,$BU61,IF(AG$8=$BV$9,$BV61,IF(AG$8=$BW$9,$BW61,IF(AG$8=$BX$9,$BX61,IF(AG$8=$BY$9,$BY61,IF(AG$8=$BZ$9,$BZ61,IF(AG$8=$CA$9,$CA61,IF(AG$8=$CC$9,$CC61,IF(AG$8=$CD$9,$CD61,IF(AG$8=$CE$9,$CE61,IF(AG$8=$CF$9,$CF61,IF(AG$8=$CG$9,$CG61,IF(AG$8=$CH$9,$CH61,IF(AG$8=$CI$9,$CI61,IF(AG$8=$CJ$9,$CJ61,IF(AG$8=$CK$9,$CK61,IF(AG$8=$CL$9,$CL61,IF(AG$8=$CM$9,$CM61,IF(AG$8=$CN$9,$CN61,IF(AG$8=$CO$9,$CO61,IF(AG$8=$CP$9,$CP61,IF(AG$8=$CQ$9,$CQ61,"НЕТ")))))))))))))))))))))))) -> НЕТ | AH61: =IF(AH$8=$BT$9,$BT61,IF(AH$8=$BS$9,$BS61,IF(AH$8=$BU$9,$BU61,IF(AH$8=$BV$9,$BV61,IF(AH$8=$BW$9,$BW61,IF(AH$8=$BX$9,$BX61,IF(AH$8=$BY$9,$BY61,IF(AH$8=$BZ$9,$BZ61,IF(AH$8=$CA$9,$CA61,IF(AH$8=$CC$9,$CC61,IF(AH$8=$CD$9,$CD61,IF(AH$8=$CE$9,$CE61,IF(AH$8=$CF$9,$CF61,IF(AH$8=$CG$9,$CG61,IF(AH$8=$CH$9,$CH61,IF(AH$8=$CI$9,$CI61,IF(AH$8=$CJ$9,$CJ61,IF(AH$8=$CK$9,$CK61,IF(AH$8=$CL$9,$CL61,IF(AH$8=$CM$9,$CM61,IF(AH$8=$CN$9,$CN61,IF(AH$8=$CO$9,$CO61,IF(AH$8=$CP$9,$CP61,IF(AH$8=$CQ$9,$CQ61,"НЕТ")))))))))))))))))))))))) -> НЕТ | AI61: =IF(AI$8=$BT$9,$BT61,IF(AI$8=$BS$9,$BS61,IF(AI$8=$BU$9,$BU61,IF(AI$8=$BV$9,$BV61,IF(AI$8=$BW$9,$BW61,IF(AI$8=$BX$9,$BX61,IF(AI$8=$BY$9,$BY61,IF(AI$8=$BZ$9,$BZ61,IF(AI$8=$CA$9,$CA61,IF(AI$8=$CC$9,$CC61,IF(AI$8=$CD$9,$CD61,IF(AI$8=$CE$9,$CE61,IF(AI$8=$CF$9,$CF61,IF(AI$8=$CG$9,$CG61,IF(AI$8=$CH$9,$CH61,IF(AI$8=$CI$9,$CI61,IF(AI$8=$CJ$9,$CJ61,IF(AI$8=$CK$9,$CK61,IF(AI$8=$CL$9,$CL61,IF(AI$8=$CM$9,$CM61,IF(AI$8=$CN$9,$CN61,IF(AI$8=$CO$9,$CO61,IF(AI$8=$CP$9,$CP61,IF(AI$8=$CQ$9,$CQ61,"НЕТ")))))))))))))))))))))))) -> ДА | AJ61: =IF(AJ$8=$BT$9,$BT61,IF(AJ$8=$BS$9,$BS61,IF(AJ$8=$BU$9,$BU61,IF(AJ$8=$BV$9,$BV61,IF(AJ$8=$BW$9,$BW61,IF(AJ$8=$BX$9,$BX61,IF(AJ$8=$BY$9,$BY61,IF(AJ$8=$BZ$9,$BZ61,IF(AJ$8=$CA$9,$CA61,IF(AJ$8=$CC$9,$CC61,IF(AJ$8=$CD$9,$CD61,IF(AJ$8=$CE$9,$CE61,IF(AJ$8=$CF$9,$CF61,IF(AJ$8=$CG$9,$CG61,IF(AJ$8=$CH$9,$CH61,IF(AJ$8=$CI$9,$CI61,IF(AJ$8=$CJ$9,$CJ61,IF(AJ$8=$CK$9,$CK61,IF(AJ$8=$CL$9,$CL61,IF(AJ$8=$CM$9,$CM61,IF(AJ$8=$CN$9,$CN61,IF(AJ$8=$CO$9,$CO61,IF(AJ$8=$CP$9,$CP61,IF(AJ$8=$CQ$9,$CQ61,"НЕТ")))))))))))))))))))))))) -> НЕТ | AK61: =IF(AK$8=$BT$9,$BT61,IF(AK$8=$BS$9,$BS61,IF(AK$8=$BU$9,$BU61,IF(AK$8=$BV$9,$BV61,IF(AK$8=$BW$9,$BW61,IF(AK$8=$BX$9,$BX61,IF(AK$8=$BY$9,$BY61,IF(AK$8=$BZ$9,$BZ61,IF(AK$8=$CA$9,$CA61,IF(AK$8=$CC$9,$CC61,IF(AK$8=$CD$9,$CD61,IF(AK$8=$CE$9,$CE61,IF(AK$8=$CF$9,$CF61,IF(AK$8=$CG$9,$CG61,IF(AK$8=$CH$9,$CH61,IF(AK$8=$CI$9,$CI61,IF(AK$8=$CJ$9,$CJ61,IF(AK$8=$CK$9,$CK61,IF(AK$8=$CL$9,$CL61,IF(AK$8=$CM$9,$CM61,IF(AK$8=$CN$9,$CN61,IF(AK$8=$CO$9,$CO61,IF(AK$8=$CP$9,$CP61,IF(AK$8=$CQ$9,$CQ61,"НЕТ")))))))))))))))))))))))) -> НЕТ | AL61: =IF(AL$8=$BT$9,$BT61,IF(AL$8=$BS$9,$BS61,IF(AL$8=$BU$9,$BU61,IF(AL$8=$BV$9,$BV61,IF(AL$8=$BW$9,$BW61,IF(AL$8=$BX$9,$BX61,IF(AL$8=$BY$9,$BY61,IF(AL$8=$BZ$9,$BZ61,IF(AL$8=$CA$9,$CA61,IF(AL$8=$CC$9,$CC61,IF(AL$8=$CD$9,$CD61,IF(AL$8=$CE$9,$CE61,IF(AL$8=$CF$9,$CF61,IF(AL$8=$CG$9,$CG61,IF(AL$8=$CH$9,$CH61,IF(AL$8=$CI$9,$CI61,IF(AL$8=$CJ$9,$CJ61,IF(AL$8=$CK$9,$CK61,IF(AL$8=$CL$9,$CL61,IF(AL$8=$CM$9,$CM61,IF(AL$8=$CN$9,$CN61,IF(AL$8=$CO$9,$CO61,IF(AL$8=$CP$9,$CP61,IF(AL$8=$CQ$9,$CQ61,"НЕТ")))))))))))))))))))))))) -> НЕТ | AM61: =IF(AL61="НЕТ","Не требуется",$CR61) -> Не требуется | AS61: =IF(BS61="ДА",$M61,"") -> 1 | AT61: =IF(BT61="ДА",$M61,"") -> 1 | AU61: =IF(BU61="ДА",$M61,"") -> 1 | AV61: =IF(BV61="ДА",$M61,"") -> 1 | AW61: =IF(BX61="ДА",$M61,"") -> 1 | AX61: =IF(BY61="ДА",$M61,"") -> 1 | AY61: =IF(BZ61="ДА",$M61,"") -> 1 | AZ61: =IF(CA61="ДА",$M61,"") -> 1 | BB61: =IF(CC61="ДА",$M61,"") -> 1 | BC61: =IF(CD61="ДА",$M61,"") -> 1 | BD61: =IF(CE61="ДА",$M61,"") | BE61: =IF(CF61="ДА",$M61,"") | BF61: =IF(CG61="ДА",$M61,"") | BG61: =IF(CH61="ДА",$M61,"") -> 1 | BH61: =IF(CI61="ДА",$M61,"") -> 1 | BI61: =IF(CJ61="ДА",$M61,"") -> 1 | ... BP61: =IF(CQ61="ДА",$M61,"") | BS61: ДА | BT61: ДА | BU61: ДА | BV61: ДА | BW61: ДА | BX61: ДА | BY61: ДА | BZ61: ДА | CA61: ДА | CC61: ДА | CD61: ДА | CE61: НЕТ | CF61: НЕТ | CG61: НЕТ | CH61: ДА | CI61: ДА | CJ61: ДА | CK61: ДА | CL61: НЕТ | CM61: НЕТ | CN61: НЕТ | CO61: НЕТ | CP61: НЕТ | CQ61: НЕТ | CR61: Не требуется
B62: Планирование KPI проектов, этапов проектов | C62: х | N62: =SUM(O62,R62,U62,X62) -> 0
B63: Мониторинг состояния показателей | C63: Мониторинг состояния показателей | N63: =SUM(O63,R63,U63,X63) -> 0
A64: 2.6. | B64: Технологические графики проекта (график декомпозированный до уровня операций, выполняемых конкретным исполнителем, с учетом технологической последовательности работ (и в т.ч. требующие проработки методологии работы с этими задачами на нижнем уровне) | C64: В целом - нет. Табличный редактор ресурсов, декомпозиция работ проводиться в редакторе планов | F64: Экспертный | G64: КОРП-проект | H64: Да | I64: Да | J64: Да | K64: Да | L64: Да | M64: 10 | N64: =SUM(O64,R64,U64,X64) -> 10 | O64: =IF(AC64="ДА",$M64,"") | Q64: =IF(AC64="ДА",ROUNDUP(O64/5,0),0) -> 0 | R64: =IF(AF64="ДА",$M64,"") -> 10 | T64: =IF(AF64="ДА",ROUNDUP(R64/5,0),0) -> 2 | U64: =IF(AI64="ДА",$M64,"") | W64: =IF(AI64="ДА",ROUNDUP(U64/5,0),0) -> 0 | X64: =IF(AL64="ДА",$M64,"") | Z64: =IF(AL64="ДА",ROUNDUP(X64/5,0),0) -> 0 | AA64: =IF(OR(AC64="ДА",AF64="ДА",AI64="ДА",AL64="ДА"),"ДА","НЕТ") -> ДА | AC64: =IF(AC$8=$BT$9,$BT64,IF(AC$8=$BS$9,$BS64,IF(AC$8=$BU$9,$BU64,IF(AC$8=$BV$9,$BV64,IF(AC$8=$BW$9,$BW64,IF(AC$8=$BX$9,$BX64,IF(AC$8=$BY$9,$BY64,IF(AC$8=$BZ$9,$BZ64,IF(AC$8=$CA$9,$CA64,IF(AC$8=$CC$9,$CC64,IF(AC$8=$CD$9,$CD64,IF(AC$8=$CE$9,$CE64,IF(AC$8=$CF$9,$CF64,IF(AC$8=$CG$9,$CG64,IF(AC$8=$CH$9,$CH64,IF(AC$8=$CI$9,$CI64,IF(AC$8=$CJ$9,$CJ64,IF(AC$8=$CK$9,$CK64,IF(AC$8=$CL$9,$CL64,IF(AC$8=$CM$9,$CM64,IF(AC$8=$CN$9,$CN64,IF(AC$8=$CO$9,$CO64,IF(AC$8=$CP$9,$CP64,IF(AC$8=$CQ$9,$CQ64,"НЕТ")))))))))))))))))))))))) -> НЕТ | AD64: =IF(AC64="НЕТ","Не требуется",$CR64) -> Не требуется | AF64: =IF(AF$8=$BT$9,$BT64,IF(AF$8=$BS$9,$BS64,IF(AF$8=$BU$9,$BU64,IF(AF$8=$BV$9,$BV64,IF(AF$8=$BW$9,$BW64,IF(AF$8=$BX$9,$BX64,IF(AF$8=$BY$9,$BY64,IF(AF$8=$BZ$9,$BZ64,IF(AF$8=$CA$9,$CA64,IF(AF$8=$CC$9,$CC64,IF(AF$8=$CD$9,$CD64,IF(AF$8=$CE$9,$CE64,IF(AF$8=$CF$9,$CF64,IF(AF$8=$CG$9,$CG64,IF(AF$8=$CH$9,$CH64,IF(AF$8=$CI$9,$CI64,IF(AF$8=$CJ$9,$CJ64,IF(AF$8=$CK$9,$CK64,IF(AF$8=$CL$9,$CL64,IF(AF$8=$CM$9,$CM64,IF(AF$8=$CN$9,$CN64,IF(AF$8=$CO$9,$CO64,IF(AF$8=$CP$9,$CP64,IF(AF$8=$CQ$9,$CQ64,"НЕТ")))))))))))))))))))))))) -> ДА | AG64: =IF(AG$8=$BT$9,$BT64,IF(AG$8=$BS$9,$BS64,IF(AG$8=$BU$9,$BU64,IF(AG$8=$BV$9,$BV64,IF(AG$8=$BW$9,$BW64,IF(AG$8=$BX$9,$BX64,IF(AG$8=$BY$9,$BY64,IF(AG$8=$BZ$9,$BZ64,IF(AG$8=$CA$9,$CA64,IF(AG$8=$CC$9,$CC64,IF(AG$8=$CD$9,$CD64,IF(AG$8=$CE$9,$CE64,IF(AG$8=$CF$9,$CF64,IF(AG$8=$CG$9,$CG64,IF(AG$8=$CH$9,$CH64,IF(AG$8=$CI$9,$CI64,IF(AG$8=$CJ$9,$CJ64,IF(AG$8=$CK$9,$CK64,IF(AG$8=$CL$9,$CL64,IF(AG$8=$CM$9,$CM64,IF(AG$8=$CN$9,$CN64,IF(AG$8=$CO$9,$CO64,IF(AG$8=$CP$9,$CP64,IF(AG$8=$CQ$9,$CQ64,"НЕТ")))))))))))))))))))))))) -> НЕТ | AH64: =IF(AH$8=$BT$9,$BT64,IF(AH$8=$BS$9,$BS64,IF(AH$8=$BU$9,$BU64,IF(AH$8=$BV$9,$BV64,IF(AH$8=$BW$9,$BW64,IF(AH$8=$BX$9,$BX64,IF(AH$8=$BY$9,$BY64,IF(AH$8=$BZ$9,$BZ64,IF(AH$8=$CA$9,$CA64,IF(AH$8=$CC$9,$CC64,IF(AH$8=$CD$9,$CD64,IF(AH$8=$CE$9,$CE64,IF(AH$8=$CF$9,$CF64,IF(AH$8=$CG$9,$CG64,IF(AH$8=$CH$9,$CH64,IF(AH$8=$CI$9,$CI64,IF(AH$8=$CJ$9,$CJ64,IF(AH$8=$CK$9,$CK64,IF(AH$8=$CL$9,$CL64,IF(AH$8=$CM$9,$CM64,IF(AH$8=$CN$9,$CN64,IF(AH$8=$CO$9,$CO64,IF(AH$8=$CP$9,$CP64,IF(AH$8=$CQ$9,$CQ64,"НЕТ")))))))))))))))))))))))) -> НЕТ | AI64: =IF(AI$8=$BT$9,$BT64,IF(AI$8=$BS$9,$BS64,IF(AI$8=$BU$9,$BU64,IF(AI$8=$BV$9,$BV64,IF(AI$8=$BW$9,$BW64,IF(AI$8=$BX$9,$BX64,IF(AI$8=$BY$9,$BY64,IF(AI$8=$BZ$9,$BZ64,IF(AI$8=$CA$9,$CA64,IF(AI$8=$CC$9,$CC64,IF(AI$8=$CD$9,$CD64,IF(AI$8=$CE$9,$CE64,IF(AI$8=$CF$9,$CF64,IF(AI$8=$CG$9,$CG64,IF(AI$8=$CH$9,$CH64,IF(AI$8=$CI$9,$CI64,IF(AI$8=$CJ$9,$CJ64,IF(AI$8=$CK$9,$CK64,IF(AI$8=$CL$9,$CL64,IF(AI$8=$CM$9,$CM64,IF(AI$8=$CN$9,$CN64,IF(AI$8=$CO$9,$CO64,IF(AI$8=$CP$9,$CP64,IF(AI$8=$CQ$9,$CQ64,"НЕТ")))))))))))))))))))))))) -> НЕТ | AJ64: =IF(AJ$8=$BT$9,$BT64,IF(AJ$8=$BS$9,$BS64,IF(AJ$8=$BU$9,$BU64,IF(AJ$8=$BV$9,$BV64,IF(AJ$8=$BW$9,$BW64,IF(AJ$8=$BX$9,$BX64,IF(AJ$8=$BY$9,$BY64,IF(AJ$8=$BZ$9,$BZ64,IF(AJ$8=$CA$9,$CA64,IF(AJ$8=$CC$9,$CC64,IF(AJ$8=$CD$9,$CD64,IF(AJ$8=$CE$9,$CE64,IF(AJ$8=$CF$9,$CF64,IF(AJ$8=$CG$9,$CG64,IF(AJ$8=$CH$9,$CH64,IF(AJ$8=$CI$9,$CI64,IF(AJ$8=$CJ$9,$CJ64,IF(AJ$8=$CK$9,$CK64,IF(AJ$8=$CL$9,$CL64,IF(AJ$8=$CM$9,$CM64,IF(AJ$8=$CN$9,$CN64,IF(AJ$8=$CO$9,$CO64,IF(AJ$8=$CP$9,$CP64,IF(AJ$8=$CQ$9,$CQ64,"НЕТ")))))))))))))))))))))))) -> НЕТ | AK64: =IF(AK$8=$BT$9,$BT64,IF(AK$8=$BS$9,$BS64,IF(AK$8=$BU$9,$BU64,IF(AK$8=$BV$9,$BV64,IF(AK$8=$BW$9,$BW64,IF(AK$8=$BX$9,$BX64,IF(AK$8=$BY$9,$BY64,IF(AK$8=$BZ$9,$BZ64,IF(AK$8=$CA$9,$CA64,IF(AK$8=$CC$9,$CC64,IF(AK$8=$CD$9,$CD64,IF(AK$8=$CE$9,$CE64,IF(AK$8=$CF$9,$CF64,IF(AK$8=$CG$9,$CG64,IF(AK$8=$CH$9,$CH64,IF(AK$8=$CI$9,$CI64,IF(AK$8=$CJ$9,$CJ64,IF(AK$8=$CK$9,$CK64,IF(AK$8=$CL$9,$CL64,IF(AK$8=$CM$9,$CM64,IF(AK$8=$CN$9,$CN64,IF(AK$8=$CO$9,$CO64,IF(AK$8=$CP$9,$CP64,IF(AK$8=$CQ$9,$CQ64,"НЕТ")))))))))))))))))))))))) -> НЕТ | AL64: =IF(AL$8=$BT$9,$BT64,IF(AL$8=$BS$9,$BS64,IF(AL$8=$BU$9,$BU64,IF(AL$8=$BV$9,$BV64,IF(AL$8=$BW$9,$BW64,IF(AL$8=$BX$9,$BX64,IF(AL$8=$BY$9,$BY64,IF(AL$8=$BZ$9,$BZ64,IF(AL$8=$CA$9,$CA64,IF(AL$8=$CC$9,$CC64,IF(AL$8=$CD$9,$CD64,IF(AL$8=$CE$9,$CE64,IF(AL$8=$CF$9,$CF64,IF(AL$8=$CG$9,$CG64,IF(AL$8=$CH$9,$CH64,IF(AL$8=$CI$9,$CI64,IF(AL$8=$CJ$9,$CJ64,IF(AL$8=$CK$9,$CK64,IF(AL$8=$CL$9,$CL64,IF(AL$8=$CM$9,$CM64,IF(AL$8=$CN$9,$CN64,IF(AL$8=$CO$9,$CO64,IF(AL$8=$CP$9,$CP64,IF(AL$8=$CQ$9,$CQ64,"НЕТ")))))))))))))))))))))))) -> НЕТ | AM64: =IF(AL64="НЕТ","Не требуется",$CR64) -> Не требуется | AS64: =IF(BS64="ДА",$M64,"") | AT64: =IF(BT64="ДА",$M64,"") | AU64: =IF(BU64="ДА",$M64,"") | AV64: =IF(BV64="ДА",$M64,"") | AW64: =IF(BX64="ДА",$M64,"") | AX64: =IF(BY64="ДА",$M64,"") -> 10 | AY64: =IF(BZ64="ДА",$M64,"") -> 10 | AZ64: =IF(CA64="ДА",$M64,"") -> 10 | BB64: =IF(CC64="ДА",$M64,"") | BC64: =IF(CD64="ДА",$M64,"") | BD64: =IF(CE64="ДА",$M64,"") | BE64: =IF(CF64="ДА",$M64,"") -> 10 | BF64: =IF(CG64="ДА",$M64,"") -> 10 | BG64: =IF(CH64="ДА",$M64,"") | BH64: =IF(CI64="ДА",$M64,"") | BI64: =IF(CJ64="ДА",$M64,"") -> 10 | ... BP64: =IF(CQ64="ДА",$M64,"") | BS64: НЕТ | BT64: НЕТ | BU64: НЕТ | BV64: НЕТ | BW64: НЕТ | BX64: НЕТ | BY64: ДА | BZ64: ДА | CA64: ДА | CC64: НЕТ | CD64: НЕТ | CE64: НЕТ | CF64: ДА | CG64: ДА | CH64: НЕТ | CI64: НЕТ | CJ64: ДА | CK64: НЕТ | CL64: НЕТ | CM64: НЕТ | CN64: НЕТ | CO64: НЕТ | CP64: НЕТ | CQ64: НЕТ | CR64: Предоставляется Заказчиком
A65: 2.7. | B65: Разработка и формирование шаблонов проектов (требует методологической проработки) | C65: В целом - есть, но с ограничениями. Любой план можно назначить шаблоном | F65: Экспертный | G65: КОРП-проект | H65: Да | I65: Да | J65: Да | K65: Да | L65: В разработке | M65: 5 | N65: =SUM(O65,R65,U65,X65) -> 0 | O65: =IF(AC65="ДА",$M65,"") | Q65: =IF(AC65="ДА",ROUNDUP(O65/5,0),0) -> 0 | R65: =IF(AF65="ДА",$M65,"") | T65: =IF(AF65="ДА",ROUNDUP(R65/5,0),0) -> 0 | U65: =IF(AI65="ДА",$M65,"") | W65: =IF(AI65="ДА",ROUNDUP(U65/5,0),0) -> 0 | X65: =IF(AL65="ДА",$M65,"") | Z65: =IF(AL65="ДА",ROUNDUP(X65/5,0),0) -> 0 | AA65: =IF(OR(AC65="ДА",AF65="ДА",AI65="ДА",AL65="ДА"),"ДА","НЕТ") -> НЕТ | AC65: =IF(AC$8=$BT$9,$BT65,IF(AC$8=$BS$9,$BS65,IF(AC$8=$BU$9,$BU65,IF(AC$8=$BV$9,$BV65,IF(AC$8=$BW$9,$BW65,IF(AC$8=$BX$9,$BX65,IF(AC$8=$BY$9,$BY65,IF(AC$8=$BZ$9,$BZ65,IF(AC$8=$CA$9,$CA65,IF(AC$8=$CC$9,$CC65,IF(AC$8=$CD$9,$CD65,IF(AC$8=$CE$9,$CE65,IF(AC$8=$CF$9,$CF65,IF(AC$8=$CG$9,$CG65,IF(AC$8=$CH$9,$CH65,IF(AC$8=$CI$9,$CI65,IF(AC$8=$CJ$9,$CJ65,IF(AC$8=$CK$9,$CK65,IF(AC$8=$CL$9,$CL65,IF(AC$8=$CM$9,$CM65,IF(AC$8=$CN$9,$CN65,IF(AC$8=$CO$9,$CO65,IF(AC$8=$CP$9,$CP65,IF(AC$8=$CQ$9,$CQ65,"НЕТ")))))))))))))))))))))))) -> НЕТ | AD65: =IF(AC65="НЕТ","Не требуется",$CR65) -> Не требуется | AF65: =IF(AF$8=$BT$9,$BT65,IF(AF$8=$BS$9,$BS65,IF(AF$8=$BU$9,$BU65,IF(AF$8=$BV$9,$BV65,IF(AF$8=$BW$9,$BW65,IF(AF$8=$BX$9,$BX65,IF(AF$8=$BY$9,$BY65,IF(AF$8=$BZ$9,$BZ65,IF(AF$8=$CA$9,$CA65,IF(AF$8=$CC$9,$CC65,IF(AF$8=$CD$9,$CD65,IF(AF$8=$CE$9,$CE65,IF(AF$8=$CF$9,$CF65,IF(AF$8=$CG$9,$CG65,IF(AF$8=$CH$9,$CH65,IF(AF$8=$CI$9,$CI65,IF(AF$8=$CJ$9,$CJ65,IF(AF$8=$CK$9,$CK65,IF(AF$8=$CL$9,$CL65,IF(AF$8=$CM$9,$CM65,IF(AF$8=$CN$9,$CN65,IF(AF$8=$CO$9,$CO65,IF(AF$8=$CP$9,$CP65,IF(AF$8=$CQ$9,$CQ65,"НЕТ")))))))))))))))))))))))) -> НЕТ | AG65: =IF(AG$8=$BT$9,$BT65,IF(AG$8=$BS$9,$BS65,IF(AG$8=$BU$9,$BU65,IF(AG$8=$BV$9,$BV65,IF(AG$8=$BW$9,$BW65,IF(AG$8=$BX$9,$BX65,IF(AG$8=$BY$9,$BY65,IF(AG$8=$BZ$9,$BZ65,IF(AG$8=$CA$9,$CA65,IF(AG$8=$CC$9,$CC65,IF(AG$8=$CD$9,$CD65,IF(AG$8=$CE$9,$CE65,IF(AG$8=$CF$9,$CF65,IF(AG$8=$CG$9,$CG65,IF(AG$8=$CH$9,$CH65,IF(AG$8=$CI$9,$CI65,IF(AG$8=$CJ$9,$CJ65,IF(AG$8=$CK$9,$CK65,IF(AG$8=$CL$9,$CL65,IF(AG$8=$CM$9,$CM65,IF(AG$8=$CN$9,$CN65,IF(AG$8=$CO$9,$CO65,IF(AG$8=$CP$9,$CP65,IF(AG$8=$CQ$9,$CQ65,"НЕТ")))))))))))))))))))))))) -> НЕТ | AH65: =IF(AH$8=$BT$9,$BT65,IF(AH$8=$BS$9,$BS65,IF(AH$8=$BU$9,$BU65,IF(AH$8=$BV$9,$BV65,IF(AH$8=$BW$9,$BW65,IF(AH$8=$BX$9,$BX65,IF(AH$8=$BY$9,$BY65,IF(AH$8=$BZ$9,$BZ65,IF(AH$8=$CA$9,$CA65,IF(AH$8=$CC$9,$CC65,IF(AH$8=$CD$9,$CD65,IF(AH$8=$CE$9,$CE65,IF(AH$8=$CF$9,$CF65,IF(AH$8=$CG$9,$CG65,IF(AH$8=$CH$9,$CH65,IF(AH$8=$CI$9,$CI65,IF(AH$8=$CJ$9,$CJ65,IF(AH$8=$CK$9,$CK65,IF(AH$8=$CL$9,$CL65,IF(AH$8=$CM$9,$CM65,IF(AH$8=$CN$9,$CN65,IF(AH$8=$CO$9,$CO65,IF(AH$8=$CP$9,$CP65,IF(AH$8=$CQ$9,$CQ65,"НЕТ")))))))))))))))))))))))) -> НЕТ | AI65: =IF(AI$8=$BT$9,$BT65,IF(AI$8=$BS$9,$BS65,IF(AI$8=$BU$9,$BU65,IF(AI$8=$BV$9,$BV65,IF(AI$8=$BW$9,$BW65,IF(AI$8=$BX$9,$BX65,IF(AI$8=$BY$9,$BY65,IF(AI$8=$BZ$9,$BZ65,IF(AI$8=$CA$9,$CA65,IF(AI$8=$CC$9,$CC65,IF(AI$8=$CD$9,$CD65,IF(AI$8=$CE$9,$CE65,IF(AI$8=$CF$9,$CF65,IF(AI$8=$CG$9,$CG65,IF(AI$8=$CH$9,$CH65,IF(AI$8=$CI$9,$CI65,IF(AI$8=$CJ$9,$CJ65,IF(AI$8=$CK$9,$CK65,IF(AI$8=$CL$9,$CL65,IF(AI$8=$CM$9,$CM65,IF(AI$8=$CN$9,$CN65,IF(AI$8=$CO$9,$CO65,IF(AI$8=$CP$9,$CP65,IF(AI$8=$CQ$9,$CQ65,"НЕТ")))))))))))))))))))))))) -> НЕТ | AJ65: =IF(AJ$8=$BT$9,$BT65,IF(AJ$8=$BS$9,$BS65,IF(AJ$8=$BU$9,$BU65,IF(AJ$8=$BV$9,$BV65,IF(AJ$8=$BW$9,$BW65,IF(AJ$8=$BX$9,$BX65,IF(AJ$8=$BY$9,$BY65,IF(AJ$8=$BZ$9,$BZ65,IF(AJ$8=$CA$9,$CA65,IF(AJ$8=$CC$9,$CC65,IF(AJ$8=$CD$9,$CD65,IF(AJ$8=$CE$9,$CE65,IF(AJ$8=$CF$9,$CF65,IF(AJ$8=$CG$9,$CG65,IF(AJ$8=$CH$9,$CH65,IF(AJ$8=$CI$9,$CI65,IF(AJ$8=$CJ$9,$CJ65,IF(AJ$8=$CK$9,$CK65,IF(AJ$8=$CL$9,$CL65,IF(AJ$8=$CM$9,$CM65,IF(AJ$8=$CN$9,$CN65,IF(AJ$8=$CO$9,$CO65,IF(AJ$8=$CP$9,$CP65,IF(AJ$8=$CQ$9,$CQ65,"НЕТ")))))))))))))))))))))))) -> НЕТ | AK65: =IF(AK$8=$BT$9,$BT65,IF(AK$8=$BS$9,$BS65,IF(AK$8=$BU$9,$BU65,IF(AK$8=$BV$9,$BV65,IF(AK$8=$BW$9,$BW65,IF(AK$8=$BX$9,$BX65,IF(AK$8=$BY$9,$BY65,IF(AK$8=$BZ$9,$BZ65,IF(AK$8=$CA$9,$CA65,IF(AK$8=$CC$9,$CC65,IF(AK$8=$CD$9,$CD65,IF(AK$8=$CE$9,$CE65,IF(AK$8=$CF$9,$CF65,IF(AK$8=$CG$9,$CG65,IF(AK$8=$CH$9,$CH65,IF(AK$8=$CI$9,$CI65,IF(AK$8=$CJ$9,$CJ65,IF(AK$8=$CK$9,$CK65,IF(AK$8=$CL$9,$CL65,IF(AK$8=$CM$9,$CM65,IF(AK$8=$CN$9,$CN65,IF(AK$8=$CO$9,$CO65,IF(AK$8=$CP$9,$CP65,IF(AK$8=$CQ$9,$CQ65,"НЕТ")))))))))))))))))))))))) -> НЕТ | AL65: =IF(AL$8=$BT$9,$BT65,IF(AL$8=$BS$9,$BS65,IF(AL$8=$BU$9,$BU65,IF(AL$8=$BV$9,$BV65,IF(AL$8=$BW$9,$BW65,IF(AL$8=$BX$9,$BX65,IF(AL$8=$BY$9,$BY65,IF(AL$8=$BZ$9,$BZ65,IF(AL$8=$CA$9,$CA65,IF(AL$8=$CC$9,$CC65,IF(AL$8=$CD$9,$CD65,IF(AL$8=$CE$9,$CE65,IF(AL$8=$CF$9,$CF65,IF(AL$8=$CG$9,$CG65,IF(AL$8=$CH$9,$CH65,IF(AL$8=$CI$9,$CI65,IF(AL$8=$CJ$9,$CJ65,IF(AL$8=$CK$9,$CK65,IF(AL$8=$CL$9,$CL65,IF(AL$8=$CM$9,$CM65,IF(AL$8=$CN$9,$CN65,IF(AL$8=$CO$9,$CO65,IF(AL$8=$CP$9,$CP65,IF(AL$8=$CQ$9,$CQ65,"НЕТ")))))))))))))))))))))))) -> НЕТ | AM65: =IF(AL65="НЕТ","Не требуется",$CR65) -> Не требуется | AS65: =IF(BS65="ДА",$M65,"") | AT65: =IF(BT65="ДА",$M65,"") | AU65: =IF(BU65="ДА",$M65,"") | AV65: =IF(BV65="ДА",$M65,"") | AW65: =IF(BX65="ДА",$M65,"") | AX65: =IF(BY65="ДА",$M65,"") | AY65: =IF(BZ65="ДА",$M65,"") | AZ65: =IF(CA65="ДА",$M65,"") -> 5 | BB65: =IF(CC65="ДА",$M65,"") | BC65: =IF(CD65="ДА",$M65,"") | BD65: =IF(CE65="ДА",$M65,"") | BE65: =IF(CF65="ДА",$M65,"") -> 5 | BF65: =IF(CG65="ДА",$M65,"") -> 5 | BG65: =IF(CH65="ДА",$M65,"") | BH65: =IF(CI65="ДА",$M65,"") | BI65: =IF(CJ65="ДА",$M65,"") | ... BP65: =IF(CQ65="ДА",$M65,"") | BS65: НЕТ | BT65: НЕТ | BU65: НЕТ | BV65: НЕТ | BW65: НЕТ | BX65: НЕТ | BY65: НЕТ | BZ65: НЕТ | CA65: ДА | CC65: НЕТ | CD65: НЕТ | CE65: НЕТ | CF65: ДА | CG65: ДА | CH65: НЕТ | CI65: НЕТ | CJ65: НЕТ | CK65: НЕТ | CL65: НЕТ | CM65: НЕТ | CN65: НЕТ | CO65: НЕТ | CP65: НЕТ | CQ65: НЕТ | CR65: Предоставляется Заказчиком
A66: 2.8. | B66: Управление рисками | C66: нет | F66: Экспертный | G66: КОРП-проект | H66: Нет | I66: Нет | J66: Да | K66: Да | L66: Нет | M66: 5 | N66: =SUM(O66,R66,U66,X66) -> 5 | O66: =IF(AC66="ДА",$M66,"") | Q66: =IF(AC66="ДА",ROUNDUP(O66/5,0),0) -> 0 | R66: =IF(AF66="ДА",$M66,"") -> 5 | T66: =IF(AF66="ДА",ROUNDUP(R66/5,0),0) -> 1 | U66: =IF(AI66="ДА",$M66,"") | W66: =IF(AI66="ДА",ROUNDUP(U66/5,0),0) -> 0 | X66: =IF(AL66="ДА",$M66,"") | Z66: =IF(AL66="ДА",ROUNDUP(X66/5,0),0) -> 0 | AA66: =IF(OR(AC66="ДА",AF66="ДА",AI66="ДА",AL66="ДА"),"ДА","НЕТ") -> ДА | AC66: =IF(AC$8=$BT$9,$BT66,IF(AC$8=$BS$9,$BS66,IF(AC$8=$BU$9,$BU66,IF(AC$8=$BV$9,$BV66,IF(AC$8=$BW$9,$BW66,IF(AC$8=$BX$9,$BX66,IF(AC$8=$BY$9,$BY66,IF(AC$8=$BZ$9,$BZ66,IF(AC$8=$CA$9,$CA66,IF(AC$8=$CC$9,$CC66,IF(AC$8=$CD$9,$CD66,IF(AC$8=$CE$9,$CE66,IF(AC$8=$CF$9,$CF66,IF(AC$8=$CG$9,$CG66,IF(AC$8=$CH$9,$CH66,IF(AC$8=$CI$9,$CI66,IF(AC$8=$CJ$9,$CJ66,IF(AC$8=$CK$9,$CK66,IF(AC$8=$CL$9,$CL66,IF(AC$8=$CM$9,$CM66,IF(AC$8=$CN$9,$CN66,IF(AC$8=$CO$9,$CO66,IF(AC$8=$CP$9,$CP66,IF(AC$8=$CQ$9,$CQ66,"НЕТ")))))))))))))))))))))))) -> НЕТ | AD66: =IF(AC66="НЕТ","Не требуется",$CR66) -> Не требуется | AF66: =IF(AF$8=$BT$9,$BT66,IF(AF$8=$BS$9,$BS66,IF(AF$8=$BU$9,$BU66,IF(AF$8=$BV$9,$BV66,IF(AF$8=$BW$9,$BW66,IF(AF$8=$BX$9,$BX66,IF(AF$8=$BY$9,$BY66,IF(AF$8=$BZ$9,$BZ66,IF(AF$8=$CA$9,$CA66,IF(AF$8=$CC$9,$CC66,IF(AF$8=$CD$9,$CD66,IF(AF$8=$CE$9,$CE66,IF(AF$8=$CF$9,$CF66,IF(AF$8=$CG$9,$CG66,IF(AF$8=$CH$9,$CH66,IF(AF$8=$CI$9,$CI66,IF(AF$8=$CJ$9,$CJ66,IF(AF$8=$CK$9,$CK66,IF(AF$8=$CL$9,$CL66,IF(AF$8=$CM$9,$CM66,IF(AF$8=$CN$9,$CN66,IF(AF$8=$CO$9,$CO66,IF(AF$8=$CP$9,$CP66,IF(AF$8=$CQ$9,$CQ66,"НЕТ")))))))))))))))))))))))) -> ДА | AG66: =IF(AG$8=$BT$9,$BT66,IF(AG$8=$BS$9,$BS66,IF(AG$8=$BU$9,$BU66,IF(AG$8=$BV$9,$BV66,IF(AG$8=$BW$9,$BW66,IF(AG$8=$BX$9,$BX66,IF(AG$8=$BY$9,$BY66,IF(AG$8=$BZ$9,$BZ66,IF(AG$8=$CA$9,$CA66,IF(AG$8=$CC$9,$CC66,IF(AG$8=$CD$9,$CD66,IF(AG$8=$CE$9,$CE66,IF(AG$8=$CF$9,$CF66,IF(AG$8=$CG$9,$CG66,IF(AG$8=$CH$9,$CH66,IF(AG$8=$CI$9,$CI66,IF(AG$8=$CJ$9,$CJ66,IF(AG$8=$CK$9,$CK66,IF(AG$8=$CL$9,$CL66,IF(AG$8=$CM$9,$CM66,IF(AG$8=$CN$9,$CN66,IF(AG$8=$CO$9,$CO66,IF(AG$8=$CP$9,$CP66,IF(AG$8=$CQ$9,$CQ66,"НЕТ")))))))))))))))))))))))) -> НЕТ | AH66: =IF(AH$8=$BT$9,$BT66,IF(AH$8=$BS$9,$BS66,IF(AH$8=$BU$9,$BU66,IF(AH$8=$BV$9,$BV66,IF(AH$8=$BW$9,$BW66,IF(AH$8=$BX$9,$BX66,IF(AH$8=$BY$9,$BY66,IF(AH$8=$BZ$9,$BZ66,IF(AH$8=$CA$9,$CA66,IF(AH$8=$CC$9,$CC66,IF(AH$8=$CD$9,$CD66,IF(AH$8=$CE$9,$CE66,IF(AH$8=$CF$9,$CF66,IF(AH$8=$CG$9,$CG66,IF(AH$8=$CH$9,$CH66,IF(AH$8=$CI$9,$CI66,IF(AH$8=$CJ$9,$CJ66,IF(AH$8=$CK$9,$CK66,IF(AH$8=$CL$9,$CL66,IF(AH$8=$CM$9,$CM66,IF(AH$8=$CN$9,$CN66,IF(AH$8=$CO$9,$CO66,IF(AH$8=$CP$9,$CP66,IF(AH$8=$CQ$9,$CQ66,"НЕТ")))))))))))))))))))))))) -> НЕТ | AI66: =IF(AI$8=$BT$9,$BT66,IF(AI$8=$BS$9,$BS66,IF(AI$8=$BU$9,$BU66,IF(AI$8=$BV$9,$BV66,IF(AI$8=$BW$9,$BW66,IF(AI$8=$BX$9,$BX66,IF(AI$8=$BY$9,$BY66,IF(AI$8=$BZ$9,$BZ66,IF(AI$8=$CA$9,$CA66,IF(AI$8=$CC$9,$CC66,IF(AI$8=$CD$9,$CD66,IF(AI$8=$CE$9,$CE66,IF(AI$8=$CF$9,$CF66,IF(AI$8=$CG$9,$CG66,IF(AI$8=$CH$9,$CH66,IF(AI$8=$CI$9,$CI66,IF(AI$8=$CJ$9,$CJ66,IF(AI$8=$CK$9,$CK66,IF(AI$8=$CL$9,$CL66,IF(AI$8=$CM$9,$CM66,IF(AI$8=$CN$9,$CN66,IF(AI$8=$CO$9,$CO66,IF(AI$8=$CP$9,$CP66,IF(AI$8=$CQ$9,$CQ66,"НЕТ")))))))))))))))))))))))) -> НЕТ | AJ66: =IF(AJ$8=$BT$9,$BT66,IF(AJ$8=$BS$9,$BS66,IF(AJ$8=$BU$9,$BU66,IF(AJ$8=$BV$9,$BV66,IF(AJ$8=$BW$9,$BW66,IF(AJ$8=$BX$9,$BX66,IF(AJ$8=$BY$9,$BY66,IF(AJ$8=$BZ$9,$BZ66,IF(AJ$8=$CA$9,$CA66,IF(AJ$8=$CC$9,$CC66,IF(AJ$8=$CD$9,$CD66,IF(AJ$8=$CE$9,$CE66,IF(AJ$8=$CF$9,$CF66,IF(AJ$8=$CG$9,$CG66,IF(AJ$8=$CH$9,$CH66,IF(AJ$8=$CI$9,$CI66,IF(AJ$8=$CJ$9,$CJ66,IF(AJ$8=$CK$9,$CK66,IF(AJ$8=$CL$9,$CL66,IF(AJ$8=$CM$9,$CM66,IF(AJ$8=$CN$9,$CN66,IF(AJ$8=$CO$9,$CO66,IF(AJ$8=$CP$9,$CP66,IF(AJ$8=$CQ$9,$CQ66,"НЕТ")))))))))))))))))))))))) -> НЕТ | AK66: =IF(AK$8=$BT$9,$BT66,IF(AK$8=$BS$9,$BS66,IF(AK$8=$BU$9,$BU66,IF(AK$8=$BV$9,$BV66,IF(AK$8=$BW$9,$BW66,IF(AK$8=$BX$9,$BX66,IF(AK$8=$BY$9,$BY66,IF(AK$8=$BZ$9,$BZ66,IF(AK$8=$CA$9,$CA66,IF(AK$8=$CC$9,$CC66,IF(AK$8=$CD$9,$CD66,IF(AK$8=$CE$9,$CE66,IF(AK$8=$CF$9,$CF66,IF(AK$8=$CG$9,$CG66,IF(AK$8=$CH$9,$CH66,IF(AK$8=$CI$9,$CI66,IF(AK$8=$CJ$9,$CJ66,IF(AK$8=$CK$9,$CK66,IF(AK$8=$CL$9,$CL66,IF(AK$8=$CM$9,$CM66,IF(AK$8=$CN$9,$CN66,IF(AK$8=$CO$9,$CO66,IF(AK$8=$CP$9,$CP66,IF(AK$8=$CQ$9,$CQ66,"НЕТ")))))))))))))))))))))))) -> НЕТ | AL66: =IF(AL$8=$BT$9,$BT66,IF(AL$8=$BS$9,$BS66,IF(AL$8=$BU$9,$BU66,IF(AL$8=$BV$9,$BV66,IF(AL$8=$BW$9,$BW66,IF(AL$8=$BX$9,$BX66,IF(AL$8=$BY$9,$BY66,IF(AL$8=$BZ$9,$BZ66,IF(AL$8=$CA$9,$CA66,IF(AL$8=$CC$9,$CC66,IF(AL$8=$CD$9,$CD66,IF(AL$8=$CE$9,$CE66,IF(AL$8=$CF$9,$CF66,IF(AL$8=$CG$9,$CG66,IF(AL$8=$CH$9,$CH66,IF(AL$8=$CI$9,$CI66,IF(AL$8=$CJ$9,$CJ66,IF(AL$8=$CK$9,$CK66,IF(AL$8=$CL$9,$CL66,IF(AL$8=$CM$9,$CM66,IF(AL$8=$CN$9,$CN66,IF(AL$8=$CO$9,$CO66,IF(AL$8=$CP$9,$CP66,IF(AL$8=$CQ$9,$CQ66,"НЕТ")))))))))))))))))))))))) -> НЕТ | AM66: =IF(AL66="НЕТ","Не требуется",$CR66) -> Не требуется | AS66: =IF(BS66="ДА",$M66,"") | AT66: =IF(BT66="ДА",$M66,"") | AU66: =IF(BU66="ДА",$M66,"") | AV66: =IF(BV66="ДА",$M66,"") | AW66: =IF(BX66="ДА",$M66,"") | AX66: =IF(BY66="ДА",$M66,"") | AY66: =IF(BZ66="ДА",$M66,"") -> 5 | AZ66: =IF(CA66="ДА",$M66,"") -> 5 | BB66: =IF(CC66="ДА",$M66,"") | BC66: =IF(CD66="ДА",$M66,"") -> 5 | BD66: =IF(CE66="ДА",$M66,"") | BE66: =IF(CF66="ДА",$M66,"") -> 5 | BF66: =IF(CG66="ДА",$M66,"") -> 5 | BG66: =IF(CH66="ДА",$M66,"") | BH66: =IF(CI66="ДА",$M66,"") -> 5 | BI66: =IF(CJ66="ДА",$M66,"") | ... BP66: =IF(CQ66="ДА",$M66,"") | BS66: НЕТ | BT66: НЕТ | BU66: НЕТ | BV66: НЕТ | BW66: НЕТ | BX66: НЕТ | BY66: НЕТ | BZ66: ДА | CA66: ДА | CC66: НЕТ | CD66: ДА | CE66: НЕТ | CF66: ДА | CG66: ДА | CH66: НЕТ | CI66: ДА | CJ66: НЕТ | CK66: НЕТ | CL66: НЕТ | CM66: НЕТ | CN66: НЕТ | CO66: НЕТ | CP66: НЕТ | CQ66: НЕТ | CR66: Предоставляется Заказчиком
A67: 3. | B67: Управление трудоемкостью и прочими ресурсами | F67: ГРУППА | G67: ГРУППА | H67: ГРУППА | I67: ГРУППА | J67: ГРУППА | K67: ГРУППА | L67: ГРУППА | M67: =SUM(M68,M75,M79,M83,M88,M93,M97,M99) -> 24 | N67: =SUM(N68,N75,N79,N83,N88,N93,N97,N99) -> 19 | O67: =SUM(O68,O75,O79,O83,O88,O93,O97,O99) -> 3 | P67: =SUM(P68,P75,P79,P83,P88,P93,P97,P99) -> 0 | Q67: =SUM(Q68,Q75,Q79,Q83,Q88,Q93,Q97,Q99) -> 2 | R67: =SUM(R68,R75,R79,R83,R88,R93,R97,R99) -> 14 | S67: =SUM(S68,S75,S79,S83,S88,S93,S97,S99) -> 0 | T67: =SUM(T68,T75,T79,T83,T88,T93,T97,T99) -> 7 | ... Z67: =SUM(Z68,Z75,Z79,Z83,Z88,Z93,Z97,Z99) -> 0 | AA67: =IF(N67>0,"ДА","НЕТ") -> ДА | AC67: =IF(O67>0,"ДА","НЕТ") -> ДА | AF67: =IF(R67>0,"ДА","НЕТ") -> ДА | AI67: =IF(U67>0,"ДА","НЕТ") -> ДА | AL67: =IF(X67>0,"ДА","НЕТ") -> НЕТ | AS67: =SUM(AS68,AS75,AS79,AS88,AS93,AS97,AS99) -> 6 | AT67: =SUM(AT68,AT75,AT79,AT88,AT93,AT97,AT99) -> 5 | AU67: =SUM(AU68,AU75,AU79,AU88,AU93,AU97,AU99) -> 3 | AV67: =SUM(AV68,AV75,AV79,AV88,AV93,AV97,AV99) -> 2 | AW67: =SUM(AW68,AW75,AW79,AW88,AW93,AW97,AW99) -> 13 | AX67: =SUM(AX68,AX75,AX79,AX88,AX93,AX97,AX99) -> 13 | AY67: =SUM(AY68,AY75,AY79,AY88,AY93,AY97,AY99) -> 13 | AZ67: =SUM(AZ68,AZ75,AZ79,AZ88,AZ93,AZ97,AZ99) -> 13 | BB67: =SUM(BB68,BB75,BB79,BB88,BB93,BB97,BB99) -> 9 | BC67: =SUM(BC68,BC75,BC79,BC88,BC93,BC97,BC99) -> 13 | BD67: =SUM(BD68,BD75,BD79,BD88,BD93,BD97,BD99) -> 9 | BE67: =SUM(BE68,BE75,BE79,BE88,BE93,BE97,BE99) -> 13 | BF67: =SUM(BF68,BF75,BF79,BF88,BF93,BF97,BF99) -> 9 | BG67: =SUM(BG68,BG75,BG79,BG88,BG93,BG97,BG99) -> 13 | BH67: =SUM(BH68,BH75,BH79,BH88,BH93,BH97,BH99) -> 9 | BI67: =SUM(BI68,BI75,BI79,BI88,BI93,BI97,BI99) -> 5 | ... BP67: =SUM(BP68,BP75,BP79,BP88,BP93,BP97,BP99) -> 0 | BS67: =IF(AS67>0,"ДА","НЕТ") -> ДА | BT67: =IF(AT67>0,"ДА","НЕТ") -> ДА | BU67: =IF(AU67>0,"ДА","НЕТ") -> ДА | BV67: =IF(AV67>0,"ДА","НЕТ") -> ДА | BW67: =IF(AS67>0,"ДА","НЕТ") -> ДА | BX67: =IF(AW67>0,"ДА","НЕТ") -> ДА | BY67: =IF(AX67>0,"ДА","НЕТ") -> ДА | BZ67: =IF(AY67>0,"ДА","НЕТ") -> ДА | CA67: =IF(AZ67>0,"ДА","НЕТ") -> ДА | CC67: =IF(BB67>0,"ДА","НЕТ") -> ДА | CD67: =IF(BC67>0,"ДА","НЕТ") -> ДА | CE67: =IF(BD67>0,"ДА","НЕТ") -> ДА | CF67: =IF(BE67>0,"ДА","НЕТ") -> ДА | CG67: =IF(BF67>0,"ДА","НЕТ") -> ДА | CH67: =IF(BG67>0,"ДА","НЕТ") -> ДА | CI67: =IF(BH67>0,"ДА","НЕТ") -> ДА | CJ67: =IF(BI67>0,"ДА","НЕТ") -> ДА | ... CQ67: =IF(BP67>0,"ДА","НЕТ") -> НЕТ
A68: 3.1. | B68: Сформировать плановые трудозатраты проектов | F68: Базовый | G68: Кейс-проект | H68: Да | I68: Да | J68: Да | K68: Да | L68: В разработке | M68: 2 | N68: =SUM(O68,R68,U68,X68) -> 4 | O68: =IF(AC68="ДА",$M68,"") -> 2 | Q68: =IF(AC68="ДА",ROUNDUP(O68/5,0),0) -> 1 | R68: =IF(AF68="ДА",$M68,"") -> 2 | T68: =IF(AF68="ДА",ROUNDUP(R68/5,0),0) -> 1 | U68: =IF(AI68="ДА",$M68,"") | W68: =IF(AI68="ДА",ROUNDUP(U68/5,0),0) -> 0 | X68: =IF(AL68="ДА",$M68,"") | Z68: =IF(AL68="ДА",ROUNDUP(X68/5,0),0) -> 0 | AA68: =IF(OR(AC68="ДА",AF68="ДА",AI68="ДА",AL68="ДА"),"ДА","НЕТ") -> ДА | AC68: =IF(AC$8=$BT$9,$BT68,IF(AC$8=$BS$9,$BS68,IF(AC$8=$BU$9,$BU68,IF(AC$8=$BV$9,$BV68,IF(AC$8=$BW$9,$BW68,IF(AC$8=$BX$9,$BX68,IF(AC$8=$BY$9,$BY68,IF(AC$8=$BZ$9,$BZ68,IF(AC$8=$CA$9,$CA68,IF(AC$8=$CC$9,$CC68,IF(AC$8=$CD$9,$CD68,IF(AC$8=$CE$9,$CE68,IF(AC$8=$CF$9,$CF68,IF(AC$8=$CG$9,$CG68,IF(AC$8=$CH$9,$CH68,IF(AC$8=$CI$9,$CI68,IF(AC$8=$CJ$9,$CJ68,IF(AC$8=$CK$9,$CK68,IF(AC$8=$CL$9,$CL68,IF(AC$8=$CM$9,$CM68,IF(AC$8=$CN$9,$CN68,IF(AC$8=$CO$9,$CO68,IF(AC$8=$CP$9,$CP68,IF(AC$8=$CQ$9,$CQ68,"НЕТ")))))))))))))))))))))))) -> ДА | AD68: =IF(AC68="НЕТ","Не требуется",$CR68) -> Не требуется | AF68: =IF(AF$8=$BT$9,$BT68,IF(AF$8=$BS$9,$BS68,IF(AF$8=$BU$9,$BU68,IF(AF$8=$BV$9,$BV68,IF(AF$8=$BW$9,$BW68,IF(AF$8=$BX$9,$BX68,IF(AF$8=$BY$9,$BY68,IF(AF$8=$BZ$9,$BZ68,IF(AF$8=$CA$9,$CA68,IF(AF$8=$CC$9,$CC68,IF(AF$8=$CD$9,$CD68,IF(AF$8=$CE$9,$CE68,IF(AF$8=$CF$9,$CF68,IF(AF$8=$CG$9,$CG68,IF(AF$8=$CH$9,$CH68,IF(AF$8=$CI$9,$CI68,IF(AF$8=$CJ$9,$CJ68,IF(AF$8=$CK$9,$CK68,IF(AF$8=$CL$9,$CL68,IF(AF$8=$CM$9,$CM68,IF(AF$8=$CN$9,$CN68,IF(AF$8=$CO$9,$CO68,IF(AF$8=$CP$9,$CP68,IF(AF$8=$CQ$9,$CQ68,"НЕТ")))))))))))))))))))))))) -> ДА | AG68: =IF(AG$8=$BT$9,$BT68,IF(AG$8=$BS$9,$BS68,IF(AG$8=$BU$9,$BU68,IF(AG$8=$BV$9,$BV68,IF(AG$8=$BW$9,$BW68,IF(AG$8=$BX$9,$BX68,IF(AG$8=$BY$9,$BY68,IF(AG$8=$BZ$9,$BZ68,IF(AG$8=$CA$9,$CA68,IF(AG$8=$CC$9,$CC68,IF(AG$8=$CD$9,$CD68,IF(AG$8=$CE$9,$CE68,IF(AG$8=$CF$9,$CF68,IF(AG$8=$CG$9,$CG68,IF(AG$8=$CH$9,$CH68,IF(AG$8=$CI$9,$CI68,IF(AG$8=$CJ$9,$CJ68,IF(AG$8=$CK$9,$CK68,IF(AG$8=$CL$9,$CL68,IF(AG$8=$CM$9,$CM68,IF(AG$8=$CN$9,$CN68,IF(AG$8=$CO$9,$CO68,IF(AG$8=$CP$9,$CP68,IF(AG$8=$CQ$9,$CQ68,"НЕТ")))))))))))))))))))))))) -> НЕТ | AH68: =IF(AH$8=$BT$9,$BT68,IF(AH$8=$BS$9,$BS68,IF(AH$8=$BU$9,$BU68,IF(AH$8=$BV$9,$BV68,IF(AH$8=$BW$9,$BW68,IF(AH$8=$BX$9,$BX68,IF(AH$8=$BY$9,$BY68,IF(AH$8=$BZ$9,$BZ68,IF(AH$8=$CA$9,$CA68,IF(AH$8=$CC$9,$CC68,IF(AH$8=$CD$9,$CD68,IF(AH$8=$CE$9,$CE68,IF(AH$8=$CF$9,$CF68,IF(AH$8=$CG$9,$CG68,IF(AH$8=$CH$9,$CH68,IF(AH$8=$CI$9,$CI68,IF(AH$8=$CJ$9,$CJ68,IF(AH$8=$CK$9,$CK68,IF(AH$8=$CL$9,$CL68,IF(AH$8=$CM$9,$CM68,IF(AH$8=$CN$9,$CN68,IF(AH$8=$CO$9,$CO68,IF(AH$8=$CP$9,$CP68,IF(AH$8=$CQ$9,$CQ68,"НЕТ")))))))))))))))))))))))) -> НЕТ | AI68: =IF(AI$8=$BT$9,$BT68,IF(AI$8=$BS$9,$BS68,IF(AI$8=$BU$9,$BU68,IF(AI$8=$BV$9,$BV68,IF(AI$8=$BW$9,$BW68,IF(AI$8=$BX$9,$BX68,IF(AI$8=$BY$9,$BY68,IF(AI$8=$BZ$9,$BZ68,IF(AI$8=$CA$9,$CA68,IF(AI$8=$CC$9,$CC68,IF(AI$8=$CD$9,$CD68,IF(AI$8=$CE$9,$CE68,IF(AI$8=$CF$9,$CF68,IF(AI$8=$CG$9,$CG68,IF(AI$8=$CH$9,$CH68,IF(AI$8=$CI$9,$CI68,IF(AI$8=$CJ$9,$CJ68,IF(AI$8=$CK$9,$CK68,IF(AI$8=$CL$9,$CL68,IF(AI$8=$CM$9,$CM68,IF(AI$8=$CN$9,$CN68,IF(AI$8=$CO$9,$CO68,IF(AI$8=$CP$9,$CP68,IF(AI$8=$CQ$9,$CQ68,"НЕТ")))))))))))))))))))))))) -> НЕТ | AJ68: =IF(AJ$8=$BT$9,$BT68,IF(AJ$8=$BS$9,$BS68,IF(AJ$8=$BU$9,$BU68,IF(AJ$8=$BV$9,$BV68,IF(AJ$8=$BW$9,$BW68,IF(AJ$8=$BX$9,$BX68,IF(AJ$8=$BY$9,$BY68,IF(AJ$8=$BZ$9,$BZ68,IF(AJ$8=$CA$9,$CA68,IF(AJ$8=$CC$9,$CC68,IF(AJ$8=$CD$9,$CD68,IF(AJ$8=$CE$9,$CE68,IF(AJ$8=$CF$9,$CF68,IF(AJ$8=$CG$9,$CG68,IF(AJ$8=$CH$9,$CH68,IF(AJ$8=$CI$9,$CI68,IF(AJ$8=$CJ$9,$CJ68,IF(AJ$8=$CK$9,$CK68,IF(AJ$8=$CL$9,$CL68,IF(AJ$8=$CM$9,$CM68,IF(AJ$8=$CN$9,$CN68,IF(AJ$8=$CO$9,$CO68,IF(AJ$8=$CP$9,$CP68,IF(AJ$8=$CQ$9,$CQ68,"НЕТ")))))))))))))))))))))))) -> НЕТ | AK68: =IF(AK$8=$BT$9,$BT68,IF(AK$8=$BS$9,$BS68,IF(AK$8=$BU$9,$BU68,IF(AK$8=$BV$9,$BV68,IF(AK$8=$BW$9,$BW68,IF(AK$8=$BX$9,$BX68,IF(AK$8=$BY$9,$BY68,IF(AK$8=$BZ$9,$BZ68,IF(AK$8=$CA$9,$CA68,IF(AK$8=$CC$9,$CC68,IF(AK$8=$CD$9,$CD68,IF(AK$8=$CE$9,$CE68,IF(AK$8=$CF$9,$CF68,IF(AK$8=$CG$9,$CG68,IF(AK$8=$CH$9,$CH68,IF(AK$8=$CI$9,$CI68,IF(AK$8=$CJ$9,$CJ68,IF(AK$8=$CK$9,$CK68,IF(AK$8=$CL$9,$CL68,IF(AK$8=$CM$9,$CM68,IF(AK$8=$CN$9,$CN68,IF(AK$8=$CO$9,$CO68,IF(AK$8=$CP$9,$CP68,IF(AK$8=$CQ$9,$CQ68,"НЕТ")))))))))))))))))))))))) -> НЕТ | AL68: =IF(AL$8=$BT$9,$BT68,IF(AL$8=$BS$9,$BS68,IF(AL$8=$BU$9,$BU68,IF(AL$8=$BV$9,$BV68,IF(AL$8=$BW$9,$BW68,IF(AL$8=$BX$9,$BX68,IF(AL$8=$BY$9,$BY68,IF(AL$8=$BZ$9,$BZ68,IF(AL$8=$CA$9,$CA68,IF(AL$8=$CC$9,$CC68,IF(AL$8=$CD$9,$CD68,IF(AL$8=$CE$9,$CE68,IF(AL$8=$CF$9,$CF68,IF(AL$8=$CG$9,$CG68,IF(AL$8=$CH$9,$CH68,IF(AL$8=$CI$9,$CI68,IF(AL$8=$CJ$9,$CJ68,IF(AL$8=$CK$9,$CK68,IF(AL$8=$CL$9,$CL68,IF(AL$8=$CM$9,$CM68,IF(AL$8=$CN$9,$CN68,IF(AL$8=$CO$9,$CO68,IF(AL$8=$CP$9,$CP68,IF(AL$8=$CQ$9,$CQ68,"НЕТ")))))))))))))))))))))))) -> НЕТ | AM68: =IF(AL68="НЕТ","Не требуется",$CR68) -> Не требуется | AS68: =IF(BS68="ДА",$M68,"") -> 2 | AT68: =IF(BT68="ДА",$M68,"") -> 2 | AU68: =IF(BU68="ДА",$M68,"") -> 2 | AV68: =IF(BV68="ДА",$M68,"") | AW68: =IF(BX68="ДА",$M68,"") -> 2 | AX68: =IF(BY68="ДА",$M68,"") -> 2 | AY68: =IF(BZ68="ДА",$M68,"") -> 2 | AZ68: =IF(CA68="ДА",$M68,"") -> 2 | BB68: =IF(CC68="ДА",$M68,"") -> 2 | BC68: =IF(CD68="ДА",$M68,"") -> 2 | BD68: =IF(CE68="ДА",$M68,"") -> 2 | BE68: =IF(CF68="ДА",$M68,"") -> 2 | BF68: =IF(CG68="ДА",$M68,"") -> 2 | BG68: =IF(CH68="ДА",$M68,"") -> 2 | BH68: =IF(CI68="ДА",$M68,"") -> 2 | BI68: =IF(CJ68="ДА",$M68,"") -> 2 | ... BP68: =IF(CQ68="ДА",$M68,"") | BS68: ДА | BT68: ДА | BU68: ДА | BV68: НЕТ | BW68: ДА | BX68: ДА | BY68: ДА | BZ68: ДА | CA68: ДА | CC68: ДА | CD68: ДА | CE68: ДА | CF68: ДА | CG68: ДА | CH68: ДА | CI68: ДА | CJ68: ДА | CK68: ДА | CL68: ДА | CM68: ДА | CN68: НЕТ | CO68: НЕТ | CP68: НЕТ | CQ68: НЕТ | CR68: Не требуется
B69: Планирование мощности ролей и подразделений | C69: Планирование мощности ролей и подразделений | N69: =SUM(O69,R69,U69,X69) -> 0 | BT69: ДА
B70: Планирование норм стоимости (ставок) ролей (специальностей) подразделений с учетом уровня квалификации | C70: Планирование норм стоимости (ставок) ролей (специальностей) подразделений с учетом уровня квалификации | N70: =SUM(O70,R70,U70,X70) -> 0 | BT70: НЕТ
B71: Планирование загрузки подразделений и специальностей по этапам проекта | C71: Планирование загрузки подразделений и специальностей по этапам проекта | N71: =SUM(O71,R71,U71,X71) -> 0 | BT71: НЕТ
B72: Планирование загрузки сотрудников по задачам проекта (без использования механизма заданий) | C72: Есть назначение сотрудников на задачи проекта. Планирование загрузки - через механизм заданий | N72: =SUM(O72,R72,U72,X72) -> 0 | BT72: НЕТ
B73: Планирование загрузки сотрудников по задачам проекта (с использованием механизма заданий) | C73: Есть назначение сотрудников на задачи проекта. Планирование загрузки - через механизм заданий | N73: =SUM(O73,R73,U73,X73) -> 0 | BT73: НЕТ
B74: Планирование оперативной загрузки сотрудников по графику в течении периода (день, неделя и т.д.) | C74: нет | N74: =SUM(O74,R74,U74,X74) -> 0 | BT74: НЕТ
A75: 3.2. | B75: Сформировать прочие ресурсные планы проектов | F75: Базовый | G75: Кейс-проект | H75: Да | I75: Да | J75: Да | K75: Да | L75: В разработке | M75: 1 | N75: =SUM(O75,R75,U75,X75) -> 1 | O75: =IF(AC75="ДА",$M75,"") | Q75: =IF(AC75="ДА",ROUNDUP(O75/5,0),0) -> 0 | R75: =IF(AF75="ДА",$M75,"") -> 1 | T75: =IF(AF75="ДА",ROUNDUP(R75/5,0),0) -> 1 | U75: =IF(AI75="ДА",$M75,"") | W75: =IF(AI75="ДА",ROUNDUP(U75/5,0),0) -> 0 | X75: =IF(AL75="ДА",$M75,"") | Z75: =IF(AL75="ДА",ROUNDUP(X75/5,0),0) -> 0 | AA75: =IF(OR(AC75="ДА",AF75="ДА",AI75="ДА",AL75="ДА"),"ДА","НЕТ") -> ДА | AC75: =IF(AC$8=$BT$9,$BT75,IF(AC$8=$BS$9,$BS75,IF(AC$8=$BU$9,$BU75,IF(AC$8=$BV$9,$BV75,IF(AC$8=$BW$9,$BW75,IF(AC$8=$BX$9,$BX75,IF(AC$8=$BY$9,$BY75,IF(AC$8=$BZ$9,$BZ75,IF(AC$8=$CA$9,$CA75,IF(AC$8=$CC$9,$CC75,IF(AC$8=$CD$9,$CD75,IF(AC$8=$CE$9,$CE75,IF(AC$8=$CF$9,$CF75,IF(AC$8=$CG$9,$CG75,IF(AC$8=$CH$9,$CH75,IF(AC$8=$CI$9,$CI75,IF(AC$8=$CJ$9,$CJ75,IF(AC$8=$CK$9,$CK75,IF(AC$8=$CL$9,$CL75,IF(AC$8=$CM$9,$CM75,IF(AC$8=$CN$9,$CN75,IF(AC$8=$CO$9,$CO75,IF(AC$8=$CP$9,$CP75,IF(AC$8=$CQ$9,$CQ75,"НЕТ")))))))))))))))))))))))) -> НЕТ | AD75: =IF(AC75="НЕТ","Не требуется",$CR75) -> Не требуется | AF75: =IF(AF$8=$BT$9,$BT75,IF(AF$8=$BS$9,$BS75,IF(AF$8=$BU$9,$BU75,IF(AF$8=$BV$9,$BV75,IF(AF$8=$BW$9,$BW75,IF(AF$8=$BX$9,$BX75,IF(AF$8=$BY$9,$BY75,IF(AF$8=$BZ$9,$BZ75,IF(AF$8=$CA$9,$CA75,IF(AF$8=$CC$9,$CC75,IF(AF$8=$CD$9,$CD75,IF(AF$8=$CE$9,$CE75,IF(AF$8=$CF$9,$CF75,IF(AF$8=$CG$9,$CG75,IF(AF$8=$CH$9,$CH75,IF(AF$8=$CI$9,$CI75,IF(AF$8=$CJ$9,$CJ75,IF(AF$8=$CK$9,$CK75,IF(AF$8=$CL$9,$CL75,IF(AF$8=$CM$9,$CM75,IF(AF$8=$CN$9,$CN75,IF(AF$8=$CO$9,$CO75,IF(AF$8=$CP$9,$CP75,IF(AF$8=$CQ$9,$CQ75,"НЕТ")))))))))))))))))))))))) -> ДА | AG75: =IF(AG$8=$BT$9,$BT75,IF(AG$8=$BS$9,$BS75,IF(AG$8=$BU$9,$BU75,IF(AG$8=$BV$9,$BV75,IF(AG$8=$BW$9,$BW75,IF(AG$8=$BX$9,$BX75,IF(AG$8=$BY$9,$BY75,IF(AG$8=$BZ$9,$BZ75,IF(AG$8=$CA$9,$CA75,IF(AG$8=$CC$9,$CC75,IF(AG$8=$CD$9,$CD75,IF(AG$8=$CE$9,$CE75,IF(AG$8=$CF$9,$CF75,IF(AG$8=$CG$9,$CG75,IF(AG$8=$CH$9,$CH75,IF(AG$8=$CI$9,$CI75,IF(AG$8=$CJ$9,$CJ75,IF(AG$8=$CK$9,$CK75,IF(AG$8=$CL$9,$CL75,IF(AG$8=$CM$9,$CM75,IF(AG$8=$CN$9,$CN75,IF(AG$8=$CO$9,$CO75,IF(AG$8=$CP$9,$CP75,IF(AG$8=$CQ$9,$CQ75,"НЕТ")))))))))))))))))))))))) -> НЕТ | AH75: =IF(AH$8=$BT$9,$BT75,IF(AH$8=$BS$9,$BS75,IF(AH$8=$BU$9,$BU75,IF(AH$8=$BV$9,$BV75,IF(AH$8=$BW$9,$BW75,IF(AH$8=$BX$9,$BX75,IF(AH$8=$BY$9,$BY75,IF(AH$8=$BZ$9,$BZ75,IF(AH$8=$CA$9,$CA75,IF(AH$8=$CC$9,$CC75,IF(AH$8=$CD$9,$CD75,IF(AH$8=$CE$9,$CE75,IF(AH$8=$CF$9,$CF75,IF(AH$8=$CG$9,$CG75,IF(AH$8=$CH$9,$CH75,IF(AH$8=$CI$9,$CI75,IF(AH$8=$CJ$9,$CJ75,IF(AH$8=$CK$9,$CK75,IF(AH$8=$CL$9,$CL75,IF(AH$8=$CM$9,$CM75,IF(AH$8=$CN$9,$CN75,IF(AH$8=$CO$9,$CO75,IF(AH$8=$CP$9,$CP75,IF(AH$8=$CQ$9,$CQ75,"НЕТ")))))))))))))))))))))))) -> НЕТ | AI75: =IF(AI$8=$BT$9,$BT75,IF(AI$8=$BS$9,$BS75,IF(AI$8=$BU$9,$BU75,IF(AI$8=$BV$9,$BV75,IF(AI$8=$BW$9,$BW75,IF(AI$8=$BX$9,$BX75,IF(AI$8=$BY$9,$BY75,IF(AI$8=$BZ$9,$BZ75,IF(AI$8=$CA$9,$CA75,IF(AI$8=$CC$9,$CC75,IF(AI$8=$CD$9,$CD75,IF(AI$8=$CE$9,$CE75,IF(AI$8=$CF$9,$CF75,IF(AI$8=$CG$9,$CG75,IF(AI$8=$CH$9,$CH75,IF(AI$8=$CI$9,$CI75,IF(AI$8=$CJ$9,$CJ75,IF(AI$8=$CK$9,$CK75,IF(AI$8=$CL$9,$CL75,IF(AI$8=$CM$9,$CM75,IF(AI$8=$CN$9,$CN75,IF(AI$8=$CO$9,$CO75,IF(AI$8=$CP$9,$CP75,IF(AI$8=$CQ$9,$CQ75,"НЕТ")))))))))))))))))))))))) -> НЕТ | AJ75: =IF(AJ$8=$BT$9,$BT75,IF(AJ$8=$BS$9,$BS75,IF(AJ$8=$BU$9,$BU75,IF(AJ$8=$BV$9,$BV75,IF(AJ$8=$BW$9,$BW75,IF(AJ$8=$BX$9,$BX75,IF(AJ$8=$BY$9,$BY75,IF(AJ$8=$BZ$9,$BZ75,IF(AJ$8=$CA$9,$CA75,IF(AJ$8=$CC$9,$CC75,IF(AJ$8=$CD$9,$CD75,IF(AJ$8=$CE$9,$CE75,IF(AJ$8=$CF$9,$CF75,IF(AJ$8=$CG$9,$CG75,IF(AJ$8=$CH$9,$CH75,IF(AJ$8=$CI$9,$CI75,IF(AJ$8=$CJ$9,$CJ75,IF(AJ$8=$CK$9,$CK75,IF(AJ$8=$CL$9,$CL75,IF(AJ$8=$CM$9,$CM75,IF(AJ$8=$CN$9,$CN75,IF(AJ$8=$CO$9,$CO75,IF(AJ$8=$CP$9,$CP75,IF(AJ$8=$CQ$9,$CQ75,"НЕТ")))))))))))))))))))))))) -> НЕТ | AK75: =IF(AK$8=$BT$9,$BT75,IF(AK$8=$BS$9,$BS75,IF(AK$8=$BU$9,$BU75,IF(AK$8=$BV$9,$BV75,IF(AK$8=$BW$9,$BW75,IF(AK$8=$BX$9,$BX75,IF(AK$8=$BY$9,$BY75,IF(AK$8=$BZ$9,$BZ75,IF(AK$8=$CA$9,$CA75,IF(AK$8=$CC$9,$CC75,IF(AK$8=$CD$9,$CD75,IF(AK$8=$CE$9,$CE75,IF(AK$8=$CF$9,$CF75,IF(AK$8=$CG$9,$CG75,IF(AK$8=$CH$9,$CH75,IF(AK$8=$CI$9,$CI75,IF(AK$8=$CJ$9,$CJ75,IF(AK$8=$CK$9,$CK75,IF(AK$8=$CL$9,$CL75,IF(AK$8=$CM$9,$CM75,IF(AK$8=$CN$9,$CN75,IF(AK$8=$CO$9,$CO75,IF(AK$8=$CP$9,$CP75,IF(AK$8=$CQ$9,$CQ75,"НЕТ")))))))))))))))))))))))) -> НЕТ | AL75: =IF(AL$8=$BT$9,$BT75,IF(AL$8=$BS$9,$BS75,IF(AL$8=$BU$9,$BU75,IF(AL$8=$BV$9,$BV75,IF(AL$8=$BW$9,$BW75,IF(AL$8=$BX$9,$BX75,IF(AL$8=$BY$9,$BY75,IF(AL$8=$BZ$9,$BZ75,IF(AL$8=$CA$9,$CA75,IF(AL$8=$CC$9,$CC75,IF(AL$8=$CD$9,$CD75,IF(AL$8=$CE$9,$CE75,IF(AL$8=$CF$9,$CF75,IF(AL$8=$CG$9,$CG75,IF(AL$8=$CH$9,$CH75,IF(AL$8=$CI$9,$CI75,IF(AL$8=$CJ$9,$CJ75,IF(AL$8=$CK$9,$CK75,IF(AL$8=$CL$9,$CL75,IF(AL$8=$CM$9,$CM75,IF(AL$8=$CN$9,$CN75,IF(AL$8=$CO$9,$CO75,IF(AL$8=$CP$9,$CP75,IF(AL$8=$CQ$9,$CQ75,"НЕТ")))))))))))))))))))))))) -> НЕТ | AM75: =IF(AL75="НЕТ","Не требуется",$CR75) -> Не требуется | AS75: =IF(BS75="ДА",$M75,"") -> 1 | AT75: =IF(BT75="ДА",$M75,"") -> 1 | AU75: =IF(BU75="ДА",$M75,"") | AV75: =IF(BV75="ДА",$M75,"") | AW75: =IF(BX75="ДА",$M75,"") -> 1 | AX75: =IF(BY75="ДА",$M75,"") -> 1 | AY75: =IF(BZ75="ДА",$M75,"") -> 1 | AZ75: =IF(CA75="ДА",$M75,"") -> 1 | BB75: =IF(CC75="ДА",$M75,"") -> 1 | BC75: =IF(CD75="ДА",$M75,"") -> 1 | BD75: =IF(CE75="ДА",$M75,"") -> 1 | BE75: =IF(CF75="ДА",$M75,"") -> 1 | BF75: =IF(CG75="ДА",$M75,"") -> 1 | BG75: =IF(CH75="ДА",$M75,"") -> 1 | BH75: =IF(CI75="ДА",$M75,"") -> 1 | BI75: =IF(CJ75="ДА",$M75,"") | ... BP75: =IF(CQ75="ДА",$M75,"") | BS75: ДА | BT75: ДА | BU75: НЕТ | BV75: НЕТ | BW75: ДА | BX75: ДА | BY75: ДА | BZ75: ДА | CA75: ДА | CC75: ДА | CD75: ДА | CE75: ДА | CF75: ДА | CG75: ДА | CH75: ДА | CI75: ДА | CJ75: НЕТ | CK75: ДА | CL75: НЕТ | CM75: ДА | CN75: НЕТ | CO75: НЕТ | CP75: НЕТ | CQ75: НЕТ | CR75: Не требуется
B76: Планирование материальных ресурсов и оборудования | C76: с ограничениями. Не для инжиниринга! | N76: =SUM(O76,R76,U76,X76) -> 0
B77: Формирование заказа поставщику | C77: нет | N77: =SUM(O77,R77,U77,X77) -> 0 | BT77: НЕТ
B78: Планирование дополнительных затрат | C78: нет | N78: =SUM(O78,R78,U78,X78) -> 0
A79: 3.3. | B79: Учесть фактические трудозатраты по проектам | F79: Базовый | G79: Кейс-проект | H79: Да | I79: Да | J79: Да | K79: Да | L79: В разработке | M79: 1 | N79: =SUM(O79,R79,U79,X79) -> 2 | O79: =IF(AC79="ДА",$M79,"") -> 1 | Q79: =IF(AC79="ДА",ROUNDUP(O79/5,0),0) -> 1 | R79: =IF(AF79="ДА",$M79,"") -> 1 | T79: =IF(AF79="ДА",ROUNDUP(R79/5,0),0) -> 1 | U79: =IF(AI79="ДА",$M79,"") | W79: =IF(AI79="ДА",ROUNDUP(U79/5,0),0) -> 0 | X79: =IF(AL79="ДА",$M79,"") | Z79: =IF(AL79="ДА",ROUNDUP(X79/5,0),0) -> 0 | AA79: =IF(OR(AC79="ДА",AF79="ДА",AI79="ДА",AL79="ДА"),"ДА","НЕТ") -> ДА | AC79: =IF(AC$8=$BT$9,$BT79,IF(AC$8=$BS$9,$BS79,IF(AC$8=$BU$9,$BU79,IF(AC$8=$BV$9,$BV79,IF(AC$8=$BW$9,$BW79,IF(AC$8=$BX$9,$BX79,IF(AC$8=$BY$9,$BY79,IF(AC$8=$BZ$9,$BZ79,IF(AC$8=$CA$9,$CA79,IF(AC$8=$CC$9,$CC79,IF(AC$8=$CD$9,$CD79,IF(AC$8=$CE$9,$CE79,IF(AC$8=$CF$9,$CF79,IF(AC$8=$CG$9,$CG79,IF(AC$8=$CH$9,$CH79,IF(AC$8=$CI$9,$CI79,IF(AC$8=$CJ$9,$CJ79,IF(AC$8=$CK$9,$CK79,IF(AC$8=$CL$9,$CL79,IF(AC$8=$CM$9,$CM79,IF(AC$8=$CN$9,$CN79,IF(AC$8=$CO$9,$CO79,IF(AC$8=$CP$9,$CP79,IF(AC$8=$CQ$9,$CQ79,"НЕТ")))))))))))))))))))))))) -> ДА | AD79: =IF(AC79="НЕТ","Не требуется",$CR79) -> Не требуется | AF79: =IF(AF$8=$BT$9,$BT79,IF(AF$8=$BS$9,$BS79,IF(AF$8=$BU$9,$BU79,IF(AF$8=$BV$9,$BV79,IF(AF$8=$BW$9,$BW79,IF(AF$8=$BX$9,$BX79,IF(AF$8=$BY$9,$BY79,IF(AF$8=$BZ$9,$BZ79,IF(AF$8=$CA$9,$CA79,IF(AF$8=$CC$9,$CC79,IF(AF$8=$CD$9,$CD79,IF(AF$8=$CE$9,$CE79,IF(AF$8=$CF$9,$CF79,IF(AF$8=$CG$9,$CG79,IF(AF$8=$CH$9,$CH79,IF(AF$8=$CI$9,$CI79,IF(AF$8=$CJ$9,$CJ79,IF(AF$8=$CK$9,$CK79,IF(AF$8=$CL$9,$CL79,IF(AF$8=$CM$9,$CM79,IF(AF$8=$CN$9,$CN79,IF(AF$8=$CO$9,$CO79,IF(AF$8=$CP$9,$CP79,IF(AF$8=$CQ$9,$CQ79,"НЕТ")))))))))))))))))))))))) -> ДА | AG79: =IF(AG$8=$BT$9,$BT79,IF(AG$8=$BS$9,$BS79,IF(AG$8=$BU$9,$BU79,IF(AG$8=$BV$9,$BV79,IF(AG$8=$BW$9,$BW79,IF(AG$8=$BX$9,$BX79,IF(AG$8=$BY$9,$BY79,IF(AG$8=$BZ$9,$BZ79,IF(AG$8=$CA$9,$CA79,IF(AG$8=$CC$9,$CC79,IF(AG$8=$CD$9,$CD79,IF(AG$8=$CE$9,$CE79,IF(AG$8=$CF$9,$CF79,IF(AG$8=$CG$9,$CG79,IF(AG$8=$CH$9,$CH79,IF(AG$8=$CI$9,$CI79,IF(AG$8=$CJ$9,$CJ79,IF(AG$8=$CK$9,$CK79,IF(AG$8=$CL$9,$CL79,IF(AG$8=$CM$9,$CM79,IF(AG$8=$CN$9,$CN79,IF(AG$8=$CO$9,$CO79,IF(AG$8=$CP$9,$CP79,IF(AG$8=$CQ$9,$CQ79,"НЕТ")))))))))))))))))))))))) -> НЕТ | AH79: =IF(AH$8=$BT$9,$BT79,IF(AH$8=$BS$9,$BS79,IF(AH$8=$BU$9,$BU79,IF(AH$8=$BV$9,$BV79,IF(AH$8=$BW$9,$BW79,IF(AH$8=$BX$9,$BX79,IF(AH$8=$BY$9,$BY79,IF(AH$8=$BZ$9,$BZ79,IF(AH$8=$CA$9,$CA79,IF(AH$8=$CC$9,$CC79,IF(AH$8=$CD$9,$CD79,IF(AH$8=$CE$9,$CE79,IF(AH$8=$CF$9,$CF79,IF(AH$8=$CG$9,$CG79,IF(AH$8=$CH$9,$CH79,IF(AH$8=$CI$9,$CI79,IF(AH$8=$CJ$9,$CJ79,IF(AH$8=$CK$9,$CK79,IF(AH$8=$CL$9,$CL79,IF(AH$8=$CM$9,$CM79,IF(AH$8=$CN$9,$CN79,IF(AH$8=$CO$9,$CO79,IF(AH$8=$CP$9,$CP79,IF(AH$8=$CQ$9,$CQ79,"НЕТ")))))))))))))))))))))))) -> НЕТ | AI79: =IF(AI$8=$BT$9,$BT79,IF(AI$8=$BS$9,$BS79,IF(AI$8=$BU$9,$BU79,IF(AI$8=$BV$9,$BV79,IF(AI$8=$BW$9,$BW79,IF(AI$8=$BX$9,$BX79,IF(AI$8=$BY$9,$BY79,IF(AI$8=$BZ$9,$BZ79,IF(AI$8=$CA$9,$CA79,IF(AI$8=$CC$9,$CC79,IF(AI$8=$CD$9,$CD79,IF(AI$8=$CE$9,$CE79,IF(AI$8=$CF$9,$CF79,IF(AI$8=$CG$9,$CG79,IF(AI$8=$CH$9,$CH79,IF(AI$8=$CI$9,$CI79,IF(AI$8=$CJ$9,$CJ79,IF(AI$8=$CK$9,$CK79,IF(AI$8=$CL$9,$CL79,IF(AI$8=$CM$9,$CM79,IF(AI$8=$CN$9,$CN79,IF(AI$8=$CO$9,$CO79,IF(AI$8=$CP$9,$CP79,IF(AI$8=$CQ$9,$CQ79,"НЕТ")))))))))))))))))))))))) -> НЕТ | AJ79: =IF(AJ$8=$BT$9,$BT79,IF(AJ$8=$BS$9,$BS79,IF(AJ$8=$BU$9,$BU79,IF(AJ$8=$BV$9,$BV79,IF(AJ$8=$BW$9,$BW79,IF(AJ$8=$BX$9,$BX79,IF(AJ$8=$BY$9,$BY79,IF(AJ$8=$BZ$9,$BZ79,IF(AJ$8=$CA$9,$CA79,IF(AJ$8=$CC$9,$CC79,IF(AJ$8=$CD$9,$CD79,IF(AJ$8=$CE$9,$CE79,IF(AJ$8=$CF$9,$CF79,IF(AJ$8=$CG$9,$CG79,IF(AJ$8=$CH$9,$CH79,IF(AJ$8=$CI$9,$CI79,IF(AJ$8=$CJ$9,$CJ79,IF(AJ$8=$CK$9,$CK79,IF(AJ$8=$CL$9,$CL79,IF(AJ$8=$CM$9,$CM79,IF(AJ$8=$CN$9,$CN79,IF(AJ$8=$CO$9,$CO79,IF(AJ$8=$CP$9,$CP79,IF(AJ$8=$CQ$9,$CQ79,"НЕТ")))))))))))))))))))))))) -> НЕТ | AK79: =IF(AK$8=$BT$9,$BT79,IF(AK$8=$BS$9,$BS79,IF(AK$8=$BU$9,$BU79,IF(AK$8=$BV$9,$BV79,IF(AK$8=$BW$9,$BW79,IF(AK$8=$BX$9,$BX79,IF(AK$8=$BY$9,$BY79,IF(AK$8=$BZ$9,$BZ79,IF(AK$8=$CA$9,$CA79,IF(AK$8=$CC$9,$CC79,IF(AK$8=$CD$9,$CD79,IF(AK$8=$CE$9,$CE79,IF(AK$8=$CF$9,$CF79,IF(AK$8=$CG$9,$CG79,IF(AK$8=$CH$9,$CH79,IF(AK$8=$CI$9,$CI79,IF(AK$8=$CJ$9,$CJ79,IF(AK$8=$CK$9,$CK79,IF(AK$8=$CL$9,$CL79,IF(AK$8=$CM$9,$CM79,IF(AK$8=$CN$9,$CN79,IF(AK$8=$CO$9,$CO79,IF(AK$8=$CP$9,$CP79,IF(AK$8=$CQ$9,$CQ79,"НЕТ")))))))))))))))))))))))) -> НЕТ | AL79: =IF(AL$8=$BT$9,$BT79,IF(AL$8=$BS$9,$BS79,IF(AL$8=$BU$9,$BU79,IF(AL$8=$BV$9,$BV79,IF(AL$8=$BW$9,$BW79,IF(AL$8=$BX$9,$BX79,IF(AL$8=$BY$9,$BY79,IF(AL$8=$BZ$9,$BZ79,IF(AL$8=$CA$9,$CA79,IF(AL$8=$CC$9,$CC79,IF(AL$8=$CD$9,$CD79,IF(AL$8=$CE$9,$CE79,IF(AL$8=$CF$9,$CF79,IF(AL$8=$CG$9,$CG79,IF(AL$8=$CH$9,$CH79,IF(AL$8=$CI$9,$CI79,IF(AL$8=$CJ$9,$CJ79,IF(AL$8=$CK$9,$CK79,IF(AL$8=$CL$9,$CL79,IF(AL$8=$CM$9,$CM79,IF(AL$8=$CN$9,$CN79,IF(AL$8=$CO$9,$CO79,IF(AL$8=$CP$9,$CP79,IF(AL$8=$CQ$9,$CQ79,"НЕТ")))))))))))))))))))))))) -> НЕТ | AM79: =IF(AL79="НЕТ","Не требуется",$CR79) -> Не требуется | AS79: =IF(BS79="ДА",$M79,"") -> 1 | AT79: =IF(BT79="ДА",$M79,"") | AU79: =IF(BU79="ДА",$M79,"") -> 1 | AV79: =IF(BV79="ДА",$M79,"") | AW79: =IF(BX79="ДА",$M79,"") -> 1 | AX79: =IF(BY79="ДА",$M79,"") -> 1 | AY79: =IF(BZ79="ДА",$M79,"") -> 1 | AZ79: =IF(CA79="ДА",$M79,"") -> 1 | BB79: =IF(CC79="ДА",$M79,"") -> 1 | BC79: =IF(CD79="ДА",$M79,"") -> 1 | BD79: =IF(CE79="ДА",$M79,"") -> 1 | BE79: =IF(CF79="ДА",$M79,"") -> 1 | BF79: =IF(CG79="ДА",$M79,"") -> 1 | BG79: =IF(CH79="ДА",$M79,"") -> 1 | BH79: =IF(CI79="ДА",$M79,"") -> 1 | BI79: =IF(CJ79="ДА",$M79,"") -> 1 | ... BP79: =IF(CQ79="ДА",$M79,"") | BS79: ДА | BT79: НЕТ | BU79: ДА | BV79: НЕТ | BW79: ДА | BX79: ДА | BY79: ДА | BZ79: ДА | CA79: ДА | CC79: ДА | CD79: ДА | CE79: ДА | CF79: ДА | CG79: ДА | CH79: ДА | CI79: ДА | CJ79: ДА | CK79: ДА | CL79: ДА | CM79: НЕТ | CN79: НЕТ | CO79: НЕТ | CP79: НЕТ | CQ79: НЕТ | CR79: Не требуется
B80: Учет рабочего времени | C80: с ограничениями! Табелирование для ресурсов с видом "Трудовые ресурсы (сотрудники) | N80: =SUM(O80,R80,U80,X80) -> 0
B81: Анализ фактических трудозатрат | C81: ПФА трудовых ресурсов | N81: =SUM(O81,R81,U81,X81) -> 0
B82: План-фактный анализ трудозатрат | C82: ПФА трудовых ресурсов | N82: =SUM(O82,R82,U82,X82) -> 0
A83: 3.4. | B83: Учесть фактический расход ресурсов | F83: Базовый | G83: Кейс-проект | H83: Да | I83: Да | J83: Да | K83: Да | L83: В разработке | M83: 1 | N83: =SUM(O83,R83,U83,X83) -> 1 | O83: =IF(AC83="ДА",$M83,"") | Q83: =IF(AC83="ДА",ROUNDUP(O83/5,0),0) -> 0 | R83: =IF(AF83="ДА",$M83,"") -> 1 | T83: =IF(AF83="ДА",ROUNDUP(R83/5,0),0) -> 1 | U83: =IF(AI83="ДА",$M83,"") | W83: =IF(AI83="ДА",ROUNDUP(U83/5,0),0) -> 0 | X83: =IF(AL83="ДА",$M83,"") | Z83: =IF(AL83="ДА",ROUNDUP(X83/5,0),0) -> 0 | AA83: =IF(OR(AC83="ДА",AF83="ДА",AI83="ДА",AL83="ДА"),"ДА","НЕТ") -> ДА | AC83: =IF(AC$8=$BT$9,$BT83,IF(AC$8=$BS$9,$BS83,IF(AC$8=$BU$9,$BU83,IF(AC$8=$BV$9,$BV83,IF(AC$8=$BW$9,$BW83,IF(AC$8=$BX$9,$BX83,IF(AC$8=$BY$9,$BY83,IF(AC$8=$BZ$9,$BZ83,IF(AC$8=$CA$9,$CA83,IF(AC$8=$CC$9,$CC83,IF(AC$8=$CD$9,$CD83,IF(AC$8=$CE$9,$CE83,IF(AC$8=$CF$9,$CF83,IF(AC$8=$CG$9,$CG83,IF(AC$8=$CH$9,$CH83,IF(AC$8=$CI$9,$CI83,IF(AC$8=$CJ$9,$CJ83,IF(AC$8=$CK$9,$CK83,IF(AC$8=$CL$9,$CL83,IF(AC$8=$CM$9,$CM83,IF(AC$8=$CN$9,$CN83,IF(AC$8=$CO$9,$CO83,IF(AC$8=$CP$9,$CP83,IF(AC$8=$CQ$9,$CQ83,"НЕТ")))))))))))))))))))))))) -> НЕТ | AD83: =IF(AC83="НЕТ","Не требуется",$CR83) -> Не требуется | AF83: =IF(AF$8=$BT$9,$BT83,IF(AF$8=$BS$9,$BS83,IF(AF$8=$BU$9,$BU83,IF(AF$8=$BV$9,$BV83,IF(AF$8=$BW$9,$BW83,IF(AF$8=$BX$9,$BX83,IF(AF$8=$BY$9,$BY83,IF(AF$8=$BZ$9,$BZ83,IF(AF$8=$CA$9,$CA83,IF(AF$8=$CC$9,$CC83,IF(AF$8=$CD$9,$CD83,IF(AF$8=$CE$9,$CE83,IF(AF$8=$CF$9,$CF83,IF(AF$8=$CG$9,$CG83,IF(AF$8=$CH$9,$CH83,IF(AF$8=$CI$9,$CI83,IF(AF$8=$CJ$9,$CJ83,IF(AF$8=$CK$9,$CK83,IF(AF$8=$CL$9,$CL83,IF(AF$8=$CM$9,$CM83,IF(AF$8=$CN$9,$CN83,IF(AF$8=$CO$9,$CO83,IF(AF$8=$CP$9,$CP83,IF(AF$8=$CQ$9,$CQ83,"НЕТ")))))))))))))))))))))))) -> ДА | AG83: =IF(AG$8=$BT$9,$BT83,IF(AG$8=$BS$9,$BS83,IF(AG$8=$BU$9,$BU83,IF(AG$8=$BV$9,$BV83,IF(AG$8=$BW$9,$BW83,IF(AG$8=$BX$9,$BX83,IF(AG$8=$BY$9,$BY83,IF(AG$8=$BZ$9,$BZ83,IF(AG$8=$CA$9,$CA83,IF(AG$8=$CC$9,$CC83,IF(AG$8=$CD$9,$CD83,IF(AG$8=$CE$9,$CE83,IF(AG$8=$CF$9,$CF83,IF(AG$8=$CG$9,$CG83,IF(AG$8=$CH$9,$CH83,IF(AG$8=$CI$9,$CI83,IF(AG$8=$CJ$9,$CJ83,IF(AG$8=$CK$9,$CK83,IF(AG$8=$CL$9,$CL83,IF(AG$8=$CM$9,$CM83,IF(AG$8=$CN$9,$CN83,IF(AG$8=$CO$9,$CO83,IF(AG$8=$CP$9,$CP83,IF(AG$8=$CQ$9,$CQ83,"НЕТ")))))))))))))))))))))))) -> НЕТ | AH83: =IF(AH$8=$BT$9,$BT83,IF(AH$8=$BS$9,$BS83,IF(AH$8=$BU$9,$BU83,IF(AH$8=$BV$9,$BV83,IF(AH$8=$BW$9,$BW83,IF(AH$8=$BX$9,$BX83,IF(AH$8=$BY$9,$BY83,IF(AH$8=$BZ$9,$BZ83,IF(AH$8=$CA$9,$CA83,IF(AH$8=$CC$9,$CC83,IF(AH$8=$CD$9,$CD83,IF(AH$8=$CE$9,$CE83,IF(AH$8=$CF$9,$CF83,IF(AH$8=$CG$9,$CG83,IF(AH$8=$CH$9,$CH83,IF(AH$8=$CI$9,$CI83,IF(AH$8=$CJ$9,$CJ83,IF(AH$8=$CK$9,$CK83,IF(AH$8=$CL$9,$CL83,IF(AH$8=$CM$9,$CM83,IF(AH$8=$CN$9,$CN83,IF(AH$8=$CO$9,$CO83,IF(AH$8=$CP$9,$CP83,IF(AH$8=$CQ$9,$CQ83,"НЕТ")))))))))))))))))))))))) -> НЕТ | AI83: =IF(AI$8=$BT$9,$BT83,IF(AI$8=$BS$9,$BS83,IF(AI$8=$BU$9,$BU83,IF(AI$8=$BV$9,$BV83,IF(AI$8=$BW$9,$BW83,IF(AI$8=$BX$9,$BX83,IF(AI$8=$BY$9,$BY83,IF(AI$8=$BZ$9,$BZ83,IF(AI$8=$CA$9,$CA83,IF(AI$8=$CC$9,$CC83,IF(AI$8=$CD$9,$CD83,IF(AI$8=$CE$9,$CE83,IF(AI$8=$CF$9,$CF83,IF(AI$8=$CG$9,$CG83,IF(AI$8=$CH$9,$CH83,IF(AI$8=$CI$9,$CI83,IF(AI$8=$CJ$9,$CJ83,IF(AI$8=$CK$9,$CK83,IF(AI$8=$CL$9,$CL83,IF(AI$8=$CM$9,$CM83,IF(AI$8=$CN$9,$CN83,IF(AI$8=$CO$9,$CO83,IF(AI$8=$CP$9,$CP83,IF(AI$8=$CQ$9,$CQ83,"НЕТ")))))))))))))))))))))))) -> НЕТ | AJ83: =IF(AJ$8=$BT$9,$BT83,IF(AJ$8=$BS$9,$BS83,IF(AJ$8=$BU$9,$BU83,IF(AJ$8=$BV$9,$BV83,IF(AJ$8=$BW$9,$BW83,IF(AJ$8=$BX$9,$BX83,IF(AJ$8=$BY$9,$BY83,IF(AJ$8=$BZ$9,$BZ83,IF(AJ$8=$CA$9,$CA83,IF(AJ$8=$CC$9,$CC83,IF(AJ$8=$CD$9,$CD83,IF(AJ$8=$CE$9,$CE83,IF(AJ$8=$CF$9,$CF83,IF(AJ$8=$CG$9,$CG83,IF(AJ$8=$CH$9,$CH83,IF(AJ$8=$CI$9,$CI83,IF(AJ$8=$CJ$9,$CJ83,IF(AJ$8=$CK$9,$CK83,IF(AJ$8=$CL$9,$CL83,IF(AJ$8=$CM$9,$CM83,IF(AJ$8=$CN$9,$CN83,IF(AJ$8=$CO$9,$CO83,IF(AJ$8=$CP$9,$CP83,IF(AJ$8=$CQ$9,$CQ83,"НЕТ")))))))))))))))))))))))) -> НЕТ | AK83: =IF(AK$8=$BT$9,$BT83,IF(AK$8=$BS$9,$BS83,IF(AK$8=$BU$9,$BU83,IF(AK$8=$BV$9,$BV83,IF(AK$8=$BW$9,$BW83,IF(AK$8=$BX$9,$BX83,IF(AK$8=$BY$9,$BY83,IF(AK$8=$BZ$9,$BZ83,IF(AK$8=$CA$9,$CA83,IF(AK$8=$CC$9,$CC83,IF(AK$8=$CD$9,$CD83,IF(AK$8=$CE$9,$CE83,IF(AK$8=$CF$9,$CF83,IF(AK$8=$CG$9,$CG83,IF(AK$8=$CH$9,$CH83,IF(AK$8=$CI$9,$CI83,IF(AK$8=$CJ$9,$CJ83,IF(AK$8=$CK$9,$CK83,IF(AK$8=$CL$9,$CL83,IF(AK$8=$CM$9,$CM83,IF(AK$8=$CN$9,$CN83,IF(AK$8=$CO$9,$CO83,IF(AK$8=$CP$9,$CP83,IF(AK$8=$CQ$9,$CQ83,"НЕТ")))))))))))))))))))))))) -> НЕТ | AL83: =IF(AL$8=$BT$9,$BT83,IF(AL$8=$BS$9,$BS83,IF(AL$8=$BU$9,$BU83,IF(AL$8=$BV$9,$BV83,IF(AL$8=$BW$9,$BW83,IF(AL$8=$BX$9,$BX83,IF(AL$8=$BY$9,$BY83,IF(AL$8=$BZ$9,$BZ83,IF(AL$8=$CA$9,$CA83,IF(AL$8=$CC$9,$CC83,IF(AL$8=$CD$9,$CD83,IF(AL$8=$CE$9,$CE83,IF(AL$8=$CF$9,$CF83,IF(AL$8=$CG$9,$CG83,IF(AL$8=$CH$9,$CH83,IF(AL$8=$CI$9,$CI83,IF(AL$8=$CJ$9,$CJ83,IF(AL$8=$CK$9,$CK83,IF(AL$8=$CL$9,$CL83,IF(AL$8=$CM$9,$CM83,IF(AL$8=$CN$9,$CN83,IF(AL$8=$CO$9,$CO83,IF(AL$8=$CP$9,$CP83,IF(AL$8=$CQ$9,$CQ83,"НЕТ")))))))))))))))))))))))) -> НЕТ | AM83: =IF(AL83="НЕТ","Не требуется",$CR83) -> Не требуется | AS83: =IF(BS83="ДА",$M83,"") -> 1 | AT83: =IF(BT83="ДА",$M83,"") -> 1 | AU83: =IF(BU83="ДА",$M83,"") | AV83: =IF(BV83="ДА",$M83,"") | AW83: =IF(BX83="ДА",$M83,"") -> 1 | AX83: =IF(BY83="ДА",$M83,"") -> 1 | AY83: =IF(BZ83="ДА",$M83,"") -> 1 | AZ83: =IF(CA83="ДА",$M83,"") -> 1 | BB83: =IF(CC83="ДА",$M83,"") -> 1 | BC83: =IF(CD83="ДА",$M83,"") -> 1 | BD83: =IF(CE83="ДА",$M83,"") -> 1 | BE83: =IF(CF83="ДА",$M83,"") -> 1 | BF83: =IF(CG83="ДА",$M83,"") -> 1 | BG83: =IF(CH83="ДА",$M83,"") -> 1 | BH83: =IF(CI83="ДА",$M83,"") -> 1 | BI83: =IF(CJ83="ДА",$M83,"") | ... BP83: =IF(CQ83="ДА",$M83,"") | BS83: ДА | BT83: ДА | BU83: НЕТ | BV83: НЕТ | BW83: ДА | BX83: ДА | BY83: ДА | BZ83: ДА | CA83: ДА | CC83: ДА | CD83: ДА | CE83: ДА | CF83: ДА | CG83: ДА | CH83: ДА | CI83: ДА | CJ83: НЕТ | CK83: ДА | CL83: НЕТ | CM83: НЕТ | CN83: НЕТ | CO83: НЕТ | CP83: НЕТ | CQ83: НЕТ | CR83: Не требуется
B84: Учет фактического использования материальных ресурсов и оборудования | C84: С ограничениями! Документ фактические ресурсы, в привязке к элементу плана | N84: =SUM(O84,R84,U84,X84) -> 0
B85: Учет факта дополнительных затрат | C85: С ограничениями! Документ фактические ресурсы, в привязке к элементу плана | N85: =SUM(O85,R85,U85,X85) -> 0
B86: План-фактный анализ затрат материальных ресурсов | C86: ПФА ресурсов и результатов работ | N86: =SUM(O86,R86,U86,X86) -> 0
B87: План-фактный анализ дополнительных затрат | C87: ПФА ресурсов и результатов работ | N87: =SUM(O87,R87,U87,X87) -> 0
A88: 3.5. | B88: Мониторинг процесса закупок ТМЦ под проект вручную в Контуре PM, или импорт из сторонней системы (ERP или др), импорт отметить в отдельном пункте в разделе Интеграции (оценка при условии разработки базовой части АРМа для РП и МТО в типовой) | C88: Нет | F88: в Разработке | G88: Проф/мини | H88: Под проект | I88: Под проект | J88: Под проект | K88: Под проект | L88: Под проект | M88: 5 | N88: =SUM(O88,R88,U88,X88) -> 5 | O88: =IF(AC88="ДА",$M88,"") | Q88: =IF(AC88="ДА",ROUNDUP(O88/5,0),0) -> 0 | R88: =IF(AF88="ДА",$M88,"") -> 5 | T88: =IF(AF88="ДА",ROUNDUP(R88/5,0),0) -> 1 | U88: =IF(AI88="ДА",$M88,"") | W88: =IF(AI88="ДА",ROUNDUP(U88/5,0),0) -> 0 | X88: =IF(AL88="ДА",$M88,"") | Z88: =IF(AL88="ДА",ROUNDUP(X88/5,0),0) -> 0 | AA88: =IF(OR(AC88="ДА",AF88="ДА",AI88="ДА",AL88="ДА"),"ДА","НЕТ") -> ДА | AC88: =IF(AC$8=$BT$9,$BT88,IF(AC$8=$BS$9,$BS88,IF(AC$8=$BU$9,$BU88,IF(AC$8=$BV$9,$BV88,IF(AC$8=$BW$9,$BW88,IF(AC$8=$BX$9,$BX88,IF(AC$8=$BY$9,$BY88,IF(AC$8=$BZ$9,$BZ88,IF(AC$8=$CA$9,$CA88,IF(AC$8=$CC$9,$CC88,IF(AC$8=$CD$9,$CD88,IF(AC$8=$CE$9,$CE88,IF(AC$8=$CF$9,$CF88,IF(AC$8=$CG$9,$CG88,IF(AC$8=$CH$9,$CH88,IF(AC$8=$CI$9,$CI88,IF(AC$8=$CJ$9,$CJ88,IF(AC$8=$CK$9,$CK88,IF(AC$8=$CL$9,$CL88,IF(AC$8=$CM$9,$CM88,IF(AC$8=$CN$9,$CN88,IF(AC$8=$CO$9,$CO88,IF(AC$8=$CP$9,$CP88,IF(AC$8=$CQ$9,$CQ88,"НЕТ")))))))))))))))))))))))) -> НЕТ | AD88: =IF(AC88="НЕТ","Не требуется",$CR88) -> Не требуется | AF88: =IF(AF$8=$BT$9,$BT88,IF(AF$8=$BS$9,$BS88,IF(AF$8=$BU$9,$BU88,IF(AF$8=$BV$9,$BV88,IF(AF$8=$BW$9,$BW88,IF(AF$8=$BX$9,$BX88,IF(AF$8=$BY$9,$BY88,IF(AF$8=$BZ$9,$BZ88,IF(AF$8=$CA$9,$CA88,IF(AF$8=$CC$9,$CC88,IF(AF$8=$CD$9,$CD88,IF(AF$8=$CE$9,$CE88,IF(AF$8=$CF$9,$CF88,IF(AF$8=$CG$9,$CG88,IF(AF$8=$CH$9,$CH88,IF(AF$8=$CI$9,$CI88,IF(AF$8=$CJ$9,$CJ88,IF(AF$8=$CK$9,$CK88,IF(AF$8=$CL$9,$CL88,IF(AF$8=$CM$9,$CM88,IF(AF$8=$CN$9,$CN88,IF(AF$8=$CO$9,$CO88,IF(AF$8=$CP$9,$CP88,IF(AF$8=$CQ$9,$CQ88,"НЕТ")))))))))))))))))))))))) -> ДА | AG88: =IF(AG$8=$BT$9,$BT88,IF(AG$8=$BS$9,$BS88,IF(AG$8=$BU$9,$BU88,IF(AG$8=$BV$9,$BV88,IF(AG$8=$BW$9,$BW88,IF(AG$8=$BX$9,$BX88,IF(AG$8=$BY$9,$BY88,IF(AG$8=$BZ$9,$BZ88,IF(AG$8=$CA$9,$CA88,IF(AG$8=$CC$9,$CC88,IF(AG$8=$CD$9,$CD88,IF(AG$8=$CE$9,$CE88,IF(AG$8=$CF$9,$CF88,IF(AG$8=$CG$9,$CG88,IF(AG$8=$CH$9,$CH88,IF(AG$8=$CI$9,$CI88,IF(AG$8=$CJ$9,$CJ88,IF(AG$8=$CK$9,$CK88,IF(AG$8=$CL$9,$CL88,IF(AG$8=$CM$9,$CM88,IF(AG$8=$CN$9,$CN88,IF(AG$8=$CO$9,$CO88,IF(AG$8=$CP$9,$CP88,IF(AG$8=$CQ$9,$CQ88,"НЕТ")))))))))))))))))))))))) -> НЕТ | AH88: =IF(AH$8=$BT$9,$BT88,IF(AH$8=$BS$9,$BS88,IF(AH$8=$BU$9,$BU88,IF(AH$8=$BV$9,$BV88,IF(AH$8=$BW$9,$BW88,IF(AH$8=$BX$9,$BX88,IF(AH$8=$BY$9,$BY88,IF(AH$8=$BZ$9,$BZ88,IF(AH$8=$CA$9,$CA88,IF(AH$8=$CC$9,$CC88,IF(AH$8=$CD$9,$CD88,IF(AH$8=$CE$9,$CE88,IF(AH$8=$CF$9,$CF88,IF(AH$8=$CG$9,$CG88,IF(AH$8=$CH$9,$CH88,IF(AH$8=$CI$9,$CI88,IF(AH$8=$CJ$9,$CJ88,IF(AH$8=$CK$9,$CK88,IF(AH$8=$CL$9,$CL88,IF(AH$8=$CM$9,$CM88,IF(AH$8=$CN$9,$CN88,IF(AH$8=$CO$9,$CO88,IF(AH$8=$CP$9,$CP88,IF(AH$8=$CQ$9,$CQ88,"НЕТ")))))))))))))))))))))))) -> НЕТ | AI88: =IF(AI$8=$BT$9,$BT88,IF(AI$8=$BS$9,$BS88,IF(AI$8=$BU$9,$BU88,IF(AI$8=$BV$9,$BV88,IF(AI$8=$BW$9,$BW88,IF(AI$8=$BX$9,$BX88,IF(AI$8=$BY$9,$BY88,IF(AI$8=$BZ$9,$BZ88,IF(AI$8=$CA$9,$CA88,IF(AI$8=$CC$9,$CC88,IF(AI$8=$CD$9,$CD88,IF(AI$8=$CE$9,$CE88,IF(AI$8=$CF$9,$CF88,IF(AI$8=$CG$9,$CG88,IF(AI$8=$CH$9,$CH88,IF(AI$8=$CI$9,$CI88,IF(AI$8=$CJ$9,$CJ88,IF(AI$8=$CK$9,$CK88,IF(AI$8=$CL$9,$CL88,IF(AI$8=$CM$9,$CM88,IF(AI$8=$CN$9,$CN88,IF(AI$8=$CO$9,$CO88,IF(AI$8=$CP$9,$CP88,IF(AI$8=$CQ$9,$CQ88,"НЕТ")))))))))))))))))))))))) -> НЕТ | AJ88: =IF(AJ$8=$BT$9,$BT88,IF(AJ$8=$BS$9,$BS88,IF(AJ$8=$BU$9,$BU88,IF(AJ$8=$BV$9,$BV88,IF(AJ$8=$BW$9,$BW88,IF(AJ$8=$BX$9,$BX88,IF(AJ$8=$BY$9,$BY88,IF(AJ$8=$BZ$9,$BZ88,IF(AJ$8=$CA$9,$CA88,IF(AJ$8=$CC$9,$CC88,IF(AJ$8=$CD$9,$CD88,IF(AJ$8=$CE$9,$CE88,IF(AJ$8=$CF$9,$CF88,IF(AJ$8=$CG$9,$CG88,IF(AJ$8=$CH$9,$CH88,IF(AJ$8=$CI$9,$CI88,IF(AJ$8=$CJ$9,$CJ88,IF(AJ$8=$CK$9,$CK88,IF(AJ$8=$CL$9,$CL88,IF(AJ$8=$CM$9,$CM88,IF(AJ$8=$CN$9,$CN88,IF(AJ$8=$CO$9,$CO88,IF(AJ$8=$CP$9,$CP88,IF(AJ$8=$CQ$9,$CQ88,"НЕТ")))))))))))))))))))))))) -> НЕТ | AK88: =IF(AK$8=$BT$9,$BT88,IF(AK$8=$BS$9,$BS88,IF(AK$8=$BU$9,$BU88,IF(AK$8=$BV$9,$BV88,IF(AK$8=$BW$9,$BW88,IF(AK$8=$BX$9,$BX88,IF(AK$8=$BY$9,$BY88,IF(AK$8=$BZ$9,$BZ88,IF(AK$8=$CA$9,$CA88,IF(AK$8=$CC$9,$CC88,IF(AK$8=$CD$9,$CD88,IF(AK$8=$CE$9,$CE88,IF(AK$8=$CF$9,$CF88,IF(AK$8=$CG$9,$CG88,IF(AK$8=$CH$9,$CH88,IF(AK$8=$CI$9,$CI88,IF(AK$8=$CJ$9,$CJ88,IF(AK$8=$CK$9,$CK88,IF(AK$8=$CL$9,$CL88,IF(AK$8=$CM$9,$CM88,IF(AK$8=$CN$9,$CN88,IF(AK$8=$CO$9,$CO88,IF(AK$8=$CP$9,$CP88,IF(AK$8=$CQ$9,$CQ88,"НЕТ")))))))))))))))))))))))) -> НЕТ | AL88: =IF(AL$8=$BT$9,$BT88,IF(AL$8=$BS$9,$BS88,IF(AL$8=$BU$9,$BU88,IF(AL$8=$BV$9,$BV88,IF(AL$8=$BW$9,$BW88,IF(AL$8=$BX$9,$BX88,IF(AL$8=$BY$9,$BY88,IF(AL$8=$BZ$9,$BZ88,IF(AL$8=$CA$9,$CA88,IF(AL$8=$CC$9,$CC88,IF(AL$8=$CD$9,$CD88,IF(AL$8=$CE$9,$CE88,IF(AL$8=$CF$9,$CF88,IF(AL$8=$CG$9,$CG88,IF(AL$8=$CH$9,$CH88,IF(AL$8=$CI$9,$CI88,IF(AL$8=$CJ$9,$CJ88,IF(AL$8=$CK$9,$CK88,IF(AL$8=$CL$9,$CL88,IF(AL$8=$CM$9,$CM88,IF(AL$8=$CN$9,$CN88,IF(AL$8=$CO$9,$CO88,IF(AL$8=$CP$9,$CP88,IF(AL$8=$CQ$9,$CQ88,"НЕТ")))))))))))))))))))))))) -> НЕТ | AM88: =IF(AL88="НЕТ","Не требуется",$CR88) -> Не требуется | AS88: =IF(BS88="ДА",$M88,"") | AT88: =IF(BT88="ДА",$M88,"") | AU88: =IF(BU88="ДА",$M88,"") | AV88: =IF(BV88="ДА",$M88,"") | AW88: =IF(BX88="ДА",$M88,"") -> 5 | AX88: =IF(BY88="ДА",$M88,"") -> 5 | AY88: =IF(BZ88="ДА",$M88,"") -> 5 | AZ88: =IF(CA88="ДА",$M88,"") -> 5 | BB88: =IF(CC88="ДА",$M88,"") -> 5 | BC88: =IF(CD88="ДА",$M88,"") -> 5 | BD88: =IF(CE88="ДА",$M88,"") -> 5 | BE88: =IF(CF88="ДА",$M88,"") -> 5 | BF88: =IF(CG88="ДА",$M88,"") -> 5 | BG88: =IF(CH88="ДА",$M88,"") -> 5 | BH88: =IF(CI88="ДА",$M88,"") -> 5 | BI88: =IF(CJ88="ДА",$M88,"") | ... BP88: =IF(CQ88="ДА",$M88,"") | BS88: НЕТ | BT88: НЕТ | BU88: НЕТ | BV88: НЕТ | BW88: ДА | BX88: ДА | BY88: ДА | BZ88: ДА | CA88: ДА | CC88: ДА | CD88: ДА | CE88: ДА | CF88: ДА | CG88: ДА | CH88: ДА | CI88: ДА | CJ88: НЕТ | CK88: ДА | CL88: НЕТ | CM88: НЕТ | CN88: НЕТ | CO88: НЕТ | CP88: НЕТ | CQ88: НЕТ | CR88: Не требуется
B89: Регистрация статуса обеспечения ТМЦ проекта по номенклатурно, в т.ч. Поступления/резервирования/ выпуска ТМЦ на складе | N89: =SUM(O89,R89,U89,X89) -> 0
B90: Регистрация стоимости поступления/резервирования/выпуска ТМЦ на складе | N90: =SUM(O90,R90,U90,X90) -> 0
B91: Регистрация плановой и фактической даты поступления ТМЦ | N91: =SUM(O91,R91,U91,X91) -> 0
B92: Актуализация сроков проекта по данным о плановых и фактических датах поступления ТМЦ | N92: =SUM(O92,R92,U92,X92) -> 0
A93: 3.6. | B93: S-кривые проектов | F93: Базовый | G93: Кейс-проект | H93: Да | I93: Да | J93: Да | K93: Да | L93: Да | M93: 2 | N93: =SUM(O93,R93,U93,X93) -> 4 | O93: =IF(AC93="ДА",$M93,"") | Q93: =IF(AC93="ДА",ROUNDUP(O93/5,0),0) -> 0 | R93: =IF(AF93="ДА",$M93,"") -> 2 | T93: =IF(AF93="ДА",ROUNDUP(R93/5,0),0) -> 1 | U93: =IF(AI93="ДА",$M93,"") -> 2 | W93: =IF(AI93="ДА",ROUNDUP(U93/5,0),0) -> 1 | X93: =IF(AL93="ДА",$M93,"") | Z93: =IF(AL93="ДА",ROUNDUP(X93/5,0),0) -> 0 | AA93: =IF(OR(AC93="ДА",AF93="ДА",AI93="ДА",AL93="ДА"),"ДА","НЕТ") -> ДА | AC93: =IF(AC$8=$BT$9,$BT93,IF(AC$8=$BS$9,$BS93,IF(AC$8=$BU$9,$BU93,IF(AC$8=$BV$9,$BV93,IF(AC$8=$BW$9,$BW93,IF(AC$8=$BX$9,$BX93,IF(AC$8=$BY$9,$BY93,IF(AC$8=$BZ$9,$BZ93,IF(AC$8=$CA$9,$CA93,IF(AC$8=$CC$9,$CC93,IF(AC$8=$CD$9,$CD93,IF(AC$8=$CE$9,$CE93,IF(AC$8=$CF$9,$CF93,IF(AC$8=$CG$9,$CG93,IF(AC$8=$CH$9,$CH93,IF(AC$8=$CI$9,$CI93,IF(AC$8=$CJ$9,$CJ93,IF(AC$8=$CK$9,$CK93,IF(AC$8=$CL$9,$CL93,IF(AC$8=$CM$9,$CM93,IF(AC$8=$CN$9,$CN93,IF(AC$8=$CO$9,$CO93,IF(AC$8=$CP$9,$CP93,IF(AC$8=$CQ$9,$CQ93,"НЕТ")))))))))))))))))))))))) -> НЕТ | AD93: =IF(AC93="НЕТ","Не требуется",$CR93) -> Не требуется | AF93: =IF(AF$8=$BT$9,$BT93,IF(AF$8=$BS$9,$BS93,IF(AF$8=$BU$9,$BU93,IF(AF$8=$BV$9,$BV93,IF(AF$8=$BW$9,$BW93,IF(AF$8=$BX$9,$BX93,IF(AF$8=$BY$9,$BY93,IF(AF$8=$BZ$9,$BZ93,IF(AF$8=$CA$9,$CA93,IF(AF$8=$CC$9,$CC93,IF(AF$8=$CD$9,$CD93,IF(AF$8=$CE$9,$CE93,IF(AF$8=$CF$9,$CF93,IF(AF$8=$CG$9,$CG93,IF(AF$8=$CH$9,$CH93,IF(AF$8=$CI$9,$CI93,IF(AF$8=$CJ$9,$CJ93,IF(AF$8=$CK$9,$CK93,IF(AF$8=$CL$9,$CL93,IF(AF$8=$CM$9,$CM93,IF(AF$8=$CN$9,$CN93,IF(AF$8=$CO$9,$CO93,IF(AF$8=$CP$9,$CP93,IF(AF$8=$CQ$9,$CQ93,"НЕТ")))))))))))))))))))))))) -> ДА | AG93: =IF(AG$8=$BT$9,$BT93,IF(AG$8=$BS$9,$BS93,IF(AG$8=$BU$9,$BU93,IF(AG$8=$BV$9,$BV93,IF(AG$8=$BW$9,$BW93,IF(AG$8=$BX$9,$BX93,IF(AG$8=$BY$9,$BY93,IF(AG$8=$BZ$9,$BZ93,IF(AG$8=$CA$9,$CA93,IF(AG$8=$CC$9,$CC93,IF(AG$8=$CD$9,$CD93,IF(AG$8=$CE$9,$CE93,IF(AG$8=$CF$9,$CF93,IF(AG$8=$CG$9,$CG93,IF(AG$8=$CH$9,$CH93,IF(AG$8=$CI$9,$CI93,IF(AG$8=$CJ$9,$CJ93,IF(AG$8=$CK$9,$CK93,IF(AG$8=$CL$9,$CL93,IF(AG$8=$CM$9,$CM93,IF(AG$8=$CN$9,$CN93,IF(AG$8=$CO$9,$CO93,IF(AG$8=$CP$9,$CP93,IF(AG$8=$CQ$9,$CQ93,"НЕТ")))))))))))))))))))))))) -> НЕТ | AH93: =IF(AH$8=$BT$9,$BT93,IF(AH$8=$BS$9,$BS93,IF(AH$8=$BU$9,$BU93,IF(AH$8=$BV$9,$BV93,IF(AH$8=$BW$9,$BW93,IF(AH$8=$BX$9,$BX93,IF(AH$8=$BY$9,$BY93,IF(AH$8=$BZ$9,$BZ93,IF(AH$8=$CA$9,$CA93,IF(AH$8=$CC$9,$CC93,IF(AH$8=$CD$9,$CD93,IF(AH$8=$CE$9,$CE93,IF(AH$8=$CF$9,$CF93,IF(AH$8=$CG$9,$CG93,IF(AH$8=$CH$9,$CH93,IF(AH$8=$CI$9,$CI93,IF(AH$8=$CJ$9,$CJ93,IF(AH$8=$CK$9,$CK93,IF(AH$8=$CL$9,$CL93,IF(AH$8=$CM$9,$CM93,IF(AH$8=$CN$9,$CN93,IF(AH$8=$CO$9,$CO93,IF(AH$8=$CP$9,$CP93,IF(AH$8=$CQ$9,$CQ93,"НЕТ")))))))))))))))))))))))) -> НЕТ | AI93: =IF(AI$8=$BT$9,$BT93,IF(AI$8=$BS$9,$BS93,IF(AI$8=$BU$9,$BU93,IF(AI$8=$BV$9,$BV93,IF(AI$8=$BW$9,$BW93,IF(AI$8=$BX$9,$BX93,IF(AI$8=$BY$9,$BY93,IF(AI$8=$BZ$9,$BZ93,IF(AI$8=$CA$9,$CA93,IF(AI$8=$CC$9,$CC93,IF(AI$8=$CD$9,$CD93,IF(AI$8=$CE$9,$CE93,IF(AI$8=$CF$9,$CF93,IF(AI$8=$CG$9,$CG93,IF(AI$8=$CH$9,$CH93,IF(AI$8=$CI$9,$CI93,IF(AI$8=$CJ$9,$CJ93,IF(AI$8=$CK$9,$CK93,IF(AI$8=$CL$9,$CL93,IF(AI$8=$CM$9,$CM93,IF(AI$8=$CN$9,$CN93,IF(AI$8=$CO$9,$CO93,IF(AI$8=$CP$9,$CP93,IF(AI$8=$CQ$9,$CQ93,"НЕТ")))))))))))))))))))))))) -> ДА | AJ93: =IF(AJ$8=$BT$9,$BT93,IF(AJ$8=$BS$9,$BS93,IF(AJ$8=$BU$9,$BU93,IF(AJ$8=$BV$9,$BV93,IF(AJ$8=$BW$9,$BW93,IF(AJ$8=$BX$9,$BX93,IF(AJ$8=$BY$9,$BY93,IF(AJ$8=$BZ$9,$BZ93,IF(AJ$8=$CA$9,$CA93,IF(AJ$8=$CC$9,$CC93,IF(AJ$8=$CD$9,$CD93,IF(AJ$8=$CE$9,$CE93,IF(AJ$8=$CF$9,$CF93,IF(AJ$8=$CG$9,$CG93,IF(AJ$8=$CH$9,$CH93,IF(AJ$8=$CI$9,$CI93,IF(AJ$8=$CJ$9,$CJ93,IF(AJ$8=$CK$9,$CK93,IF(AJ$8=$CL$9,$CL93,IF(AJ$8=$CM$9,$CM93,IF(AJ$8=$CN$9,$CN93,IF(AJ$8=$CO$9,$CO93,IF(AJ$8=$CP$9,$CP93,IF(AJ$8=$CQ$9,$CQ93,"НЕТ")))))))))))))))))))))))) -> НЕТ | AK93: =IF(AK$8=$BT$9,$BT93,IF(AK$8=$BS$9,$BS93,IF(AK$8=$BU$9,$BU93,IF(AK$8=$BV$9,$BV93,IF(AK$8=$BW$9,$BW93,IF(AK$8=$BX$9,$BX93,IF(AK$8=$BY$9,$BY93,IF(AK$8=$BZ$9,$BZ93,IF(AK$8=$CA$9,$CA93,IF(AK$8=$CC$9,$CC93,IF(AK$8=$CD$9,$CD93,IF(AK$8=$CE$9,$CE93,IF(AK$8=$CF$9,$CF93,IF(AK$8=$CG$9,$CG93,IF(AK$8=$CH$9,$CH93,IF(AK$8=$CI$9,$CI93,IF(AK$8=$CJ$9,$CJ93,IF(AK$8=$CK$9,$CK93,IF(AK$8=$CL$9,$CL93,IF(AK$8=$CM$9,$CM93,IF(AK$8=$CN$9,$CN93,IF(AK$8=$CO$9,$CO93,IF(AK$8=$CP$9,$CP93,IF(AK$8=$CQ$9,$CQ93,"НЕТ")))))))))))))))))))))))) -> НЕТ | AL93: =IF(AL$8=$BT$9,$BT93,IF(AL$8=$BS$9,$BS93,IF(AL$8=$BU$9,$BU93,IF(AL$8=$BV$9,$BV93,IF(AL$8=$BW$9,$BW93,IF(AL$8=$BX$9,$BX93,IF(AL$8=$BY$9,$BY93,IF(AL$8=$BZ$9,$BZ93,IF(AL$8=$CA$9,$CA93,IF(AL$8=$CC$9,$CC93,IF(AL$8=$CD$9,$CD93,IF(AL$8=$CE$9,$CE93,IF(AL$8=$CF$9,$CF93,IF(AL$8=$CG$9,$CG93,IF(AL$8=$CH$9,$CH93,IF(AL$8=$CI$9,$CI93,IF(AL$8=$CJ$9,$CJ93,IF(AL$8=$CK$9,$CK93,IF(AL$8=$CL$9,$CL93,IF(AL$8=$CM$9,$CM93,IF(AL$8=$CN$9,$CN93,IF(AL$8=$CO$9,$CO93,IF(AL$8=$CP$9,$CP93,IF(AL$8=$CQ$9,$CQ93,"НЕТ")))))))))))))))))))))))) -> НЕТ | AM93: =IF(AL93="НЕТ","Не требуется",$CR93) -> Не требуется | AS93: =IF(BS93="ДА",$M93,"") -> 2 | AT93: =IF(BT93="ДА",$M93,"") -> 2 | AU93: =IF(BU93="ДА",$M93,"") | AV93: =IF(BV93="ДА",$M93,"") -> 2 | AW93: =IF(BX93="ДА",$M93,"") -> 2 | AX93: =IF(BY93="ДА",$M93,"") -> 2 | AY93: =IF(BZ93="ДА",$M93,"") -> 2 | AZ93: =IF(CA93="ДА",$M93,"") -> 2 | BB93: =IF(CC93="ДА",$M93,"") | BC93: =IF(CD93="ДА",$M93,"") -> 2 | BD93: =IF(CE93="ДА",$M93,"") | BE93: =IF(CF93="ДА",$M93,"") -> 2 | BF93: =IF(CG93="ДА",$M93,"") | BG93: =IF(CH93="ДА",$M93,"") -> 2 | BH93: =IF(CI93="ДА",$M93,"") | BI93: =IF(CJ93="ДА",$M93,"") | ... BP93: =IF(CQ93="ДА",$M93,"") | BS93: ДА | BT93: ДА | BU93: НЕТ | BV93: ДА | BW93: ДА | BX93: ДА | BY93: ДА | BZ93: ДА | CA93: ДА | CC93: НЕТ | CD93: ДА | CE93: НЕТ | CF93: ДА | CG93: НЕТ | CH93: ДА | CI93: НЕТ | CJ93: НЕТ | CK93: ДА | CL93: НЕТ | CM93: НЕТ | CN93: НЕТ | CO93: НЕТ | CP93: НЕТ | CQ93: НЕТ | CR93: Не требуется
B94: Анализ фактического % готовности проектов, % готовности ожидаемой по сроку на текущую дату, % освоенных трудозатрат и % освоенного объема | C94: Отчет Анализ показателей, либо настройка в панели руководителя | N94: =SUM(O94,R94,U94,X94) -> 0
B95: Анализ отклонений по срокам на S-кривых проектов | C95: Отчет Анализ показателей, либо настройка в панели руководителя | N95: =SUM(O95,R95,U95,X95) -> 0
B96: Анализ отклонений по стоимости на S-кривых проектов | C96: Отчет Анализ показателей, либо настройка в панели руководителя | N96: =SUM(O96,R96,U96,X96) -> 0
A97: 3.6. | B97: KPI проектов по трудоемкости | F97: Проф | G97: ПРОФ-проект | H97: Да | I97: Да | J97: Да | K97: Да | L97: В разработке | M97: 2 | N97: =SUM(O97,R97,U97,X97) -> 2 | O97: =IF(AC97="ДА",$M97,"") | Q97: =IF(AC97="ДА",ROUNDUP(O97/5,0),0) -> 0 | R97: =IF(AF97="ДА",$M97,"") -> 2 | T97: =IF(AF97="ДА",ROUNDUP(R97/5,0),0) -> 1 | U97: =IF(AI97="ДА",$M97,"") | W97: =IF(AI97="ДА",ROUNDUP(U97/5,0),0) -> 0 | X97: =IF(AL97="ДА",$M97,"") | Z97: =IF(AL97="ДА",ROUNDUP(X97/5,0),0) -> 0 | AA97: =IF(OR(AC97="ДА",AF97="ДА",AI97="ДА",AL97="ДА"),"ДА","НЕТ") -> ДА | AC97: =IF(AC$8=$BT$9,$BT97,IF(AC$8=$BS$9,$BS97,IF(AC$8=$BU$9,$BU97,IF(AC$8=$BV$9,$BV97,IF(AC$8=$BW$9,$BW97,IF(AC$8=$BX$9,$BX97,IF(AC$8=$BY$9,$BY97,IF(AC$8=$BZ$9,$BZ97,IF(AC$8=$CA$9,$CA97,IF(AC$8=$CC$9,$CC97,IF(AC$8=$CD$9,$CD97,IF(AC$8=$CE$9,$CE97,IF(AC$8=$CF$9,$CF97,IF(AC$8=$CG$9,$CG97,IF(AC$8=$CH$9,$CH97,IF(AC$8=$CI$9,$CI97,IF(AC$8=$CJ$9,$CJ97,IF(AC$8=$CK$9,$CK97,IF(AC$8=$CL$9,$CL97,IF(AC$8=$CM$9,$CM97,IF(AC$8=$CN$9,$CN97,IF(AC$8=$CO$9,$CO97,IF(AC$8=$CP$9,$CP97,IF(AC$8=$CQ$9,$CQ97,"НЕТ")))))))))))))))))))))))) -> НЕТ | AD97: =IF(AC97="НЕТ","Не требуется",$CR97) -> Не требуется | AF97: =IF(AF$8=$BT$9,$BT97,IF(AF$8=$BS$9,$BS97,IF(AF$8=$BU$9,$BU97,IF(AF$8=$BV$9,$BV97,IF(AF$8=$BW$9,$BW97,IF(AF$8=$BX$9,$BX97,IF(AF$8=$BY$9,$BY97,IF(AF$8=$BZ$9,$BZ97,IF(AF$8=$CA$9,$CA97,IF(AF$8=$CC$9,$CC97,IF(AF$8=$CD$9,$CD97,IF(AF$8=$CE$9,$CE97,IF(AF$8=$CF$9,$CF97,IF(AF$8=$CG$9,$CG97,IF(AF$8=$CH$9,$CH97,IF(AF$8=$CI$9,$CI97,IF(AF$8=$CJ$9,$CJ97,IF(AF$8=$CK$9,$CK97,IF(AF$8=$CL$9,$CL97,IF(AF$8=$CM$9,$CM97,IF(AF$8=$CN$9,$CN97,IF(AF$8=$CO$9,$CO97,IF(AF$8=$CP$9,$CP97,IF(AF$8=$CQ$9,$CQ97,"НЕТ")))))))))))))))))))))))) -> ДА | AG97: =IF(AG$8=$BT$9,$BT97,IF(AG$8=$BS$9,$BS97,IF(AG$8=$BU$9,$BU97,IF(AG$8=$BV$9,$BV97,IF(AG$8=$BW$9,$BW97,IF(AG$8=$BX$9,$BX97,IF(AG$8=$BY$9,$BY97,IF(AG$8=$BZ$9,$BZ97,IF(AG$8=$CA$9,$CA97,IF(AG$8=$CC$9,$CC97,IF(AG$8=$CD$9,$CD97,IF(AG$8=$CE$9,$CE97,IF(AG$8=$CF$9,$CF97,IF(AG$8=$CG$9,$CG97,IF(AG$8=$CH$9,$CH97,IF(AG$8=$CI$9,$CI97,IF(AG$8=$CJ$9,$CJ97,IF(AG$8=$CK$9,$CK97,IF(AG$8=$CL$9,$CL97,IF(AG$8=$CM$9,$CM97,IF(AG$8=$CN$9,$CN97,IF(AG$8=$CO$9,$CO97,IF(AG$8=$CP$9,$CP97,IF(AG$8=$CQ$9,$CQ97,"НЕТ")))))))))))))))))))))))) -> НЕТ | AH97: =IF(AH$8=$BT$9,$BT97,IF(AH$8=$BS$9,$BS97,IF(AH$8=$BU$9,$BU97,IF(AH$8=$BV$9,$BV97,IF(AH$8=$BW$9,$BW97,IF(AH$8=$BX$9,$BX97,IF(AH$8=$BY$9,$BY97,IF(AH$8=$BZ$9,$BZ97,IF(AH$8=$CA$9,$CA97,IF(AH$8=$CC$9,$CC97,IF(AH$8=$CD$9,$CD97,IF(AH$8=$CE$9,$CE97,IF(AH$8=$CF$9,$CF97,IF(AH$8=$CG$9,$CG97,IF(AH$8=$CH$9,$CH97,IF(AH$8=$CI$9,$CI97,IF(AH$8=$CJ$9,$CJ97,IF(AH$8=$CK$9,$CK97,IF(AH$8=$CL$9,$CL97,IF(AH$8=$CM$9,$CM97,IF(AH$8=$CN$9,$CN97,IF(AH$8=$CO$9,$CO97,IF(AH$8=$CP$9,$CP97,IF(AH$8=$CQ$9,$CQ97,"НЕТ")))))))))))))))))))))))) -> НЕТ | AI97: =IF(AI$8=$BT$9,$BT97,IF(AI$8=$BS$9,$BS97,IF(AI$8=$BU$9,$BU97,IF(AI$8=$BV$9,$BV97,IF(AI$8=$BW$9,$BW97,IF(AI$8=$BX$9,$BX97,IF(AI$8=$BY$9,$BY97,IF(AI$8=$BZ$9,$BZ97,IF(AI$8=$CA$9,$CA97,IF(AI$8=$CC$9,$CC97,IF(AI$8=$CD$9,$CD97,IF(AI$8=$CE$9,$CE97,IF(AI$8=$CF$9,$CF97,IF(AI$8=$CG$9,$CG97,IF(AI$8=$CH$9,$CH97,IF(AI$8=$CI$9,$CI97,IF(AI$8=$CJ$9,$CJ97,IF(AI$8=$CK$9,$CK97,IF(AI$8=$CL$9,$CL97,IF(AI$8=$CM$9,$CM97,IF(AI$8=$CN$9,$CN97,IF(AI$8=$CO$9,$CO97,IF(AI$8=$CP$9,$CP97,IF(AI$8=$CQ$9,$CQ97,"НЕТ")))))))))))))))))))))))) -> НЕТ | AJ97: =IF(AJ$8=$BT$9,$BT97,IF(AJ$8=$BS$9,$BS97,IF(AJ$8=$BU$9,$BU97,IF(AJ$8=$BV$9,$BV97,IF(AJ$8=$BW$9,$BW97,IF(AJ$8=$BX$9,$BX97,IF(AJ$8=$BY$9,$BY97,IF(AJ$8=$BZ$9,$BZ97,IF(AJ$8=$CA$9,$CA97,IF(AJ$8=$CC$9,$CC97,IF(AJ$8=$CD$9,$CD97,IF(AJ$8=$CE$9,$CE97,IF(AJ$8=$CF$9,$CF97,IF(AJ$8=$CG$9,$CG97,IF(AJ$8=$CH$9,$CH97,IF(AJ$8=$CI$9,$CI97,IF(AJ$8=$CJ$9,$CJ97,IF(AJ$8=$CK$9,$CK97,IF(AJ$8=$CL$9,$CL97,IF(AJ$8=$CM$9,$CM97,IF(AJ$8=$CN$9,$CN97,IF(AJ$8=$CO$9,$CO97,IF(AJ$8=$CP$9,$CP97,IF(AJ$8=$CQ$9,$CQ97,"НЕТ")))))))))))))))))))))))) -> НЕТ | AK97: =IF(AK$8=$BT$9,$BT97,IF(AK$8=$BS$9,$BS97,IF(AK$8=$BU$9,$BU97,IF(AK$8=$BV$9,$BV97,IF(AK$8=$BW$9,$BW97,IF(AK$8=$BX$9,$BX97,IF(AK$8=$BY$9,$BY97,IF(AK$8=$BZ$9,$BZ97,IF(AK$8=$CA$9,$CA97,IF(AK$8=$CC$9,$CC97,IF(AK$8=$CD$9,$CD97,IF(AK$8=$CE$9,$CE97,IF(AK$8=$CF$9,$CF97,IF(AK$8=$CG$9,$CG97,IF(AK$8=$CH$9,$CH97,IF(AK$8=$CI$9,$CI97,IF(AK$8=$CJ$9,$CJ97,IF(AK$8=$CK$9,$CK97,IF(AK$8=$CL$9,$CL97,IF(AK$8=$CM$9,$CM97,IF(AK$8=$CN$9,$CN97,IF(AK$8=$CO$9,$CO97,IF(AK$8=$CP$9,$CP97,IF(AK$8=$CQ$9,$CQ97,"НЕТ")))))))))))))))))))))))) -> НЕТ | AL97: =IF(AL$8=$BT$9,$BT97,IF(AL$8=$BS$9,$BS97,IF(AL$8=$BU$9,$BU97,IF(AL$8=$BV$9,$BV97,IF(AL$8=$BW$9,$BW97,IF(AL$8=$BX$9,$BX97,IF(AL$8=$BY$9,$BY97,IF(AL$8=$BZ$9,$BZ97,IF(AL$8=$CA$9,$CA97,IF(AL$8=$CC$9,$CC97,IF(AL$8=$CD$9,$CD97,IF(AL$8=$CE$9,$CE97,IF(AL$8=$CF$9,$CF97,IF(AL$8=$CG$9,$CG97,IF(AL$8=$CH$9,$CH97,IF(AL$8=$CI$9,$CI97,IF(AL$8=$CJ$9,$CJ97,IF(AL$8=$CK$9,$CK97,IF(AL$8=$CL$9,$CL97,IF(AL$8=$CM$9,$CM97,IF(AL$8=$CN$9,$CN97,IF(AL$8=$CO$9,$CO97,IF(AL$8=$CP$9,$CP97,IF(AL$8=$CQ$9,$CQ97,"НЕТ")))))))))))))))))))))))) -> НЕТ | AM97: =IF(AL97="НЕТ","Не требуется",$CR97) -> Не требуется | AS97: =IF(BS97="ДА",$M97,"") | AT97: =IF(BT97="ДА",$M97,"") | AU97: =IF(BU97="ДА",$M97,"") | AV97: =IF(BV97="ДА",$M97,"") | AW97: =IF(BX97="ДА",$M97,"") -> 2 | AX97: =IF(BY97="ДА",$M97,"") -> 2 | AY97: =IF(BZ97="ДА",$M97,"") -> 2 | AZ97: =IF(CA97="ДА",$M97,"") -> 2 | BB97: =IF(CC97="ДА",$M97,"") | BC97: =IF(CD97="ДА",$M97,"") -> 2 | BD97: =IF(CE97="ДА",$M97,"") | BE97: =IF(CF97="ДА",$M97,"") -> 2 | BF97: =IF(CG97="ДА",$M97,"") | BG97: =IF(CH97="ДА",$M97,"") -> 2 | BH97: =IF(CI97="ДА",$M97,"") | BI97: =IF(CJ97="ДА",$M97,"") -> 2 | ... BP97: =IF(CQ97="ДА",$M97,"") | BS97: НЕТ | BT97: НЕТ | BU97: НЕТ | BV97: НЕТ | BW97: НЕТ | BX97: ДА | BY97: ДА | BZ97: ДА | CA97: ДА | CC97: НЕТ | CD97: ДА | CE97: НЕТ | CF97: ДА | CG97: НЕТ | CH97: ДА | CI97: НЕТ | CJ97: ДА | CK97: ДА | CL97: НЕТ | CM97: НЕТ | CN97: НЕТ | CO97: НЕТ | CP97: НЕТ | CQ97: НЕТ | CR97: Предоставляется Заказчиком
B98: Мониторинг KPI сотрудников по трудоемкости (% трудозатрат по количеству и стоимости (предварительного и окончательного уровней), трудозатраты план (предварительного и окончательного уровней), трудозатраты факт) | C98: Немного другое сутевое наполнение показателей KPI. Другие методические решения. Есть набор показателей, с которыми можно идти, как минимум, в пилот | N98: =SUM(O98,R98,U98,X98) -> 0
A99: 3.8. | B99: Нормирование трудозатрат | C99: Нет | F99: Экспертный | G99: КОРП-проект | H99: Под проект | I99: Под проект | J99: Под проект | K99: Под проект | L99: Под проект | M99: 10 | N99: =SUM(O99,R99,U99,X99) -> 0 | O99: =IF(AC99="ДА",$M99,"") | Q99: =IF(AC99="ДА",ROUNDUP(O99/5,0),0) -> 0 | R99: =IF(AF99="ДА",$M99,"") | T99: =IF(AF99="ДА",ROUNDUP(R99/5,0),0) -> 0 | U99: =IF(AI99="ДА",$M99,"") | W99: =IF(AI99="ДА",ROUNDUP(U99/5,0),0) -> 0 | X99: =IF(AL99="ДА",$M99,"") | Z99: =IF(AL99="ДА",ROUNDUP(X99/5,0),0) -> 0 | AA99: =IF(OR(AC99="ДА",AF99="ДА",AI99="ДА",AL99="ДА"),"ДА","НЕТ") -> НЕТ | AC99: =IF(AC$8=$BT$9,$BT99,IF(AC$8=$BS$9,$BS99,IF(AC$8=$BU$9,$BU99,IF(AC$8=$BV$9,$BV99,IF(AC$8=$BW$9,$BW99,IF(AC$8=$BX$9,$BX99,IF(AC$8=$BY$9,$BY99,IF(AC$8=$BZ$9,$BZ99,IF(AC$8=$CA$9,$CA99,IF(AC$8=$CC$9,$CC99,IF(AC$8=$CD$9,$CD99,IF(AC$8=$CE$9,$CE99,IF(AC$8=$CF$9,$CF99,IF(AC$8=$CG$9,$CG99,IF(AC$8=$CH$9,$CH99,IF(AC$8=$CI$9,$CI99,IF(AC$8=$CJ$9,$CJ99,IF(AC$8=$CK$9,$CK99,IF(AC$8=$CL$9,$CL99,IF(AC$8=$CM$9,$CM99,IF(AC$8=$CN$9,$CN99,IF(AC$8=$CO$9,$CO99,IF(AC$8=$CP$9,$CP99,IF(AC$8=$CQ$9,$CQ99,"НЕТ")))))))))))))))))))))))) -> НЕТ | AD99: =IF(AC99="НЕТ","Не требуется",$CR99) -> Не требуется | AF99: =IF(AF$8=$BT$9,$BT99,IF(AF$8=$BS$9,$BS99,IF(AF$8=$BU$9,$BU99,IF(AF$8=$BV$9,$BV99,IF(AF$8=$BW$9,$BW99,IF(AF$8=$BX$9,$BX99,IF(AF$8=$BY$9,$BY99,IF(AF$8=$BZ$9,$BZ99,IF(AF$8=$CA$9,$CA99,IF(AF$8=$CC$9,$CC99,IF(AF$8=$CD$9,$CD99,IF(AF$8=$CE$9,$CE99,IF(AF$8=$CF$9,$CF99,IF(AF$8=$CG$9,$CG99,IF(AF$8=$CH$9,$CH99,IF(AF$8=$CI$9,$CI99,IF(AF$8=$CJ$9,$CJ99,IF(AF$8=$CK$9,$CK99,IF(AF$8=$CL$9,$CL99,IF(AF$8=$CM$9,$CM99,IF(AF$8=$CN$9,$CN99,IF(AF$8=$CO$9,$CO99,IF(AF$8=$CP$9,$CP99,IF(AF$8=$CQ$9,$CQ99,"НЕТ")))))))))))))))))))))))) -> НЕТ | AG99: =IF(AG$8=$BT$9,$BT99,IF(AG$8=$BS$9,$BS99,IF(AG$8=$BU$9,$BU99,IF(AG$8=$BV$9,$BV99,IF(AG$8=$BW$9,$BW99,IF(AG$8=$BX$9,$BX99,IF(AG$8=$BY$9,$BY99,IF(AG$8=$BZ$9,$BZ99,IF(AG$8=$CA$9,$CA99,IF(AG$8=$CC$9,$CC99,IF(AG$8=$CD$9,$CD99,IF(AG$8=$CE$9,$CE99,IF(AG$8=$CF$9,$CF99,IF(AG$8=$CG$9,$CG99,IF(AG$8=$CH$9,$CH99,IF(AG$8=$CI$9,$CI99,IF(AG$8=$CJ$9,$CJ99,IF(AG$8=$CK$9,$CK99,IF(AG$8=$CL$9,$CL99,IF(AG$8=$CM$9,$CM99,IF(AG$8=$CN$9,$CN99,IF(AG$8=$CO$9,$CO99,IF(AG$8=$CP$9,$CP99,IF(AG$8=$CQ$9,$CQ99,"НЕТ")))))))))))))))))))))))) -> НЕТ | AH99: =IF(AH$8=$BT$9,$BT99,IF(AH$8=$BS$9,$BS99,IF(AH$8=$BU$9,$BU99,IF(AH$8=$BV$9,$BV99,IF(AH$8=$BW$9,$BW99,IF(AH$8=$BX$9,$BX99,IF(AH$8=$BY$9,$BY99,IF(AH$8=$BZ$9,$BZ99,IF(AH$8=$CA$9,$CA99,IF(AH$8=$CC$9,$CC99,IF(AH$8=$CD$9,$CD99,IF(AH$8=$CE$9,$CE99,IF(AH$8=$CF$9,$CF99,IF(AH$8=$CG$9,$CG99,IF(AH$8=$CH$9,$CH99,IF(AH$8=$CI$9,$CI99,IF(AH$8=$CJ$9,$CJ99,IF(AH$8=$CK$9,$CK99,IF(AH$8=$CL$9,$CL99,IF(AH$8=$CM$9,$CM99,IF(AH$8=$CN$9,$CN99,IF(AH$8=$CO$9,$CO99,IF(AH$8=$CP$9,$CP99,IF(AH$8=$CQ$9,$CQ99,"НЕТ")))))))))))))))))))))))) -> НЕТ | AI99: =IF(AI$8=$BT$9,$BT99,IF(AI$8=$BS$9,$BS99,IF(AI$8=$BU$9,$BU99,IF(AI$8=$BV$9,$BV99,IF(AI$8=$BW$9,$BW99,IF(AI$8=$BX$9,$BX99,IF(AI$8=$BY$9,$BY99,IF(AI$8=$BZ$9,$BZ99,IF(AI$8=$CA$9,$CA99,IF(AI$8=$CC$9,$CC99,IF(AI$8=$CD$9,$CD99,IF(AI$8=$CE$9,$CE99,IF(AI$8=$CF$9,$CF99,IF(AI$8=$CG$9,$CG99,IF(AI$8=$CH$9,$CH99,IF(AI$8=$CI$9,$CI99,IF(AI$8=$CJ$9,$CJ99,IF(AI$8=$CK$9,$CK99,IF(AI$8=$CL$9,$CL99,IF(AI$8=$CM$9,$CM99,IF(AI$8=$CN$9,$CN99,IF(AI$8=$CO$9,$CO99,IF(AI$8=$CP$9,$CP99,IF(AI$8=$CQ$9,$CQ99,"НЕТ")))))))))))))))))))))))) -> НЕТ | AJ99: =IF(AJ$8=$BT$9,$BT99,IF(AJ$8=$BS$9,$BS99,IF(AJ$8=$BU$9,$BU99,IF(AJ$8=$BV$9,$BV99,IF(AJ$8=$BW$9,$BW99,IF(AJ$8=$BX$9,$BX99,IF(AJ$8=$BY$9,$BY99,IF(AJ$8=$BZ$9,$BZ99,IF(AJ$8=$CA$9,$CA99,IF(AJ$8=$CC$9,$CC99,IF(AJ$8=$CD$9,$CD99,IF(AJ$8=$CE$9,$CE99,IF(AJ$8=$CF$9,$CF99,IF(AJ$8=$CG$9,$CG99,IF(AJ$8=$CH$9,$CH99,IF(AJ$8=$CI$9,$CI99,IF(AJ$8=$CJ$9,$CJ99,IF(AJ$8=$CK$9,$CK99,IF(AJ$8=$CL$9,$CL99,IF(AJ$8=$CM$9,$CM99,IF(AJ$8=$CN$9,$CN99,IF(AJ$8=$CO$9,$CO99,IF(AJ$8=$CP$9,$CP99,IF(AJ$8=$CQ$9,$CQ99,"НЕТ")))))))))))))))))))))))) -> НЕТ | AK99: =IF(AK$8=$BT$9,$BT99,IF(AK$8=$BS$9,$BS99,IF(AK$8=$BU$9,$BU99,IF(AK$8=$BV$9,$BV99,IF(AK$8=$BW$9,$BW99,IF(AK$8=$BX$9,$BX99,IF(AK$8=$BY$9,$BY99,IF(AK$8=$BZ$9,$BZ99,IF(AK$8=$CA$9,$CA99,IF(AK$8=$CC$9,$CC99,IF(AK$8=$CD$9,$CD99,IF(AK$8=$CE$9,$CE99,IF(AK$8=$CF$9,$CF99,IF(AK$8=$CG$9,$CG99,IF(AK$8=$CH$9,$CH99,IF(AK$8=$CI$9,$CI99,IF(AK$8=$CJ$9,$CJ99,IF(AK$8=$CK$9,$CK99,IF(AK$8=$CL$9,$CL99,IF(AK$8=$CM$9,$CM99,IF(AK$8=$CN$9,$CN99,IF(AK$8=$CO$9,$CO99,IF(AK$8=$CP$9,$CP99,IF(AK$8=$CQ$9,$CQ99,"НЕТ")))))))))))))))))))))))) -> НЕТ | AL99: =IF(AL$8=$BT$9,$BT99,IF(AL$8=$BS$9,$BS99,IF(AL$8=$BU$9,$BU99,IF(AL$8=$BV$9,$BV99,IF(AL$8=$BW$9,$BW99,IF(AL$8=$BX$9,$BX99,IF(AL$8=$BY$9,$BY99,IF(AL$8=$BZ$9,$BZ99,IF(AL$8=$CA$9,$CA99,IF(AL$8=$CC$9,$CC99,IF(AL$8=$CD$9,$CD99,IF(AL$8=$CE$9,$CE99,IF(AL$8=$CF$9,$CF99,IF(AL$8=$CG$9,$CG99,IF(AL$8=$CH$9,$CH99,IF(AL$8=$CI$9,$CI99,IF(AL$8=$CJ$9,$CJ99,IF(AL$8=$CK$9,$CK99,IF(AL$8=$CL$9,$CL99,IF(AL$8=$CM$9,$CM99,IF(AL$8=$CN$9,$CN99,IF(AL$8=$CO$9,$CO99,IF(AL$8=$CP$9,$CP99,IF(AL$8=$CQ$9,$CQ99,"НЕТ")))))))))))))))))))))))) -> НЕТ | AM99: =IF(AL99="НЕТ","Не требуется",$CR99) -> Не требуется | AS99: =IF(BS99="ДА",$M99,"") | AT99: =IF(BT99="ДА",$M99,"") | AU99: =IF(BU99="ДА",$M99,"") | AV99: =IF(BV99="ДА",$M99,"") | AW99: =IF(BX99="ДА",$M99,"") | AX99: =IF(BY99="ДА",$M99,"") | AY99: =IF(BZ99="ДА",$M99,"") | AZ99: =IF(CA99="ДА",$M99,"") | BB99: =IF(CC99="ДА",$M99,"") | BC99: =IF(CD99="ДА",$M99,"") | BD99: =IF(CE99="ДА",$M99,"") | BE99: =IF(CF99="ДА",$M99,"") | BF99: =IF(CG99="ДА",$M99,"") | BG99: =IF(CH99="ДА",$M99,"") | BH99: =IF(CI99="ДА",$M99,"") | BI99: =IF(CJ99="ДА",$M99,"") | ... BP99: =IF(CQ99="ДА",$M99,"") | BS99: НЕТ | BT99: НЕТ | BU99: НЕТ | BV99: НЕТ | BW99: НЕТ | BX99: НЕТ | BY99: НЕТ | BZ99: НЕТ | CA99: НЕТ | CC99: НЕТ | CD99: НЕТ | CE99: НЕТ | CF99: НЕТ | CG99: НЕТ | CH99: НЕТ | CI99: НЕТ | CJ99: НЕТ | CK99: ДА | CL99: НЕТ | CM99: НЕТ | CN99: НЕТ | CO99: НЕТ | CP99: НЕТ | CQ99: НЕТ | CR99: Предоставляется Заказчиком
A100: 4. | B100: Проектное бюджетирование | F100: ГРУППА | G100: ГРУППА | H100: ГРУППА | I100: ГРУППА | J100: ГРУППА | K100: ГРУППА | L100: ГРУППА | M100: =SUM(M101,M107,M115,M120,M130,M134,M137,M141,M144,M146) -> 26 | N100: =SUM(N101,N107,N115,N120,N130,N134,N137,N141,N144,N146) -> 27 | O100: =SUM(O101,O107,O115,O120,O130,O134,O137,O141,O144,O146) -> 0 | P100: =SUM(P101,P107,P115,P120,P130,P134,P137,P141,P144,P146) -> 0 | Q100: =SUM(Q101,Q107,Q115,Q120,Q130,Q134,Q137,Q141,Q144,Q146) -> 0 | R100: =SUM(R101,R107,R115,R120,R130,R134,R137,R141,R144,R146) -> 22 | S100: =SUM(S101,S107,S115,S120,S130,S134,S137,S141,S144,S146) -> 0 | T100: =SUM(T101,T107,T115,T120,T130,T134,T137,T141,T144,T146) -> 8 | ... Z100: =SUM(Z101,Z107,Z115,Z120,Z130,Z134,Z137,Z141,Z144,Z146) -> 0 | AA100: =IF(N100>0,"ДА","НЕТ") -> ДА | AC100: =IF(O100>0,"ДА","НЕТ") -> НЕТ | AF100: =IF(R100>0,"ДА","НЕТ") -> ДА | AI100: =IF(U100>0,"ДА","НЕТ") -> ДА | AL100: =IF(X100>0,"ДА","НЕТ") -> НЕТ | AS100: =SUM(AS101,AS107,AS115,AS120,AS130,AS141,AS144,AS146) -> 5 | AT100: =SUM(AT101,AT107,AT115,AT120,AT130,AT141,AT144,AT146) -> 2 | AU100: =SUM(AU101,AU107,AU115,AU120,AU130,AU141,AU144,AU146) -> 0 | AV100: =SUM(AV101,AV107,AV115,AV120,AV130,AV141,AV144,AV146) -> 5 | AW100: =SUM(AW101,AW107,AW115,AW120,AW130,AW141,AW144,AW146) -> 9 | AX100: =SUM(AX101,AX107,AX115,AX120,AX130,AX141,AX144,AX146) -> 12 | AY100: =SUM(AY101,AY107,AY115,AY120,AY130,AY141,AY144,AY146) -> 12 | AZ100: =SUM(AZ101,AZ107,AZ115,AZ120,AZ130,AZ141,AZ144,AZ146) -> 14 | BB100: =SUM(BB101,BB107,BB115,BB120,BB130,BB141,BB144,BB146) -> 9 | BC100: =SUM(BC101,BC107,BC115,BC120,BC130,BC141,BC144,BC146) -> 11 | BD100: =SUM(BD101,BD107,BD115,BD120,BD130,BD141,BD144,BD146) -> 12 | BE100: =SUM(BE101,BE107,BE115,BE120,BE130,BE141,BE144,BE146) -> 2 | BF100: =SUM(BF101,BF107,BF115,BF120,BF130,BF141,BF144,BF146) -> 0 | BG100: =SUM(BG101,BG107,BG115,BG120,BG130,BG141,BG144,BG146) -> 9 | BH100: =SUM(BH101,BH107,BH115,BH120,BH130,BH141,BH144,BH146) -> 5 | BI100: =SUM(BI101,BI107,BI115,BI120,BI130,BI141,BI144,BI146) -> 7 | ... BP100: =SUM(BP101,BP107,BP115,BP120,BP130,BP141,BP144,BP146) -> 0 | BS100: =IF(AS100>0,"ДА","НЕТ") -> ДА | BT100: =IF(AT100>0,"ДА","НЕТ") -> ДА | BU100: =IF(AU100>0,"ДА","НЕТ") -> НЕТ | BV100: =IF(AV100>0,"ДА","НЕТ") -> ДА | BW100: =IF(AS100>0,"ДА","НЕТ") -> ДА | BX100: =IF(AW100>0,"ДА","НЕТ") -> ДА | BY100: =IF(AX100>0,"ДА","НЕТ") -> ДА | BZ100: =IF(AY100>0,"ДА","НЕТ") -> ДА | CA100: =IF(AZ100>0,"ДА","НЕТ") -> ДА | CC100: =IF(BB100>0,"ДА","НЕТ") -> ДА | CD100: =IF(BC100>0,"ДА","НЕТ") -> ДА | CE100: =IF(BD100>0,"ДА","НЕТ") -> ДА | CF100: =IF(BE100>0,"ДА","НЕТ") -> ДА | CG100: =IF(BF100>0,"ДА","НЕТ") -> НЕТ | CH100: =IF(BG100>0,"ДА","НЕТ") -> ДА | CI100: =IF(BH100>0,"ДА","НЕТ") -> ДА | CJ100: =IF(BI100>0,"ДА","НЕТ") -> ДА | ... CQ100: =IF(BP100>0,"ДА","НЕТ") -> НЕТ
...

Sheet 3.ФС Девелопмент, Капстрой, EPC
A1: № | B1: Процессы/Блоки | C1: Программные комплексы | L1: Роли, для которых актуально (преимущественно) | V1: Отрасль, для которой актуально | X1: Могут использоваться данные ЦИМ | Y1: Заполняется
C2: 1С:PM ПРОФ | D2: 1С:PM КОРП | E2: 1С:Девеломпент ПРОФ (1С:PM+Риелтор) | F2: 1С:Девелопмент 3.0 (1С:PM+Смета) | G2: 1С:Девеломпент КОРП (1С:ERP+PM+Смета+Риелтор +Аренда и эксплуатация) | H2: 1С:Девелопмент 4.0 (1С:PM+Смета ТИМ КОРП) | I2: 1С:УСО+PM | J2: 1С:BIM 6D | K2: Дополнительные модули | L2: Инвестор/Девелопер | M2: Застройщик | N2: Техзаказчик | O2: Генподрядчик | P2: Генпроектировщик | Q2: Проектировщик | R2: Подрядчик | S2: Поставщик | T2: Риелтор | U2: Эксплуатация | V2: Гражданское строительство (девелопмент) | W2: Промышленное строительство | Y2: Требуется в Очередь 1 | Z2: Ответственный | AA2: Требуется в Очередь 2 | AB2: Ответственный | AC2: Требуется в Очередь 3 | AD2: Ответственный | AE2: Функциональный заказчик | AF2: Примечание
A3: 1 | B3: Финмодель, заявочная кампания, подбор площадок (инициация и оценка проектов/объектов) | C3: - | D3: + | E3: + | F3: + | G3: + | H3: + | I3: + | J3: + | K3: + | L3: + | M3: + | N3: - | O3: - | P3: - | Q3: - | R3: - | S3: - | T3: - | U3: - | V3: + | W3: + | X3: +
A4: 1 | B4: Управление заявками на проекты | C4: - | D4: + | E4: + | F4: + | G4: + | H4: + | I4: + | J4: +
A5: 2 | B5: Инвестиционная оценка проектов (финмодель) | C5: - | D5: + | E5: + | F5: + | G5: + | H5: + | I5: + | J5: + | K5: Математическое нормирование
A6: 3 | B6: Формирование инвестиционных программ | C6: - | D6: + | E6: + | F6: + | G6: + | H6: + | I6: + | J6: +
A7: 2 | B7: Управление портфелями и программами проектов/объектов | C7: +/- | D7: +/- | E7: +/- | F7: +/- | G7: +/- | H7: +/- | I7: +/- | J7: +/- | K7: + | L7: + | M7: + | N7: + | O7: + | P7: + | Q7: + | R7: + | S7: - | T7: - | U7: - | V7: + | W7: +
A8: 1 | B8: Управление структурами программ и портфелей | C8: - | D8: + | E8: + | F8: + | G8: + | H8: + | I8: + | J8: +
A9: 2 | B9: Оценка проекта и расчет цены (если строим под заказ) | C9: - | D9: + | E9: + | F9: + | G9: + | H9: + | I9: + | J9: +
A10: 3 | B10: Сводный статус по продажам проектов (если строим под заказ) | C10: - | D10: + | E10: + | F10: + | G10: + | H10: + | I10: + | J10: +
A11: 4 | B11: Многоуровневые проекты | C11: - | D11: + | E11: + | F11: + | G11: + | H11: + | I11: + | J11: +
A12: 5 | B12: KPI портфелей, программ и темплана | C12: +/- | D12: + | E12: + | F12: + | G12: + | H12: + | I12: + | J12: +
A13: 6 | B13: Панель руководителя | C13: + | D13: + | E13: + | F13: + | G13: + | H13: + | I13: + | J13: +
A14: 7 | B14: Управление пространственными данными по объектам | C14: - | D14: - | E14: - | F14: - | G14: - | H14: - | I14: - | J14: + | K14: 1С:GIS
A15: 3 | B15: Календрано-сетевое планирование и жизненный цикл проекта | C15: +/- | D15: + | E15: + | F15: + | G15: + | H15: + | I15: + | J15: + | L15: + | M15: + | N15: + | O15: + | P15: + | Q15: + | R15: + | S15: +/- | T15: - | U15: - | V15: + | W15: + | X15: +
A16: 1 | B16: Формирование списка проектов, рабочее место руководителя проектов | C16: + | D16: + | E16: + | F16: + | G16: + | H16: + | I16: + | J16: +
A17: 2 | B17: Планирование содержания и сроков проекта, диаграмма Ганта | C17: + | D17: + | E17: + | F17: + | G17: + | H17: + | I17: + | J17: +
A18: 3 | B18: Фазы и контрольные точки проекта | C18: - | D18: + | E18: + | F18: + | G18: + | H18: + | I18: + | J18: +
A19: 4 | B19: Прогнозные сроки | C19: - | D19: + | E19: + | F19: + | G19: + | H19: + | I19: + | J19: +
A20: 5 | B20: Версионирование проекта | C20: + | D20: + | E20: + | F20: + | G20: + | H20: + | I20: + | J20: +
A21: 6 | B21: Сквозное версионирование проектов | C21: + | D21: + | E21: + | F21: + | G21: + | H21: + | I21: + | J21: +
A22: 7 | B22: Актуализация проекта | C22: + | D22: + | E22: + | F22: + | G22: + | H22: + | I22: + | J22: +
A23: 8 | B23: Анализ проектов с группировкой по портфелям и программам | C23: + | D23: + | E23: + | F23: + | G23: + | H23: + | I23: + | J23: +
A24: 4 | B24: Проектное бюджетирование | C24: +/- | D24: + | E24: + | F24: + | G24: + | H24: + | I24: + | J24: + | L24: + | M24: + | N24: + | O24: + | P24: + | Q24: + | R24: + | S24: +/- | T24: - | U24: - | V24: + | W24: + | X24: +
A25: 1 | B25: Бюджеты проектов | C25: + | D25: + | E25: + | F25: + | G25: + | H25: + | I25: + | J25: +
A26: 2 | B26: Управление проектными договорами | C26: - | D26: + | E26: + | F26: + | G26: + | H26: + | I26: + | J26: +
A27: 3 | B27: Регистрация фактических данных и событий проекта | C27: + | D27: + | E27: + | F27: + | G27: + | H27: + | I27: + | J27: +
A28: 4 | B28: Отражение первичных документов в проектном бюджетировании | C28: - | D28: + | E28: + | F28: + | G28: + | H28: + | I28: + | J28: +
A29: 5 | B29: План-фактный анализ проекта | C29: + | D29: + | E29: + | F29: + | G29: + | H29: + | I29: + | J29: +
A30: 6 | B30: KPI проектов по экономике | C30: +/- | D30: + | E30: + | F30: + | G30: + | H30: + | I30: + | J30: +
A31: 5 | B31: Управление ПИР и другими трудоемкими работами + проектный документооборот и MDR | C31: +/- | D31: + | E31: + | F31: + | G31: + | H31: + | I31: + | J31: + | L31: - | M31: - | N31: +/- | O31: +/- | P31: + | Q31: + | R31: + | S31: - | T31: - | U31: - | V31: + | W31: +
A32: 1 | B32: Проектная продукция (реестр проектных документов, MDR) | C32: - | D32: + | E32: + | F32: + | G32: + | H32: + | I32: + | J32: +
A33: 2 | B33: Планирование персонала и трудозатрат проекта | C33: + | D33: + | E33: + | F33: + | G33: + | H33: + | I33: + | J33: +
A34: 3 | B34: Управление ресурсами проектной команды | C34: + | D34: + | E34: + | F34: + | G34: + | H34: + | I34: + | J34: +
A35: 4 | B35: Управление загрузкой и рабочим временем по проектам | C35: + | D35: + | E35: + | F35: + | G35: + | H35: + | I35: + | J35: +
A36: 5 | B36: Согласование трудозатрат | C36: - | D36: + | E36: + | F36: + | G36: + | H36: + | I36: + | J36: +
A37: 6 | B37: KPI проектов по трудоемкости | C37: +/- | D37: + | E37: + | F37: + | G37: + | H37: + | I37: + | J37: +
A38: 6 | B38: Работа архитектора, конструктора, инженера с моделью 3D | C38: +/- | D38: + | E38: + | F38: + | G38: + | H38: + | I38: + | J38: + | L38: - | M38: - | N38: - | O38: - | P38: + | Q38: + | R38: - | S38: - | T38: - | U38: - | V38: + | W38: + | X38: +
A39: 1 | B39: Открытие проекта в формате RNP | C39: - | D39: - | E39: - | F39: - | G39: - | H39: - | I39: - | J39: +
A40: 2 | B40: Работа с шаблоном проекта в формате RNT | C40: - | D40: - | E40: - | F40: - | G40: - | H40: - | I40: - | J40: +
A41: 3 | B41: Инструменты Renga для моделирования здания | C41: - | D41: - | E41: - | F41: - | G41: - | H41: - | I41: - | J41: +
A42: 4 | B42: Вставка из DWG/DXF и PDF | C42: - | D42: - | E42: - | F42: - | G42: - | H42: - | I42: - | J42: +
A43: 5 | B43: Вставка из 3D-форматов 3DS, LightWave 3D, STL, OBJ, COLLADA, FBX | C43: - | D43: - | E43: - | F43: - | G43: - | H43: - | I43: - | J43: +
A44: 6 | B44: Вставка из 3D-формата C3D | C44: - | D44: - | E44: - | F44: - | G44: - | H44: - | I44: - | J44: +
A45: 7 | B45: Инструменты Renga для оформления документации | C45: - | D45: - | E45: - | F45: - | G45: - | H45: - | I45: - | J45: +
A46: 8 | B46: Вставка форм в формате RTB | C46: - | D46: - | E46: - | F46: - | G46: - | H46: - | I46: - | J46: +
A47: 9 | B47: Экспорт в формат CSV | C47: - | D47: - | E47: - | F47: - | G47: - | H47: - | I47: - | J47: +
A48: 10 | B48: Экспорт в формат RTB | C48: - | D48: - | E48: - | F48: - | G48: - | H48: - | I48: - | J48: +
A49: 11 | B49: Экспорт в форматы DWG, DXF, PDF и OXPS | C49: - | D49: - | E49: - | F49: - | G49: - | H49: - | I49: - | J49: +
A50: 12 | B50: Экспорт в 3D-форматы OBJ, COLLADA, STL, C3D | C50: - | D50: - | E50: - | F50: - | G50: - | H50: - | I50: - | J50: +
... A56: 18 | B56: Совместная работа в режиме реального времени | C56: - | D56: - | E56: - | F56: - | G56: - | H56: - | I56: - | J56: +
A57: 7 | B57: Осмечивание и формирование объемов работ | C57: +/- | D57: +/- | E57: +/- | F57: +/- | G57: +/- | H57: + | I57: + | J57: + | L57: - | M57: +/- | N57: +/- | O57: + | P57: + | Q57: + | R57: +/- | S57: - | T57: - | U57: - | V57: + | W57: + | X57: +
A58: 1 | B58: Создание и ведение собственных классификаторов видов работ, материалов и элементов для последующего их сопоставления со значениями параметров в элементах модели и наполнения ведомости объемов работ | C58: - | D58: - | E58: - | F58: - | G58: - | H58: + | I58: - | J58: -
A59: 2 | B59: Параметризация и нормализация свойств элементов моделей | C59: - | D59: - | E59: - | F59: - | G59: - | H59: + | I59: - | J59: -
A60: 3 | B60: Анализ изменений по загруженным информационным версиям модели и сравнение загруженных версий с помощью отчетов | C60: - | D60: - | E60: - | F60: - | G60: - | H60: + | I60: - | J60: -
A61: 4 | B61: формирование ведомостей объема работ по назначенным видам работ на элементы информационных моделей, назначение расценок из данных ведомости объема работ | C61: - | D61: - | E61: - | F61: - | G61: - | H61: + | I61: - | J61: -
A62: 5 | B62: Автоматическое формирование локальной сметы по назначенным расценкам | C62: - | D62: - | E62: - | F62: + | G62: + | H62: + | I62: + | J62: +
A63: 6 | B63: Проверка качества информационных моделей по заданным правилам | C63: - | D63: - | E63: - | F63: - | G63: - | H63: + | I63: - | J63: -
A64: 7 | B64: Осмечивание сложных сборных конструкций (сборок) | C64: - | D64: - | E64: - | F64: + | G64: + | H64: + | I64: + | J64: +
A65: 8 | B65: Формирование связанной с информационной моделью структуры сметной документации | C65: - | D65: - | E65: - | F65: + | G65: + | H65: + | I65: + | J65: +
A66: 9 | B66: Подготовка комплекта проектно‑сметной документации в соответствии с действующими нормативными требованиями: локальные, объектные, сводные сметы; | C66: - | D66: - | E66: - | F66: + | G66: + | H66: + | I66: + | J66: +
A67: 10 | B67: Определение стоимости строительства базисным методом с использованием сметно‑нормативных баз в уровне цен на 01.01.2000; | C67: - | D67: - | E67: - | F67: + | G67: + | H67: + | I67: + | J67: +
A68: 11 | B68: Коммерческие методики, возможность расчета смет в собственных (не государственных) расценках в текущем уровне цен | C68: - | D68: - | E68: - | F68: + | G68: + | H68: + | I68: + | J68: +
A69: 12 | B69: Определение стоимости строительства ресурсным методом, учитывающим реальные условия производства и современную номенклатуру строительных ресурсов (текущие цены, замена ресурсов со сметных на современные); | C69: - | D69: - | E69: - | F69: + | G69: + | H69: + | I69: + | J69: +
... A88: 31 | B88: Экспертиза сметной документации по выбранным параметрам с выводом подробного отчета; | C88: - | D88: - | E88: - | F88: + | G88: + | H88: + | I88: + | J88: +
A89: 32 | B89: АРМ для мэппинга сметы и элементов календарно-сетевого графика проекта | C89: - | D89: - | E89: - | F89: - | G89: - | H89: - | I89: - | J89: - | K89: Мэппинг КСП и Сметы
A90: 8 | B90: Управление СМР | C90: +/- | D90: +/- | E90: +/- | F90: +/- | G90: +/- | H90: + | I90: + | J90: + | L90: - | M90: +/- | N90: + | O90: + | P90: - | Q90: - | R90: + | S90: - | T90: - | U90: - | V90: + | W90: + | X90: +
A91: 1 | B91: Планирование объемов и поставок проекта | C91: + | D91: + | E91: + | F91: + | G91: + | H91: + | I91: + | J91: +
A92: 2 | B92: Управление этапом СМР на уровне Девелопера, Заказчика, Инвестора | C92: + | D92: + | E92: + | F92: + | G92: + | H92: + | I92: + | J92: +
A93: 3 | B93: Ведение учета выполненных работ и фактически использованных ресурсов (формы КС‑6, КС‑3, М‑29); | C93: - | D93: - | E93: - | F93: - | G93: + | H93: + | I93: + | J93: +
A94: 4 | B94: Учет выполненных работ в разрезе объектов строительства и локальных смет; | C94: - | D94: - | E94: - | F94: + | G94: + | H94: + | I94: + | J94: +
A95: 5 | B95: Ввод актов по остаткам; | C95: - | D95: - | E95: - | F95: + | G95: + | H95: + | I95: + | J95: +
A96: 6 | B96: Формирование недельно-суточных графиков работ за любой период времени | C96: - | D96: - | E96: - | F96: - | G96: - | H96: + | I96: + | J96: +
A97: 7 | B97: Стройконтроль | C97: - | D97: - | E97: - | F97: - | G97: - | H97: + | I97: + | J97: +
A98: 8 | B98: Управление основными средствами | C98: - | D98: - | E98: - | F98: - | G98: + | H98: + | I98: + | J98: +
A99: 9 | B99: Бухгалтерский учет с учетом строительной специфики | C99: - | D99: - | E99: - | F99: - | G99: - | H99: + | I99: + | J99: +
A100: 9 | B100: Исполнительная документация | C100: +/- | D100: + | E100: + | F100: + | G100: + | H100: + | I100: + | J100: + | L100: - | M100: + | N100: + | O100: + | P100: +/- | Q100: +/- | R100: + | S100: - | T100: - | U100: - | V100: + | W100: +
A101: 1 | B101: Централизованное хранение ИД | C101: - | D101: - | E101: - | F101: - | G101: - | H101: - | I101: - | J101: +
A102: 2 | B102: Согласование ИД с участниками проекта | C102: - | D102: - | E102: - | F102: - | G102: - | H102: - | I102: - | J102: +
A103: 3 | B103: Контроль задач исполнителей и закрытие выполненных объемов исполнительной документации | C103: + | D103: + | E103: + | F103: + | G103: + | H103: + | I103: + | J103: +
A104: 4 | B104: Сдача ИД заказчику онлайн | C104: - | D104: - | E104: - | F104: - | G104: - | H104: - | I104: - | J104: +
A105: 5 | B105: Контроль качества и устранения замечаний | C105: - | D105: - | E105: - | F105: - | G105: - | H105: - | I105: - | J105: +
