Workbook

Sheet МоделиУпр
C2: Тип производства/Виды деятельности
C3: Трудоемкое | R3: Трудоемкое+сборка | AB3: Материалоемкое | AC3: Фондо/ Финансовоемкое
B4: Сегменты | C4: НИПИ | H4: ИТ/консалтинг | M4: Проектный офис (Коммуникации и трекинг) | R4: Инжиниринг | W4: Медиа | AB4: Машиностроение/ проектное производство | AC4: Проектные инвестиции | AD4: Капстрой | AE4: Девелопмент
B5: Соло | C5: Ведение проекта для РП. | R5: Ведение проекта для РП (М) | AB5: Х | AC5: Х | AD5: Х | AG5: Шаги проработки
C6: =CONCATENATE("РП ",Соло!C3,"%") -> РП 27% | R6: =CONCATENATE("РП ",'Соло-М'!C3,"%") -> РП 19% | AH6: 1
B7: МикроГД | C7: Проектное управление для компании. Специалисты подчиняются ГД. | R7: Проектное управление для компании. Специалисты подчиняются ГД. (М) | AB7: Х | AC7: Х | AD7: Х | AH7: 2
C8: =CONCATENATE("ГД ",МикроГД!C3,"%") -> ГД 43% | E8: =CONCATENATE("РП ",МикроРП!C3,"%") -> РП 30% | H8: =CONCATENATE("ГД ",МикроГД!C3,"%") -> ГД 43% | J8: =CONCATENATE("РП ",МикроРП!C3,"%") -> РП 30% | M8: =CONCATENATE("ГД ",МикроГД!C3,"%") -> ГД 43% | O8: =CONCATENATE("РП ",МикроРП!C3,"%") -> РП 30% | R8: =CONCATENATE("ГД ",'МикроГД-М'!C3,"%") -> ГД 38% | T8: =CONCATENATE("РП ",'МикроРП-М'!C3,"%") -> РП 37% | W8: =CONCATENATE("ГД ",'МикроГД-М'!C3,"%") -> ГД 38% | Y8: =CONCATENATE("РП ",'МикроРП-М'!C3,"%") -> РП 37% | AH8: 3
B9: МикроРСП | C9: Проектное управление для подразделения. Специалисты подчиняются РСП. | R9: Проектное управление для подразделения. Специалисты подчиняются РСП. (М) | AB9: Х | AC9: Х | AD9: Х | AH9: 4
C10: =CONCATENATE("РСП ",МикроРСП!C3,"%") -> РСП 32% | E10: =CONCATENATE("РП ",МикроРП!C3,"%") -> РП 30% | H10: =CONCATENATE("РСП ",МикроРСП!C3,"%") -> РСП 32% | J10: =CONCATENATE("РП ",МикроРП!C3,"%") -> РП 30% | M10: =CONCATENATE("РСП ",МикроРСП!C3,"%") -> РСП 32% | O10: =CONCATENATE("РП ",МикроРП!C3,"%") -> РП 30% | R10: =CONCATENATE("РСП ",'МикроРСП-М'!C3,"%") -> РСП 35% | T10: =CONCATENATE("РП ",'МикроРП-М'!C3,"%") -> РП 37% | W10: =CONCATENATE("РСП ",'МикроРСП-М'!C3,"%") -> РСП 35% | Y10: =CONCATENATE("РП ",'МикроРП-М'!C3,"%") -> РП 37% | AH10: 5
B11: Малый1 | C11: Нескольких проектных направлений. Проекты в рамках направлений. | R11: Нескольких проектных направлений. Проекты в рамках направлений. (М) | AB11: Х | AC11: Х | AD11: Х
C12: =CONCATENATE("ГД ",'Мал1-2ГД'!C3,"%") -> ГД 46% | D12: =CONCATENATE("ФД ",'Мал1-2ФД'!C3,"%") -> ФД 58% | E12: =CONCATENATE("РП ",'Мал1-2РП'!C3,"%") -> РП 30% | G12: =CONCATENATE("РН ",Мал1РН!C3,"%") -> РН 37% | H12: =CONCATENATE("ГД ",'Мал1-2ГД'!C3,"%") -> ГД 46% | I12: =CONCATENATE("ФД ",'Мал1-2ФД'!C3,"%") -> ФД 58% | K12: =CONCATENATE("РП ",'Мал1-2РП'!C3,"%") -> РП 30% | L12: =CONCATENATE("РН ",Мал1РН!C3,"%") -> РН 37% | M12: =CONCATENATE("ГД ",'Мал1-2ГД'!C3,"%") -> ГД 46% | N12: =CONCATENATE("ФД ",'Мал1-2ФД'!C3,"%") -> ФД 58% | O12: =CONCATENATE("РП ",'Мал1-2РП'!C3,"%") -> РП 30% | Q12: =CONCATENATE("РН ",Мал1РН!C3,"%") -> РН 37% | R12: =CONCATENATE("ГД ",'Мал1-2ГД'!C3,"%") -> ГД 46% | S12: =CONCATENATE("ФД ",'Мал1-2ФД'!C3,"%") -> ФД 58% | T12: =CONCATENATE("РП ",'Мал1-2РП-М'!C3,"%") -> РП 37% | V12: =CONCATENATE("РН ",'Мал1РН-М'!C3,"%") -> РН 36% | W12: =CONCATENATE("ГД ",'Мал1-2ГД'!C3,"%") -> ГД 46% | X12: =CONCATENATE("ФД ",'Мал1-2ФД'!C3,"%") -> ФД 58% | Z12: =CONCATENATE("РП ",'Мал1-2РП-М'!C3,"%") -> РП 37% | AA12: =CONCATENATE("РН ",'Мал1РН-М'!C3,"%") -> РН 36%
B13: Малый2.1. | C13: Проектное управление для организации со слабоматричной структурой. Сквозные проекты. | R13: Слабоматричная структура. Сквозные проекты. (М) | AB13: Х | AC13: Х | AD13: Х
C14: =CONCATENATE("ГД ",'Мал1-2ГД'!C3,"%") -> ГД 46% | D14: =CONCATENATE("ФД ",'Мал1-2ФД'!C3,"%") -> ФД 58% | E14: =CONCATENATE("РП ",'Мал1-2РП'!C3,"%") -> РП 30% | G14: =CONCATENATE("ППО ",Мал2ППО!C3,"%") -> ППО 30% | H14: =CONCATENATE("ГД ",'Мал1-2ГД'!C3,"%") -> ГД 46% | I14: =CONCATENATE("ФД ",'Мал1-2ФД'!C3,"%") -> ФД 58% | K14: =CONCATENATE("РП ",'Мал1-2РП'!C3,"%") -> РП 30% | L14: =CONCATENATE("ППО ",Мал2ППО!C3,"%") -> ППО 30% | M14: =CONCATENATE("ГД ",'Мал1-2ГД'!C3,"%") -> ГД 46% | N14: =CONCATENATE("ФД ",'Мал1-2ФД'!C3,"%") -> ФД 58% | O14: =CONCATENATE("РП ",'Мал1-2РП'!C3,"%") -> РП 30% | Q14: =CONCATENATE("ППО ",Мал2ППО!C3,"%") -> ППО 30% | R14: =CONCATENATE("ГД ",'Мал1-2ГД'!C3,"%") -> ГД 46% | S14: =CONCATENATE("ФД ",'Мал1-2ФД'!C3,"%") -> ФД 58% | T14: =CONCATENATE("РП ",'Мал1-2РП-М'!C3,"%") -> РП 37% | V14: =CONCATENATE("ППО ",'Мал2ППО-М'!C3,"%") -> ППО 30% | W14: =CONCATENATE("ГД ",'Мал1-2ГД'!C3,"%") -> ГД 46% | X14: =CONCATENATE("ФД ",'Мал1-2ФД'!C3,"%") -> ФД 58% | Z14: =CONCATENATE("РП ",'Мал1-2РП-М'!C3,"%") -> РП 37% | AA14: =CONCATENATE("ППО ",'Мал2ППО-М'!C3,"%") -> ППО 30%
B15: Малый2.2. | C15: Проектное управление для организации с сильноматричной структурой. Сквозные проекты. | R15: Сильноматрична структура. Сквозные проекты.(М) | AB15: Х | AC15: Х | AD15: Х
C16: =CONCATENATE("ГД ",'Мал1-2ГД'!C3,"%") -> ГД 46% | D16: =CONCATENATE("ФД ",'Мал1-2ФД'!C3,"%") -> ФД 58% | E16: =CONCATENATE("РП ",'Мал1-2РП'!C3,"%") -> РП 30% | G16: =CONCATENATE("ППО ",Мал2ППО!C3,"%") -> ППО 30% | H16: =CONCATENATE("ГД ",'Мал1-2ГД'!C3,"%") -> ГД 46% | I16: =CONCATENATE("ФД ",'Мал1-2ФД'!C3,"%") -> ФД 58% | K16: =CONCATENATE("РП ",'Мал1-2РП'!C3,"%") -> РП 30% | L16: =CONCATENATE("ППО ",Мал2ППО!C3,"%") -> ППО 30% | M16: =CONCATENATE("ГД ",'Мал1-2ГД'!C3,"%") -> ГД 46% | N16: =CONCATENATE("ФД ",'Мал1-2ФД'!C3,"%") -> ФД 58% | O16: =CONCATENATE("РП ",'Мал1-2РП'!C3,"%") -> РП 30% | Q16: =CONCATENATE("ППО ",Мал2ППО!C3,"%") -> ППО 30% | R16: =CONCATENATE("ГД ",'Мал1-2ГД'!C3,"%") -> ГД 46% | S16: =CONCATENATE("ФД ",'Мал1-2ФД'!C3,"%") -> ФД 58% | T16: =CONCATENATE("РП ",'Мал1-2РП-М'!C3,"%") -> РП 37% | V16: =CONCATENATE("ППО ",'Мал2ППО-М'!C3,"%") -> ППО 30% | W16: =CONCATENATE("ГД ",'Мал1-2ГД'!C3,"%") -> ГД 46% | X16: =CONCATENATE("ФД ",'Мал1-2ФД'!C3,"%") -> ФД 58% | Z16: =CONCATENATE("РП ",'Мал1-2РП-М'!C3,"%") -> РП 37% | AA16: =CONCATENATE("ППО ",'Мал2ППО-М'!C3,"%") -> ППО 30%
B17: Средний1 | C17: Средний1.ПЭО+ПДО. Заказчик - ФД | H17: Х | M17: Х | R17: Х | W17: Х
C18: =CONCATENATE("ФД ",Ср1ФД!C3,"%") -> ФД 55% | E18: =CONCATENATE("ПДО ",Ср1ПДО!C3,"%") -> ПДО 38%
B19: Средний2 | C19: Средний2.НИПИ без РП. Дир. по произв-ву и ФД | H19: Х | M19: Х | R19: Средний2.НИПИ без РП. Дир. по произв-ву и ФД (М)
C20: =CONCATENATE("ГД ",'Ср2-5ГД'!C3,"%") -> ГД 50% | D20: =CONCATENATE("ДП ",Ср2ДП!C3,"%") -> ДП 33% | E20: =CONCATENATE("ППО ",Ср2ППО!C3,"%") -> ППО 38% | G20: =CONCATENATE("ФД ",'Ср2-5ФД'!C3,"%") -> ФД 55% | R20: =CONCATENATE("ГД ",'Ср2-5ГД'!C3,"%") -> ГД 50% | S20: =CONCATENATE("ДП ",'Ср2ДП-М'!C3,"%") -> ДП 21% | T20: =CONCATENATE("ППО ",Ср2ППО!C3,"%") -> ППО 38% | V20: =CONCATENATE("ФД ",'Ср2-5ФД'!C3,"%") -> ФД 55% | W20: =CONCATENATE("ГД ",'Ср2-5ГД'!C3,"%") -> ГД 50% | X20: =CONCATENATE("ДП ",'Ср2ДП-М'!C3,"%") -> ДП 21% | Y20: =CONCATENATE("ППО ",Ср2ППО!C3,"%") -> ППО 38% | AA20: =CONCATENATE("ФД ",'Ср2-5ФД'!C3,"%") -> ФД 55%
B21: Средний3-5 | C21: Средний3.НИПИ | H21: Средний5.ИТ. Буккирование. Контрактация. Произв. отделы участвуют в управлении. | R21: Средний4.Инжиниринг
C22: =CONCATENATE("ГД ",'Ср2-5ГД'!C3,"%") -> ГД 50% | D22: =CONCATENATE("ДП ",Ср3ДП!C3,"%") -> ДП 28% | E22: =CONCATENATE("ППО ", Ср3ППО!C3,"%") -> ППО 18% | F22: =CONCATENATE("РП ",Ср3РП!C3,"%") -> РП 28% | G22: =CONCATENATE("ФД ",'Ср2-5ФД'!C3,"%") -> ФД 55% | H22: =CONCATENATE("ГД ",'Ср2-5ГД'!C3,"%") -> ГД 50% | I22: =CONCATENATE("РПО ",Ср5РПО!C3,"%") -> РПО 29% | J22: =CONCATENATE("ПрОф ",Ср5ПрОф!C3,"%") -> ПрОф 24% | K22: =CONCATENATE("РП ",Ср5РП!C3,"%") -> РП 31% | L22: =CONCATENATE("ФД ",'Ср2-5ФД'!C3,"%") -> ФД 55% | M22: =CONCATENATE("ГД ",'Ср2-5ГД'!C3,"%") -> ГД 50% | N22: =CONCATENATE("РПО ",Ср5РПО!C3,"%") -> РПО 29% | O22: =CONCATENATE("ПрОф ",Ср5ПрОф!C3,"%") -> ПрОф 24% | P22: =CONCATENATE("РП ",Ср5РП!C3,"%") -> РП 31% | Q22: =CONCATENATE("ФД ",'Ср2-5ФД'!C3,"%") -> ФД 55% | R22: =CONCATENATE("ГД ",'Ср2-5ГД'!C3,"%") -> ГД 50% | S22: =CONCATENATE("ДПм ",'Ср4ДПм-М'!C3,"%") -> ДПм 22% | T22: =CONCATENATE("РПО ",'Ср4РПО-М'!C3,"%") -> РПО 20% | U22: =CONCATENATE("РП ",'Ср4РП-М'!C3,"%") -> РП 31% | V22: =CONCATENATE("ФД ",'Ср2-5ФД'!C3,"%") -> ФД 55% | W22: =CONCATENATE("ГД ",'Ср2-5ГД'!C3,"%") -> ГД 50% | X22: =CONCATENATE("ДПм ",'Ср4ДПм-М'!C3,"%") -> ДПм 22% | Y22: =CONCATENATE("РПО ",'Ср4РПО-М'!C3,"%") -> РПО 20% | Z22: =CONCATENATE("РП ",'Ср4РП-М'!C3,"%") -> РП 31% | AA22: =CONCATENATE("ФД ",'Ср2-5ФД'!C3,"%") -> ФД 55%
B23: Крупный1 | C23: Институт в Институте. Проекты в рамках направлений. | R23: Институт в Институте. Проекты в рамках направлений.
C24: =CONCATENATE("1ЗГД ",Кр11ЗГД!C3,"%") -> 1ЗГД 20% | D24: =CONCATENATE("ППО ",Кр1ППО!C3,"%") -> ППО 44% | E24: =CONCATENATE("РЦ ",Кр1РЦ!C3,"%") -> РЦ 18% | F24: =CONCATENATE("ПДО ",Кр1ПДО!C3,"%") -> ПДО 23% | G24: =CONCATENATE("РП ",Кр1РП!C3,"%") -> РП 31% | H24: =CONCATENATE("1ЗГД ",Кр11ЗГД!C3,"%") -> 1ЗГД 20% | I24: =CONCATENATE("ППО ",Кр1ППО!C3,"%") -> ППО 44% | J24: =CONCATENATE("РЦ ",Кр1РЦ!C3,"%") -> РЦ 18% | K24: =CONCATENATE("ПДО ",Кр1ПДО!C3,"%") -> ПДО 23% | L24: =CONCATENATE("РП ",Кр1РП!C3,"%") -> РП 31% | M24: =CONCATENATE("1ЗГД ",Кр11ЗГД!C3,"%") -> 1ЗГД 20% | N24: =CONCATENATE("ППО ",Кр1ППО!C3,"%") -> ППО 44% | O24: =CONCATENATE("РЦ ",Кр1РЦ!C3,"%") -> РЦ 18% | P24: =CONCATENATE("ПДО ",Кр1ПДО!C3,"%") -> ПДО 23% | Q24: =CONCATENATE("РП ",Кр1РП!C3,"%") -> РП 31% | R24: =CONCATENATE("1ЗГД ",Кр11ЗГД!C3,"%") -> 1ЗГД 20% | S24: =CONCATENATE("ППО ",'Кр1ППО-М'!C3,"%") -> ППО 47% | T24: =CONCATENATE("РЦ ",'Кр1РЦ-М'!C3,"%") -> РЦ 18% | U24: =CONCATENATE("ПДО ",'Кр1ПДО-М'!C3,"%") -> ПДО 23% | V24: =CONCATENATE("РП ",'Кр1РП-М'!C3,"%") -> РП 32% | W24: =CONCATENATE("1ЗГД ",Кр11ЗГД!C3,"%") -> 1ЗГД 20% | X24: =CONCATENATE("ППО ",'Кр1ППО-М'!C3,"%") -> ППО 47% | Y24: =CONCATENATE("РЦ ",'Кр1РЦ-М'!C3,"%") -> РЦ 18% | Z24: =CONCATENATE("ПДО ",'Кр1ПДО-М'!C3,"%") -> ПДО 23% | AA24: =CONCATENATE("РП ",'Кр1РП-М'!C3,"%") -> РП 32%
B25: Крупный2 | C25: Х | H25: Х | M25: Х | R25: Х | AB25: Сквозные проекты. Два уровня диспетчеров.
AB26: =CONCATENATE("ДП ",Кр2МшДПр!C3,"%") -> ДП 25%
B27: Холдинг1.1. | C27: ППО и ДЗО в одной базе | R27: ППО и ДЗО в одной базе
C28: =CONCATENATE("ППО ",Х1_ППО!C3,"%") -> ППО 33% | R28: =CONCATENATE("ППО ",'Х1_ППО-М'!C3,"%") -> ППО 40%
B29: Холдинг 1.2. | C29: ППО и ДЗО в разных базах | R29: ППО и ДЗО в разных базах
C30: =CONCATENATE("ППО ",Х1_ППО!C3,"%") -> ППО 33% | R30: =CONCATENATE("ППО ",'Х1_ППО-М'!C3,"%") -> ППО 40%
B31: Холдинг2 | C31: УК-ДЗО. Инвестиционные проекты. Gate, Заявки
C32: =CONCATENATE("ДИД ",Х2_ДИД!C3,"%") -> ДИД 25% | E32: =CONCATENATE("НИО ",Х2_НИО!C3,"%") -> НИО 8%

Sheet Решения
B1: Идея | C1: Статус | E1: Комментарий
B2: 1С:Взаимодействие | C2: 0 | D2: 1 | E2: Нет в сценарии
B3: Gate | C3: 0.5 | G3: 1
B4: MDR | C4: 0 | D4: 1
B5: Актуализация и балансировка фин.планов | C5: 0.5 | D5: 1
B6: Актуализация инвестпрограммы на основании связанных проектов | C6: 0.5
B7: Актуализация информации по проектам | C7: 0.5 | D7: 1
B8: Анализ обеспеченности (в т.ч. ТМЦ) и формирование фронта работ | C8: 0
B9: Анализ обеспеченности и формирование фронта работ | C9: 0
B10: Балансировка и минимизация кассовых разрывов | C10: 0.5 | D10: 1
B11: Балансировка объемов и минимизация ресурсных конфликтов | C11: 0.5
B12: Бронирование базовое | C12: 0
B13: Бюджеты для финансирования возможностей | C13: 0.5
B14: Влияние производительности ресурсов на трудоемкость и сроки | C14: 0.5
B15: Диспетчирование работ (поручения) | C15: 0.5 | D15: 1
B16: Единообразное планирование проектов (План-график, трудозатраты, фин план) | C16: 0.5 | D16: 1
B17: Загрузка из файла-шаблона с PDM/PLM данными. Состав изделия, состав работ, связи | C17: 0
B18: Инвестзаявки в системе | C18: 0.5 | G18: 1
B19: Инвестпрограмма | C19: 0.5 | G19: 1
B20: Интеграция баз Холдинг-ДЗО | C20: 0
B21: Интеграция с КИС | C21: 0
B22: Интеграция с системой управления проектами | C22: 0
B23: Интеграция с трекинг-системами | C23: 0.5 | D23: 1
B24: Канбан-доска | C24: 0 | D24: 1 | E24: Нет Функций ИС
B25: Контроль актирования | C25: 0
B26: Контроль качества и применимость ресурсов (компетенции, квалификации) | C26: 0
B27: Механизм укрупненной оценки проектов на структуре проекта с печатной формой (Обоснование стоимости проекта) | C27: 0.3 | D27: 1 | G27: 1
B28: Многомерные проекты | C28: 0.5 | D28: 1 | E28: Нет Функций ИС
B29: Объединенные закупки (лоты) | C29: 0
B30: Оперативный фронт работ (план производственных подраз): - подошли сроки, работы обеспечены, баласировки под мощность подразделений | C30: 0
B31: Отметка в работах проекта о наличии ТМЦ из спецификаций и смена статуса работ на "обеспеченные" | C31: 0
B32: Платежный календарь | C32: 0.5 | D32: 1
B33: Подробные планы загрузки сотрудников | C33: 0.5 | D33: 1
B34: Привязка спецификаций к работам проекта | C34: 0
B35: Проектный документооборот (~MDR базовый) (жизненный цикл основных проектных артефактов, указанных в ТЗ и договоре) | C35: 0 | D35: 1
B36: Проектный калькулятор | C36: 0.5
B37: Расчет финпоказателей в заявках | C37: 0.5 | G37: 1
B38: РСП: управление пакетами работ, за которые они назначены ответственными | C38: 0 | G38: 1
B39: Сводная картина по экономике фирмы и ден.потоку на основании актуального сводного плана и плана инвестиций | C39: 0.5
B40: Связь проектов, заказов поставщикам и факта поставки ТМЦ | C40: 0.8
B41: Синхронизация мониторинга производственной деятельности с планами по проектам, объемам и по ресурсам | C41: 0.5
B42: Средство визуализации 3D модели изделий и последовательностей изготовления, привязанных к плану проекта | C42: 0.5 | G42: 1
B43: Статус-отчеты по проекту. От Фазы Пресейла до Завершения договора | C43: 0.5 | D43: 1 | G43: 1
B44: Сценарное моделирование. «Что если». | C44: 0
B45: Темплан, включая планирование контрактации | C45: 0 | G45: ?
B46: Темплан, включая планирование объемов актирования по контрактации (без самой контрактации) | C46: 0.5
B47: Тиражирование технологий управления на все направления | C47: 0
B48: Тиражирование технологий управления на все проекты | C48: 0
B49: Трехуровневое ресурсное планирование с прогнозами | C49: 0
B50: Упр и ресурсный учет подразделения в разрезе проектов | C50: 0.5
B51: Упр.учет фирмы в разрезе подразделений, направлений, проектов | C51: 0.8 | D51: 1
B52: Управление договорами | C52: 0.5 | D52: 1 | G52: 1
B53: Управление портфелями и программами | C53: 0.5 | G53: 1
B54: Управление проектами | C54: 0.5
B55: Управление сводными планами | C55: 0.5
B56: Учет факта выполнения работ | C56: 0.5
B57: Формирование отчетности по проектам | C57: 0.5 | D57: 1
B63: Не занимались | C63: 0
B64: В работе | C64: 0.1
B65: Техническая реализация | C65: 0.5
B66: Базовая реализация (в т.ч. удобно) | C66: 0.8
B67: Глубокая реализация | C67: 1

Sheet НИПИ_списком
B2: Оглавление Lean Canvas Model для РМ5
B4: Сегмент | C4: LCM | D4: Вид заказчика. Краткое описание | E4: Специфическая задача сегмента | F4: Особенности | G4: Вид продукта PM | H4: Вид комплексного продукта PM | I4: ДО | J4: Корп.бюдж. (+Казна) | K4: Учет
B5: Соло | C5: РП | D5: Заказчик - РП под свои проекты. | E5: Ведение проекта для РП | F5: Простой аналог работы в MS Project и MS Excel. Каждый РП ведет свой проект. Бюджетирование проектов. Многомерные проекты, Проектная продукция, task tracker+канбан-доска с лимитами | G5: PM.ПРОФ в ГРМ/ | H5: - | I5: Диск | J5: - | K5: -
D6: Есть исполнители. | G6: PM.Стандарт
B7: МикроГД | C7: ГД | D7: До 60 человек; Заказчик – ГД. В управлении нет руководителей производственных отделов | E7: Проектное управление | F7: Управление ресурсами | G7: PM.ПРОФ | H7: УНФ+PM | I7: ДО | J7: УНФ/Свое | K7: УНФ/БП
B8: МикроРСП | C8: РСП | D8: Заказчик – руководитель подразделения внутри организации | E8: для организации с функц. или проектной структурами | F8: (доступность, решение конфликтов), Моделирование проектной загрузки. Бюджетирование по организации. Косвенные по организации в целом. Структура проектов предприятия (EPS) | G8: PM.ПРОФ | H8: УНФ+PM | I8: ДО | J8: УНФ/Свое | K8: УНФ/ERP/БП
B9: Малый1 | C9: ГД | D9: 60-200 человек; Направления со своим управлением. | E9: Разрез по подразделениям в произв. и экономических данных | F9: Темплан. Объемное планирование, ресурсные планы. Бюджетирование по подразделениям. Финрез по подразделениям и косвенные затраты по подразделениям | G9: PM.ПРОФ | H9: УНФ+PM ERP+PM | I9: ДО/Другие | J9: УНФ/ERP/Свое | K9: УНФ/ERP/БП
C10: ФД | D10: Проекты внутри направлений.
C11: РукНапр | D11: Разрез по подразделениям в произв. и экономических данных
B12: Малый2 | C12: ГД | D12: 60-200 человек; ГИПы+Рук.подр., сквозные проекты, | E12: Проектное управление для организации с матричной стр. | F12: Поддержка матричной системы, бронирование | G12: PM.КОРП | H12: УНФ+PM ERP+PM | I12: ДО/Другие | J12: УНФ/ERP/Свое | K12: УНФ/ERP/БП
C13: ФД
C14: РПО | D14: Производственные отделы участвуют в управлении
B15: Средний1 | C15: ФД | D15: 200-600 человек; | E15: Проектное управление | F15: Контрактация проектов. | G15: PM.КОРП | H15: ERP+PM | I15: ДО/Другие | J15: ERP/Свое | K15: ERP/БП
D16: ПЭО и ПДО под ФД | E16: для организации с матричной структурой | F16: Проектный калькулятор.
B17: Средний2 | C17: ГД | D17: 200-600 человек; | E17: +Оценка и Контрактация | F17: Управление договорами. | G17: PM.КОРП | H17: ERP+PM | I17: ДО/Другие | J17: ERP/Свое | K17: ERP/БП
C18: ДП
C19: ФД | D19: Дир.Произв и ФД | F19: Модели управления портфелями, программами. Фазы.
B20: Средний3 | C20: ГД | D20: 200-600 человек; НИПИ, ГИПы+Рук.подр. | F20: Ведение графиков проектов в несколько десятков тысяч строк. | G20: PM.КОРП | H20: ERP+PM | I20: ДО/Другие | J20: ERP/Свое | K20: ERP/БП
C21: ДП | D21: Производственные отделы участвуют в управлении; | F21: ГОЗ (Специальные счета казначейства, контроль БДДС по счетам, учет трудозатрат в разрезе работ по ГОЗ), Иерархические проекты.
C22: ФД | D22: м.б. Контрактация | F22: MDR – управление реестром и структурой документации. Управление рисками.
B23: Средний4 | C23: ГД | D23: 200-600 человек; Инж, ГИПы+Рук.подр. | F23: Моделирование «что если» внутри проекта. | G23: PM.КОРП | H23: ERP+PM | I23: ДО/Другие | J23: ERP/Свое | K23: ERP/БП
C24: ДП | D24: Производственные отделы участвуют в управлении; | F24: Мат.нормирование проекта (по драйверам).
C25: ФД | D25: м.б. Контрактация | F25: API c системами управления проектами и объемами.
B26: Средний5 ИТ | C26: ГД | D26: 200-600 человек; ИТ | G26: PM.КОРП | H26: ERP+PM | I26: ДО/Другие | J26: ERP/Свое | K26: ERP/БП
C27: ДП | D27: Производственные отделы участвуют в управлении;
C28: ФД | D28: Контрактация, буккирование.
B29: Крупный1 | C29: 1-й зам ГД/ИспДир | D29: 600-3000 человек; | E29: Проектное управление для организации со сложной иерархической структурой | F29: Институт в институте. | G29: PM.КОРП | H29: ? | I29: ДО/Другие | J29: ERP/УХ/Свое | K29: УХ + ERP/УХ/БП
C30: РукЦентров | D30: Институт в институте; 2 уровня ПЭО | G30: (? PM.КОРП Холдинг)
B31: Крупный2 | C31: ДП | D31: 600-3000 человек; | G31: PM.КОРП | H31: ? | I31: ДО/Другие | J31: УХ | K31: УХ + Шаблон на ERP
D32: Сквозные проекты; 2 уровня диспетчеров | G32: (? PM.КОРП Холдинг) | J32: (УХ.ERP в ДЗО)
B33: Холдинг1.1/ Кооперация | C33: ППО | D33: Головной-Соисполнители. Сквозные проекты. Головной ППО и ДЗО в одной базе | E33: Управление работами соисполнителей | F33: Общее управление ресурсами (Голова-Соисп.) | G33: PM.КОРП Упр.Кооп.(?) | H33: ? | I33: ДО/Другие | J33: - | K33: -
B34: Холдинг1.2/ Кооперация | C34: ППО | D34: Головной-Соисполнители. Сквозные проекты. Головной ППО и ДЗО в разных базах | E34: Управление работами соисполнителей | F34: Общее управление ресурсами (Голова-Соисп.) Иерархические проекты в разных базах. | G34: PM.КОРП Упр.Кооп.(?) | H34: ? | I34: ДО/Другие | J34: - | K34: -
B35: Холдинг2 Инвест | C35: ДИД | D35: Холдинг. УК-ДЗО. | E35: Управление инвестпрограммой | F35: Заявки, Gate, Моделирование «что если» для инвестпрограммы. | G35: PM.КОРП Холдинг | H35: ? | I35: ДО/Другие | J35: УХ (УХ.ERP в ДЗО) | K35: УХ + Шаблон на ERP
C36: НИО | D36: Инвестиционные проекты. Gate, Заявки
B38: Концепция | C38: e1cib/data/Справочник.Файлы?ref=80f7000c295e34e311ea467fc0ee57af

Sheet Проекты и бюджеты под контролем
B2: Продукт | I2: Рынок
B3: 2.1 Проблема | C3: 2.1. Сопоставление с проблемами в презентации | D3: =ROUND(AVERAGE(D6:D16),2) -> 0.5 | E3: 4. Решение | F3: Связь | G3: =AVERAGE(G4:G16) -> 0.61111111 | H3: 3. Уникальная ценность (УТП) | J3: 9. Скрытое преимущество | K3: 1.1 Сегменты потребителей
B4: 1.1. Остутствие единой среды ведения проектов - все ведут проекты в разных инструментах | C4: НА старте портфеля разрозненные инструменты работают, но по мере роста кол-ва проектов, появляются органичения. Существующая система перестала работать? (общая канва, не отдельная проблематика в презентации) | D4: =ROUND(AVERAGE(D8:D13),2) -> 0.39 | E4: Единое окно с набором актуальных показателей по реестру проектов (БДР, риски, сроки). Панель руководителя | F4: 1.1. | G4: 0.8 | H4: 1С:PM Создает единую управленческую среду где данные обновляются в процессе работы, а руководитель видит отклонение, ответсвенных и последствия в одном контуре: - Елиные правила управления (ПРоекты ведутся в общей логике: структура, роли и контрольные точки) - Контроль через отклонения (Руководитель видит где проблема и может сразу провалиться в причину) - Связь проектов и экономики (Сроки, жтапы и фин. показатели связаны между собой. Изменения сразу отражаются на бюджете) Порядок в проектах при любом текущем состоянии проектного управления Уверенная основа для дальнейшего развития проектного управления За счет айтисистемы и методической оддержки вы получите: Дашборд с консолидированной информацией о состоянии проектов (вехи, сроки, бюджеты, риски) Минимизация трудозатрат руководителя на получение информации о состоянии проектов Быстрый и легкий старт работы в системе Автомический контроль исполнительской дисциплины Стоимость до 2,5 млн., сроки - до 2х мес. запуска | J4: Богатый базовый фунционал решения Возможность повторения уникальной отчетности Возможность Интеграции с учетными системами: БУХ, УНФ, ERP | K4: Для компаний с начальным уровнем проектного управления (внешние проекты - оборот 800М до 4Я), (внутренние проекты - оборот от 2Я). Генеральный директор / РПО / ТОП Менеджер (ответсвенный за проектную деятельность) - потребитель отчетности от РП. осуществляет контроль за ходом реализации реестра проектов в одном окне (Вехи), показатели (план/факт сроки, бюджеты, риски). В основном контроль за внутренними проектами. РП (администратор проекта) - быстрое ведение проектов без детализации до объемов и ресурсов актуализация План/факт Вехи, сроки, бюджет, риски Тригеры: 1. Существующая система перестала работать из-за использования разрозненных инструментов, и отсетствия методики ведения проектов 2. Управленческие решения запаздывают из-за отсутсвия актуальной информации по проектам
B5: 1. Большое кол-во разрозненной информации по проектам, не понятно, на что уделить внимание - ключевые показатели всегда перед глазами онлайн | C5: Проблема: Нет фокуса. Руководителю сложно понять какие проекты требуют внимания,
B6: 1.1. Остутствие единой среды ведения проектов - все ведут проекты по разному | C6: Проблема: Проекты ведутся по разным правилам и с разной детализацией. | D6: =AVERAGE(G4,G7) -> 0.8 | E6: Совокупность Вех по всем проектам (аналог ВК в панели руководителя)
B7: 1.2. Остутсвие актуальной информации по проектам (на какой вехе/ кто за нее ответсвенный | C7: Проблематика: .2.Размытая ответственность за проекты и их задачи. Добавить раздел в презентацию. | E7: Отвественные за проекты (РП), ответсвенные за задачи | F7: 1.1. | G7: 0.8
B8: 1.2. Остутсвие актуальной информации по проектам (, попадаем ли в сроки, есть/нет ли рисков, подписаны ли акты, списание ДС. ) - тратим много времени на сбор акутальной информации | C8: 1. Проблема: Экономика и сроки ведутся в разных инструментах. 2. Проблема: Отчетность собирается вручную и быстро устаревает | D8: =AVERAGE(G10,G9,G11,G12,G13) -> 0.68
B9: 1.3. РП Забывают внести данные - смотрим на ситуацию в прошлом | C9: Проблема: РП Забывают внести данные (Добавить новый раздел) | D9: =AVERAGE(G14) -> 0 | E9: КСГ проекта / актируемые этапы - план/факт сроков | F9: 1.2. | G9: 0.8
B10: 2. Оперативный и достоверный учет фактических данных по первичным документам - опция 1 | C10: Проблема: Факт по бюджетам ведется в учетной системе и не сопоставим с планом. Нужно видеть факт в проектах вплоть до первичных документов. Двойной ввод данных | E10: Контрольных точек ( Проектные решения - ответственных за них) план/факт исполнения КТ; Вехам (из-за чего проиходит сдвиг, какие промблемы) | F10: 1.2. | G10: 0.5
B11: 3. Актуальный БДР и БДДС по портфелю (план и факт) - опция 2 | C11: Не получить актуальный прогноз по бюджетам портфеля с учетом фактических данных Трудоемко обновлять план с учетом фактических отклонений.. | E11: Потенциальные риски Есть/нет наличие | F11: 1.2. | G11: 0.5
E12: БДР и БДДС - План/факт | F12: 1.2. | G12: 0.8
B13: 1.4. Порядок | C13: Проблема: Система сама по себе не наводит порядок без правил. | D13: =AVERAGE(G15) -> 0.5 | E13: Факт и актуализация в ручном режиме | F13: 1.2. | G13: 0.8
E14: Автоматический контроль за актуализацией данных | F14: 1.3. | G14: 0
E15: Методическая поддержка | F15: 1.4. | G15: 0.5
B17: 2.2 Альтернативы | E17: 8. Ключевые метрики | J17: 5. Каналы | K17: 1.2 Ранние последователи
B18: Битрикс 24 Excel Он-лайн табличный процессор Адванта (базовый запуск) Яндекс трекер Импортозамещается: Шарепоинт + ПроджектСервер + Локальный Проджект + MS BI | E18: Количество продаж; Количество пользователей в ГРМ; Количество отзывов | K18: Х продаж за первые 3 мес.; У продаж за вторые 3 мес.
B19: 7. Структура издержек | I19: 6. Потоки прибыли
B22: решение не сформулировано | E22: Не занимались | F22: 0 | H22: Что нужно доработать:
B23: решение сформулировано частично | E23: В работе | F23: 0.1
B24: решение сформулировано | E24: Техническая реализация | F24: 0.5
E25: Базовая реализация (в т.ч. удобно) | F25: 0.8
E26: Глубокая реализация | F26: 1 | H26: Что нужно ОП для старта: демо-база, презентации.
B31: РАС Промблематика: | E31: Для кого: Генеральный директор (РПО)
B32: 1. Большое кол-во разразненной информации по проектам, не понятно на что уделить внимание - ключевые показатели всегда перед глазами онлайн | E32: Исполнитель - РП
B33: 1.1. Остутствие едиой среды ведения проектов - все ведут проекты по разному в разных инструментах
B34: 1.2. Остутсвие актуальной информации по проектам (на какой вехи/ кто за нее ответсвенный, попадаем ли в сроки, есть/нет ли рисков, подписаны ли акты, списание ДС. ) - тратим много времени на сбор акутальной информации | E34: Бизнес задача: Верхнеуровневый контроль состояния проектов реестра
B35: 1.3. РП Забывают внести данные - смотрим на ситуацию в прошлом
E36: Актуальная информация по реестру проектов в разрезе (анализ текущего состоянию проектов):
E37: КСГ проекта (актируемые этапы) план/факт сроков
E38: Контрольных точек ( Проектные решения - ответственных за них) план/факт исполнения КТ
E39: Потенциальные риски Есть/нет наличие
E40: БДР и БДДС - План/факт
E42: Факт и актуализация в ручном режиме
B46: сколько запросов под эту тематику за год было
B47: больше 2 млдр. Не Трудоемкое производство - 90 SQL
B48: как первый шаг на РМ5 для стандарт проектов - 119 SQL
B49: запросов какое количество было бы куплено
B50: больше 2 млдр. Не Трудоемкое производство - 19
B51: как первый шаг на РМ5 для стандарт проектов - 41
B52: какое количество заказчиков купило бы такое предложение из текущей воронки
B53: как первый шаг на РМ5 для стандарт проектов -98

Sheet ПиБпК_после вебинара
B2: Продукт | H2: Рынок
B3: 2.1 Проблема | D3: 4. Решение | E3: Связь | F3: =AVERAGE(F4:F16) -> 0.61111111 | G3: 3. Уникальная ценность (УТП) | I3: 9. Скрытое преимущество | J3: 1.1 Сегменты потребителей
B4: Нет фокуса. Руководителю сложно понять, какие проекты требуют внимания | D4: Единая панель по портфелю проектов с индикаторами состояния проекта по срокам, бюджету и наличия рисков | F4: 0.8 | G4: Единое окно с набором актуальных показателей по проекту и ответственным Единые правила управления. Проекты ведутся в общей логике: структура, роли, контрольные точки Финансы в привязке к срокам проектов. Сроки, этапы и бюджеты связаны между собой, изменения сразу отражаются в отчетности Контрольные точки. Контроль графика ведения проектов по вехам и ответственным Данные «до первички» Возможность «провалиться» в проект и узнать всю информацию о проекте до первички Стоимость до 2,5 млн., сроки - до 2х мес. запуска | I4: Богатый базовый фунционал решения Возможность повторения уникальной отчетности Возможность Интеграции с учетными системами: БУХ, УНФ, ERP | J4: Для компаний с начальным уровнем проектного управления (внешние проекты - оборот 800М до 4Я), (внутренние проекты - оборот от 2Я). Генеральный директор / РПО / ТОП Менеджер (ответсвенный за проектную деятельность) - потребитель отчетности от РП. осуществляет контроль за ходом реализации реестра проектов в одном окне (Вехи), показатели (план/факт сроки, бюджеты, риски). В основном контроль за внутренними проектами. РП (администратор проекта) - быстрое ведение проектов без детализации до объемов и ресурсов актуализация План/факт Вехи, сроки, бюджет, риски Тригеры: 1. Существующая система перестала работать из-за использования разрозненных инструментов, и отсетствия методики ведения проектов 2. Управленческие решения запаздывают из-за отсутсвия актуальной информации по проектам
B5: Размытая ответственность за проекты и их задачи | D5: РП каждого проекта и ответственный по каждой задаче внутри проекта КСГ проекта / актируемые этапы –план/факт сроков с ответственными
B6: Проекты ведутся по разным правилам: разные форматы, разные инструменты, разная детализация. Сравнивать проекты невозможно | D6: Единый ЖЦ проектов Единая структура этапов и КТ Единый формат дорожной карты проектов Единая шкала статусов готовности и % исполнения задач
B7: Экономика проекта и сроки ведутся в разных инструментах Не видны изменения бюджетов проектов при изменении сроков Отчетность по портфелю собирается вручную из разрозненных файлов. Подготовленный отчет уже не актуален | D7: Сквозное решение для управления сроками и бюджетами проектов Пользователь один раз задает сроки актирования и условия оплаты по проекту, а система сама рассчитывает сроки поступлений и платежей Актуализация данных в системе по мере возникновения информации, а не под отчет | F7: 0.8
B8: Факт по бюджетам ведется в учетной системе и не сопоставим с планом Нужно видеть факт в проектах вплоть до первичных документов Двойной ввод данных | D8: Ввод факта напрямую в системе или интеграции с учётными системами (опционально)
B9: Не получить актуальный прогноз по бюджетам портфеля с учетом фактических данных | D9: Автоматическая актуализация прогноза по факту (опционально) | F9: 0.8
F10: 0.5
F11: 0.5
F12: 0.8
F13: 0.8
F14: 0
F15: 0.5
B17: 2.2 Альтернативы | D17: 8. Ключевые метрики | I17: 5. Каналы | J17: 1.2 Ранние последователи
B18: Битрикс 24 Excel Он-лайн табличный процессор Адванта (базовый запуск) Яндекс трекер Импортозамещается: Шарепоинт + ПроджектСервер + Локальный Проджект + MS BI | D18: Количество продаж; Количество пользователей в ГРМ; Количество отзывов | J18: Х продаж за первые 3 мес.; У продаж за вторые 3 мес.
B19: 7. Структура издержек | H19: 6. Потоки прибыли
B22: решение не сформулировано | D22: Не занимались | E22: 0 | G22: Что нужно доработать:
B23: решение сформулировано частично | D23: В работе | E23: 0.1
B24: решение сформулировано | D24: Техническая реализация | E24: 0.5
D25: Базовая реализация (в т.ч. удобно) | E25: 0.8
D26: Глубокая реализация | E26: 1 | G26: Что нужно ОП для старта: демо-база, презентации.
B31: РАС Промблематика: | D31: Для кого: Генеральный директор (РПО)
B32: 1. Большое кол-во разразненной информации по проектам, не понятно на что уделить внимание - ключевые показатели всегда перед глазами онлайн | D32: Исполнитель - РП
B33: 1.1. Остутствие едиой среды ведения проектов - все ведут проекты по разному в разных инструментах
B34: 1.2. Остутсвие актуальной информации по проектам (на какой вехи/ кто за нее ответсвенный, попадаем ли в сроки, есть/нет ли рисков, подписаны ли акты, списание ДС. ) - тратим много времени на сбор акутальной информации | D34: Бизнес задача: Верхнеуровневый контроль состояния проектов реестра
B35: 1.3. РП Забывают внести данные - смотрим на ситуацию в прошлом
D36: Актуальная информация по реестру проектов в разрезе (анализ текущего состоянию проектов):
D37: КСГ проекта (актируемые этапы) план/факт сроков
D38: Контрольных точек ( Проектные решения - ответственных за них) план/факт исполнения КТ
D39: Потенциальные риски Есть/нет наличие
D40: БДР и БДДС - План/факт
D42: Факт и актуализация в ручном режиме
B46: сколько запросов под эту тематику за год было
B47: больше 2 млдр. Не Трудоемкое производство - 90 SQL
B48: как первый шаг на РМ5 для стандарт проектов - 119 SQL
B49: запросов какое количество было бы куплено
B50: больше 2 млдр. Не Трудоемкое производство - 19
B51: как первый шаг на РМ5 для стандарт проектов - 41
B52: какое количество заказчиков купило бы такое предложение из текущей воронки
B53: как первый шаг на РМ5 для стандарт проектов -98

Sheet ПиБпК_сопоставление
B2: Продукт | I2: Рынок
B3: 2.1 Проблема | C3: 2.1. Сопоставление с проблемами в презентации с вебинара | D3: =ROUND(AVERAGE(D6:D16),2) -> 0.5 | E3: 4. Решение | F3: Связь | G3: =AVERAGE(G4:G16) -> 0.61111111 | H3: 3. Уникальная ценность (УТП) | J3: 9. Скрытое преимущество | K3: 1.1 Сегменты потребителей
B4: 1.1. Остутствие единой среды ведения проектов - все ведут проекты в разных инструментах | C4: НА старте портфеля разрозненные инструменты работают, но по мере роста кол-ва проектов, появляются органичения. Существующая система перестала работать? (общая канва, не отдельная проблематика в презентации) | D4: =ROUND(AVERAGE(D8:D13),2) -> 0.39 | E4: Единое окно с набором актуальных показателей по реестру проектов (БДР, риски, сроки). Панель руководителя | F4: 1.1. | G4: 0.8 | H4: 1С:PM Создает единую управленческую среду где данные обновляются в процессе работы, а руководитель видит отклонение, ответсвенных и последствия в одном контуре: - Елиные правила управления (ПРоекты ведутся в общей логике: структура, роли и контрольные точки) - Контроль через отклонения (Руководитель видит где проблема и может сразу провалиться в причину) - Связь проектов и экономики (Сроки, жтапы и фин. показатели связаны между собой. Изменения сразу отражаются на бюджете) Порядок в проектах при любом текущем состоянии проектного управления Уверенная основа для дальнейшего развития проектного управления За счет айтисистемы и методической оддержки вы получите: Дашборд с консолидированной информацией о состоянии проектов (вехи, сроки, бюджеты, риски) Минимизация трудозатрат руководителя на получение информации о состоянии проектов Быстрый и легкий старт работы в системе Автомический контроль исполнительской дисциплины Стоимость до 2,5 млн., сроки - до 2х мес. запуска | J4: Богатый базовый фунционал решения Возможность повторения уникальной отчетности Возможность Интеграции с учетными системами: БУХ, УНФ, ERP | K4: Для компаний с начальным уровнем проектного управления (внешние проекты - оборот 800М до 4Я), (внутренние проекты - оборот от 2Я). Генеральный директор / РПО / ТОП Менеджер (ответсвенный за проектную деятельность) - потребитель отчетности от РП. осуществляет контроль за ходом реализации реестра проектов в одном окне (Вехи), показатели (план/факт сроки, бюджеты, риски). В основном контроль за внутренними проектами. РП (администратор проекта) - быстрое ведение проектов без детализации до объемов и ресурсов актуализация План/факт Вехи, сроки, бюджет, риски Тригеры: 1. Существующая система перестала работать из-за использования разрозненных инструментов, и отсетствия методики ведения проектов 2. Управленческие решения запаздывают из-за отсутсвия актуальной информации по проектам
B5: 1. Большое кол-во разрозненной информации по проектам, не понятно, на что уделить внимание - ключевые показатели всегда перед глазами онлайн | C5: Нет фокуса. Руководителю сложно понять, какие проекты требуют внимания
B6: 1.1. Остутствие единой среды ведения проектов - все ведут проекты по разному | C6: Проекты ведутся по разным правилам: разные форматы, разные инструменты, разная детализация. Сравнивать проекты невозможно | D6: =AVERAGE(G4,G7) -> 0.8 | E6: Совокупность Вех по всем проектам (аналог ВК в панели руководителя)
B7: 1.2. Остутсвие актуальной информации по проектам (на какой вехе/ кто за нее ответсвенный | C7: Размытая ответственность за проекты и их задачи | E7: Отвественные за проекты (РП), ответсвенные за задачи | F7: 1.1. | G7: 0.8
B8: 1.2. Остутсвие актуальной информации по проектам (, попадаем ли в сроки, есть/нет ли рисков, подписаны ли акты, списание ДС. ) - тратим много времени на сбор акутальной информации | C8: Экономика проекта и сроки ведутся в разных инструментах Не видны изменения бюджетов проектов при изменении сроков Отчетность по портфелю собирается вручную из разрозненных файлов. Подготовленный отчет уже не актуален | D8: =AVERAGE(G10,G9,G11,G12,G13) -> 0.68
B9: 1.3. РП Забывают внести данные - смотрим на ситуацию в прошлом | C9: Проблема: РП Забывают внести данные (Добавить новый раздел) | D9: =AVERAGE(G14) -> 0 | E9: КСГ проекта / актируемые этапы - план/факт сроков | F9: 1.2. | G9: 0.8
B10: 2. Оперативный и достоверный учет фактических данных по первичным документам - опция 1 | C10: Факт по бюджетам ведется в учетной системе и не сопоставим с планом Нужно видеть факт в проектах вплоть до первичных документов Двойной ввод данных | E10: Контрольных точек ( Проектные решения - ответственных за них) план/факт исполнения КТ; Вехам (из-за чего проиходит сдвиг, какие промблемы) | F10: 1.2. | G10: 0.5
B11: 3. Актуальный БДР и БДДС по портфелю (план и факт) - опция 2 | C11: Не получить актуальный прогноз по бюджетам портфеля с учетом фактических данных | E11: Потенциальные риски Есть/нет наличие | F11: 1.2. | G11: 0.5
E12: БДР и БДДС - План/факт | F12: 1.2. | G12: 0.8
B13: 1.4. Порядок | C13: Проблема: Система сама по себе не наводит порядок без правил. | D13: =AVERAGE(G15) -> 0.5 | E13: Факт и актуализация в ручном режиме | F13: 1.2. | G13: 0.8
E14: Автоматический контроль за актуализацией данных | F14: 1.3. | G14: 0
E15: Методическая поддержка | F15: 1.4. | G15: 0.5
B17: 2.2 Альтернативы | E17: 8. Ключевые метрики | J17: 5. Каналы | K17: 1.2 Ранние последователи
B18: Битрикс 24 Excel Он-лайн табличный процессор Адванта (базовый запуск) Яндекс трекер Импортозамещается: Шарепоинт + ПроджектСервер + Локальный Проджект + MS BI | E18: Количество продаж; Количество пользователей в ГРМ; Количество отзывов | K18: Х продаж за первые 3 мес.; У продаж за вторые 3 мес.
B19: 7. Структура издержек | I19: 6. Потоки прибыли
B22: решение не сформулировано | E22: Не занимались | F22: 0 | H22: Что нужно доработать:
B23: решение сформулировано частично | E23: В работе | F23: 0.1
B24: решение сформулировано | E24: Техническая реализация | F24: 0.5
E25: Базовая реализация (в т.ч. удобно) | F25: 0.8
E26: Глубокая реализация | F26: 1 | H26: Что нужно ОП для старта: демо-база, презентации.
B31: РАС Промблематика: | E31: Для кого: Генеральный директор (РПО)
B32: 1. Большое кол-во разразненной информации по проектам, не понятно на что уделить внимание - ключевые показатели всегда перед глазами онлайн | E32: Исполнитель - РП
B33: 1.1. Остутствие едиой среды ведения проектов - все ведут проекты по разному в разных инструментах
B34: 1.2. Остутсвие актуальной информации по проектам (на какой вехи/ кто за нее ответсвенный, попадаем ли в сроки, есть/нет ли рисков, подписаны ли акты, списание ДС. ) - тратим много времени на сбор акутальной информации | E34: Бизнес задача: Верхнеуровневый контроль состояния проектов реестра
B35: 1.3. РП Забывают внести данные - смотрим на ситуацию в прошлом
E36: Актуальная информация по реестру проектов в разрезе (анализ текущего состоянию проектов):
E37: КСГ проекта (актируемые этапы) план/факт сроков
E38: Контрольных точек ( Проектные решения - ответственных за них) план/факт исполнения КТ
E39: Потенциальные риски Есть/нет наличие
E40: БДР и БДДС - План/факт
E42: Факт и актуализация в ручном режиме
B46: сколько запросов под эту тематику за год было
B47: больше 2 млдр. Не Трудоемкое производство - 90 SQL
B48: как первый шаг на РМ5 для стандарт проектов - 119 SQL
B49: запросов какое количество было бы куплено
B50: больше 2 млдр. Не Трудоемкое производство - 19
B51: как первый шаг на РМ5 для стандарт проектов - 41
B52: какое количество заказчиков купило бы такое предложение из текущей воронки
B53: как первый шаг на РМ5 для стандарт проектов -98

Sheet 1+автоактуализация бюджетов
B2: Продукт | H2: Рынок
B3: 2.1 Проблема | C3: =ROUND(AVERAGE(C5:C14),2) -> 0.48 | D3: 4. Решение | E3: Связь | F3: =AVERAGE(F4:F14) -> 0.58181818 | G3: 3. Уникальная ценность (УТП) | I3: 9. Скрытое преимущество | J3: 1.1 Сегменты потребителей
B4: 1. Большое кол-во разразненной информации по проектам, не понятно на что уделить внимание - ключевые показатели всегда перед глазами онлайн | C4: =ROUND(AVERAGE(C6:C8),2) -> 0.39 | D4: Единое окно с набором актуальных показателей по реестру проектов (Вехи, БДР, риски, сроки). Панель руководителя | E4: 1.1. | F4: 0.8 | G4: Порядок в проектах при любом текущем состоянии проектного управления Дашборд с консолидированной информацией о состоянии проектов (вехи, сроки, бюджеты, риски) Минимизация трудозатрат руководителя на получение информации о состоянии проектов Быстрый и легкий старт работы в системе Автомическое контроль исполнительской дисциплины Интеграции с учетными системами: БП, УНФ, ERP (опционально) ОП: Стоимость от 3 до 5 млн., сроки - до 4х мес. запуска Производство: Стоимость до млн., сроки - до х мес. запуска | I4: Уверенная основа для дальнейшего развития проектного управления Богатый базовый фунционал решения Возможность повторения уникальной отчетности | J4: Для компаний с начальным уровнем проектного управления (внешние и внутренние проекты). Генеральный директор / РПО / ТОП Менеджер (ответсвенный за проетконую деятельность) - потребитель отчетности от РП. осуществляет контроль за ходом реализации реестра проектов в одном окне (Вехи), показатели (план/факт сроки, бюджеты, риски). В основном контроль за внутренними проектами. РП (администратор проекта) - быстрое ведение проектов без детализации до объемов и ресурсов актуализация План/факт Вехи, сроки, бюджет, риски
B5: 1.1. Остутствие единой среды ведения проектов - все ведут проекты по разному в разных инструментах | C5: =AVERAGE(F4,F5) -> 0.8 | D5: Ответственные за проекты (РП) | E5: 1.1. | F5: 0.8
B6: 1.2. Остутсвие актуальной информации по проектам (на какой вехи/ кто за нее ответсвенный, попадаем ли в сроки, есть/нет ли рисков, подписаны ли акты, списание ДС. ) - тратим много времени на сбор акутальной информации | C6: =AVERAGE(F7,F6,F8,F9,F10) -> 0.68 | D6: КСГ проекта / актируемые этапы - план/факт сроков | E6: 1.2. | F6: 0.8
B7: 1.3. РП Забывают внести данные - смотрим на ситуацию в прошлом | C7: =AVERAGE(F11) -> 0 | D7: Контрольные точки ( Проектные решения - ответственных за них) план/факт исполнения КТ; Вехам (из-за чего проиходит сдвиг, какие промблемы) | E7: 1.2. | F7: 0.5
B8: 1.4. Порядок | C8: =AVERAGE(F12) -> 0.5 | D8: Потенциальные риски Есть/нет наличие | E8: 1.2. | F8: 0.5
B9: 2. Оперативный и достоверный учет фактических данных по первичным документам - опция 1 | C9: =AVERAGE(F13) -> 0.8 | D9: БДР и БДДС - План/факт | E9: 1.2. | F9: 0.8
B10: 3. Актуальный БДР и БДДС по портфелю (план и факт) - опция 2 | C10: =AVERAGE(F14) -> 0.1 | D10: Факт и актуализация в ручном режиме | E10: 1.2. | F10: 0.8
D11: Автоматический контроль за актуализацией данных | E11: 1.3. | F11: 0
D12: Методическая поддержка | E12: 1.4. | F12: 0.5
D13: Интеграция для получения учетных данных из БП; Трансляция фактических данных из УНФ+РМ, ERP+РМ (опционально 1). | E13: 2 | F13: 0.8
D14: Механизм автоматической актуализации плановых данных по бюджетам (плана по факту) - (опционально 2) | E14: 3 | F14: 0.1
B15: 2.2 Альтернативы | D15: 8. Ключевые метрики | I15: 5. Каналы | J15: 1.2 Ранние последователи
B16: Битрикс 24 Excel Он-лайн табличный процессор Адванта (базовый запуск) Яндекс трекер Импортозамещается: Шарепоинт + ПроджектСервер + Локальный Проджект + MS BI | D16: Количество продаж; Количество пользователей в ГРМ; Количество отзывов | J16: Х продаж за первые 3 мес.; У продаж за вторые 3 мес.
B17: 7. Структура издержек | H17: 6. Потоки прибыли
B20: решение не сформулировано | D20: Не занимались | E20: 0 | G20: Что нужно доработать: | I20: Отчетность по ключевым вехам (как в ЦКБМ)
B21: решение сформулировано частично | D21: В работе | E21: 0.1 | I21: Механизм влияния рисков и других показателей (go, get, …) на расчет плановых данных
B22: решение сформулировано | D22: Техническая реализация | E22: 0.5 | I22: Интеграция с Битрикс24
D23: Базовая реализация (в т.ч. удобно) | E23: 0.8 | I23: Вехи в панели руководителя
D24: Глубокая реализация | E24: 1 | H24: Опция 2: | I24: Механизм автоматической актуализации плановых данных по бюджетам (плана по факту)
H26: Опции | I26: 1. вопрос Актуализации (без перевод всех планов в ручной режим. Это наше ключевое конкурентное преимущество и основа эффектов от автоматизации)
I27: 2. трансляция БДР в БДДС (не знаю сделана сейчас или нет, но на тот момент ее не было),
I28: 3. вопрос настроек трансляции в зависимости от договора (т.к. это влияет как раз на формирование ДДС)
B29: РАС Промблематика: | D29: Для кого: Генеральный директор (РПО) | I29: 4. ну и всеже работа с НДС у разных заказчиков с разными ставками. точно не знаю, но боюсь, что там сценарий не проверялся. сроков проекта
B30: 1. Большое кол-во разразненной информации по проектам, не понятно на что уделить внимание - ключевые показатели всегда перед глазами онлайн | D30: Исполнитель - РП | I30: 5. другие критичные задачи из бэклога очереди 2
B31: 1.1. Остутствие едиой среды ведения проектов - все ведут проекты по разному в разных инструментах
B32: 1.2. Остутсвие актуальной информации по проектам (на какой вехи/ кто за нее ответсвенный, попадаем ли в сроки, есть/нет ли рисков, подписаны ли акты, списание ДС. ) - тратим много времени на сбор акутальной информации | D32: Бизнес задача: Верхнеуровневый контроль состояния проектов реестра | I32: Равно БЗ 1 уровень ФД
B33: 1.3. РП Забывают внести данные - смотрим на ситуацию в прошлом
D34: Актуальная информация по реестру проектов в разрезе (анализ текущего состоянию проектов): | G34: Варианты оценки стоимости трансляции факта бюджетов в проетный контур и интеграций. Производственная оценка, без резервов
D35: КСГ проекта (актируемые этапы) план/факт сроков | G35: Вариант 1: | H35: 250 000 р + 2 недели к сроку проекта | I35: Трансляция данных первичных документов ERP+PM по основным хоз. операциям при налиции соответствующих аналитик учета | N35: может быть применим к Проекты и бюджеты под контролем при наличии соответствующих аналитик в документах
D36: Контрольных точек ( Проектные решения - ответственных за них) план/факт исполнения КТ | G36: Вариант 2: | H36: от 1500 000 р. От 2 месяцев | I36: Трансляция данных первичных документов ERP+PM по не стандартным хоз. операциям при налиции соответствующих аналитик учета
D37: Потенциальные риски Есть/нет наличие | I37: Подробная оценка по Варианту 1,2 по заполнению чек-листа: Чек-лист настройки правил трасляции из ERP в PM через Проектное бюджетирование: e1cib/data/Справочник.ВнутренниеДокументы?ref=8122000c295e34e311ef1e892acfb24d
D38: БДР и БДДС - План/факт | G38: Вариант 3: | H38: 250000 + 2 недели к сроку проекта | I38: Настройка типовых правил загрузки факта из БП 3.0 в PM (При их реализации в типовой и наличии соответсвующей детализации учета в Бухгалтерии, и готовности Бухгалтерии к интеграции в управленческими системами) | N38: может быть применим к Проекты и бюджеты под контролем при наличии соответствующих аналитик в документах
G39: Вариант 4: | H39: При разработке под Заказчика порядка 4-6 млн, срок 3 месяца | I39: НАИБОЛЕЕ вероятный, в реальной жизни: При неготовности учетной системы Заказчика (недостаточность аналитики в учете для автоматической перекладки данных правилами изи интеграцийе без двойного ввода) Необходимо прорабатывать рабочее место экономиста для корректного разнесения факта бюджетов по проектам вручную по данным отраженным в учете
D40: Факт и актуализация в ручном режиме
B44: сколько запросов под эту тематику за год было
B45: больше 2 млдр. Не Трудоемкое производство - 90 SQL
B46: как первый шаг на РМ5 для стандарт проектов - 119 SQL
B47: запросов какое количество было бы куплено
B48: больше 2 млдр. Не Трудоемкое производство - 19
B49: как первый шаг на РМ5 для стандарт проектов - 41
B50: какое количество заказчиков купило бы такое предложение из текущей воронки
B51: как первый шаг на РМ5 для стандарт проектов -98

Sheet КапСтрой и инвестиции
B2: Продукт | H2: Рынок
B3: 2.1 Проблема | D3: 4. Решение | E3: Связь | F3: =AVERAGE(F4:F19) -> #DIV/0! | G3: 3. Уникальная ценность (УТП) | I3: 9. Скрытое преимущество | J3: 1.1 Сегменты потребителей
B4: 1. Огромные инвестиции, которые требуют контроля. Пример: Северсталь - 100млрд инвест.программа. 1 ошибка в планировании проекта, которая привела на 1 день просрочки простаивания ресурсов может стоить в большом проекте десятки миллионов рублей. | D4: Прединвестиционная стадия | G4: Единственное отраслевое решение на 1С, адаптированное для кап.строя и инвестиций Автоматизация актуализация прогноза с учетом фактических данных, получение фактических данных из учетных систем на 1С Единое информационное пространство по управлению инвест.программой компании Своевременнная индикация критичных отклонений по срокам и бюджетам проектов Продуманная связка с учетными системами компании | I4: Опыт лидеров отрасли, заложенный в решение Быстрая интеграция с существующей корпоративной архитектурой Бизнес-модель | J4: Сегмент - Ultra 10млрд+, все отрасли - Директор по инвестициям - или может быть бюджетом конкретного проекта - директор этого проекта Событие? Необходимость отказа от управления проектами кап.строя в Excel: 1) Павртия сказала через 2 года отказаться и перейти на отчественные решения, а российский аналог Excel не тянет требуемый функционал 2) Очень сильная зависимость от конкретных людей - например, всю модель управления разработал 1 человек, который может уйти в любой момент
B5: 2. Очень длительные проекты - чем больше горизонт планирования, тем сложнее строить отчетность + больше параллельных проектов, больше ошибок в планировании | D5: Решение для исполнения инвест.программы (что-то написать, чтобы разрулить B9 2-е предложение)
B6: 3. Необходимость отказа от управления проектами кап.строя в Excel. Почему уходят: - российский аналог Excel не тянет требуемый функционал: ...(конкретика) б). Очень сильная зависимость от конкретных людей - например, всю модель управления разработал 1 человек, который может уйти в любой момент | D6: Решение для исполнения инвест.проекта
B7: 4. Внутреннее спокойствие ЛПРа. Людей много, много экселей, много денег, а управляемости не чувствуется. | D7: Особенности: -- 3 ключевых показателя - освоение бюджета (объемы), финансирование (БДДС) и ввод объекта в эксплуатацию (БДР).
B8: В любой момент убедиться, что все в порядке, сроки не срываются и не сорвутся, из бюджета не вышли и не выйдем. Нужен факт и прогноз. | D8: -- факторный анализ отклонений по бюджетам - из-за чего произошли отклонения
B9: Управление одним монопроектом бывает, но редко. Чаще будет - управление исполнением инвестиционной программы (состояние каждого проекта в отдельности и исполнение инвест.программы на год) | D9: -- распределение затрат на объекты разные схемы
D10: -- важная аналитика - объект
B11: Если есть отклонения - кто их источник - какой отдел, подрядчик, по какому договору, | D11: -- валютный учёт (столкнулись в 2-х проектах) - например, бюджет поехал потому что изменился курс валют
D12: -- много интеграций (но нас выручает шина 1С, можно показать на шине структуру интеграции)
D13: -- интеграция по УХ
D14: -- S-кривые с прогнозом освоения и финансирования
B21: 2.2 Альтернативы | D21: 8. Ключевые метрики | I21: 5. Каналы | J21: 1.2 Ранние последователи
B22: Планнер, РМ-софт Excel | D22: Количество продаж; Количество пользователей в ГРМ; Количество отзывов | J22: Запросы за последние месяцы: Новатек, Роснефть, Эфко, Таиф, Евраз, Мособлэнерго - по каждому есть демо-базы Х продаж за первые 3 мес.; У продаж за вторые 3 мес.
B23: 7. Структура издержек | H23: 6. Потоки прибыли
B26: решение не сформулировано | D26: Не занимались | E26: 0 | G26: Что нужно доработать:
B27: решение сформулировано частично | D27: В работе | E27: 0.1
B28: решение сформулировано | D28: Техническая реализация | E28: 0.5
D29: Базовая реализация (в т.ч. удобно) | E29: 0.8
D30: Глубокая реализация | E30: 1 | G30: Что нужно ОП для старта: демо-база, презентации.
B33: У Айтиленд богатый опыт работы с кап.строем. Но есть внутр. ограничение - оценка от 100млн. Между тем, задачи можно стандартизировать. Глеб понимает, как.
B34: Нюансы: есть ли потребность в автоматизации прединвестиционного этапа (фин.моделирование, инвестиции, заявки, ранжирование, инвест.проекты)? Или реализация?
B35: Опыт - часто показываем из девеломпента т.к. там много общего
B36: Особенности: -- 3 ключевых показателя - освоение бюджета, финансирование и ввод объекта в эксплуатацию. -- факторный анализ отклонений по бюджетам - из-за чего произошли отклонения -- распределение затрат на объекты разные схемы -- важная аналитика - объект -- валютный учёт (столкнулись в 2-х проектах) - например, бюджет поехал потому что изменился курс валют -- много интеграций (но нас выручает шина 1С, можно показать на шине структуру интеграции)
B37: Портфели и программы
B38: Тематическое планирование
B39: Проекты, паспорт, KPI
B40: Дорожные карты проектов (Gates)
B41: Календарно-сетевое планирование
B42: Проектное бюджетирование
B43: Объемы проектов
B44: Материалы и оборудование проектов
... B50: Расширение: Математическое нормирование
B51: Расширение: Тендерная работа | C51: Уже есть в УХ
B52: Расширение: Распределение затрат | C52: Важно!
B53: Расширение: Перепланирование с учетом факта

Sheet от Лены
B2: Крупный бизнес (Стандарт.проекты, заказные проекты)
B3: ЛПР | C3: Проблемы/ Боли/ Задачи За что ЛПР будет готов заплатить 1млн.+ руб.? | D3: Потери/ недополученная прибыль
B4: Финансовый директор | C4: №1 Предсказуемость и управляемость (Скорость и качество управленческих решений, возможность влиять на ситуацию) То, чт о раньше было просто - теперь стало сложно (отчетность). Нужно переходить от EXCEL - Куда-то. Куда пока не ясно. Сводные данные по конторе - есть и без нас. Шаг 1 - им нужна информация по маржинальности по подразделениям с возможностью провалиться до первички Шаг 2 - нужен переход от котлового учета, чтобы внутри подразделений видеть маржинальность до уровня направлений/ проектов | D4: Невозможно управлять маржинальностью, отсюда большие финансовые потери, низкая скорость реакции и неверные управленческие решения
C5: №2 Рост маржинальности портфеля проектов за счет управляемости - из-за сдвигов сроков и внеплановых затрат снижается маржинальность - Нет оценки проектов - При оценке маржинальности проектов не учитывается стоимость денег - … дополнить | D5: Не выполняется план по прибыли Большие финансовые потери Нет понимания, как выйти на желаемую прибыль
C6: №3 Актуальный бюджет и Прибыль организации - Бюджет теряет актуальность уже через 1-2 месяца т.к. ситуация на проектах меняется - Учетная система зачастую не содержит информации о перспективных объемов, их планируют общей суммой (серая зона = зона нехватки объемов), поэтому невозможно оценить прогресс контрактации и осуществимость этих планов. - подразделения не отвечают за прибыль, расходы растут, не понятно какие из них действительно нужны, а какие можно срезать - Инвестиционные расходы в итоге выше, чем прибыль организации | D6: Не выполняется план по прибыли Нет возможности повлиять на ситуацию, когда ещё можно Инвестиции превышают доходы компании или наоборот, упущенная выгода от того что не вложили в развитие
C7: №4 Предотвращение кассовых разрывов и контроль ликвидности (является прямым следствием маржинальности организации) - Из-за неактуальных данных кассовые разрывы чаще всего не видны - Из-за этого постоянно приходится "тушить пожары" - Что в свою очередь снижает рентабельность бизнеса | D7: Снижение маржинальности бизнеса (прибыли) из-за "внезапных" кассовых разрывов, погасить которые стоит дорого
C8: №5 Дефицит бюджета т.к. турбулентность на рынке, не выполняются планы по объемам
B9: Директор по производству | C9: №1 Регулярные срывы сроков по проектам и перерасход нормочасов - не можем вовремя увидеть, где есть отклонения по проекту и принять меры, часто принимаем интуитивные решения а не на основе цифр, Перерасход по нормочасам видим, когда исправить уже ничего нельзя - Нельзя сравнить проекты между собой. В итоге - не выстроить внятные контролируемые показатели - Разные подразделения не понимают кто что делает. Взаимодействуют через руководителя. В итоге- нарушена коммуникация участников внутри проекта. Ручное разруливание конфликтов лично руководителем - Специалисты на проектах делают то, что им удобно, а не то что нужно по графику В итоге - это ставит под угрозу срывы сроков на проектах | D9: Прямые финансовые потери на перерасходах. Условно: на проекте стоимостью 1млн.руб. потери могут составлять 200-300тыс.
C10: №2 Выполнение объемов: Не выполнить / непонимаю как выполнить план, который мне ставят, текущими ресурсами, а руководство настаивает - Нет взаимосвязей между разными проектами. Сложно проследить, как сдвиг сроков на одном проекте влияет на другой проект. В итоге - ситуации, когда люди перегружены и рарываются между проектами и мы не можем выполнить объем. - Нет синхронизации с планами по продажам. В итоге приходят выгодные контракты, которые мы не можем начать выполнять из-за нехватки мощности. - Не понимаем при старте проекта, выполним ли он в указанные сроки или нет. В итоге - берем проект, сроки все время на грани срывов. - Страдает качество и актуальность экономических и финансовых данных по проектной деятельности | D10: Не получается масштабировать
C11: №3 Не хвататет объемов, чтобы обеспечить загрузку сотрудников. Простои. | D11: Прямые убытки - ЗП платим, доходы снижаются, люди не загружены
C12: №4 Маржинальность портфеля проектов - Не понимаем, насколько необходимо делать все эти работы, которые списываем на проект - Не понимаем, насколько корректно мы оцениваем будущие проекты из-за кривой статистики - Не понимаем актуальную загрузку (свободную мощность подразделения, текущие трудовые резервы) - Понимаем, что есть недополученная прибыль, но за счет чего ее можно добиться - непонятно. - Каждый проект вынуждены выполнять как уникальный, несмотря на то, что есть "типовые задачи", как следствие проекты менее маржинальны | D12: Упущенная выгода. Прибыли можно получать больше!
C13: №5 Команда: Ключевые специалисты перегружены - "Бегство" ключевых специалистов из-за хаоса и выгорания
B14: Генеральный директор. | C14: 1. Прозрачность, управлемость порядок - Нет актуальной аналитики. Решения принимаются вслепую или на основе неактуальных данных. - Непредсказуемость сроков и хронические срывы сроков. | D14: - Потери от неправильных решений - неправильные решения ТОПового уровня ведут к Потери миллионов - авральный режим работы - упущенная выгода от Потери клиента - репутационные риски - вплодь до Потери бизнеса.
C15: 2. Повышение прибыльности/маржинальности бизнеса за счет повышения эффективности процессов и сокращения расходов - Неконтролируемые финансовые потери по проектам (из-за срыва сроков, перерасходов по трудозатратам, недоучтенным материалам >20-30%) - Рост накладных расходов | D15: Прямые финансовые потери на перерасходах. Условно: на проекте стоимостью 1млн.руб. потери могут составлять 200-300тыс.
C16: 3. Масштабирование бизнеса - брать больше проектов и не терять в качестве - Перегрузка ключевых сотрудников - Хаос в процессах. Нет регламентов, нормативов. Сотрудники делают что им хочется, а не то что нужно - Все проекты "индивидуальные", отсутсвует единая методология ведения проектов - Постоянные конфликты между отделами, парализующие работу (отдел продаж продает нереализуемое, производство не успевает, финансы блокируют все инициативы) | D16: - Нехватка квалифицированных кадров, не можем брать больше проектов - Мы не можем тиражировать успешные практики, теряем прибыль - Страдает качество и репутация
C17: 4. Выжить в условиях турбулентности. Сохранить прибыль. Не потерять команду.

Sheet Соло
B2: Продукт | H2: Рынок
B3: 2.1 Проблема | C3: =ROUND(AVERAGE(C4:C15)*100,0) -> 27 | D3: 4. Решение | E3: Связь | F3: =AVERAGE(F4:F15) -> 0.34545455 | G3: 3. Уникальная ценность (УТП) | I3: 9. Скрытое преимущество | J3: 1.1 Сегменты потребителей
B4: 1) Нет единой системы управления проектами и проектного документооборота (~MDR базовый) | C4: =AVERAGE(F5,F6) -> 0.25 | D4: Комплексная система по управлению проектом для РП, обеспечивающая: | G4: Комплексная система для РП по управлению проектами, ресурсами и финансами проектов, проектным документооборотом | I4: Интеграция с CRM-системой (УНФ или Б24); Возможность доработки; Облако-коробка. | J4: РП из проектного офиса под свои проекты, которому нужно передавать результаты заказчику, управлять на основе разнородных данных и формировать стандартизированную регулярную честную отчетность руководству. Увеличивается объем проектов, нужно автоматизировать рутинные операции, уменьшить к-во ошибок.
B5: 2) Тратится много времени на обмен печ.формами и реестрами с заказчиком/своей бухгалтерией. Нужно регистрировать такой вспомогательный документооборот и отслеживать его статусы в привязке к Проекту и этапу проекта. | C5: =F6 -> 0 | D5: =Решения!B16 -> Единообразное планирование проектов (План-график, трудозатраты, фин план) | E5: [1, 4] | F5: =Решения!C16 -> 0.5
B6: 3) Нет возможности полуавтоматической генерации отчетности по проекту заказчику/руководству. | C6: =AVERAGE(F7,F8, F9) -> 0.5 | D6: =Решения!B35 -> Проектный документооборот (~MDR базовый) (жизненный цикл основных проектных артефактов, указанных в ТЗ и договоре) | E6: [1, 2, 4] | F6: =Решения!C35 -> 0
B7: 4) Сложно организовать хранение разноплановых данных: этапы, сроки, документы, реестры, обязательства предконтрактной стадии и договорные суммы, ресурсы | C7: =AVERAGE(F5,F6, F14, F15) -> 0.325 | D7: =Решения!B7 -> Актуализация информации по проектам | E7: [3] | F7: =Решения!C7 -> 0.5
B8: 5) Нет удобной и надежной системы взаимодействия с исполнителями работ | C8: =AVERAGE(F12,F10, F11, F13) -> 0.25 | D8: =Решения!B57 -> Формирование отчетности по проектам | E8: [3] | F8: =Решения!C57 -> 0.5
D9: =Решения!B43 -> Статус-отчеты по проекту. От Фазы Пресейла до Завершения договора | E9: [3] | F9: =Решения!C43 -> 0.5
D10: =Решения!B15 -> Диспетчирование работ (поручения) | E10: [5] | F10: =Решения!C15 -> 0.5
D11: =Решения!B24 -> Канбан-доска | E11: [5] | F11: =Решения!C24 -> 0
D12: =Решения!B23 -> Интеграция с трекинг-системами | E12: [5] | F12: =Решения!C23 -> 0.5
D13: =Решения!B2 -> 1С:Взаимодействие | E13: [5] | F13: =Решения!C2 -> 0
D14: =Решения!B28 -> Многомерные проекты | E14: [4] | F14: =Решения!C28 -> 0.5
D15: =Решения!B27 -> Механизм укрупненной оценки проектов на структуре проекта с печатной формой (Обоснование стоимости проекта) | E15: [4] | F15: =Решения!C27 -> 0.3
B16: 2.2 Альтернативы | D16: 8. Ключевые метрики | I16: 5. Каналы | J16: 1.2 Ранние последователи
B17: MS Excel, MS Project, Трекинговые системы 1С:ДО (!!!) с доработками Б24 с доработками А2 (?) | D17: Количество продаж; Количество пользователей в ГРМ; Количество отзывов
B18: 7. Структура издержек | H18: 6. Потоки прибыли
A20: %
B21: решение не сформулировано | D21: Не занимались | E21: 0
B22: решение сформулировано частично | D22: В работе | E22: 0.1
B23: решение сформулировано | D23: Техническая реализация | E23: 0.5
D24: Базовая реализация (в т.ч. удобно) | E24: 0.8
D25: Глубокая реализация | E25: 1

Sheet Соло-М
B2: Продукт | H2: Рынок
B3: 2.1 Проблема | C3: =ROUND(AVERAGE(C4:C15)*100,0) -> 19 | D3: 4. Решение | E3: Связь | F3: =AVERAGE(F4:F17) -> 0.29230769 | G3: 3. Уникальная ценность (УТП) | I3: 9. Скрытое преимущество | J3: 1.1 Сегменты потребителей
B4: 1) Нет единой системы управления проектами и проектного документооборота (~MDR базовый) | C4: =AVERAGE(F5,F6) -> 0.25 | D4: Комплексная система по управлению проектом для РП, обеспечивающая: | G4: Комплексная система для РП по управлению проектами, ресурсами и финансами проектов, проектным документооборотом Сокращение простоев за счет планирования и анализа обеспеченности работ | I4: Интеграция с CRM-системой (УНФ или Б24); Возможность доработки; Облако-коробка. | J4: РП из проектного офиса под свои проекты, которому нужно передавать результаты заказчику, управлять на основе разнородных данных и формировать стандартизированную регулярную честную отчетность руководству. Увеличивается объем проектов, нужно автоматизировать рутинные операции, уменьшить к-во ошибок.
B5: 2) Тратится много времени на обмен печ.формами и реестрами с заказчиком/своей бухгалтерией. Нужно регистрировать такой вспомогательный документооборот и отслеживать его статусы в привязке к Проекту и этапу проекта. | C5: =F6 -> 0 | D5: =Решения!B16 -> Единообразное планирование проектов (План-график, трудозатраты, фин план) | E5: [1, 4] | F5: =Решения!C16 -> 0.5
B6: 3) Нет возможности полуавтоматической генерации отчетности по проекту заказчику/руководству. | C6: =AVERAGE(F7,F8, F9) -> 0.5 | D6: =Решения!B35 -> Проектный документооборот (~MDR базовый) (жизненный цикл основных проектных артефактов, указанных в ТЗ и договоре) | E6: [1, 2, 4] | F6: =Решения!C35 -> 0
B7: 4) Сложно организовать хранение разноплановых данных: этапы, сроки, документы, реестры, обязательства предконтрактной стадии и договорные суммы, ресурсы | C7: =AVERAGE(F5,F6, F14, F15) -> 0.325 | D7: =Решения!B7 -> Актуализация информации по проектам | E7: [3] | F7: =Решения!C7 -> 0.5
B8: 5) Нет удобной и надежной системы взаимодействия с исполнителями работ | C8: =AVERAGE(F12,F10, F11, F13) -> 0.25 | D8: =Решения!B57 -> Формирование отчетности по проектам | E8: [3] | F8: =Решения!C57 -> 0.5
B9: 6) Нет четкого понимания когда и какие ТМЦ будут нужны с учетом текущей ситуации по проекту | C9: =F16 -> 0 | D9: =Решения!B43 -> Статус-отчеты по проекту. От Фазы Пресейла до Завершения договора | E9: [3] | F9: =Решения!C43 -> 0.5
B10: 7) Нет данных какие работы обеспечены ТМЦ | C10: =F17 -> 0 | D10: =Решения!B15 -> Диспетчирование работ (поручения) | E10: [5] | F10: =Решения!C15 -> 0.5
D11: =Решения!B24 -> Канбан-доска | E11: [5] | F11: =Решения!C24 -> 0
D12: =Решения!B23 -> Интеграция с трекинг-системами | E12: [5] | F12: =Решения!C23 -> 0.5
D13: =Решения!B2 -> 1С:Взаимодействие | E13: [5] | F13: =Решения!C2 -> 0
D14: =Решения!B28 -> Многомерные проекты | E14: [4] | F14: =Решения!C28 -> 0.5
D15: =Решения!B27 -> Механизм укрупненной оценки проектов на структуре проекта с печатной формой (Обоснование стоимости проекта) | E15: [4] | F15: =Решения!C27 -> 0.3
D16: =Решения!B34 -> Привязка спецификаций к работам проекта | E16: [6] | F16: =Решения!C34 -> 0
D17: =Решения!B31 -> Отметка в работах проекта о наличии ТМЦ из спецификаций и смена статуса работ на "обеспеченные" | E17: [7] | F17: =Решения!C31 -> 0
B18: 2.2 Альтернативы | D18: 8. Ключевые метрики | I18: 5. Каналы | J18: 1.2 Ранние последователи
B19: MS Excel, MS Project, Трекинговые системы 1С:ДО (!!!) с доработками Б24 с доработками А2 (?) | D19: Количество продаж; Количество пользователей в ГРМ; Количество отзывов
B20: 7. Структура издержек | H20: 6. Потоки прибыли
B23: решение не сформулировано | D23: Не занимались | E23: 0
B24: решение сформулировано частично | D24: В работе | E24: 0.1
B25: решение сформулировано | D25: Техническая реализация | E25: 0.5
D26: Базовая реализация (в т.ч. удобно) | E26: 0.8
D27: Глубокая реализация | E27: 1

Sheet МикроГД
B2: Продукт | H2: Рынок
B3: 2.1 Проблема | C3: =ROUND(AVERAGE(C4:C11)*100,0) -> 43 | D3: 4. Решение | E3: Связь | F3: =AVERAGE(F4:F11) -> 0.45 | G3: 3. Уникальная ценность (УТП) | I3: 9. Скрытое преимущество | J3: 1.1 Сегменты потребителей
B4: 1) Не понятна рентабельность проектов | C4: =AVERAGE(F5,F6,F8) -> 0.53333333 | D4: =Решения!B54 -> Управление проектами | E4: [4] | F4: =Решения!C54 -> 0.5 | G4: Комплексные управление проектами, бюджетами и упр.учет в одной системе. Управление рентабельностью проектов и фирмы в целом. Сохранение/оптимизация баланса затрат и свободного/чистого денежного потока. Увеличение объемов/рентабельности через управление загрузкой, сроками и стоимостью. | I4: Многофирменный учет; Бесшовная интеграция с 1С (УНФ, БП); Облако-коробка; Возможность доработки. | J4: Небольшие проектные организации. ГД
B5: 2) Неравномерная рваная загрузка | C5: =AVERAGE(F7) -> 0.5 | D5: =Решения!B51 -> Упр.учет фирмы в разрезе подразделений, направлений, проектов | E5: [1] | F5: =Решения!C51 -> 0.8
B6: 3) Сложности устойчивого роста (с т.з. синхронного роста объемов и персонала) | C6: =F9 -> 0.5 | D6: =Решения!B27 -> Механизм укрупненной оценки проектов на структуре проекта с печатной формой (Обоснование стоимости проекта) | E6: [1] | F6: =Решения!C27 -> 0.3
B7: 4) Как сохранить контроль и прозрачность при делегировании | C7: =F4 -> 0.5 | D7: =Решения!B11 -> Балансировка объемов и минимизация ресурсных конфликтов | E7: [2, 6] | F7: =Решения!C11 -> 0.5
B8: 5) Кассовые разрывы (тогда и не обращаются) | C8: =F10 -> 0.5 | D8: =Решения!B5 -> Актуализация и балансировка фин.планов | E8: [1] | F8: =Решения!C5 -> 0.5
B9: 6) Сложное перераспределение специалистов по задачам проектов | C9: =F7 -> 0.5 | D9: =Решения!B55 -> Управление сводными планами | E9: [3] | F9: =Решения!C55 -> 0.5
B10: 7) Непонимание фронта работ, готовых к исполнению | C10: =F11 -> 0 | D10: =Решения!B10 -> Балансировка и минимизация кассовых разрывов | E10: [5] | F10: =Решения!C10 -> 0.5
D11: =Решения!B9 -> Анализ обеспеченности и формирование фронта работ | E11: [7] | F11: =Решения!C9 -> 0
B12: 2.2 Альтернативы | D12: 8. Ключевые метрики | I12: 5. Каналы | J12: 1.2 Ранние последователи
D13: Количество продаж; Количество пользователей в ГРМ; Количество отзывов | I13: Свои каналы 1C 1C:УНФ Где тусуются?
B14: 7. Структура издержек | H14: 6. Потоки прибыли
B17: решение не сформулировано | D17: Не занимались | E17: 0
B18: решение сформулировано частично | D18: В работе | E18: 0.1
B19: решение сформулировано | D19: Техническая реализация | E19: 0.5
D20: Базовая реализация (в т.ч. удобно) | E20: 0.8
D21: Глубокая реализация | E21: 1

Sheet МикроГД-М
B2: Продукт | H2: Рынок
B3: 2.1 Проблема | C3: =ROUND(AVERAGE(C4:C13)*100,0) -> 38 | D3: 4. Решение | F3: =AVERAGE(F4:F12) -> 0.4 | G3: 3. Уникальная ценность (УТП) | I3: 9. Скрытое преимущество | J3: 1.1 Сегменты потребителей
B4: 1) Не понятна рентабельность проектов | C4: =AVERAGE(F5,F6,F8) -> 0.53333333 | D4: =Решения!B54 -> Управление проектами | E4: [4] | F4: =Решения!C54 -> 0.5 | G4: Комплексные управление проектами, бюджетами и упр.учет в одной системе. Управление рентабельностью проектов и фирмы в целом. Сохранение/оптимизация баланса затрат и свободного/чистого денежного потока. Увеличение объемов/рентабельности через управление загрузкой, сроками и стоимостью. Сокращение простоев за счет планирования и анализа обеспеченности работ Повышение рентабельности за счет объединенных закупок | I4: Многофирменный учет; Бесшовная интеграция с 1С (УНФ, БП); Облако-коробка; Возможность доработки. | J4: Небольшие проектные организации со сборкой. ГД
B5: 2) Неравномерная рваная загрузка | C5: =AVERAGE(F7) -> 0.5 | D5: =Решения!B51 -> Упр.учет фирмы в разрезе подразделений, направлений, проектов | E5: [1] | F5: =Решения!C51 -> 0.8
B6: 3) Сложности устойчивого роста (с т.з. синхронного роста объемов и персонала) | C6: =F9 -> 0.5 | D6: =Решения!B27 -> Механизм укрупненной оценки проектов на структуре проекта с печатной формой (Обоснование стоимости проекта) | E6: [1] | F6: =Решения!C27 -> 0.3
B7: 4) Как сохранить контроль и прозрачность при делегировании | C7: =F4 -> 0.5 | D7: =Решения!B11 -> Балансировка объемов и минимизация ресурсных конфликтов | E7: [2, 6] | F7: =Решения!C11 -> 0.5
B8: 5) Кассовые разрывы (тогда и не обращаются) | C8: =F10 -> 0.5 | D8: =Решения!B5 -> Актуализация и балансировка фин.планов | E8: [1] | F8: =Решения!C5 -> 0.5
B9: 6) Сложное перераспределение специалистов по задачам проектов | C9: =F7 -> 0.5 | D9: =Решения!B55 -> Управление сводными планами | E9: [3] | F9: =Решения!C55 -> 0.5
B10: 7) Непонимание фронта работ, готовых к исполнению (в т.ч. обеспеченных ТМЦ) | C10: =F11 -> 0 | D10: =Решения!B10 -> Балансировка и минимизация кассовых разрывов | E10: [5] | F10: =Решения!C10 -> 0.5
B11: 8) Высокая трудоемкость и стоимость каждой отдельной закупки ТМЦ. Закупок очень много. | C11: =F12 -> 0 | D11: =Решения!B8 -> Анализ обеспеченности (в т.ч. ТМЦ) и формирование фронта работ | E11: [7] | F11: =Решения!C8 -> 0
D12: =Решения!B29 -> Объединенные закупки (лоты) | E12: [8] | F12: =Решения!C29 -> 0
B14: 2.2 Альтернативы | D14: 8. Ключевые метрики | I14: 5. Каналы | J14: 1.2 Ранние последователи
D15: Количество продаж; Количество пользователей в ГРМ; Количество отзывов | I15: Свои каналы 1C 1C:УНФ Где тусуются?
B16: 7. Структура издержек | H16: 6. Потоки прибыли
B19: решение не сформулировано | D19: Не занимались | E19: 0
B20: решение сформулировано частично | D20: В работе | E20: 0.1
B21: решение сформулировано | D21: Техническая реализация | E21: 0.5
D22: Базовая реализация (в т.ч. удобно) | E22: 0.8
D23: Глубокая реализация | E23: 1

Sheet МикроРП
B2: Продукт | H2: Рынок
B3: 2.1 Проблема | C3: =ROUND(AVERAGE(C4:C17)*100,0) -> 30 | D3: 4. Решение | E3: Связь | F3: =AVERAGE(F4:F17) -> 0.35384615 | G3: 3. Уникальная ценность (УТП) | I3: 9. Скрытое преимущество | J3: 1.1 Сегменты потребителей
B4: 1) Нет единой системы управления проектами и проектного документооборота (~MDR базовый) | C4: =AVERAGE(F5,F6) -> 0.25 | D4: Комплексная система по управлению проектом для РП, обеспечивающая: | G4: Комплексные управление проектами, бюджетами и упр.учет в одной системе. Управление рентабельностью проектов и фирмы в целом. Сохранение/оптимизация баланса затрат и свободного/чистого денежного потока. Увеличение объемов/рентабельности через управление загрузкой, сроками и стоимостью. | I4: Многофирменный учет; Бесшовная интеграция с 1С (УНФ, БП); Облако-коробка; Возможность доработки. | J4: Небольшие проектные организации. РП
B5: 2) Тратится много времени на обмен печ.формами и реестрами с заказчиком/своей бухгалтерией. Нужно регистрировать такой вспомогательный документооборот и отслеживать его статусы в привязке к Проекту и этапу проекта. | C5: =F6 -> 0 | D5: =Решения!B16 -> Единообразное планирование проектов (План-график, трудозатраты, фин план) | E5: [1, 4] | F5: =Решения!C16 -> 0.5
B6: 3) Нет возможности полуавтоматической генерации отчетности по проекту заказчику/руководству. | C6: =AVERAGE(F7,F8, F9) -> 0.5 | D6: =Решения!B35 -> Проектный документооборот (~MDR базовый) (жизненный цикл основных проектных артефактов, указанных в ТЗ и договоре) | E6: [1, 2, 4] | F6: =Решения!C35 -> 0
B7: 4) Сложно организовать хранение разноплановых данных: этапы, сроки, документы, реестры, обязательства предконтрактной стадии и договорные суммы, ресурсы | C7: =AVERAGE(F5,F6, F14, F15) -> 0.325 | D7: =Решения!B7 -> Актуализация информации по проектам | E7: [3] | F7: =Решения!C7 -> 0.5
B8: 5) Нет удобной и надежной системы взаимодействия с исполнителями работ | C8: =AVERAGE(F12,F10, F11, F13) -> 0.25 | D8: =Решения!B57 -> Формирование отчетности по проектам | E8: [3] | F8: =Решения!C57 -> 0.5
B9: 6) Не понятна рентабельность проекта | C9: =F16 -> 0.8 | D9: =Решения!B43 -> Статус-отчеты по проекту. От Фазы Пресейла до Завершения договора | E9: [3] | F9: =Решения!C43 -> 0.5
B10: 7) Нет понимания фронта работ, готовых к исполнению | C10: =AVERAGE(F17) -> 0 | D10: =Решения!B15 -> Диспетчирование работ (поручения) | E10: [5] | F10: =Решения!C15 -> 0.5
D11: =Решения!B24 -> Канбан-доска | E11: [5] | F11: =Решения!C24 -> 0
D12: =Решения!B23 -> Интеграция с трекинг-системами | E12: [5] | F12: =Решения!C23 -> 0.5
D13: =Решения!B2 -> 1С:Взаимодействие | E13: [5] | F13: =Решения!C2 -> 0
D14: =Решения!B28 -> Многомерные проекты | E14: [4] | F14: =Решения!C28 -> 0.5
D15: =Решения!B27 -> Механизм укрупненной оценки проектов на структуре проекта с печатной формой (Обоснование стоимости проекта) | E15: [4] | F15: =Решения!C27 -> 0.3
D16: =Решения!B51 -> Упр.учет фирмы в разрезе подразделений, направлений, проектов | E16: [6] | F16: =Решения!C51 -> 0.8
D17: =Решения!B9 -> Анализ обеспеченности и формирование фронта работ | E17: [7] | F17: =Решения!C9 -> 0
B18: 2.2 Альтернативы | D18: 8. Ключевые метрики | I18: 5. Каналы | J18: 1.2 Ранние последователи
D19: Количество продаж; Количество пользователей в ГРМ; Количество отзывов | I19: Свои каналы 1C 1C:УНФ Где тусуются?
B20: 7. Структура издержек | H20: 6. Потоки прибыли
B23: решение не сформулировано | D23: Не занимались | E23: 0
B24: решение сформулировано частично | D24: В работе | E24: 0.1
B25: решение сформулировано | D25: Техническая реализация | E25: 0.5
D26: Базовая реализация (в т.ч. удобно) | E26: 0.8
D27: Глубокая реализация | E27: 1

Sheet МикроРП-М
B2: Продукт | H2: Рынок
B3: 2.1 Проблема | C3: =ROUND(AVERAGE(C4:C17)*100,0) -> 37 | D3: 4. Решение | E3: Связь | F3: =AVERAGE(F4:F17) -> 0.35384615 | G3: 3. Уникальная ценность (УТП) | I3: 9. Скрытое преимущество | J3: 1.1 Сегменты потребителей
B4: 1) Нет единой системы управления проектами и проектного документооборота (~MDR базовый) | C4: =AVERAGE(F5,F6) -> 0.25 | D4: Комплексная система по управлению проектом для РП, обеспечивающая: | G4: Комплексные управление проектами, бюджетами и упр.учет в одной системе. Управление рентабельностью проектов и фирмы в целом. Сохранение/оптимизация баланса затрат и свободного/чистого денежного потока. Увеличение объемов/рентабельности через управление загрузкой, сроками и стоимостью. | I4: Многофирменный учет; Бесшовная интеграция с 1С (УНФ, БП); Облако-коробка; Возможность доработки. | J4: Небольшие проектные организации. РП
B5: 2) Тратится много времени на обмен печ.формами и реестрами с заказчиком/своей бухгалтерией. Нужно регистрировать такой вспомогательный документооборот и отслеживать его статусы в привязке к Проекту и этапу проекта. | C5: =F6 -> 0 | D5: =Решения!B16 -> Единообразное планирование проектов (План-график, трудозатраты, фин план) | E5: [1, 4] | F5: =Решения!C16 -> 0.5
B6: 3) Нет возможности полуавтоматической генерации отчетности по проекту заказчику/руководству. | C6: =AVERAGE(F7,F8, F9) -> 0.5 | D6: =Решения!B35 -> Проектный документооборот (~MDR базовый) (жизненный цикл основных проектных артефактов, указанных в ТЗ и договоре) | E6: [1, 2, 4] | F6: =Решения!C35 -> 0
B7: 4) Сложно организовать хранение разноплановых данных: этапы, сроки, документы, реестры, обязательства предконтрактной стадии и договорные суммы, ресурсы | C7: =AVERAGE(F5,F6, F14, F15) -> 0.325 | D7: =Решения!B7 -> Актуализация информации по проектам | E7: [3] | F7: =Решения!C7 -> 0.5
B8: 5) Нет удобной и надежной системы взаимодействия с исполнителями работ | C8: =AVERAGE(F12,F10, F11, F13) -> 0.25 | D8: =Решения!B57 -> Формирование отчетности по проектам | E8: [3] | F8: =Решения!C57 -> 0.5
B9: 6) Не понятна рентабельность проекта | C9: =F16 -> 0.8 | D9: =Решения!B43 -> Статус-отчеты по проекту. От Фазы Пресейла до Завершения договора | E9: [3] | F9: =Решения!C43 -> 0.5
B10: 7) Нет понимания фронта работ, готовых к исполнению | C10: =AVERAGE(F17) -> 0 | D10: =Решения!B15 -> Диспетчирование работ (поручения) | E10: [5] | F10: =Решения!C15 -> 0.5
B11: 8) Нет четкого понимания когда и какие ТМЦ будут нужны с учетом текущей ситуации по проекту | C11: =AVERAGE(F19,F18) -> 0.4 | D11: =Решения!B24 -> Канбан-доска | E11: [5] | F11: =Решения!C24 -> 0
B12: 9) Нет данных когда требуемые проекту ТМЦ поступят | C12: =F19 -> 0.8 | D12: =Решения!B23 -> Интеграция с трекинг-системами | E12: [5] | F12: =Решения!C23 -> 0.5
D13: =Решения!B2 -> 1С:Взаимодействие | E13: [5] | F13: =Решения!C2 -> 0
D14: =Решения!B28 -> Многомерные проекты | E14: [4] | F14: =Решения!C28 -> 0.5
D15: =Решения!B27 -> Механизм укрупненной оценки проектов на структуре проекта с печатной формой (Обоснование стоимости проекта) | E15: [4] | F15: =Решения!C27 -> 0.3
D16: =Решения!B51 -> Упр.учет фирмы в разрезе подразделений, направлений, проектов | E16: [6] | F16: =Решения!C51 -> 0.8
D17: =Решения!B8 -> Анализ обеспеченности (в т.ч. ТМЦ) и формирование фронта работ | E17: [7] | F17: =Решения!C8 -> 0
D18: =Решения!B34 -> Привязка спецификаций к работам проекта | E18: [8] | F18: =Решения!C34 -> 0
D19: =Решения!B40 -> Связь проектов, заказов поставщикам и факта поставки ТМЦ | E19: [8, 9] | F19: =Решения!C40 -> 0.8
B20: 2.2 Альтернативы | D20: 8. Ключевые метрики | I20: 5. Каналы | J20: 1.2 Ранние последователи
D21: Количество продаж; Количество пользователей в ГРМ; Количество отзывов | I21: Свои каналы 1C 1C:УНФ Где тусуются?
B22: 7. Структура издержек | H22: 6. Потоки прибыли
B25: решение не сформулировано | D25: Не занимались | E25: 0
B26: решение сформулировано частично | D26: В работе | E26: 0.1
B27: решение сформулировано | D27: Техническая реализация | E27: 0.5
D28: Базовая реализация (в т.ч. удобно) | E28: 0.8
D29: Глубокая реализация | E29: 1

Sheet МикроРСП
B2: Продукт | H2: Рынок
B3: 2.1 Проблема | C3: =ROUND(AVERAGE(C4:C10)*100,0) -> 32 | D3: 4. Решение | E3: Связь | F3: =AVERAGE(F4:F10) -> 0.32857143 | G3: 3. Уникальная ценность (УТП) | I3: 9. Скрытое преимущество | J3: 1.1 Сегменты потребителей
B4: 1) Не понятна рентабельность проектов | C4: =AVERAGE(F4,F6, F9) -> 0.43333333 | D4: =Решения!B50 -> Упр и ресурсный учет подразделения в разрезе проектов | E4: [1, 3] | F4: =Решения!C50 -> 0.5 | G4: Комплексные управление проектами, бюджетами и упр.учет в одной системе. Управление рентабельностью проектов и направления в целом. Увеличение объемов/ рентабельности через управление загрузкой, сроками и стоимостью. Сокращение простоев за счет планирования и анализа обеспеченности работ при интеграции с КИС. | I4: Многофирменный учет; Интеграция 1С:РМ с КИС на 1С; Облако-коробка; Возможность доработки. | J4: Небольшие проектные организации. Руководитель проектного подразделения
B5: 2) Неравномерная рваная загрузка | C5: =AVERAGE(F5) -> 0.5 | D5: =Решения!B11 -> Балансировка объемов и минимизация ресурсных конфликтов | E5: [2, 5] | F5: =Решения!C11 -> 0.5
B6: 3) Сложности в обосновании привлечения ресурсов (увеличение штата/ привлечение подрядчиков) | C6: =AVERAGE(F4) -> 0.5 | D6: =Решения!B5 -> Актуализация и балансировка фин.планов | E6: [1] | F6: =Решения!C5 -> 0.5
B7: 4) Не оплачиваются счета на оплату подрядчиков. | C7: =AVERAGE(F8) -> 0 | D7: =Решения!B9 -> Анализ обеспеченности и формирование фронта работ | E7: [7] | F7: =Решения!C9 -> 0
B8: 5) Сложное перераспределение специалистов по задачам проектов | C8: =F5 -> 0.5 | D8: =Решения!B21 -> Интеграция с КИС | E8: [4] | F8: =Решения!C21 -> 0
B9: 6) Насколько исполняются проекты подразделения. | C9: =F9 -> 0.3 | D9: =Решения!B27 -> Механизм укрупненной оценки проектов на структуре проекта с печатной формой (Обоснование стоимости проекта) | E9: [1] | F9: =Решения!C27 -> 0.3
B10: 7) Понимание фронта работ, готовых к исполнению | C10: =F7 -> 0 | D10: =Решения!B54 -> Управление проектами | E10: [6] | F10: =Решения!C54 -> 0.5
B11: 2.2 Альтернативы | D11: 8. Ключевые метрики | I11: 5. Каналы | J11: 1.2 Ранние последователи
D12: Количество продаж; Количество пользователей в ГРМ; Количество отзывов | I12: Свои каналы 1C Специализированные тематические площадки
B13: 7. Структура издержек | H13: 6. Потоки прибыли
B16: решение не сформулировано | D16: Не занимались | E16: 0
B17: решение сформулировано частично | D17: В работе | E17: 0.1
B18: решение сформулировано | D18: Техническая реализация | E18: 0.5
D19: Базовая реализация (в т.ч. удобно) | E19: 0.8
D20: Глубокая реализация | E20: 1

Sheet МикроРСП-М
B2: Продукт | H2: Рынок
B3: 2.1 Проблема | C3: =ROUND(AVERAGE(C4:C10)*100,0) -> 35 | D3: 4. Решение | E3: Связь | F3: =AVERAGE(F4:F10) -> 0.32857143 | G3: 3. Уникальная ценность (УТП) | I3: 9. Скрытое преимущество | J3: 1.1 Сегменты потребителей
B4: 1) Не понятна рентабельность проектов | C4: =AVERAGE(F4,F6, F9) -> 0.43333333 | D4: =Решения!B50 -> Упр и ресурсный учет подразделения в разрезе проектов | E4: [1, 3] | F4: =Решения!C50 -> 0.5 | G4: Комплексные управление проектами, бюджетами и упр.учет в одной системе. Управление рентабельностью проектов и направления в целом. Увеличение объемов/ рентабельности через управление загрузкой, сроками и стоимостью. Сокращение простоев за счет планирования и анализа обеспеченности работ при интеграции с КИС. | I4: Многофирменный учет; Интеграция 1С:РМ с КИС на 1С; Облако-коробка; Возможность доработки. | J4: Небольшие проектные организации. Руководитель проектного подразделения
B5: 2) Неравномерная рваная загрузка | C5: =AVERAGE(F5) -> 0.5 | D5: =Решения!B11 -> Балансировка объемов и минимизация ресурсных конфликтов | E5: [2, 5] | F5: =Решения!C11 -> 0.5
B6: 3) Сложности в обосновании привлечения ресурсов (увеличение штата/ привлечение подрядчиков) | C6: =AVERAGE(F4) -> 0.5 | D6: =Решения!B5 -> Актуализация и балансировка фин.планов | E6: [1] | F6: =Решения!C5 -> 0.5
B7: 4) Не оплачиваются счета на оплату подрядчиков. | C7: =AVERAGE(F8) -> 0 | D7: =Решения!B8 -> Анализ обеспеченности (в т.ч. ТМЦ) и формирование фронта работ | E7: [7] | F7: =Решения!C9 -> 0
B8: 5) Сложное перераспределение специалистов по задачам проектов | C8: =F5 -> 0.5 | D8: =Решения!B21 -> Интеграция с КИС | E8: [4] | F8: =Решения!C21 -> 0
B9: 6) Насколько исполняются проекты подразделения. | C9: =F10 -> 0.5 | D9: =Решения!B27 -> Механизм укрупненной оценки проектов на структуре проекта с печатной формой (Обоснование стоимости проекта) | E9: [1] | F9: =Решения!C27 -> 0.3
B10: 7) Понимание фронта работ, готовых к исполнению | C10: =F7 -> 0 | D10: =Решения!B54 -> Управление проектами | E10: [6] | F10: =Решения!C54 -> 0.5
B11: 8) Нет данных когда требуемые проекту ТМЦ поступят | C11: =F11 -> 0.8 | D11: =Решения!B40 -> Связь проектов, заказов поставщикам и факта поставки ТМЦ | E11: [8] | F11: =Решения!C40 -> 0.8
B12: 2.2 Альтернативы | D12: 8. Ключевые метрики | I12: 5. Каналы | J12: 1.2 Ранние последователи
D13: Количество продаж; Количество пользователей в ГРМ; Количество отзывов | I13: Свои каналы 1C Специализированные тематические площадки
B14: 7. Структура издержек | H14: 6. Потоки прибыли
B17: решение не сформулировано | D17: Не занимались | E17: 0
B18: решение сформулировано частично | D18: В работе | E18: 0.1
B19: решение сформулировано | D19: Техническая реализация | E19: 0.5
D20: Базовая реализация (в т.ч. удобно) | E20: 0.8
D21: Глубокая реализация | E21: 1

Sheet Мал1-2ГД
B2: Продукт | H2: Рынок
B3: 2.1 Проблема | C3: =ROUND(AVERAGE(C4:C8)*100,0) -> 46 | D3: 4. Решение | E3: Связь | F3: =AVERAGE(F4:F8) -> 0.46 | G3: 3. Уникальная ценность (УТП) | I3: 9. Скрытое преимущество | J3: 1.1 Сегменты потребителей
B4: 1) Не понятна рентабельность (подразделений/ направлений) | C4: =F4 -> 0.8 | D4: =Решения!B51 -> Упр.учет фирмы в разрезе подразделений, направлений, проектов | E4: [1] | F4: =Решения!C51 -> 0.8 | G4: Комплексные управление бюджетами и упр.учет в одной системе. Управление рентабельностью подразделений/направлений/организации. Сохранение/оптимизация баланса затрат и свободного/чистого денежного потока. Увеличение объемов/рентабельности через управление загрузкой, сроками и стоимостью. | I4: Многофирменный учет; Бесшовная интеграция с 1С; Возможность самостоятельной доработки; Облако-коробка (размещение на своих серверах). | J4: Малые проектные фирмы. ГД
B5: 2) Сложности устойчивого роста (с т.з. синхронного роста объемов, обеспеченности заказами и персонала) | C5: =F5 -> 0.5 | D5: =Решения!B55 -> Управление сводными планами | E5: [2] | F5: =Решения!C55 -> 0.5
B6: 3) На все ли открывшиеся возможности хватит денег | C6: =F6 -> 0.5 | D6: =Решения!B13 -> Бюджеты для финансирования возможностей | E6: [3] | F6: =Решения!C13 -> 0.5
B7: 4) Как сохранить прозрачность и контроль при делегировании | C7: =F7 -> 0.5 | D7: =Решения!B54 -> Управление проектами | E7: [4] | F7: =Решения!C54 -> 0.5
B8: 5) Отсутствие передачи лучших практик между направлениями | C8: =F8 -> 0 | D8: =Решения!B47 -> Тиражирование технологий управления на все направления | E8: [5] | F8: =Решения!C47 -> 0
B9: 2.2 Альтернативы | D9: 8. Ключевые метрики | I9: 5. Каналы | J9: 1.2 Ранние последователи
D10: Количество продаж; Количество отзывов | I10: Свои каналы 1C 1C:УНФ
B11: 7. Структура издержек | H11: 6. Потоки прибыли
B14: решение не сформулировано | D14: Не занимались | E14: 0
B15: решение сформулировано частично | D15: В работе | E15: 0.1
B16: решение сформулировано | D16: Техническая реализация | E16: 0.5
D17: Базовая реализация (в т.ч. удобно) | E17: 0.8
D18: Глубокая реализация | E18: 1

Sheet Мал1-2ФД
B2: Продукт | H2: Рынок
B3: 2.1 Проблема | C3: =ROUND(AVERAGE(C4:C7)*100,0) -> 58 | D3: 4. Решение | E3: Связь | F3: =AVERAGE(F4:F7) -> 0.575 | G3: 3. Уникальная ценность (УТП) | I3: 9. Скрытое преимущество | J3: 1.1 Сегменты потребителей
B4: 1) Сводный бюджет организации не актуализируется по изменениям сводного плана. Нет инфо об изменениях в проектах. | C4: =AVERAGE(F4, F5) -> 0.5 | D4: =Решения!B39 -> Сводная картина по экономике фирмы и ден.потоку на основании актуального сводного плана и плана инвестиций | E4: [1, 2] | F4: =Решения!C39 -> 0.5 | G4: Сводная картина по экономике организации и ден.потоку на основании актуального сводного плана и плана инвестиций. При изменении любой сущности все пересчитывается, т.к. взаимосвязано. | I4: Многофирменный учет; Бесшовная интеграция с 1С; Возможность самостоятельной доработки; Облако-коробка (размещение на своих серверах). | J4: Малые проектные фирмы. ФД
B5: 2) Кассовые разрывы из-за п.1 и больших инвестиций. | C5: =F4 -> 0.5 | D5: =Решения!B7 -> Актуализация информации по проектам | E5: [1] | F5: =Решения!C7 -> 0.5
B6: 3) Котловой учет себестоимости, нет инструмента для управления рентабельностью проектов/подразделений/направлений. | C6: =F7 -> 0.8 | D6: =Решения!B32 -> Платежный календарь | E6: [4] | F6: =Решения!C32 -> 0.5
B7: 4) Платежный календарь верстается вручную в XLS. Заявки ходят по почте. | C7: =F6 -> 0.5 | D7: =Решения!B51 -> Упр.учет фирмы в разрезе подразделений, направлений, проектов | E7: [3] | F7: =Решения!C51 -> 0.8
B8: 2.2 Альтернативы | D8: 8. Ключевые метрики | I8: 5. Каналы | J8: 1.2 Ранние последователи
B9: 1C:УНФ с доработками 1С:Бит.Финанс с доработками Б24 с доработками | D9: Количество продаж; Количество отзывов | I9: Свои каналы 1C 1C:УНФ
B10: 7. Структура издержек | H10: 6. Потоки прибыли
B13: решение не сформулировано | D13: Не занимались | E13: 0
B14: решение сформулировано частично | D14: В работе | E14: 0.1
B15: решение сформулировано | D15: Техническая реализация | E15: 0.5
D16: Базовая реализация (в т.ч. удобно) | E16: 0.8
D17: Глубокая реализация | E17: 1

Sheet Мал1РН
B2: Продукт | H2: Рынок
B3: 2.1 Проблема | C3: =ROUND(AVERAGE(C4:C11)*100,0) -> 37 | D3: 4. Решение | E3: Связь | F3: =AVERAGE(F4:F11) -> 0.2875 | G3: 3. Уникальная ценность (УТП) | I3: 9. Скрытое преимущество | J3: 1.1 Сегменты потребителей
B4: 1) Нужна система мониторинга производственной деятельности, синхронизированная с планами по проектам, объемам и по ресурсам | C4: =AVERAGE(F4, F5) -> 0.25 | D4: =Решения!B21 -> Интеграция с КИС | E4: [1] | F4: =Решения!C21 -> 0 | G4: Система мониторинга производственной деятельности, синхронизированная с планами по проектам, объемам и по ресурсам. Управление загрузкой, сроками и стоимостью по проектам портфеля для увеличения объемов/рентабельности. | I4: Возможность самостоятельной доработки. ??? | J4: Малые проектные фирмы. Руководители направления (не влияют на покупку системы).
B5: 2) Сложности устойчивого роста | C5: =AVERAGE(C6, C7, C8, C9, C10) -> 0.39333333 | D5: =Решения!B41 -> Синхронизация мониторинга производственной деятельности с планами по проектам, объемам и по ресурсам | E5: [1] | F5: =Решения!C41 -> 0.5
B6: 2.1) с т.з. синхронного роста объемов и персонала | C6: =AVERAGE(F6) -> 0.5 | D6: =Решения!B11 -> Балансировка объемов и минимизация ресурсных конфликтов | E6: [2.1, 2.2] | F6: =Решения!C11 -> 0.5
B7: 2.2) Неравномерная рваная загрузка (не скажут об этом) | C7: =AVERAGE(F6) -> 0.5 | D7: =Решения!B27 -> Механизм укрупненной оценки проектов на структуре проекта с печатной формой (Обоснование стоимости проекта) | E7: [2.4] | F7: =Решения!C27 -> 0.3
B8: 2.3) Несогласованность возможностей производственных направлений и планов продаж | C8: =AVERAGE(F11) -> 0.5 | D8: =Решения!B49 -> Трехуровневое ресурсное планирование с прогнозами | E8: [2.5] | F8: =Решения!C49 -> 0
B9: 2.4) Требуется сокращение сроков и повышение точности предварительной оценки проектов | C9: =AVERAGE(F7) -> 0.3 | D9: =Решения!B26 -> Контроль качества и применимость ресурсов (компетенции, квалификации) | E9: [2.5] | F9: =Решения!C26 -> 0
B10: 2.5) Нужно зрелое ресурсное линейно-функциональное/ проектное управление. | C10: =AVERAGE(F8, F9, F10) -> 0.16666667 | D10: =Решения!B14 -> Влияние производительности ресурсов на трудоемкость и сроки | E10: [2.5] | F10: =Решения!C14 -> 0.5
D11: =Решения!B46 -> Темплан, включая планирование объемов актирования по контрактации (без самой контрактации) | E11: [2.3] | F11: =Решения!C46 -> 0.5
B12: 2.2 Альтернативы | D12: 8. Ключевые метрики | I12: 5. Каналы | J12: 1.2 Ранние последователи
D13: Количество продаж; Количество отзывов
B14: 7. Структура издержек | H14: 6. Потоки прибыли
B17: решение не сформулировано | D17: Не занимались | E17: 0
B18: решение сформулировано частично | D18: В работе | E18: 0.1
B19: решение сформулировано | D19: Техническая реализация | E19: 0.5
D20: Базовая реализация (в т.ч. удобно) | E20: 0.8
D21: Глубокая реализация | E21: 1

Sheet Мал1РН-М
B2: Продукт | H2: Рынок
B3: 2.1 Проблема | C3: =ROUND(AVERAGE(C4:C11)*100,0) -> 36 | D3: 4. Решение | E3: Связь | F3: =AVERAGE(F4:F11) -> 0.2875 | G3: 3. Уникальная ценность (УТП) | I3: 9. Скрытое преимущество | J3: 1.1 Сегменты потребителей
B4: 1) Нужна система мониторинга производственной деятельности, синхронизированная с планами по проектам, объемам и по ресурсам | C4: =AVERAGE(F4, F5) -> 0.25 | D4: =Решения!B21 -> Интеграция с КИС | E4: [1, 2.6] | F4: =Решения!C21 -> 0 | G4: Система мониторинга производственной деятельности, синхронизированная с планами по проектам, объемам и по ресурсам. Управление загрузкой, сроками и стоимостью по проектам портфеля для увеличения объемов/рентабельности. Сокращение простоев за счет планирования и анализа обеспеченности работ | I4: Возможность самостоятельной доработки. ??? | J4: Малые проектные фирмы. Руководители направления (не влияют на покупку системы).
B5: 2) Сложности устойчивого роста | C5: =AVERAGE(C6, C7, C8, C9, C10) -> 0.39333333 | D5: =Решения!B41 -> Синхронизация мониторинга производственной деятельности с планами по проектам, объемам и по ресурсам | E5: [1] | F5: =Решения!C41 -> 0.5
B6: 2.1) с т.з. синхронного роста объемов и персонала | C6: =AVERAGE(F6) -> 0.5 | D6: =Решения!B11 -> Балансировка объемов и минимизация ресурсных конфликтов | E6: [2.1, 2.2] | F6: =Решения!C11 -> 0.5
B7: 2.2) Неравномерная рваная загрузка (не скажут об этом) | C7: =AVERAGE(F6) -> 0.5 | D7: =Решения!B27 -> Механизм укрупненной оценки проектов на структуре проекта с печатной формой (Обоснование стоимости проекта) | E7: [2.4] | F7: =Решения!C27 -> 0.3
B8: 2.3) Несогласованность возможностей производственных направлений и планов продаж | C8: =AVERAGE(F11) -> 0.5 | D8: =Решения!B49 -> Трехуровневое ресурсное планирование с прогнозами | E8: [2.5, 2.6] | F8: =Решения!C49 -> 0
B9: 2.4) Требуется сокращение сроков и повышение точности предварительной оценки проектов | C9: =AVERAGE(F7) -> 0.3 | D9: =Решения!B26 -> Контроль качества и применимость ресурсов (компетенции, квалификации) | E9: [2.5] | F9: =Решения!C26 -> 0
B10: 2.5) Нужно зрелое ресурсное линейно-функциональное/ проектное управление. | C10: =AVERAGE(F8, F9, F10) -> 0.16666667 | D10: =Решения!B14 -> Влияние производительности ресурсов на трудоемкость и сроки | E10: [2.5] | F10: =Решения!C14 -> 0.5
B11: 2.6) Понимание фронта работ, готовых к исполнению (в т.ч. обеспеченных ТМЦ) | C11: =AVERAGE(F4, F8, F12) -> 0.26666667 | D11: =Решения!B46 -> Темплан, включая планирование объемов актирования по контрактации (без самой контрактации) | E11: [2.3] | F11: =Решения!C46 -> 0.5
B12: 3) Высокая трудоемкость и стоимость каждой отдельной закупки ТМЦ. Закупок очень много. | C12: =AVERAGE(F13) -> 0 | D12: =Решения!B40 -> Связь проектов, заказов поставщикам и факта поставки ТМЦ | E12: [2.6] | F12: =Решения!C40 -> 0.8
D13: =Решения!B29 -> Объединенные закупки (лоты) | E13: [3] | F13: =Решения!C29 -> 0
B14: 2.2 Альтернативы | D14: 8. Ключевые метрики | I14: 5. Каналы | J14: 1.2 Ранние последователи
D15: Количество продаж; Количество отзывов
B16: 7. Структура издержек | H16: 6. Потоки прибыли
B19: решение не сформулировано | D19: Не занимались | E19: 0
B20: решение сформулировано частично | D20: В работе | E20: 0.1
B21: решение сформулировано | D21: Техническая реализация | E21: 0.5
D22: Базовая реализация (в т.ч. удобно) | E22: 0.8
D23: Глубокая реализация | E23: 1

Sheet Мал1-2РП
B2: Продукт | H2: Рынок
B3: 2.1 Проблема | C3: =ROUND(AVERAGE(C4:C17)*100,0) -> 30 | D3: 4. Решение | E3: Связь | F3: =AVERAGE(F4:F17) -> 0.35384615 | G3: 3. Уникальная ценность (УТП) | I3: 9. Скрытое преимущество | J3: 1.1 Сегменты потребителей
B4: 1) Нет единой системы управления проектами и проектного документооборота (~MDR базовый) | C4: =AVERAGE(F5,F6) -> 0.25 | D4: Комплексная система по управлению проектом для РП, обеспечивающая: | G4: Комплексные управление проектами, бюджетами и упр.учет в одной системе. Управление рентабельностью проектов и фирмы в целом. Сохранение/оптимизация баланса затрат и свободного/чистого денежного потока. Увеличение объемов/рентабельности через управление загрузкой, сроками и стоимостью. | I4: Многофирменный учет; Бесшовная интеграция с 1С (УНФ, БП); Облако-коробка; Возможность доработки. | J4: Малые проектные организации. РП
B5: 2) Тратится много времени на обмен печ.формами и реестрами с заказчиком/своей бухгалтерией. Нужно регистрировать такой вспомогательный документооборот и отслеживать его статусы в привязке к Проекту и этапу проекта. | C5: =F6 -> 0 | D5: =Решения!B16 -> Единообразное планирование проектов (План-график, трудозатраты, фин план) | E5: [1, 4] | F5: =Решения!C16 -> 0.5
B6: 3) Нет возможности полуавтоматической генерации отчетности по проекту заказчику/руководству. | C6: =AVERAGE(F7,F8, F9) -> 0.5 | D6: =Решения!B35 -> Проектный документооборот (~MDR базовый) (жизненный цикл основных проектных артефактов, указанных в ТЗ и договоре) | E6: [1, 2, 4] | F6: =Решения!C35 -> 0
B7: 4) Сложно организовать хранение разноплановых данных: этапы, сроки, документы, реестры, обязательства предконтрактной стадии и договорные суммы, ресурсы | C7: =AVERAGE(F5,F6, F14, F15) -> 0.325 | D7: =Решения!B7 -> Актуализация информации по проектам | E7: [3] | F7: =Решения!C7 -> 0.5
B8: 5) Нет удобной и надежной системы взаимодействия с исполнителями работ | C8: =AVERAGE(F12,F10, F11, F13) -> 0.25 | D8: =Решения!B57 -> Формирование отчетности по проектам | E8: [3] | F8: =Решения!C57 -> 0.5
B9: 6) Не понятна рентабельность проекта | C9: =F16 -> 0.8 | D9: =Решения!B43 -> Статус-отчеты по проекту. От Фазы Пресейла до Завершения договора | E9: [3] | F9: =Решения!C43 -> 0.5
B10: 7) Нет понимания фронта работ, готовых к исполнению | C10: =AVERAGE(F17) -> 0 | D10: =Решения!B15 -> Диспетчирование работ (поручения) | E10: [5] | F10: =Решения!C15 -> 0.5
D11: =Решения!B24 -> Канбан-доска | E11: [5] | F11: =Решения!C24 -> 0
D12: =Решения!B23 -> Интеграция с трекинг-системами | E12: [5] | F12: =Решения!C23 -> 0.5
D13: =Решения!B2 -> 1С:Взаимодействие | E13: [5] | F13: =Решения!C2 -> 0
D14: =Решения!B28 -> Многомерные проекты | E14: [4] | F14: =Решения!C28 -> 0.5
D15: =Решения!B27 -> Механизм укрупненной оценки проектов на структуре проекта с печатной формой (Обоснование стоимости проекта) | E15: [4] | F15: =Решения!C27 -> 0.3
D16: =Решения!B51 -> Упр.учет фирмы в разрезе подразделений, направлений, проектов | E16: [6] | F16: =Решения!C51 -> 0.8
D17: =Решения!B9 -> Анализ обеспеченности и формирование фронта работ | E17: [7] | F17: =Решения!C9 -> 0
B18: 2.2 Альтернативы | D18: 8. Ключевые метрики | I18: 5. Каналы | J18: 1.2 Ранние последователи
D19: Количество продаж; Количество пользователей в ГРМ; Количество отзывов | I19: Свои каналы 1C 1C:УНФ Где тусуются?
B20: 7. Структура издержек | H20: 6. Потоки прибыли
B23: решение не сформулировано | D23: Не занимались | E23: 0
B24: решение сформулировано частично | D24: В работе | E24: 0.1
B25: решение сформулировано | D25: Техническая реализация | E25: 0.5
D26: Базовая реализация (в т.ч. удобно) | E26: 0.8
D27: Глубокая реализация | E27: 1

Sheet Мал1-2РП-М
B2: Продукт | H2: Рынок
B3: 2.1 Проблема | C3: =ROUND(AVERAGE(C4:C17)*100,0) -> 37 | D3: 4. Решение | E3: Связь | F3: =AVERAGE(F4:F17) -> 0.35384615 | G3: 3. Уникальная ценность (УТП) | I3: 9. Скрытое преимущество | J3: 1.1 Сегменты потребителей
B4: 1) Нет единой системы управления проектами и проектного документооборота (~MDR базовый) | C4: =AVERAGE(F5,F6) -> 0.25 | D4: Комплексная система по управлению проектом для РП, обеспечивающая: | G4: Комплексные управление проектами, бюджетами и упр.учет в одной системе. Управление рентабельностью проектов и фирмы в целом. Сохранение/оптимизация баланса затрат и свободного/чистого денежного потока. Увеличение объемов/рентабельности через управление загрузкой, сроками и стоимостью. | I4: Многофирменный учет; Бесшовная интеграция с 1С (УНФ, БП); Облако-коробка; Возможность доработки. | J4: Малые проектные организации. РП
B5: 2) Тратится много времени на обмен печ.формами и реестрами с заказчиком/своей бухгалтерией. Нужно регистрировать такой вспомогательный документооборот и отслеживать его статусы в привязке к Проекту и этапу проекта. | C5: =F6 -> 0 | D5: =Решения!B16 -> Единообразное планирование проектов (План-график, трудозатраты, фин план) | E5: [1, 4] | F5: =Решения!C16 -> 0.5
B6: 3) Нет возможности полуавтоматической генерации отчетности по проекту заказчику/руководству. | C6: =AVERAGE(F7,F8, F9) -> 0.5 | D6: =Решения!B35 -> Проектный документооборот (~MDR базовый) (жизненный цикл основных проектных артефактов, указанных в ТЗ и договоре) | E6: [1, 2, 4] | F6: =Решения!C35 -> 0
B7: 4) Сложно организовать хранение разноплановых данных: этапы, сроки, документы, реестры, обязательства предконтрактной стадии и договорные суммы, ресурсы | C7: =AVERAGE(F5,F6, F14, F15) -> 0.325 | D7: =Решения!B7 -> Актуализация информации по проектам | E7: [3] | F7: =Решения!C7 -> 0.5
B8: 5) Нет удобной и надежной системы взаимодействия с исполнителями работ | C8: =AVERAGE(F12,F10, F11, F13) -> 0.25 | D8: =Решения!B57 -> Формирование отчетности по проектам | E8: [3] | F8: =Решения!C57 -> 0.5
B9: 6) Не понятна рентабельность проекта | C9: =F16 -> 0.8 | D9: =Решения!B43 -> Статус-отчеты по проекту. От Фазы Пресейла до Завершения договора | E9: [3] | F9: =Решения!C43 -> 0.5
B10: 7) Нет понимания фронта работ, готовых к исполнению | C10: =AVERAGE(F17) -> 0 | D10: =Решения!B15 -> Диспетчирование работ (поручения) | E10: [5] | F10: =Решения!C15 -> 0.5
B11: 8) Нет четкого понимания когда и какие ТМЦ будут нужны с учетом текущей ситуации по проекту | C11: =AVERAGE(F19,F18) -> 0.4 | D11: =Решения!B24 -> Канбан-доска | E11: [5] | F11: =Решения!C24 -> 0
B12: 9) Нет данных когда требуемые проекту ТМЦ поступят | C12: =F19 -> 0.8 | D12: =Решения!B23 -> Интеграция с трекинг-системами | E12: [5] | F12: =Решения!C23 -> 0.5
D13: =Решения!B2 -> 1С:Взаимодействие | E13: [5] | F13: =Решения!C2 -> 0
D14: =Решения!B28 -> Многомерные проекты | E14: [4] | F14: =Решения!C28 -> 0.5
D15: =Решения!B27 -> Механизм укрупненной оценки проектов на структуре проекта с печатной формой (Обоснование стоимости проекта) | E15: [4] | F15: =Решения!C27 -> 0.3
D16: =Решения!B51 -> Упр.учет фирмы в разрезе подразделений, направлений, проектов | E16: [6] | F16: =Решения!C51 -> 0.8
D17: =Решения!B8 -> Анализ обеспеченности (в т.ч. ТМЦ) и формирование фронта работ | E17: [7] | F17: =Решения!C8 -> 0
D18: =Решения!B34 -> Привязка спецификаций к работам проекта | E18: [8] | F18: =Решения!C34 -> 0
D19: =Решения!B40 -> Связь проектов, заказов поставщикам и факта поставки ТМЦ | E19: [8, 9] | F19: =Решения!C40 -> 0.8
B20: 2.2 Альтернативы | D20: 8. Ключевые метрики | I20: 5. Каналы | J20: 1.2 Ранние последователи
D21: Количество продаж; Количество пользователей в ГРМ; Количество отзывов | I21: Свои каналы 1C 1C:УНФ Где тусуются?
B22: 7. Структура издержек | H22: 6. Потоки прибыли
B25: решение не сформулировано | D25: Не занимались | E25: 0
B26: решение сформулировано частично | D26: В работе | E26: 0.1
B27: решение сформулировано | D27: Техническая реализация | E27: 0.5
D28: Базовая реализация (в т.ч. удобно) | E28: 0.8
D29: Глубокая реализация | E29: 1

Sheet Мал2ППО
B2: Продукт | H2: Рынок
B3: 2.1 Проблема | C3: =ROUND(AVERAGE(C4,C6:C12)*100,0) -> 30 | D3: 4. Решение | E3: Связь | F3: =AVERAGE(F4:F15) -> 0.25454545 | G3: 3. Уникальная ценность (УТП) | I3: 9. Скрытое преимущество | J3: 1.1 Сегменты потребителей
B4: 1) Нужна система мониторинга производственной деятельности, синхронизированная с планами по проектам, объемам и по ресурсам | C4: =AVERAGE(F4, F5) -> 0.25 | D4: =Решения!B21 -> Интеграция с КИС | E4: [1] | F4: =Решения!C21 -> 0 | G4: Система мониторинга производственной деятельности, синхронизированная с планами по проектам, объемам и по ресурсам. Управление загрузкой, сроками и стоимостью по проектам портфеля для увеличения объемов/рентабельности. | I4: Возможность самостоятельной доработки. ??? | J4: Малые проектные фирмы. Дир по производству (РПО, ГИ+ППО).
B5: 2) Сложности устойчивого роста | C5: =AVERAGE(C6, C7, C8, C9, C10) -> 0.385 | D5: =Решения!B41 -> Синхронизация мониторинга производственной деятельности с планами по проектам, объемам и по ресурсам | E5: [1] | F5: =Решения!C41 -> 0.5
B6: 2.1) с т.з. синхронного роста объемов и персонала | C6: =AVERAGE(F6) -> 0.5 | D6: =Решения!B11 -> Балансировка объемов и минимизация ресурсных конфликтов | E6: [2.1, 2.2] | F6: =Решения!C11 -> 0.5
B7: 2.2) Неравномерная рваная загрузка (не скажут об этом) | C7: =AVERAGE(F6) -> 0.5 | D7: =Решения!B27 -> Механизм укрупненной оценки проектов на структуре проекта с печатной формой (Обоснование стоимости проекта) | E7: [2.4] | F7: =Решения!C27 -> 0.3
B8: 2.3) Несогласованность возможностей производственных направлений и планов продаж | C8: =AVERAGE(F13) -> 0.5 | D8: Матричное ресурсное управление:
B9: 2.4) Требуется сокращение сроков и повышение точности предварительной оценки проектов | C9: =AVERAGE(F7) -> 0.3 | D9: =Решения!B38 -> РСП: управление пакетами работ, за которые они назначены ответственными | E9: [2.5] | F9: =Решения!C38 -> 0
B10: 2.5) Нужно зрелое ресурсное матричное управление | C10: =AVERAGE(F10, F9,F11,F12) -> 0.125 | D10: =Решения!B12 -> Бронирование базовое | E10: [2.5] | F10: =Решения!C12 -> 0
B11: 3) Нужно автоформирование оперативного фронта работ (плана производства). | C11: =AVERAGE(F14) -> 0 | D11: =Решения!B26 -> Контроль качества и применимость ресурсов (компетенции, квалификации) | E11: [2.5] | F11: =Решения!C26 -> 0
B12: 4) Недостаточный контроль заключения договоров и актирования | C12: =AVERAGE(F15:F16) -> 0.25 | D12: =Решения!B14 -> Влияние производительности ресурсов на трудоемкость и сроки | E12: [2.5] | F12: =Решения!C14 -> 0.5
D13: =Решения!B46 -> Темплан, включая планирование объемов актирования по контрактации (без самой контрактации) | E13: [2.3] | F13: =Решения!C46 -> 0.5
D14: =Решения!B30 -> Оперативный фронт работ (план производственных подраз): - подошли сроки, работы обеспечены, баласировки под мощность подразделений | E14: [3] | F14: =Решения!C30 -> 0
D15: =Решения!B52 -> Управление договорами | E15: [4] | F15: =Решения!C52 -> 0.5
D16: =Решения!B25 -> Контроль актирования | E16: [4] | F16: =Решения!C25 -> 0
B17: 2.2 Альтернативы | D17: 8. Ключевые метрики | I17: 5. Каналы | J17: 1.2 Ранние последователи
D18: Количество продаж; Количество отзывов
B19: 7. Структура издержек | H19: 6. Потоки прибыли
B22: решение не сформулировано | D22: Не занимались | E22: 0
B23: решение сформулировано частично | D23: В работе | E23: 0.1
B24: решение сформулировано | D24: Техническая реализация | E24: 0.5
D25: Базовая реализация (в т.ч. удобно) | E25: 0.8
D26: Глубокая реализация | E26: 1

Sheet Мал2ППО-М
B2: Продукт | H2: Рынок
B3: 2.1 Проблема | C3: =ROUND(AVERAGE(C4,C6:C12)*100,0) -> 30 | D3: 4. Решение | E3: Связь | F3: =AVERAGE(F4:F15) -> 0.25454545 | G3: 3. Уникальная ценность (УТП) | I3: 9. Скрытое преимущество | J3: 1.1 Сегменты потребителей
B4: 1) Нужна система мониторинга производственной деятельности, синхронизированная с планами по проектам, объемам и по ресурсам | C4: =AVERAGE(F4, F5) -> 0.25 | D4: =Решения!B21 -> Интеграция с КИС | E4: [1] | F4: =Решения!C21 -> 0 | G4: Система мониторинга производственной деятельности, синхронизированная с планами по проектам, объемам и по ресурсам. Управление загрузкой, сроками и стоимостью по проектам портфеля для увеличения объемов/рентабельности. | I4: Возможность самостоятельной доработки. ??? | J4: Малые инжиниринговые фирмы. Дир по производству (РПО, ГИ+ППО).
B5: 2) Сложности устойчивого роста | C5: =AVERAGE(C6, C7, C8, C9, C10) -> 0.385 | D5: =Решения!B41 -> Синхронизация мониторинга производственной деятельности с планами по проектам, объемам и по ресурсам | E5: [1] | F5: =Решения!C41 -> 0.5
B6: 2.1) с т.з. синхронного роста объемов и персонала | C6: =AVERAGE(F6) -> 0.5 | D6: =Решения!B11 -> Балансировка объемов и минимизация ресурсных конфликтов | E6: [2.1, 2.2] | F6: =Решения!C11 -> 0.5
B7: 2.2) Неравномерная рваная загрузка (не скажут об этом) | C7: =AVERAGE(F6) -> 0.5 | D7: =Решения!B27 -> Механизм укрупненной оценки проектов на структуре проекта с печатной формой (Обоснование стоимости проекта) | E7: [2.4] | F7: =Решения!C27 -> 0.3
B8: 2.3) Несогласованность возможностей производственных направлений и планов продаж | C8: =AVERAGE(F13) -> 0.5 | D8: Матричное ресурсное управление:
B9: 2.4) Требуется сокращение сроков и повышение точности предварительной оценки проектов | C9: =AVERAGE(F7) -> 0.3 | D9: =Решения!B38 -> РСП: управление пакетами работ, за которые они назначены ответственными | E9: [2.5] | F9: =Решения!C38 -> 0
B10: 2.5) Нужно зрелое ресурсное матричное управление | C10: =AVERAGE(F10, F9,F11,F12) -> 0.125 | D10: =Решения!B12 -> Бронирование базовое | E10: [2.5] | F10: =Решения!C12 -> 0
B11: 3) Нужно автоформирование оперативного фронта работ (плана производства), в т.ч. ТМЦ. | C11: =AVERAGE(F14) -> 0 | D11: =Решения!B26 -> Контроль качества и применимость ресурсов (компетенции, квалификации) | E11: [2.5] | F11: =Решения!C26 -> 0
B12: 4) Недостаточный контроль заключения договоров и актирования | C12: =AVERAGE(F15:F16) -> 0.25 | D12: =Решения!B14 -> Влияние производительности ресурсов на трудоемкость и сроки | E12: [2.5] | F12: =Решения!C14 -> 0.5
D13: =Решения!B46 -> Темплан, включая планирование объемов актирования по контрактации (без самой контрактации) | E13: [2.3] | F13: =Решения!C46 -> 0.5
D14: =Решения!B30 -> Оперативный фронт работ (план производственных подраз): - подошли сроки, работы обеспечены, баласировки под мощность подразделений | E14: [3] | F14: =Решения!C30 -> 0
D15: =Решения!B52 -> Управление договорами | E15: [4] | F15: =Решения!C52 -> 0.5
D16: =Решения!B25 -> Контроль актирования | E16: [4] | F16: =Решения!C25 -> 0
B17: 2.2 Альтернативы | D17: 8. Ключевые метрики | I17: 5. Каналы | J17: 1.2 Ранние последователи
D18: Количество продаж; Количество отзывов
B19: 7. Структура издержек | H19: 6. Потоки прибыли
B22: решение не сформулировано | D22: Не занимались | E22: 0
B23: решение сформулировано частично | D23: В работе | E23: 0.1
B24: решение сформулировано | D24: Техническая реализация | E24: 0.5
D25: Базовая реализация (в т.ч. удобно) | E25: 0.8
D26: Глубокая реализация | E26: 1

Sheet Ср1ФД
B2: Продукт | H2: Рынок
B3: 2.1 Проблема | C3: =ROUND(AVERAGE(C4:C11)*100,0) -> 55 | D3: 4. Решение | F3: =AVERAGE(F4:F11) -> 0.475 | G3: 3. Уникальная ценность (УТП) | I3: 9. Скрытое преимущество | J3: 1.1 Сегменты потребителей
B4: 1) Котловой учет себестоимости, нет инструмента для управления рентабельностью проектов/подразделений/направлений. | C4: =AVERAGE(F4) -> 0.8 | D4: =Решения!B51 -> Упр.учет фирмы в разрезе подразделений, направлений, проектов | E4: [1] | F4: =Решения!C51 -> 0.8 | G4: Сводная картина по экономике организации и ден.потоку на основании актуального сводного плана и плана инвестиций. | I4: Многофирменный учет; Бесшовная интеграция с 1С; Возможность самостоятельной доработки; | J4: Средние проектные фирмы. ФД
B5: 2) Неравномерная рваная загрузка | C5: =AVERAGE(F5,F7) -> 0.5 | D5: =Решения!B11 -> Балансировка объемов и минимизация ресурсных конфликтов | E5: [2] | F5: =Решения!C11 -> 0.5
B6: 3) Разрозненные данные по отдельным проектам. Нет актуальной сводной информации и анализа перегрузов, недогрузов, БДР и БДДС. | C6: =AVERAGE(F6:F10) -> 0.4 | D6: =Решения!B5 -> Актуализация и балансировка фин.планов | E6: [3] | F6: =Решения!C5 -> 0.5
B7: 4) Недостаточный контроль за исполнением обязательств по договорам. | C7: =AVERAGE(F11) -> 0.5 | D7: =Решения!B55 -> Управление сводными планами | E7: [2, 3] | F7: =Решения!C55 -> 0.5
D8: =Решения!B10 -> Балансировка и минимизация кассовых разрывов | E8: [3] | F8: =Решения!C10 -> 0.5
D9: =Решения!B22 -> Интеграция с системой управления проектами | E9: [3] | F9: =Решения!C22 -> 0
D10: =Решения!B23 -> Интеграция с трекинг-системами | E10: [3] | F10: =Решения!C23 -> 0.5
D11: =Решения!B52 -> Управление договорами | E11: [4] | F11: =Решения!C52 -> 0.5
B12: 2.2 Альтернативы | D12: 8. Ключевые метрики | I12: 5. Каналы | J12: 1.2 Ранние последователи
B13: 1C: ERP с доработками 1С:Бит.Финанс с доработками Б24 с доработками | D13: Количество продаж; Количество отзывов | I13: 1C 1С:ERP Финансовой направленности
B14: 7. Структура издержек | H14: 6. Потоки прибыли
B17: решение не сформулировано | D17: Не занимались | E17: 0
B18: решение сформулировано частично | D18: В работе | E18: 0.1
B19: решение сформулировано | D19: Техническая реализация | E19: 0.5
D20: Базовая реализация (в т.ч. удобно) | E20: 0.8
D21: Глубокая реализация | E21: 1

Sheet Ср1ПДО
B2: Продукт | H2: Рынок
B3: 2.1 Проблема | C3: =ROUND(AVERAGE(C4:C7)*100,0) -> 38 | D3: 4. Решение | F3: =AVERAGE(F4:F7) -> 0.375 | G3: 3. Уникальная ценность (УТП) | I3: 9. Скрытое преимущество | J3: 1.1 Сегменты потребителей
B4: 1) Неравномерная рваная загрузка | C4: =AVERAGE(F4, F5) -> 0.5 | D4: =Решения!B11 -> Балансировка объемов и минимизация ресурсных конфликтов | E4: [1] | F4: =Решения!C11 -> 0.5 | G4: Сводная картина по экономике организации и ден.потоку на основании актуального сводного плана и плана инвестиций. | I4: Многофирменный учет; Бесшовная интеграция с 1С; Возможность самостоятельной доработки; | J4: Средние проектные фирмы. ПДО
B5: 2) Разрозненные данные по отдельным проектам. Нет актуальной сводной информации и анализа перегрузов, недогрузов. | C5: =AVERAGE(F5) -> 0.5 | D5: =Решения!B55 -> Управление сводными планами | E5: [1, 2] | F5: =Решения!C55 -> 0.5
B6: 3) Очень трудоемко и долго актуализировать данные по проектам и подразделениям | C6: =AVERAGE(F6) -> 0 | D6: =Решения!B22 -> Интеграция с системой управления проектами | E6: [3] | F6: =Решения!C22 -> 0
B7: 4) Сложно обеспечивать ритмичный ход производства (диспетчирование и планирование) | C7: =AVERAGE(F7) -> 0.5 | D7: =Решения!B23 -> Интеграция с трекинг-системами | E7: [4] | F7: =Решения!C23 -> 0.5
B8: 2.2 Альтернативы | D8: 8. Ключевые метрики | I8: 5. Каналы | J8: 1.2 Ранние последователи
B9: 1C: ERP с доработками 1С:Бит.Финанс с доработками Б24 с доработками | I9: 1C 1С:ERP Финансовой направленности
B10: 7. Структура издержек | H10: 6. Потоки прибыли
B13: решение не сформулировано | D13: Не занимались | E13: 0
B14: решение сформулировано частично | D14: В работе | E14: 0.1
B15: решение сформулировано | D15: Техническая реализация | E15: 0.5
D16: Базовая реализация (в т.ч. удобно) | E16: 0.8
D17: Глубокая реализация | E17: 1

Sheet Ср2-5ГД
B2: Продукт | H2: Рынок
B3: 2.1 Проблема | C3: =ROUND(AVERAGE(C4:C6)*100,0) -> 50 | D3: 4. Решение | F3: =AVERAGE(F4:F6) -> 0.5 | G3: 3. Уникальная ценность (УТП) | I3: 9. Скрытое преимущество | J3: 1.1 Сегменты потребителей
B4: 1) Сложности устойчивого роста (с т.з. синхронного роста объемов, обеспеченности заказами и персонала) | C4: =AVERAGE(F4) -> 0.5 | D4: =Решения!B55 -> Управление сводными планами | E4: [1, 3] | F4: =Решения!C55 -> 0.5 | G4: Комплексные управление бюджетами и упр.учет в одной системе. | I4: Многофирменный учет; Бесшовная интеграция с 1С; Возможность самостоятельной доработки; Облако-коробка (размещение на своих серверах). | J4: Средние проектные фирмы. ГД
B5: 2) На все ли открывшиеся возможности хватит денег | C5: =AVERAGE(F5) -> 0.5 | D5: =Решения!B13 -> Бюджеты для финансирования возможностей | E5: [2] | F5: =Решения!C13 -> 0.5
B6: 3) Как сохранить прозрачность и контроль при делегировании | C6: =AVERAGE(F4) -> 0.5
B7: 2.2 Альтернативы | D7: 8. Ключевые метрики | I7: 5. Каналы | J7: 1.2 Ранние последователи
D8: Количество продаж; Количество отзывов | I8: Свои каналы 1C 1C:ERP Отраслевые ресурсы
B9: 7. Структура издержек | H9: 6. Потоки прибыли
B12: решение не сформулировано | D12: Не занимались | E12: 0
B13: решение сформулировано частично | D13: В работе | E13: 0.1
B14: решение сформулировано | D14: Техническая реализация | E14: 0.5
D15: Базовая реализация (в т.ч. удобно) | E15: 0.8
D16: Глубокая реализация | E16: 1

Sheet Ср2-5ФД
B2: Продукт | H2: Рынок
B3: 2.1 Проблема | C3: =ROUND(AVERAGE(C4:C7)*100,0) -> 55 | D3: 4. Решение | F3: =AVERAGE(F4:F7) -> 0.575 | G3: 3. Уникальная ценность (УТП) | I3: 9. Скрытое преимущество | J3: 1.1 Сегменты потребителей
B4: 1) Котловой учет себестоимости, нет инструмента для управления рентабельностью проектов/подразделений/направлений. | C4: =AVERAGE(F4:F6) -> 0.6 | D4: =Решения!B51 -> Упр.учет фирмы в разрезе подразделений, направлений, проектов | E4: [1] | F4: =Решения!C51 -> 0.8 | G4: Сводная картина по экономике организации и ден.потоку на основании актуального сводного плана и плана инвестиций. | I4: Многофирменный учет; Бесшовная интеграция с 1С; Возможность самостоятельной доработки; | J4: Средние проектные фирмы. ФД
B5: 2)Непрозрачное планирование затрат на ФОТ | C5: =AVERAGE(F7) -> 0.5 | D5: =Решения!B5 -> Актуализация и балансировка фин.планов | E5: [1] | F5: =Решения!C5 -> 0.5
D6: =Решения!B10 -> Балансировка и минимизация кассовых разрывов | E6: [1] | F6: =Решения!C10 -> 0.5
D7: =Решения!B33 -> Подробные планы загрузки сотрудников | E7: [2] | F7: =Решения!C33 -> 0.5
B8: 2.2 Альтернативы | I8: 5. Каналы | J8: 1.2 Ранние последователи
B9: 1C:ERP с доработками 1С:Бит.Финанс с доработками Б24 с доработками | D9: Количество продаж; Количество отзывов | I9: 1C 1С:ERP Финансовой направленности
B10: 7. Структура издержек | H10: 6. Потоки прибыли
B13: решение не сформулировано | D13: Не занимались | E13: 0
B14: решение сформулировано частично | D14: В работе | E14: 0.1
B15: решение сформулировано | D15: Техническая реализация | E15: 0.5
D16: Базовая реализация (в т.ч. удобно) | E16: 0.8
D17: Глубокая реализация | E17: 1

Sheet Ср2ДП
B2: Продукт | H2: Рынок
B3: 2.1 Проблема | C3: =ROUND(AVERAGE(C4:C11)*100,0) -> 33 | D3: 4. Решение | F3: =AVERAGE(F4:F11) -> 0.25 | G3: 3. Уникальная ценность (УТП) | I3: 9. Скрытое преимущество | J3: 1.1 Сегменты потребителей
B4: 1) Нужна система мониторинга производственной деятельности, синхронизированная с планами по проектам, объемам и по ресурсам | C4: =AVERAGE(F4:F5, F8) -> 0 | D4: =Решения!B21 -> Интеграция с КИС | E4: [1] | F4: =Решения!C21 -> 0 | G4: Система мониторинга производственной деятельности, синхронизированная с планами по проектам, объемам и по ресурсам. Управление загрузкой, сроками и стоимостью по проектам портфеля для увеличения объемов/рентабельности. | I4: Возможность самостоятельной доработки. | J4: Средние проектные фирмы. Директора по производству.
B5: 2) Сложности устойчивого роста | D5: =Решения!B22 -> Интеграция с системой управления проектами | E5: [1] | F5: =Решения!C22 -> 0
B6: 2.1) с т.з. синхронного роста объемов и персонала | C6: =AVERAGE(F6) -> 0.5 | D6: =Решения!B41 -> Синхронизация мониторинга производственной деятельности с планами по проектам, объемам и по ресурсам | E6: [2.1] | F6: =Решения!C41 -> 0.5
B7: 2.2) Неравномерная рваная загрузка | C7: =AVERAGE(F7) -> 0.5 | D7: =Решения!B11 -> Балансировка объемов и минимизация ресурсных конфликтов | E7: [2.2] | F7: =Решения!C11 -> 0.5
B8: 2.3) Несогласованность возможностей производственных направлений и планов продаж | C8: =AVERAGE(F11) -> 0 | D8: =Решения!B49 -> Трехуровневое ресурсное планирование с прогнозами | E8: [1] | F8: =Решения!C49 -> 0
B9: 3) Недостаточный контроль за исполнением обязательств по договорам. | C9: =AVERAGE(F10) -> 0.5 | D9: =Решения!B53 -> Управление портфелями и программами | E9: [4] | F9: =Решения!C53 -> 0.5
B10: 4) Нет компоновок совокупности проектов под различные цели. | C10: =AVERAGE(F9) -> 0.5 | D10: =Решения!B52 -> Управление договорами | E10: [3] | F10: =Решения!C52 -> 0.5
D11: =Решения!B45 -> Темплан, включая планирование контрактации | E11: [2.3] | F11: =Решения!C45 -> 0
B12: 2.2 Альтернативы | D12: 8. Ключевые метрики | I12: 5. Каналы | J12: 1.2 Ранние последователи
D13: Количество продаж; Количество отзывов | I13: Свои каналы 1C 1C:ERP Отраслевые ресурсы
B14: 7. Структура издержек | H14: 6. Потоки прибыли
B17: решение не сформулировано | D17: Не занимались | E17: 0
B18: решение сформулировано частично | D18: В работе | E18: 0.1
B19: решение сформулировано | D19: Техническая реализация | E19: 0.5
D20: Базовая реализация (в т.ч. удобно) | E20: 0.8
D21: Глубокая реализация | E21: 1

Sheet Ср2ДП-М
B2: Продукт | H2: Рынок
B3: 2.1 Проблема | C3: =ROUND(AVERAGE(C4:C12)*100,0) -> 21 | D3: 4. Решение | F3: =AVERAGE(F4:F12) -> 0.16666667 | G3: 3. Уникальная ценность (УТП) | I3: 9. Скрытое преимущество | J3: 1.1 Сегменты потребителей
B4: 1) Нужна система мониторинга производственной деятельности, синхронизированная с планами по проектам, объемам и по ресурсам | C4: =AVERAGE(F4:F5, F8) -> 0 | D4: =Решения!B21 -> Интеграция с КИС | E4: [1] | F4: =Решения!C21 -> 0 | G4: Система мониторинга производственной деятельности, синхронизированная с планами по проектам, объемам и по ресурсам. Управление загрузкой, сроками и стоимостью по проектам портфеля для увеличения объемов/рентабельности. | I4: Возможность самостоятельной доработки. | J4: Средние проектные фирмы. Директора по производству.
B5: 2) Сложности устойчивого роста | D5: =Решения!B22 -> Интеграция с системой управления проектами | E5: [1] | F5: =Решения!C22 -> 0
B6: 2.1) с т.з. синхронного роста объемов и персонала | C6: =AVERAGE(F6) -> 0.5 | D6: =Решения!B41 -> Синхронизация мониторинга производственной деятельности с планами по проектам, объемам и по ресурсам | E6: [2.1] | F6: =Решения!C41 -> 0.5
B7: 2.2) Неравномерная рваная загрузка | C7: =AVERAGE(F7) -> 0.5 | D7: =Решения!B11 -> Балансировка объемов и минимизация ресурсных конфликтов | E7: [2.2] | F7: =Решения!C11 -> 0.5
B8: 2.3) Несогласованность возможностей производственных направлений и планов продаж | C8: =AVERAGE(F11) -> 0 | D8: =Решения!B49 -> Трехуровневое ресурсное планирование с прогнозами | E8: [1] | F8: =Решения!C49 -> 0
B9: 3) Недостаточный контроль за исполнением обязательств по договорам. | C9: =AVERAGE(F10) -> 0.5 | D9: =Решения!B53 -> Управление портфелями и программами | E9: [4] | F9: =Решения!C49 -> 0
B10: 4) Нет компоновок совокупности проектов под различные цели. | C10: =AVERAGE(F9) -> 0 | D10: =Решения!B52 -> Управление договорами | E10: [3] | F10: =Решения!C52 -> 0.5
B11: 5) Понимание фронта работ, готовых к исполнению (в т.ч. обеспеченных ТМЦ) | C11: =AVERAGE(F12) -> 0 | D11: =Решения!B45 -> Темплан, включая планирование контрактации | E11: [2.3] | F11: =Решения!C45 -> 0
D12: =Решения!B8 -> Анализ обеспеченности (в т.ч. ТМЦ) и формирование фронта работ | E12: [5] | F12: =Решения!C8 -> 0
B13: 2.2 Альтернативы | D13: 8. Ключевые метрики | I13: 5. Каналы | J13: 1.2 Ранние последователи
D14: Количество продаж; Количество отзывов | I14: Свои каналы 1C 1C:ERP Отраслевые ресурсы
B15: 7. Структура издержек | H15: 6. Потоки прибыли
B18: решение не сформулировано | D18: Не занимались | E18: 0
B19: решение сформулировано частично | D19: В работе | E19: 0.1
B20: решение сформулировано | D20: Техническая реализация | E20: 0.5
D21: Базовая реализация (в т.ч. удобно) | E21: 0.8
D22: Глубокая реализация | E22: 1

Sheet Ср2ППО
B2: Продукт | H2: Рынок
B3: 2.1 Проблема | C3: =ROUND(AVERAGE(C4:C7)*100,0) -> 38 | D3: 4. Решение | F3: =AVERAGE(F4:F7) -> 0.375 | G3: 3. Уникальная ценность (УТП) | I3: 9. Скрытое преимущество | J3: 1.1 Сегменты потребителей
B4: 1) Неравномерная рваная загрузка | C4: =AVERAGE(F4, F5) -> 0.5 | D4: =Решения!B11 -> Балансировка объемов и минимизация ресурсных конфликтов | E4: [1] | F4: =Решения!C11 -> 0.5 | G4: Сводная картина по экономике организации и ден.потоку на основании актуального сводного плана и плана инвестиций. | I4: Многофирменный учет; Бесшовная интеграция с 1С; Возможность самостоятельной доработки; | J4: Средние проектные фирмы. ППО
B5: 2) Разрозненные данные по отдельным проектам. Нет актуальной сводной информации и анализа перегрузов, недогрузов. | C5: =AVERAGE(F5) -> 0.5 | D5: =Решения!B55 -> Управление сводными планами | E5: [1, 2] | F5: =Решения!C55 -> 0.5
B6: 3) Очень трудоемко и долго актуализировать данные по проектам и подразделениям | C6: =AVERAGE(F6) -> 0 | D6: =Решения!B22 -> Интеграция с системой управления проектами | E6: [3] | F6: =Решения!C22 -> 0
B7: 4) Сложно обеспечивать ритмичный ход производства (диспетчирование и планирование) | C7: =AVERAGE(F7) -> 0.5 | D7: =Решения!B23 -> Интеграция с трекинг-системами | E7: [4] | F7: =Решения!C23 -> 0.5
B8: 2.2 Альтернативы | D8: 8. Ключевые метрики | I8: 5. Каналы | J8: 1.2 Ранние последователи
B9: 1C: ERP с доработками 1С:Бит.Финанс с доработками Б24 с доработками | D9: Количество продаж; Количество отзывов | I9: 1C 1С:ERP Финансовой направленности
B10: 7. Структура издержек | H10: 6. Потоки прибыли
B13: решение не сформулировано | D13: Не занимались | E13: 0
B14: решение сформулировано частично | D14: В работе | E14: 0.1
B15: решение сформулировано | D15: Техническая реализация | E15: 0.5
D16: Базовая реализация (в т.ч. удобно) | E16: 0.8
D17: Глубокая реализация | E17: 1

Sheet Ср3ДП
B2: Продукт | H2: Рынок
B3: 2.1 Проблема | C3: =ROUND(AVERAGE(C4:C14)*100,0) -> 28 | D3: 4. Решение | F3: =AVERAGE(F4:F14) -> 0.25454545 | G3: 3. Уникальная ценность (УТП) | I3: 9. Скрытое преимущество | J3: 1.1 Сегменты потребителей
B4: 1) Нужна система мониторинга производственной деятельности, синхронизированная с планами по проектам, объемам и по ресурсам | C4: =AVERAGE(F4:F5, F8) -> 0.1 | D4: =Решения!B21 -> Интеграция с КИС | E4: [1] | F4: =Решения!C21 -> 0 | G4: Система мониторинга производственной деятельности, синхронизированная с планами по проектам, объемам и по ресурсам. Управление загрузкой, сроками и стоимостью по проектам портфеля для увеличения объемов/рентабельности. | I4: Возможность самостоятельной доработки. | J4: Средние проектные фирмы. Директора по производству.
B5: 2) Сложности устойчивого роста | D5: =Решения!B27 -> Механизм укрупненной оценки проектов на структуре проекта с печатной формой (Обоснование стоимости проекта) | E5: [2.4]. | F5: =Решения!C27 -> 0.3
B6: 2.1) с т.з. синхронного роста объемов и персонала | C6: =AVERAGE(F6) -> 0.5 | D6: =Решения!B41 -> Синхронизация мониторинга производственной деятельности с планами по проектам, объемам и по ресурсам | E6: [2.1] | F6: =Решения!C41 -> 0.5
B7: 2.2) Неравномерная рваная загрузка | C7: =AVERAGE(F7) -> 0.5 | D7: =Решения!B11 -> Балансировка объемов и минимизация ресурсных конфликтов | E7: [2.2] | F7: =Решения!C11 -> 0.5
B8: 2.3) Несогласованность возможностей производственных направлений и планов продаж | C8: =AVERAGE(F11) -> 0 | D8: =Решения!B49 -> Трехуровневое ресурсное планирование с прогнозами | E8: [1] | F8: =Решения!C49 -> 0
B9: 2.4) Требуется сокращение сроков и повышение точности предварительной оценки проектов | C9: =AVERAGE(F5, F12) -> 0.4 | D9: =Решения!B53 -> Управление портфелями и программами | E9: [4] | F9: =Решения!C53 -> 0.5
B10: 2.5) Нужно зрелое ресурсное управление. | C10: =AVERAGE(F13:F14) -> 0.25 | D10: =Решения!B48 -> Тиражирование технологий управления на все проекты | E10: [3] | F10: =Решения!C48 -> 0
B11: 3) Отсутствие передачи лучших практик между проектами. | C11: =AVERAGE(F10) -> 0 | D11: =Решения!B45 -> Темплан, включая планирование контрактации | E11: [2.3] | F11: =Решения!C45 -> 0
B12: 4) Нет компоновок совокупности проектов под различные цели. | C12: =AVERAGE(F9) -> 0.5 | D12: =Решения!B36 -> Проектный калькулятор | E12: [2.4]. | F12: =Решения!C36 -> 0.5
D13: =Решения!B26 -> Контроль качества и применимость ресурсов (компетенции, квалификации) | E13: [2.5]. | F13: =Решения!C26 -> 0
D14: =Решения!B14 -> Влияние производительности ресурсов на трудоемкость и сроки | E14: [2.5]. | F14: =Решения!C14 -> 0.5
B15: 2.2 Альтернативы | D15: 8. Ключевые метрики | I15: 5. Каналы | J15: 1.2 Ранние последователи
D16: Количество продаж; Количество отзывов | I16: Свои каналы 1C 1C:ERP Отраслевые ресурсы
B17: 7. Структура издержек | H17: 6. Потоки прибыли
B20: решение не сформулировано | D20: Не занимались | E20: 0
B21: решение сформулировано частично | D21: В работе | E21: 0.1
B22: решение сформулировано | D22: Техническая реализация | E22: 0.5
D23: Базовая реализация (в т.ч. удобно) | E23: 0.8
D24: Глубокая реализация | E24: 1

Sheet Ср3ППО
B2: Продукт | H2: Рынок
B3: 2.1 Проблема | C3: =ROUND(AVERAGE(C4:C12)*100,0) -> 18 | D3: 4. Решение | F3: =AVERAGE(F4:F12) -> 0.22222222 | G3: 3. Уникальная ценность (УТП) | I3: 9. Скрытое преимущество | J3: 1.1 Сегменты потребителей
B4: 1) Нужна система мониторинга производственной деятельности, синхронизированная с планами по проектам, объемам и по ресурсам | C4: =AVERAGE(F4:F5) -> 0.25 | D4: Интеграция с внешней производственной системой | E4: [1] | F4: 0 | I4: Многофирменный учет; Бесшовная интеграция с 1С; Возможность самостоятельной доработки; | J4: НИПИ ППО
B5: 2) Неравномерная рваная загрузка (не скажут об этом) | C5: =AVERAGE(F6:F7) -> 0.5 | D5: Синхронизация мониторинга производственной деятельности с планами по проектам, объемам и по ресурсам | E5: [1] | F5: 0.5
B6: 3) Нужно зрелое ресурсное матричное управление | C6: =AVERAGE(F8:F10) -> 0.16666667 | D6: Актуализация загрузки | E6: [2] | F6: 0.5
B7: 4) Нужно автоформирование оперативного фронта работ (плана производства). | C7: =AVERAGE(F11) -> 0 | D7: Составление сводных планов, балансировка и минимизация ресурсных конфликтов | E7: [2] | F7: 0.5
B8: 5) Сложно обеспечивать ритмичный ход производства (диспетчирование и планирование) | C8: =AVERAGE(F12) -> 0 | D8: Контроль качества и применимость ресурсов (компетенции, квалификации) | E8: [3] | F8: 0
D9: Влияние производительности ресурсов на трудоемкость и сроки | E9: [3] | F9: 0.5
D10: Матричное ресурсное управление | E10: [3] | F10: 0
D11: Оперативный фронт работ (план производства) | E11: [4] | F11: 0
D12: Интеграции c системой трекинга работ | E12: [5] | F12: 0
B13: 2.2 Альтернативы | D13: 8. Ключевые метрики | I13: 5. Каналы | J13: 1.2 Ранние последователи
B14: 1C: ERP с доработками 1С:Бит.Финанс с доработками Б24 с доработками | D14: Количество продаж; Количество отзывов | I14: 1C 1С:ERP Финансовой направленности
B15: 7. Структура издержек | H15: 6. Потоки прибыли
B18: решение не сформулировано | D18: Не занимались | E18: 0
B19: решение сформулировано частично | D19: В работе | E19: 0.1
B20: решение сформулировано | D20: Техническая реализация | E20: 0.5
D21: Базовая реализация (в т.ч. удобно) | E21: 0.8
D22: Глубокая реализация | E22: 1

Sheet Ср3РП
B2: Продукт | H2: Рынок
B3: 2.1 Проблема | C3: =ROUND(AVERAGE(C4:C17)*100,0) -> 28 | D3: 4. Решение | E3: Связь | F3: =AVERAGE(F4:F17) -> 0.25384615 | G3: 3. Уникальная ценность (УТП) | I3: 9. Скрытое преимущество | J3: 1.1 Сегменты потребителей
B4: 1) Нет единой системы управления проектами | C4: =AVERAGE(F5,F6) -> 0.25 | D4: Комплексная система по управлению проектом для РП, обеспечивающая: | G4: Комплексные управление проектами, бюджетами и упр.учет в одной системе. Управление рентабельностью проектов и фирмы в целом. Сохранение/оптимизация баланса затрат и свободного/чистого денежного потока. Увеличение объемов/рентабельности через управление загрузкой, сроками и стоимостью. | I4: Многофирменный учет; Бесшовная интеграция с 1С (УНФ, БП); Облако-коробка; Возможность доработки. | J4: Средние проектные организации. НИПИ. РП
B5: 2) Тратится много времени на обмен печ.формами и реестрами с заказчиком/своей бухгалтерией. Нужно регистрировать такой вспомогательный документооборот и отслеживать его статусы в привязке к Проекту и этапу проекта. | C5: =F6 -> 0 | D5: Единообразное планирование проектов (План-график, трудозатраты, фин план) | E5: [1, 4] | F5: 0.5
B6: 3) Нет возможности полуавтоматической генерации отчетности по проекту заказчику/руководству. | C6: =AVERAGE(F7,F8, F9) -> 0.33333333 | D6: MDR | E6: [1, 2, 4] | F6: 0
B7: 4) Сложно организовать хранение разноплановых данных: этапы, сроки, документы, реестры, обязательства предконтрактной стадии и договорные суммы, ресурсы | C7: =AVERAGE(F5,F6, F14, F15) -> 0.25 | D7: Актуализация информации | E7: [3] | F7: 0.5
B8: 5) Нет удобной и надежной системы взаимодействия с исполнителями работ | C8: =AVERAGE(F12,F10, F11, F13) -> 0.125 | D8: Формирование отчетности по проектам | E8: [3] | F8: 0.5
B9: 6) Не понятна рентабельность проекта | C9: =F16 -> 0.8 | D9: Статус-отчеты по проекту. От Фазы Пресейла до Завершения договора | E9: [3] | F9: 0
B10: 7) Нет понимания фронта работ, готовых к исполнению | C10: =AVERAGE(F17) -> 0 | D10: Диспетчирование работ (поручения) | E10: [5] | F10: 0.5
B11: 8) У служб предприятия отличаются взгляды (подходы) к планированию проекта | C11: =F14 -> 0.5 | D11: Канбан-доска | E11: [5] | F11: 0
D12: Интеграция с трекинг-системами | E12: [5] | F12: 0
D13: 1С:Взаимодействие | E13: [5] | F13: 0
D14: Многомерный проект (проект, у которого несколько планов) | E14: [8] | F14: 0.5
D15: Предконтрактный план с оценкой (простой проектный калькулятор) | E15: [4] | F15: 0
D16: Упр.учет фирмы в разрезе проектов | E16: [6] | F16: 0.8
D17: Анализ обеспеченности и формирование фронта работ | E17: [7] | F17: 0
B18: 2.2 Альтернативы | D18: 8. Ключевые метрики | I18: 5. Каналы | J18: 1.2 Ранние последователи
D19: Количество продаж; Количество пользователей в ГРМ; Количество отзывов | I19: Свои каналы 1C 1C:УНФ Где тусуются?
B20: 7. Структура издержек | H20: 6. Потоки прибыли
B23: решение не сформулировано | D23: Не занимались | E23: 0
B24: решение сформулировано частично | D24: В работе | E24: 0.1
B25: решение сформулировано | D25: Техническая реализация | E25: 0.5
D26: Базовая реализация (в т.ч. удобно) | E26: 0.8
D27: Глубокая реализация | E27: 1

Sheet Ср4ДПм-М
B2: Продукт | H2: Рынок
B3: 2.1 Проблема | C3: =ROUND(AVERAGE(C4:C14)*100,0) -> 22 | D3: 4. Решение | F3: =AVERAGE(F4:F14) -> 0.18181818 | G3: 3. Уникальная ценность (УТП) | I3: 9. Скрытое преимущество | J3: 1.1 Сегменты потребителей
B4: 1) Нужна система мониторинга производственной деятельности, синхронизированная с планами по проектам, объемам и по ресурсам | C4: =AVERAGE(F4:F5, F8) -> 0 | D4: Интеграция с внешней производственной системой | E4: [1] | F4: 0 | G4: Система мониторинга производственной деятельности, синхронизированная с планами по проектам, объемам и по ресурсам. Актуализация: сроки закупки ТМЦ и актуализируемый план проекта в обе стороны | I4: Возможность самостоятельной доработки. | J4: Инжиниринговые организации. Директора по проектам.
B5: 2) Сложности устойчивого роста | D5: Механизм укрупненной оценки проектов на структуре проекта с печатной формой (Обоснование стоимости проекта) | E5: [2.4]. | F5: 0
B6: 2.1) с т.з. синхронного роста объемов и персонала | C6: =AVERAGE(F6) -> 0.5 | D6: Синхронизация мониторинга производственной деятельности с планами по проектам, объемам и по ресурсам | E6: [2.1] | F6: 0.5
B7: 2.2) Неравномерная рваная загрузка | C7: =AVERAGE(F7) -> 0.5 | D7: Балансировка объемов и ресурсов | E7: [2.2] | F7: 0.5
B8: 2.3) Несогласованность возможностей производственных направлений и планов продаж | C8: =AVERAGE(F11) -> 0.5 | D8: Трехуровневое ресурсное планирование с прогнозами | E8: [1] | F8: 0
B9: 2.4) Требуется сокращение сроков и повышение точности предварительной оценки проектов | C9: =AVERAGE(F5, F12) -> 0 | D9: Управление портфелями и программами | E9: [4] | F9: 0
B10: 2.5) Нужно зрелое ресурсное управление. | C10: =AVERAGE(F13:F14) -> 0.25 | D10: Тиражирование технологий управления на все проекты | E10: [3] | F10: 0
B11: 3) Отсутствие передачи лучших практик между проектами. | C11: =AVERAGE(F10) -> 0 | D11: Темплан, включая планирование объемов актирования по контрактации (без самой контрактации) | E11: [2.3] | F11: 0.5
B12: 4) Нет компоновок совокупности проектов под различные цели. | C12: =AVERAGE(F9) -> 0 | D12: Проектный калькулятор | E12: [2.4]. | F12: 0
D13: Контроль качества и применимость ресурсов (компетенции, квалификации) | E13: [2.5]. | F13: 0
D14: Влияние производительности ресурсов на трудоемкость и сроки | E14: [2.5]. | F14: 0.5
B15: 2.2 Альтернативы | D15: 8. Ключевые метрики | I15: 5. Каналы | J15: 1.2 Ранние последователи
D16: Количество продаж; Количество отзывов | I16: Свои каналы 1C 1C:ERP Отраслевые ресурсы
B17: 7. Структура издержек | H17: 6. Потоки прибыли
B20: решение не сформулировано | D20: Не занимались | E20: 0
B21: решение сформулировано частично | D21: В работе | E21: 0.1
B22: решение сформулировано | D22: Техническая реализация | E22: 0.5
D23: Базовая реализация (в т.ч. удобно) | E23: 0.8
D24: Глубокая реализация | E24: 1

Sheet Ср4РПО-М
B2: Продукт | H2: Рынок
B3: 2.1 Проблема | C3: =ROUND(AVERAGE(C4:C14)*100,0) -> 20 | D3: 4. Решение | F3: =AVERAGE(F4:F14) -> 0.18181818 | G3: 3. Уникальная ценность (УТП) | I3: 9. Скрытое преимущество | J3: 1.1 Сегменты потребителей
B4: 1) Нужна система мониторинга производственной деятельности, синхронизированная с планами по проектам, объемам и по ресурсам | C4: =AVERAGE(F4, F6) -> 0.25 | D4: Интеграция с внешней производственной системой | E4: [1] | F4: 0 | G4: Система мониторинга производственной деятельности, синхронизированная с планами по проектам, объемам и по ресурсам. Управление загрузкой, сроками и стоимостью по проектам портфеля для увеличения объемов/рентабельности. | I4: Возможность самостоятельной доработки. | J4: Инжиниринговые организации. Дир по производству (РПО, ГИ+ППО).
B5: 2) Сложности устойчивого роста | D5: Механизм укрупненной оценки проектов на структуре проекта с печатной формой (Обоснование стоимости проекта) | E5: [2.4] | F5: 0
B6: 2.1) с т.з. синхронного роста объемов и персонала | C6: =AVERAGE(F7) -> 0.5 | D6: Синхронизация мониторинга производственной деятельности с планами по проектам, объемам и по ресурсам | E6: [1] | F6: 0.5
B7: 2.2) Неравномерная рваная загрузка | C7: =AVERAGE(F8) -> 0 | D7: Балансировка объемов и ресурсов | E7: [2.1] | F7: 0.5
B8: 2.3) Несогласованность возможностей производственных направлений и планов продаж | C8: =AVERAGE(F10) -> 0.5 | D8: Трехуровневое ресурсное планирование с прогнозами | E8: [2.2] | F8: 0
B9: 2.4) Требуется сокращение сроков и повышение точности предварительной оценки проектов | C9: =AVERAGE(F5, F11) -> 0 | D9: Оперативный фронт работ (план производства) | E9: [3] | F9: 0
B10: 2.5) Нужно зрелое ресурсное матричное управление | C10: =AVERAGE(F12:F14) -> 0.16666667 | D10: Темплан, включая планирование объемов актирования по контрактации (без самой контрактации) | E10: [2.3] | F10: 0.5
B11: 3) Нужно автоформирование оперативного фронта работ (плана производства) из обеспеченных работ (в т.ч. ТМЦ) | C11: =AVERAGE(F9) -> 0 | D11: Проектный калькулятор | E11: [2.4] | F11: 0
D12: Матричное ресурсное управление | E12: [2.5] | F12: 0
D13: Контроль качества и применимость ресурсов (компетенции, квалификации) | E13: [2.5] | F13: 0
D14: Влияние производительности ресурсов на трудоемкость и сроки | E14: [2.5] | F14: 0.5
B15: 2.2 Альтернативы | D15: 8. Ключевые метрики | I15: 5. Каналы | J15: 1.2 Ранние последователи
D16: Количество продаж; Количество отзывов | I16: Свои каналы 1C 1C:ERP Отраслевые ресурсы
B17: 7. Структура издержек | H17: 6. Потоки прибыли
B20: решение не сформулировано | D20: Не занимались | E20: 0
B21: решение сформулировано частично | D21: В работе | E21: 0.1
B22: решение сформулировано | D22: Техническая реализация | E22: 0.5
D23: Базовая реализация (в т.ч. удобно) | E23: 0.8
D24: Глубокая реализация | E24: 1

Sheet Ср4РП-М
B2: Продукт | H2: Рынок
B3: 2.1 Проблема | C3: =ROUND(AVERAGE(C4:C11)*100,0) -> 31 | D3: 4. Решение | F3: =AVERAGE(F4:F11) -> 0.2875 | G3: 3. Уникальная ценность (УТП) | I3: 9. Скрытое преимущество | J3: 1.1 Сегменты потребителей
B4: 1) Не понятна рентабельность проекта | C4: =AVERAGE(F7,F4) -> 0.4 | D4: Упр.учет фирмы в разрезе проектов | E4: [1] | F4: 0.8 | G4: Комплексные управление проектами, бюджетами и упр.учет в одной системе. Управление рентабельностью проектов и фирмы в целом. Сохранение/оптимизация баланса затрат и свободного/чистого денежного потока. Увеличение объемов/рентабельности через управление загрузкой, сроками и стоимостью. | I4: Многофирменный учет; Бесшовная интеграция с 1С (УНФ, БП); Облако-коробка; Возможность доработки. | J4: Инжиниринговые организации. РП
B5: 2) Очень много субпродуктов проекта с различных статусах и составах. | C5: =AVERAGE(F5) -> 0 | D5: MDR | E5: [2] | F5: 0
B6: 3) Нет понимания фронта работ, готовых к исполнению (в т.ч. обеспеченных ТМЦ) | C6: =AVERAGE(F6) -> 0 | D6: Анализ обеспеченности и формирование фронта работ | E6: [3] | F6: 0
B7: 4) Слабый контроль выполнения работ. Не укладываются в срок. | C7: =AVERAGE(F8) -> 0.5 | D7: Предконтрактный план с оценкой (простой проектный калькулятор) | E7: [1] | F7: 0
B8: 5) У служб предприятия отличаются взгляды (подходы) к планированию проекта | C8: =AVERAGE(F9) -> 0.5 | D8: Учет факта выполнения работ | E8: [4] | F8: 0.5
B9: 6) Нет четкого понимания когда и какие ТМЦ будут нужны с учетом текущей ситуации по проекту | C9: =AVERAGE(F10:F11) -> 0.25 | D9: Многомерные проекты | E9: [5] | F9: 0.5
B10: 7) Нет данных когда требуемые проекту ТМЦ поступят | C10: =AVERAGE(F11) -> 0.5 | D10: Привязка спецификаций к работам проекта | E10: [6] | F10: 0
D11: Связь проектов, заказов поставщикам и факта поставки ТМЦ | E11: [6, 7] | F11: 0.5
B12: 2.2 Альтернативы | D12: 8. Ключевые метрики | I12: 5. Каналы | J12: 1.2 Ранние последователи
D13: Количество продаж; Количество пользователей в ГРМ; Количество отзывов | I13: Свои каналы 1C 1C:УНФ Где тусуются?
B14: 7. Структура издержек | H14: 6. Потоки прибыли
B17: решение не сформулировано | D17: Не занимались | E17: 0
B18: решение сформулировано частично | D18: В работе | E18: 0.1
B19: решение сформулировано | D19: Техническая реализация | E19: 0.5
D20: Базовая реализация (в т.ч. удобно) | E20: 0.8
D21: Глубокая реализация | E21: 1

Sheet Ср5РПО
B2: Продукт | H2: Рынок
B3: 2.1 Проблема | C3: =ROUND(AVERAGE(C4:C12)*100,0) -> 29 | D3: 4. Решение | F3: =AVERAGE(F4:F12) -> 0.25555556 | G3: 3. Уникальная ценность (УТП) | I3: 9. Скрытое преимущество | J3: 1.1 Сегменты потребителей
B4: 1) Не понятна рентабельность (подразделений/ направлений/проектов) | C4: =AVERAGE(F4) -> 0.8 | D4: Упр.учет фирмы в разрезе подразделений, направлений, проектов | E4: [1] | F4: 0.8 | G4: Система мониторинга производственной и закупочной деятельности, синхронизированная с планами по проектам, объемам и по ресурсам. Актуализация: сроки закупки ТМЦ и актуализируемый план проекта в обе стороны | I4: Возможность самостоятельной доработки. | J4: Средние ИТ организации. Директора по проектам/РПО.
B5: 2) Сложности устойчивого роста | D5: Синхронизация мониторинга производственной деятельности с планами по проектам, объемам и по ресурсам | E5: [2.1] | F5: 0.5
B6: 2.1) с т.з. синхронного роста объемов и персонала | C6: =AVERAGE(F5) -> 0.5 | D6: Механизм укрупненной оценки проектов на структуре проекта с печатной формой (Обоснование стоимости проекта) | E6: [2.3] | F6: 0
B7: 2.2) Несогласованность возможностей производственных направлений и планов продаж | C7: =AVERAGE(F12) -> 0.5 | D7: Проектный калькулятор | E7: [2.3] | F7: 0
B8: 2.3) Требуется сокращение сроков и повышение точности предварительной оценки проектов | C8: =AVERAGE(F6:F7) -> 0 | D8: Контроль качества и применимость ресурсов (компетенции, квалификации) | E8: [2.4] | F8: 0
B9: 2.4) Нужно зрелое ресурсное управление. | C9: =AVERAGE(F8, F9) -> 0.25 | D9: Влияние производительности ресурсов на трудоемкость и сроки | E9: [2.4] | F9: 0.5
B10: 3) Отсутствие передачи лучших практик между проектами. | C10: =AVERAGE(F10) -> 0 | D10: Тиражирование технологий управления на все проекты | E10: [3] | F10: 0
B11: 4) Нет компоновок совокупности проектов под различные цели. | C11: =AVERAGE(F11) -> 0 | D11: Управление портфелями и программами | E11: [4] | F11: 0
D12: Темплан, включая планирование объемов актирования по контрактации (без самой контрактации) | E12: [2.2] | F12: 0.5
B13: 2.2 Альтернативы | D13: 8. Ключевые метрики | I13: 5. Каналы | J13: 1.2 Ранние последователи
D14: Количество продаж; Количество отзывов | I14: Свои каналы 1C 1C:ERP Отраслевые ресурсы
B15: 7. Структура издержек | H15: 6. Потоки прибыли
B18: решение не сформулировано | D18: Не занимались | E18: 0
B19: решение сформулировано частично | D19: В работе | E19: 0.1
B20: решение сформулировано | D20: Техническая реализация | E20: 0.5
D21: Базовая реализация (в т.ч. удобно) | E21: 0.8
D22: Глубокая реализация | E22: 1

Sheet Ср5ПрОф
B2: Продукт | H2: Рынок
B3: 2.1 Проблема | C3: =ROUND(AVERAGE(C4:C13)*100,0) -> 24 | D3: 4. Решение | F3: =AVERAGE(F4:F13) -> 0.2 | G3: 3. Уникальная ценность (УТП) | I3: 9. Скрытое преимущество | J3: 1.1 Сегменты потребителей
B4: 1) Требуется планировать, балансировать и актуализировать объемы по проектам и подразделениям на длительный срок (производственная программа). | C4: =AVERAGE(F4,F9) -> 0.5 | D4: Синхронизация мониторинга производственной деятельности с планами по проектам, объемам и по ресурсам | E4: [1] | F4: 0.5 | G4: Система мониторинга производственной деятельности, синхронизированная с планами по проектам, объемам и по ресурсам. Управление загрузкой, сроками и стоимостью по проектам портфеля для увеличения объемов/рентабельности. | I4: Возможность самостоятельной доработки. ??? | J4: Средние ИТ организации. Проектный офис
B5: 2) Сложности устойчивого роста | D5: Механизм укрупненной оценки проектов на структуре проекта с печатной формой (Обоснование стоимости проекта) | E5: [2.4] | F5: 0
B6: 2.1) с т.з. синхронного роста объемов и персонала | C6: =AVERAGE(F6) -> 0.5 | D6: Балансировка объемов и ресурсов | E6: [2.1] | F6: 0.5
B7: 2.2) Неравномерная рваная загрузка | C7: =AVERAGE(F7) -> 0 | D7: Трехуровневое ресурсное планирование с прогнозами | E7: [2.2] | F7: 0
B8: 2.3) Несогласованность возможностей производственных направлений и планов продаж | C8: =AVERAGE(F9) -> 0.5 | D8: Оперативный фронт работ (план производства) | E8: [3] | F8: 0
B9: 2.4) Требуется сокращение сроков и повышение точности предварительной оценки проектов | C9: =AVERAGE(F5, F10) -> 0 | D9: Темплан, включая планирование объемов актирования по контрактации (без самой контрактации) | E9: [1, 2.3] | F9: 0.5
B10: 2.5) Нужно зрелое ресурсное матричное управление | C10: =AVERAGE(F11:F13) -> 0.16666667 | D10: Проектный калькулятор | E10: [2.4] | F10: 0
B11: 3) Нужно автоформирование оперативного фронта работ (плана производства) из обеспеченных работ (в т.ч. ТМЦ) | C11: =AVERAGE(F8) -> 0 | D11: Матричное ресурсное управление | E11: [2.5] | F11: 0
D12: Контроль качества и применимость ресурсов (компетенции, квалификации) | E12: [2.5] | F12: 0
D13: Влияние производительности ресурсов на трудоемкость и сроки | E13: [2.5] | F13: 0.5
B14: 2.2 Альтернативы | D14: 8. Ключевые метрики | I14: 5. Каналы | J14: 1.2 Ранние последователи
D15: Количество продаж; Количество отзывов
B16: 7. Структура издержек | H16: 6. Потоки прибыли
B19: решение не сформулировано | D19: Не занимались | E19: 0
B20: решение сформулировано частично | D20: В работе | E20: 0.1
B21: решение сформулировано | D21: Техническая реализация | E21: 0.5
D22: Базовая реализация (в т.ч. удобно) | E22: 0.8
D23: Глубокая реализация | E23: 1

Sheet Ср5РП
B2: Продукт | H2: Рынок
B3: 2.1 Проблема | C3: =ROUND(AVERAGE(C4:C18)*100,0) -> 31 | D3: 4. Решение | E3: Связь | F3: =AVERAGE(F4:F18) -> 0.27142857 | G3: 3. Уникальная ценность (УТП) | I3: 9. Скрытое преимущество | J3: 1.1 Сегменты потребителей
B4: 1) Нет единой системы управления проектами | C4: =AVERAGE(F5,F6) -> 0.25 | D4: Комплексная система по управлению проектом для РП, обеспечивающая: | G4: Комплексные управление проектами, бюджетами и упр.учет в одной системе. Управление рентабельностью проектов и фирмы в целом. Сохранение/оптимизация баланса затрат и свободного/чистого денежного потока. Увеличение объемов/рентабельности через управление загрузкой, сроками и стоимостью. | I4: Многофирменный учет; Бесшовная интеграция с 1С (УНФ, БП); Облако-коробка; Возможность доработки. | J4: Средние ИТ организации. РП
B5: 2) Тратится много времени на обмен печ.формами и реестрами с заказчиком/своей бухгалтерией. Нужно регистрировать такой вспомогательный документооборот и отслеживать его статусы в привязке к Проекту и этапу проекта. | C5: =F6 -> 0 | D5: Единообразное планирование проектов (План-график, трудозатраты, фин план) | E5: [1, 4] | F5: 0.5
B6: 3) Нет возможности полуавтоматической генерации отчетности по проекту заказчику/руководству. | C6: =AVERAGE(F7,F8, F9) -> 0.33333333 | D6: MDR | E6: [1, 2, 4] | F6: 0
B7: 4) Сложно организовать хранение разноплановых данных: этапы, сроки, документы, реестры, обязательства предконтрактной стадии и договорные суммы, ресурсы | C7: =AVERAGE(F5,F6, F14, F15) -> 0.25 | D7: Актуализация информации | E7: [3] | F7: 0.5
B8: 5) Нет удобной и надежной системы взаимодействия с исполнителями работ | C8: =AVERAGE(F12,F10, F11, F13) -> 0.125 | D8: Формирование отчетности по проектам | E8: [3] | F8: 0.5
B9: 6) Не понятна рентабельность проекта | C9: =F16 -> 0.8 | D9: Статус-отчеты по проекту. От Фазы Пресейла до Завершения договора | E9: [3] | F9: 0
B10: 7) Нет понимания фронта работ, готовых к исполнению | C10: =AVERAGE(F17) -> 0 | D10: Диспетчирование работ (поручения) | E10: [5] | F10: 0.5
B11: 8) У служб предприятия отличаются взгляды (подходы) к планированию проекта | C11: =F14 -> 0.5 | D11: Канбан-доска | E11: [5] | F11: 0
B12: 9) Слабый контроль выполнения работ. Не укладываются в срок. | C12: =F18 -> 0.5 | D12: Интеграция с трекинг-системами | E12: [5] | F12: 0
D13: 1С:Взаимодействие | E13: [5] | F13: 0
D14: Многомерный проект (проект, у которого несколько планов) | E14: [8] | F14: 0.5
D15: Предконтрактный план с оценкой (простой проектный калькулятор) | E15: [4] | F15: 0
D16: Упр.учет фирмы в разрезе проектов | E16: [6] | F16: 0.8
D17: Анализ обеспеченности и формирование фронта работ | E17: [7] | F17: 0
D18: Учет факта выполнения работ. | E18: [9] | F18: 0.5
B19: 2.2 Альтернативы | D19: 8. Ключевые метрики | I19: 5. Каналы | J19: 1.2 Ранние последователи
D20: Количество продаж; Количество пользователей в ГРМ; Количество отзывов | I20: Свои каналы 1C 1C:УНФ Где тусуются?
B21: 7. Структура издержек | H21: 6. Потоки прибыли
B24: решение не сформулировано | D24: Не занимались | E24: 0
B25: решение сформулировано частично | D25: В работе | E25: 0.1
B26: решение сформулировано | D26: Техническая реализация | E26: 0.5
D27: Базовая реализация (в т.ч. удобно) | E27: 0.8
D28: Глубокая реализация | E28: 1

Sheet Кр11ЗГД
B2: Продукт | H2: Рынок
B3: 2.1 Проблема | C3: =ROUND(AVERAGE(C4:C8)*100,0) -> 20 | D3: 4. Решение | F3: =AVERAGE(F4:F8) -> 0.125 | G3: 3. Уникальная ценность (УТП) | I3: 9. Скрытое преимущество | J3: 1.1 Сегменты потребителей
B4: 1) Как обеспечить прозрачность и контроль | C4: =AVERAGE(F4) -> 0.5 | D4: Управление сводными планами | E4: [1, 2] | F4: 0.5 | G4: Комплексные управление основной проектной деятельностью и инвестпроектами в разрезе финансов, ресурсов и пр.. Управление и учет по ЦФО/Направлениям | I4: Бесшовная интеграция с 1С:ERP (Финансы, ЗУП, Закупки, ...); Поддержка учета в филиальной структуре; Импортонезависимый стек; Поддержка ГОЗ; Возможность самостоятельной доработки и поддержки внутренними центрами компетенций. | J4: Крупные проектные организации. ГД, 1-й Зам ГД.
B5: 2) Сложности устойчивого роста (с т.з. синхронного роста объемов, обеспеченности заказами и персонала) | C5: =AVERAGE(F4) -> 0.5 | D5: Бюджеты для финансирования возможностей | E5: [3] | F5: 0
B6: 3) Синхронизированность денпотоков по основной деятельности, инвестициям и фин.инструментам. | C6: =AVERAGE(F5) -> 0 | D6: Тиражирование технологий управления на все направления | E6: [4] | F6: 0
B7: 4) Отсутствие передачи лучших практик между направлениями. | C7: =AVERAGE(F6) -> 0 | D7: Управление портфелями и программами | E7: [5] | F7: 0
B8: 5) Нужно мониторить достижение стратегических целей. | C8: =AVERAGE(F7) -> 0
B9: 2.2 Альтернативы | D9: 8. Ключевые метрики | I9: 5. Каналы | J9: 1.2 Ранние последователи
D10: Количество продаж; Количество отзывов | I10: Свои каналы 1C 1C:ERP Отраслевые ресурсы
B11: 7. Структура издержек | H11: 6. Потоки прибыли
B14: решение не сформулировано | D14: Не занимались | E14: 0
B15: решение сформулировано частично | D15: В работе | E15: 0.1
B16: решение сформулировано | D16: Техническая реализация | E16: 0.5
D17: Базовая реализация (в т.ч. удобно) | E17: 0.8
D18: Глубокая реализация | E18: 1

Sheet Кр1ППО
B2: Продукт | H2: Рынок
B3: 2.1 Проблема | C3: =ROUND(AVERAGE(C4:C7)*100,0) -> 44 | D3: 4. Решение | F3: =AVERAGE(F4:F7) -> 0.375 | G3: 3. Уникальная ценность (УТП) | I3: 9. Скрытое преимущество | J3: 1.1 Сегменты потребителей
B4: 1) Нужна система мониторинга производственной деятельности, синхронизированная с планами по проектам, объемам и по ресурсам | C4: =AVERAGE(F4:F5,F7) -> 0.33333333 | D4: Интеграция с внешней производственной системой | E4: [1] | F4: 0 | G4: Система мониторинга производственной деятельности, синхронизированная с планами по проектам, объемам и по ресурсам. Управление загрузкой, сроками и стоимостью по проектам портфеля для увеличения объемов/рентабельности. | I4: Возможность самостоятельной доработки. | J4: Крупные проектные организации. ППО
B5: 2) Неравномерная рваная загрузка | C5: =AVERAGE(F6) -> 0.5 | D5: Синхронизация мониторинга производственной деятельности с планами по проектам, объемам и по ресурсам | E5: [1] | F5: 0.5
B6: 3) Требуется планировать, балансировать и актуализировать объемы по проектам и подразделениям на длительный срок (производственная программа). | C6: =AVERAGE(F7) -> 0.5 | D6: Балансировка объемов и ресурсов | E6: [2] | F6: 0.5
D7: Темплан, включая планирование объемов актирования по контрактации (без самой контрактации) | E7: [1, 3] | F7: 0.5
B8: 2.2 Альтернативы | D8: 8. Ключевые метрики | I8: 5. Каналы | J8: 1.2 Ранние последователи
I9: Свои каналы 1C 1C:ERP Отраслевые ресурсы
B10: 7. Структура издержек | H10: 6. Потоки прибыли
B13: решение не сформулировано | D13: Не занимались | E13: 0
B14: решение сформулировано частично | D14: В работе | E14: 0.1
B15: решение сформулировано | D15: Техническая реализация | E15: 0.5
D16: Базовая реализация (в т.ч. удобно) | E16: 0.8
D17: Глубокая реализация | E17: 1

Sheet Кр1ППО-М
B2: Продукт | H2: Рынок
B3: 2.1 Проблема | C3: =ROUND(AVERAGE(C4:C8)*100,0) -> 47 | D3: 4. Решение | F3: =AVERAGE(F4:F8) -> 0.4 | G3: 3. Уникальная ценность (УТП) | I3: 9. Скрытое преимущество | J3: 1.1 Сегменты потребителей
B4: 1) Нужна система мониторинга производственной деятельности, синхронизированная с планами по проектам, объемам и по ресурсам | C4: =AVERAGE(F4:F5,F7) -> 0.33333333 | D4: Интеграция с внешней производственной системой | E4: [1] | F4: 0 | G4: Система мониторинга производственной деятельности, синхронизированная с планами по проектам, объемам и по ресурсам. Управление загрузкой, сроками и стоимостью по проектам портфеля для увеличения объемов/рентабельности. | I4: Возможность самостоятельной доработки. | J4: Крупные проектные организации. ППО
B5: 2) Неравномерная рваная загрузка | C5: =AVERAGE(F6) -> 0.5 | D5: Синхронизация мониторинга производственной деятельности с планами по проектам, объемам и по ресурсам | E5: [1] | F5: 0.5
B6: 3) Нет четкого понимания когда и какие ТМЦ будут нужны с учетом текущей ситуации по проекту | C6: =AVERAGE(F8) -> 0.5 | D6: Балансировка объемов и ресурсов | E6: [2] | F6: 0.5
B7: 4) Нет данных когда требуемые проекту ТМЦ поступят | C7: =AVERAGE(F8) -> 0.5 | D7: Темплан, включая планирование объемов актирования по контрактации (без самой контрактации) | E7: [1, 5] | F7: 0.5
B8: 5) Требуется планировать, балансировать и актуализировать объемы по проектам и подразделениям на длительный срок (производственная программа). | C8: =AVERAGE(F7) -> 0.5 | D8: Связь проектов, заказов поставщикам и факта поставки ТМЦ | E8: [3, 4] | F8: 0.5
B9: 2.2 Альтернативы | D9: 8. Ключевые метрики | I9: 5. Каналы | J9: 1.2 Ранние последователи
I10: Свои каналы 1C 1C:ERP Отраслевые ресурсы
B11: 7. Структура издержек | H11: 6. Потоки прибыли
B14: решение не сформулировано | D14: Не занимались | E14: 0
B15: решение сформулировано частично | D15: В работе | E15: 0.1
B16: решение сформулировано | D16: Техническая реализация | E16: 0.5
D17: Базовая реализация (в т.ч. удобно) | E17: 0.8
D18: Глубокая реализация | E18: 1

Sheet Кр1РЦ
B2: Продукт | H2: Рынок
B3: 2.1 Проблема | C3: =ROUND(AVERAGE(C4:C15)*100,0) -> 18 | D3: 4. Решение | F3: =AVERAGE(F4:F15) -> 0.125 | G3: 3. Уникальная ценность (УТП) | I3: 9. Скрытое преимущество | J3: 1.1 Сегменты потребителей
B4: 1) Нужна система мониторинга производственной деятельности, синхронизированная с планами по проектам, объемам и по ресурсам | C4: =AVERAGE(F4:F5,F8:F9) -> 0.25 | D4: Интеграция с внешней производственной системой | E4: [1] | F4: 0 | G4: Система мониторинга производственной деятельности, синхронизированная с планами по проектам, объемам и по ресурсам. Управление загрузкой, сроками и стоимостью по проектам портфеля для увеличения объемов/рентабельности. | I4: Возможность самостоятельной доработки. | J4: Крупные проектные организации. Руководители центров/ направлений
B5: 2) Сложности устойчивого роста | D5: Синхронизация мониторинга производственной деятельности с планами по проектам, объемам и по ресурсам | E5: [1, 2.1] | F5: 0.5
B6: 2.1) с т.з. синхронного роста объемов и персонала | C6: =AVERAGE(F5) -> 0.5 | D6: Механизм укрупненной оценки проектов на структуре проекта с печатной формой (Обоснование стоимости проекта) | E6: [2.4] | F6: 0
B7: 2.2) Неравномерная рваная загрузка | C7: =AVERAGE(F7:F8) -> 0.25 | D7: Балансировка объемов и ресурсов | E7: [2.2, 2.5] | F7: 0.5
B8: 2.3) Несогласованность возможностей производственных направлений и планов продаж | C8: =AVERAGE(F9) -> 0.5 | D8: Трехуровневое ресурсное планирование с прогнозами | E8: [1, 2.2] | F8: 0
B9: 2.4) Требуется сокращение сроков и повышение точности предварительной оценки проектов | C9: =AVERAGE(F6, F10) -> 0 | D9: Темплан, включая планирование контрактации | E9: [1, 2.3] | F9: 0.5
B10: 2.5) Нужно зрелое ресурсное матричное управление | C10: =AVERAGE(F7, F11:F13) -> 0.125 | D10: Проектный калькулятор | E10: [2.4] | F10: 0
B11: 3) Отсутствие передачи лучших практик между проектами. | C11: =AVERAGE( F14) -> 0 | D11: Матричное ресурсное управление | E11: [2.5] | F11: 0
B12: 4) Нет компоновок совокупности проектов под различные цели. | C12: =AVERAGE( F15) -> 0 | D12: Контроль качества и применимость ресурсов (компетенции, квалификации) | E12: [2.5, 5] | F12: 0
B13: 5) Слабый контроль за повышением производительности труда | C13: =AVERAGE( F12) -> 0 | D13: Влияние производительности ресурсов на трудоемкость и сроки | E13: [2.5] | F13: 0
D14: Тиражирование технологий управления на все проекты | E14: [3] | F14: 0
D15: Управление портфелями и программами | E15: [4] | F15: 0
B16: 2.2 Альтернативы | D16: 8. Ключевые метрики | I16: 5. Каналы | J16: 1.2 Ранние последователи
I17: Свои каналы 1C 1C:ERP Отраслевые ресурсы
B18: 7. Структура издержек | H18: 6. Потоки прибыли
B21: решение не сформулировано | D21: Не занимались | E21: 0
B22: решение сформулировано частично | D22: В работе | E22: 0.1
B23: решение сформулировано | D23: Техническая реализация | E23: 0.5
D24: Базовая реализация (в т.ч. удобно) | E24: 0.8
D25: Глубокая реализация | E25: 1

Sheet Кр1РЦ-М
B2: Продукт | H2: Рынок
B3: 2.1 Проблема | C3: =ROUND(AVERAGE(C4:C15)*100,0) -> 18 | D3: 4. Решение | F3: =AVERAGE(F4:F15) -> 0.125 | G3: 3. Уникальная ценность (УТП) | I3: 9. Скрытое преимущество | J3: 1.1 Сегменты потребителей
B4: 1) Нужна система мониторинга производственной деятельности, синхронизированная с планами по проектам, объемам и по ресурсам | C4: =AVERAGE(F4:F5,F8:F9) -> 0.25 | D4: Интеграция с внешней производственной системой | E4: [1] | F4: 0 | G4: Система мониторинга производственной деятельности, синхронизированная с планами по проектам, объемам и по ресурсам. Управление загрузкой, сроками и стоимостью по проектам портфеля для увеличения объемов/рентабельности. | I4: Возможность самостоятельной доработки. | J4: Крупные проектно-инжиниринговые организации. Руководители центров/ направлений
B5: 2) Сложности устойчивого роста | D5: Синхронизация мониторинга производственной деятельности с планами по проектам, объемам и по ресурсам | E5: [1, 2.1] | F5: 0.5
B6: 2.1) с т.з. синхронного роста объемов и персонала | C6: =AVERAGE(F5) -> 0.5 | D6: Механизм укрупненной оценки проектов на структуре проекта с печатной формой (Обоснование стоимости проекта) | E6: [2.4] | F6: 0
B7: 2.2) Неравномерная рваная загрузка | C7: =AVERAGE(F7:F8) -> 0.25 | D7: Балансировка объемов и ресурсов | E7: [2.2, 2.5] | F7: 0.5
B8: 2.3) Несогласованность возможностей производственных направлений и планов продаж | C8: =AVERAGE(F9) -> 0.5 | D8: Трехуровневое ресурсное планирование с прогнозами | E8: [1, 2.2] | F8: 0
B9: 2.4) Требуется сокращение сроков и повышение точности предварительной оценки проектов | C9: =AVERAGE(F6, F10) -> 0 | D9: Темплан, включая планирование контрактации | E9: [1, 2.3] | F9: 0.5
B10: 2.5) Нужно зрелое ресурсное матричное управление | C10: =AVERAGE(F7, F11:F13) -> 0.125 | D10: Проектный калькулятор | E10: [2.4] | F10: 0
B11: 3) Отсутствие передачи лучших практик между проектами. | C11: =AVERAGE( F14) -> 0 | D11: Матричное ресурсное управление | E11: [2.5] | F11: 0
B12: 4) Нет компоновок совокупности проектов под различные цели. | C12: =AVERAGE( F15) -> 0 | D12: Контроль качества и применимость ресурсов (компетенции, квалификации) | E12: [2.5, 5] | F12: 0
B13: 5) Слабый контроль за повышением производительности труда | C13: =AVERAGE( F12) -> 0 | D13: Влияние производительности ресурсов на трудоемкость и сроки | E13: [2.5] | F13: 0
D14: Тиражирование технологий управления на все проекты | E14: [3] | F14: 0
D15: Управление портфелями и программами | E15: [4] | F15: 0
B16: 2.2 Альтернативы | D16: 8. Ключевые метрики | I16: 5. Каналы | J16: 1.2 Ранние последователи
I17: Свои каналы 1C 1C:ERP Отраслевые ресурсы
B18: 7. Структура издержек | H18: 6. Потоки прибыли
B21: решение не сформулировано | D21: Не занимались | E21: 0
B22: решение сформулировано частично | D22: В работе | E22: 0.1
B23: решение сформулировано | D23: Техническая реализация | E23: 0.5
D24: Базовая реализация (в т.ч. удобно) | E24: 0.8
D25: Глубокая реализация | E25: 1

Sheet Кр1ПДО
B2: Продукт | H2: Рынок
B3: 2.1 Проблема | C3: =ROUND(AVERAGE(C4:C14)*100,0) -> 23 | D3: 4. Решение | F3: =AVERAGE(F4:F14) -> 0.13636364 | G3: 3. Уникальная ценность (УТП) | I3: 9. Скрытое преимущество | J3: 1.1 Сегменты потребителей
B4: 1) Нужна система мониторинга производственной деятельности, синхронизированная с планами по проектам, объемам и по ресурсам | C4: =AVERAGE(F4:F5,F8:F9) -> 0.25 | D4: Интеграция с внешней производственной системой | E4: [1] | F4: 0 | G4: Система мониторинга производственной деятельности, синхронизированная с планами по проектам, объемам и по ресурсам. Управление загрузкой, сроками и стоимостью по проектам портфеля для увеличения объемов/рентабельности. | I4: Возможность самостоятельной доработки. | J4: Крупные проектные организации. ПДО
B5: 2) Сложности устойчивого роста | D5: Синхронизация мониторинга производственной деятельности с планами по проектам, объемам и по ресурсам | E5: [1, 2.1] | F5: 0.5
B6: 2.1) с т.з. синхронного роста объемов и персонала | C6: =AVERAGE(F5) -> 0.5 | D6: Механизм укрупненной оценки проектов на структуре проекта с печатной формой (Обоснование стоимости проекта) | E6: [2.4] | F6: 0
B7: 2.2) Неравномерная рваная загрузка | C7: =AVERAGE(F7:F8) -> 0.25 | D7: Балансировка объемов и ресурсов | E7: [2.2, 2.5] | F7: 0.5
B8: 2.3) Несогласованность возможностей производственных направлений и планов продаж | C8: =AVERAGE(F9) -> 0.5 | D8: Трехуровневое ресурсное планирование с прогнозами | E8: [1, 2.2] | F8: 0
B9: 2.4) Требуется сокращение сроков и повышение точности предварительной оценки проектов | C9: =AVERAGE(F6, F10) -> 0 | D9: Темплан, включая планирование объемов актирования по контрактации (без самой контрактации) | E9: [1, 2.3] | F9: 0.5
B10: 2.5) Нужно зрелое ресурсное матричное управление | C10: =AVERAGE(F7, F11:F13) -> 0.125 | D10: Проектный калькулятор | E10: [2.4] | F10: 0
B11: 3) Нужно автоформирование оперативного фронта работ (плана производства). | C11: =AVERAGE( F14) -> 0 | D11: Матричное ресурсное управление | E11: [2.5] | F11: 0
D12: Контроль качества и применимость ресурсов (компетенции, квалификации) | E12: [2.5, 5] | F12: 0
D13: Влияние производительности ресурсов на трудоемкость и сроки | E13: [2.5] | F13: 0
D14: Оперативный фронт работ (план производства) | E14: [3] | F14: 0
B15: 2.2 Альтернативы | D15: 8. Ключевые метрики | I15: 5. Каналы | J15: 1.2 Ранние последователи
I16: Свои каналы 1C 1C:ERP Отраслевые ресурсы
B17: 7. Структура издержек | H17: 6. Потоки прибыли
B20: решение не сформулировано | D20: Не занимались | E20: 0
B21: решение сформулировано частично | D21: В работе | E21: 0.1
B22: решение сформулировано | D22: Техническая реализация | E22: 0.5
D23: Базовая реализация (в т.ч. удобно) | E23: 0.8
D24: Глубокая реализация | E24: 1

Sheet Кр1ПДО-М
B2: Продукт | H2: Рынок
B3: 2.1 Проблема | C3: =ROUND(AVERAGE(C4:C14)*100,0) -> 23 | D3: 4. Решение | F3: =AVERAGE(F4:F14) -> 0.13636364 | G3: 3. Уникальная ценность (УТП) | I3: 9. Скрытое преимущество | J3: 1.1 Сегменты потребителей
B4: 1) Нужна система мониторинга производственной деятельности, синхронизированная с планами по проектам, объемам и по ресурсам | C4: =AVERAGE(F4:F5,F8:F9) -> 0.25 | D4: Интеграция с внешней производственной системой | E4: [1] | F4: 0 | G4: Система мониторинга производственной деятельности, синхронизированная с планами по проектам, объемам и по ресурсам. Управление загрузкой, сроками и стоимостью по проектам портфеля для увеличения объемов/рентабельности. | I4: Возможность самостоятельной доработки. | J4: Крупные проектные организации. ПДО
B5: 2) Сложности устойчивого роста | D5: Синхронизация мониторинга производственной деятельности с планами по проектам, объемам и по ресурсам | E5: [1, 2.1] | F5: 0.5
B6: 2.1) с т.з. синхронного роста объемов и персонала | C6: =AVERAGE(F5) -> 0.5 | D6: Механизм укрупненной оценки проектов на структуре проекта с печатной формой (Обоснование стоимости проекта) | E6: [2.4] | F6: 0
B7: 2.2) Неравномерная рваная загрузка | C7: =AVERAGE(F7:F8) -> 0.25 | D7: Балансировка объемов и ресурсов | E7: [2.2, 2.5] | F7: 0.5
B8: 2.3) Несогласованность возможностей производственных направлений и планов продаж | C8: =AVERAGE(F9) -> 0.5 | D8: Трехуровневое ресурсное планирование с прогнозами | E8: [1, 2.2] | F8: 0
B9: 2.4) Требуется сокращение сроков и повышение точности предварительной оценки проектов | C9: =AVERAGE(F6, F10) -> 0 | D9: Темплан, включая планирование объемов актирования по контрактации (без самой контрактации) | E9: [1, 2.3] | F9: 0.5
B10: 2.5) Нужно зрелое ресурсное матричное управление | C10: =AVERAGE(F7, F11:F13) -> 0.125 | D10: Проектный калькулятор | E10: [2.4] | F10: 0
B11: 3) Нужно автоформирование оперативного фронта работ (плана производства) (в т.ч. ТМЦ) | C11: =AVERAGE( F14) -> 0 | D11: Матричное ресурсное управление | E11: [2.5] | F11: 0
D12: Контроль качества и применимость ресурсов (компетенции, квалификации) | E12: [2.5, 5] | F12: 0
D13: Влияние производительности ресурсов на трудоемкость и сроки | E13: [2.5] | F13: 0
D14: Оперативный фронт работ (план производства) | E14: [3] | F14: 0
B15: 2.2 Альтернативы | D15: 8. Ключевые метрики | I15: 5. Каналы | J15: 1.2 Ранние последователи
I16: Свои каналы 1C 1C:ERP Отраслевые ресурсы
B17: 7. Структура издержек | H17: 6. Потоки прибыли
B20: решение не сформулировано | D20: Не занимались | E20: 0
B21: решение сформулировано частично | D21: В работе | E21: 0.1
B22: решение сформулировано | D22: Техническая реализация | E22: 0.5
D23: Базовая реализация (в т.ч. удобно) | E23: 0.8
D24: Глубокая реализация | E24: 1

Sheet Кр1РП
B2: Продукт | H2: Рынок
B3: 2.1 Проблема | C3: =ROUND(AVERAGE(C4:C18)*100,0) -> 31 | D3: 4. Решение | E3: Связь | F3: =AVERAGE(F4:F18) -> 0.27142857 | G3: 3. Уникальная ценность (УТП) | I3: 9. Скрытое преимущество | J3: 1.1 Сегменты потребителей
B4: 1) Нет единой системы управления проектами | C4: =AVERAGE(F5,F6) -> 0.25 | D4: Комплексная система по управлению проектом для РП, обеспечивающая: | G4: Комплексные управление проектами, бюджетами и упр.учет в одной системе. Управление рентабельностью проектов и фирмы в целом. Сохранение/оптимизация баланса затрат и свободного/чистого денежного потока. Увеличение объемов/рентабельности через управление загрузкой, сроками и стоимостью. | I4: Многофирменный учет; Бесшовная интеграция с 1С (УНФ, БП); Облако-коробка; Возможность доработки. | J4: Крупные проектные организации. РП
B5: 2) Тратится много времени на обмен печ.формами и реестрами с заказчиком/своей бухгалтерией. Нужно регистрировать такой вспомогательный документооборот и отслеживать его статусы в привязке к Проекту и этапу проекта. | C5: =F6 -> 0 | D5: Единообразное планирование проектов (План-график, трудозатраты, фин план) | E5: [1, 4] | F5: 0.5
B6: 3) Нет возможности полуавтоматической генерации отчетности по проекту заказчику/руководству. | C6: =AVERAGE(F7,F8, F9) -> 0.33333333 | D6: MDR | E6: [1, 2, 4] | F6: 0
B7: 4) Сложно организовать хранение разноплановых данных: этапы, сроки, документы, реестры, обязательства предконтрактной стадии и договорные суммы, ресурсы | C7: =AVERAGE(F5,F6, F14, F15) -> 0.25 | D7: Актуализация информации | E7: [3] | F7: 0.5
B8: 5) Нет удобной и надежной системы взаимодействия с исполнителями работ | C8: =AVERAGE(F12,F10, F11, F13) -> 0.125 | D8: Формирование отчетности по проектам | E8: [3] | F8: 0.5
B9: 6) Не понятна рентабельность проекта | C9: =F16 -> 0.8 | D9: Статус-отчеты по проекту. От Фазы Пресейла до Завершения договора | E9: [3] | F9: 0
B10: 7) Нет понимания фронта работ, готовых к исполнению | C10: =AVERAGE(F17) -> 0 | D10: Диспетчирование работ (поручения) | E10: [5] | F10: 0.5
B11: 8) У служб предприятия отличаются взгляды (подходы) к планированию проекта | C11: =F14 -> 0.5 | D11: Канбан-доска | E11: [5] | F11: 0
B12: 9) Слабый контроль выполнения работ. Не укладываются в срок. | C12: =F18 -> 0.5 | D12: Интеграция с трекинг-системами | E12: [5] | F12: 0
D13: 1С:Взаимодействие | E13: [5] | F13: 0
D14: Многомерный проект (проект, у которого несколько планов) | E14: [8] | F14: 0.5
D15: Предконтрактный план с оценкой (простой проектный калькулятор) | E15: [4] | F15: 0
D16: Упр.учет фирмы в разрезе проектов | E16: [6] | F16: 0.8
D17: Анализ обеспеченности и формирование фронта работ | E17: [7] | F17: 0
D18: Учет факта выполнения работ. | E18: [9] | F18: 0.5
B19: 2.2 Альтернативы | D19: 8. Ключевые метрики | I19: 5. Каналы | J19: 1.2 Ранние последователи
D20: Количество продаж; Количество пользователей в ГРМ; Количество отзывов | I20: Свои каналы 1C 1C:УНФ Где тусуются?
B21: 7. Структура издержек | H21: 6. Потоки прибыли
B24: решение не сформулировано | D24: Не занимались | E24: 0
B25: решение сформулировано частично | D25: В работе | E25: 0.1
B26: решение сформулировано | D26: Техническая реализация | E26: 0.5
D27: Базовая реализация (в т.ч. удобно) | E27: 0.8
D28: Глубокая реализация | E28: 1

Sheet Кр1РП-М
B2: Продукт | H2: Рынок
B3: 2.1 Проблема | C3: =ROUND(AVERAGE(C4:C20)*100,0) -> 32 | D3: 4. Решение | E3: Связь | F3: =AVERAGE(F4:F18) -> 0.27142857 | G3: 3. Уникальная ценность (УТП) | I3: 9. Скрытое преимущество | J3: 1.1 Сегменты потребителей
B4: 1) Нет единой системы управления проектами | C4: =AVERAGE(F5,F6) -> 0.25 | D4: Комплексная система по управлению проектом для РП, обеспечивающая: | G4: Комплексные управление проектами, бюджетами и упр.учет в одной системе. Управление рентабельностью проектов и фирмы в целом. Сохранение/оптимизация баланса затрат и свободного/чистого денежного потока. Увеличение объемов/рентабельности через управление загрузкой, сроками и стоимостью. | I4: Многофирменный учет; Бесшовная интеграция с 1С (УНФ, БП); Облако-коробка; Возможность доработки. | J4: Крупные инжиниринговые организации. РП
B5: 2) Тратится много времени на обмен печ.формами и реестрами с заказчиком/своей бухгалтерией. Нужно регистрировать такой вспомогательный документооборот и отслеживать его статусы в привязке к Проекту и этапу проекта. | C5: =F6 -> 0 | D5: Единообразное планирование проектов (План-график, трудозатраты, фин план) | E5: [1, 4] | F5: 0.5
B6: 3) Нет возможности полуавтоматической генерации отчетности по проекту заказчику/руководству. | C6: =AVERAGE(F7,F8, F9) -> 0.33333333 | D6: MDR | E6: [1, 2, 4] | F6: 0
B7: 4) Сложно организовать хранение разноплановых данных: этапы, сроки, документы, реестры, обязательства предконтрактной стадии и договорные суммы, ресурсы | C7: =AVERAGE(F5,F6, F14, F15) -> 0.25 | D7: Актуализация информации | E7: [3] | F7: 0.5
B8: 5) Нет удобной и надежной системы взаимодействия с исполнителями работ | C8: =AVERAGE(F12,F10, F11, F13) -> 0.125 | D8: Формирование отчетности по проектам | E8: [3] | F8: 0.5
B9: 6) Не понятна рентабельность проекта | C9: =F16 -> 0.8 | D9: Статус-отчеты по проекту. От Фазы Пресейла до Завершения договора | E9: [3] | F9: 0
B10: 7) Нет понимания фронта работ, готовых к исполнению (в т.ч. обеспеченных ТМЦ) | C10: =AVERAGE(F17) -> 0 | D10: Диспетчирование работ (поручения) | E10: [5] | F10: 0.5
B11: 8) У служб предприятия отличаются взгляды (подходы) к планированию проекта | C11: =F14 -> 0.5 | D11: Канбан-доска | E11: [5] | F11: 0
B12: 9) Слабый контроль выполнения работ. Не укладываются в срок. | C12: =F18 -> 0.5 | D12: Интеграция с трекинг-системами | E12: [5] | F12: 0
B13: 10) Нет четкого понимания когда и какие ТМЦ будут нужны с учетом текущей ситуации по проекту | C13: =AVERAGE(F20,F19) -> 0.25 | D13: 1С:Взаимодействие | E13: [5] | F13: 0
B14: 11) Нет данных когда требуемые проекту ТМЦ поступят | C14: =F20 -> 0.5 | D14: Многомерный проект (проект, у которого несколько планов) | E14: [8] | F14: 0.5
D15: Предконтрактный план с оценкой (простой проектный калькулятор) | E15: [4] | F15: 0
D16: Упр.учет фирмы в разрезе проектов | E16: [6] | F16: 0.8
D17: Анализ обеспеченности и формирование фронта работ | E17: [7] | F17: 0
D18: Учет факта выполнения работ. | E18: [9] | F18: 0.5
D19: Привязка спецификаций к работам проекта | E19: [10] | F19: 0
D20: Связь проектов, заказов поставщикам и факта поставки ТМЦ | E20: [10, 11] | F20: 0.5
B21: 2.2 Альтернативы | D21: 8. Ключевые метрики | I21: 5. Каналы | J21: 1.2 Ранние последователи
D22: Количество продаж; Количество пользователей в ГРМ; Количество отзывов | I22: Свои каналы 1C 1C:УНФ Где тусуются?
B23: 7. Структура издержек | H23: 6. Потоки прибыли
B26: решение не сформулировано | D26: Не занимались | E26: 0
B27: решение сформулировано частично | D27: В работе | E27: 0.1
B28: решение сформулировано | D28: Техническая реализация | E28: 0.5
D29: Базовая реализация (в т.ч. удобно) | E29: 0.8
D30: Глубокая реализация | E30: 1

Sheet Кр2МшДПр
B2: Продукт | H2: Рынок
B3: 2.1 Проблема | C3: =ROUND(AVERAGE(C4:C7)*100,0) -> 25 | D3: 4. Решение | F3: =AVERAGE(F4:F7) -> 0.25 | G3: 3. Уникальная ценность (УТП) | I3: 9. Скрытое преимущество | J3: 1.1 Сегменты потребителей
B4: 1) Нет автоматической связи/акутализации данных между разными уровнями управления (2 уровня диспетчеров). План-графики неактуальны. | C4: =AVERAGE(F4) -> 0.5 | D4: Многомерные проекты. | E4: [1] | F4: 0.5 | G4: Многомерные взаимосвязанные графики; Актуализация план-графика работ по данным производства (по разным уровням); Формирование фронта работ цехов на основании графиков работ и приоритезации. Формирование планов проектов на основании структуры изделий из PDM. Анализ обеспеченности работ. Визуализация в 3D производства изделия для мониторинга состояния объекта, проверки последовательности работ в плане. | I4: Бесшовная интеграция с 1С:ERP (производство, спецификации, номенклатура); Возможность доработки; Импортонезависимый стек. | J4: Проектное производство/ машиностроительные организации. Дир.по производству/по проектам
B5: 2) По цехам нет актуального приоритизированного фронта работ. | C5: =AVERAGE(F5) -> 0.5 | D5: Оперативный фронт работ (план производства). | E5: [2] | F5: 0.5
B6: 3) В планах проектов отражены не все работы, которые необходимы для выпуска изделий и постройки объектов. РП при составлении планов по незнанию указывает не все связи. | C6: =AVERAGE(F6) -> 0 | D6: Загрузка из файла-шаблона с PDM/PLM данными. Состав изделия, состав работ, связи. | E6: [3] | F6: 0
B7: 4) Нет визуализации состава и последовательности изготовления изделий: - Не очевидна последовательность сборки изделий - | C7: =AVERAGE(F7) -> 0 | D7: Средство визуализации 3D модели изделий и последовательностей изготовления, привязанных к плану проекта | E7: [4] | F7: 0
B8: 2.2 Альтернативы | D8: 8. Ключевые метрики | I8: 5. Каналы | J8: 1.2 Ранние последователи
B9: Своя разработка; ERP: цепочка заказов <-> производство | D9: Количество продаж; Количество отзывов | I9: Тематика машиностроения (авиа, судо, станко строение) - выставки, конференции,
B10: 7. Структура издержек | H10: 6. Потоки прибыли
B13: решение не сформулировано | D13: Не занимались | E13: 0
B14: решение сформулировано частично | D14: В работе | E14: 0.1
B15: решение сформулировано | D15: Техническая реализация | E15: 0.5
D16: Базовая реализация (в т.ч. удобно) | E16: 0.8
D17: Глубокая реализация | E17: 1

Sheet Х1_ППО
B2: Продукт | H2: Рынок
B3: 2.1 Проблема | C3: =ROUND(AVERAGE(C4:C6)*100,0) -> 33 | D3: 4. Решение | F3: =AVERAGE(F4:F6) -> 0.33333333 | G3: 3. Уникальная ценность (УТП) | I3: 9. Скрытое преимущество | J3: 1.1 Сегменты потребителей
B4: 1) Неравномерная рваная загрузка ресурсов холдинга | C4: =AVERAGE(F4) -> 0.5 | D4: Cоставление сводных планов, минимизация ресурсных конфликтов. | E4: [1] | F4: 0.5 | G4: Иерархические проекты | I4: Возможность доработки; | J4: Начальник ППО Холдинга
B5: 2) Оперативное получение актуальных данных от ДЗО | C5: =AVERAGE(F5) -> 0.5 | D5: Актуализация загрузки | E5: [2] | F5: 0.5
B6: 3) Для Холдинг1.2. понимание актуальных планов, причин проблем, подтвержденные планами и фактом из баз ДЗО | C6: =AVERAGE(F6) -> 0 | D6: Интеграция баз Холдинг-ДЗО. | E6: [3] | F6: 0
B7: 2.2 Альтернативы | D7: 8. Ключевые метрики | I7: 5. Каналы | J7: 1.2 Ранние последователи
D8: Количество продаж; Количество отзывов
B9: 7. Структура издержек | H9: 6. Потоки прибыли
B12: решение не сформулировано | D12: Не занимались | E12: 0
B13: решение сформулировано частично | D13: В работе | E13: 0.1
B14: решение сформулировано | D14: Техническая реализация | E14: 0.5
D15: Базовая реализация (в т.ч. удобно) | E15: 0.8
D16: Глубокая реализация | E16: 1

Sheet Х1_ППО-М
B2: Продукт | H2: Рынок
B3: 2.1 Проблема | C3: =ROUND(AVERAGE(C4:C8)*100,0) -> 40 | D3: 4. Решение | F3: =AVERAGE(F4:F8) -> 0.375 | G3: 3. Уникальная ценность (УТП) | I3: 9. Скрытое преимущество | J3: 1.1 Сегменты потребителей
B4: 1) Неравномерная рваная загрузка ресурсов холдинга | C4: =AVERAGE(F4) -> 0.5 | D4: Cоставление сводных планов, минимизация ресурсных конфликтов. | E4: [1] | F4: 0.5 | G4: Иерархические проекты | I4: Возможность доработки | J4: ППО. Трудоемкое+сборка (Закупка у Холдинга)
B5: 2) Оперативное получение актуальных данных от ДЗО | C5: =AVERAGE(F5) -> 0.5 | D5: Актуализация загрузки | E5: [2] | F5: 0.5
B6: 3) Для Холдинг1.2. понимание актуальных планов, причин проблем, подтвержденные планами и фактом из баз ДЗО | C6: =AVERAGE(F6) -> 0 | D6: Интеграция баз Холдинг-ДЗО. | E6: [3] | F6: 0
B7: 3) Нет четкого понимания когда и какие ТМЦ будут нужны с учетом текущей ситуации по проекту | C7: =AVERAGE(F7) -> 0.5 | D7: Связь проектов, заказов поставщикам и факта поставки ТМЦ | E7: [3, 4] | F7: 0.5
B8: 4) Нет данных когда требуемые проекту ТМЦ поступят | C8: =AVERAGE(F7) -> 0.5
B9: 2.2 Альтернативы | D9: 8. Ключевые метрики | I9: 5. Каналы | J9: 1.2 Ранние последователи
D10: Количество продаж; Количество отзывов
B11: 7. Структура издержек | H11: 6. Потоки прибыли
B14: решение не сформулировано | D14: Не занимались | E14: 0
B15: решение сформулировано частично | D15: В работе | E15: 0.1
B16: решение сформулировано | D16: Техническая реализация | E16: 0.5
D17: Базовая реализация (в т.ч. удобно) | E17: 0.8
D18: Глубокая реализация | E18: 1

Sheet Х2_ДИД
B2: Продукт | H2: Рынок
B3: 2.1 Проблема | C3: =ROUND(AVERAGE(C4:C7)*100,0) -> 25 | D3: 4. Решение | F3: =AVERAGE(F4:F7) -> 0.125 | G3: 3. Уникальная ценность (УТП) | I3: 9. Скрытое преимущество | J3: 1.1 Сегменты потребителей
B4: 1) Нет точных расчетов инвестпрограммы | C4: =AVERAGE(F4:F6) -> 0 | D4: Расчет финпоказателей в заявках. | E4: [1] | F4: 0 | G4: Оперативная сборка и актуализация исполнения инвестпрограммы Сценарное моделирование. | J4: Инвест подразделения в Холдингах. Директор инвестдепартамента (ДИД)
B5: 2) Редко и трудоемко собирается и актуализируется инвестпрограмма | C5: =AVERAGE(F7) -> 0.5 | D5: Инвестпрограмма. | E5: [1] | F5: 0
D6: Сценарное моделирование. «Что если». | E6: [1] | F6: 0
D7: Актуализация инвестпрограммы на основании связанных проектов. | E7: [2] | F7: 0.5
B8: 2.2 Альтернативы | D8: 8. Ключевые метрики | I8: 5. Каналы | J8: 1.2 Ранние последователи
D9: Количество продаж; Количество отзывов
B10: 7. Структура издержек | H10: 6. Потоки прибыли
B13: решение не сформулировано | D13: Не занимались | E13: 0
B14: решение сформулировано частично | D14: В работе | E14: 0.1
B15: решение сформулировано | D15: Техническая реализация | E15: 0.5
D16: Базовая реализация (в т.ч. удобно) | E16: 0.8
D17: Глубокая реализация | E17: 1

Sheet Х2_НИО
B2: Продукт | H2: Рынок
B3: 2.1 Проблема | C3: =ROUND(AVERAGE(C4:C9)*100,0) -> 8 | D3: 4. Решение | F3: =AVERAGE(F4:F9) -> 0.083333333 | G3: 3. Уникальная ценность (УТП) | I3: 9. Скрытое преимущество | J3: 1.1 Сегменты потребителей
B4: 1) Заявки передаются разными каналами, теряются, в разных форматах, нет всех данных. | C4: =AVERAGE(F4) -> 0 | D4: Заявки в системе | E4: [1] | F4: 0 | G4: Сценарное моделирование. | J4: Инвест подразделения в Холдингах. Начальник инвест отдела
B5: 2) Не рассчитывается эконэффект и финпоказатели | C5: =AVERAGE(F5) -> 0 | D5: Расчет финпоказателей в заявках | E5: [2] | F5: 0
B6: 3) Долго формируется сводная инвестпрограмма. | C6: =AVERAGE(F6) -> 0 | D6: Инвестпрограмма | E6: [3] | F6: 0
B7: 4) Нет контрольных точек продолжения финансирования | C7: =AVERAGE(F7) -> 0 | D7: Gate | E7: [4] | F7: 0
B8: 5) Разрозненные данные по исполнению инвестпрограммы | C8: =AVERAGE(F8) -> 0.5 | D8: Актуализация инвестпрограммы на основании связанных проектов | E8: [5] | F8: 0.5
B9: 6) Нет связи между рисками и инвестпроектами | C9: =AVERAGE(F9) -> 0 | D9: Сценарное моделирование. «Что если» | E9: [6] | F9: 0
B10: 2.2 Альтернативы | D10: 8. Ключевые метрики | I10: 5. Каналы | J10: 1.2 Ранние последователи
D11: Количество продаж; Количество отзывов | I11: Тематические выставки
B12: 7. Структура издержек | H12: 6. Потоки прибыли
B15: решение не сформулировано | D15: Не занимались | E15: 0
B16: решение сформулировано частично | D16: В работе | E16: 0.1
B17: решение сформулировано | D17: Техническая реализация | E17: 0.5
D18: Базовая реализация (в т.ч. удобно) | E18: 0.8
D19: Глубокая реализация | E19: 1

Sheet LCM
B2: Lean Canvas Model
B3: Отдельная таблица на каждый сегмент
B7: https://habr.com/ru/companies/productstar/articles/508994/
B8: https://scrumtrek.ru/blog/product-management/9113/lean-canvas-chto-eto/

Sheet Шаблон
B2: Продукт | H2: Рынок
B3: 2.1 Проблема | C3: % | D3: 4. Решение | E3: Связь | F3: % | G3: 3. Уникальная ценность (УТП) | I3: 9. Скрытое преимущество | J3: 1.1 Сегменты потребителей
B5: 2.2 Альтернативы | D5: 8. Ключевые метрики | I5: 5. Каналы | J5: 1.2 Ранние последователи
B7: 7. Структура издержек | H7: 6. Потоки прибыли
